Workbook

Sheet Summary
A1: Armenia: sovereign credit summary | B1: as of 09-Oct-26
A2: Ratings | B2: =Inputs!B29&" / "&Inputs!B30&" / "&Inputs!B31 | C2: Fitch / S&P / Moody's (see Inputs for dates)
A3: Ex-ante real policy rate (%) | B3: =Calc!B2
A4: Debt-stabilising PB (% GDP) | B4: =Calc!B4
A5: PB gap (% GDP) | B5: =Calc!B5
A6: Reserves / ST ext. debt (x) | B6: =Calc!B6
A7: Debt in 5 years, baseline (% GDP) | B7: =Calc!F12
A8: Debt in 5 years, shock (% GDP) | B8: =Calc!F13
A9: Interest / revenue (%) | B9: =Inputs!$B$12
A10: Gross financing need (% GDP) | B10: =Inputs!$B$13
A12: All derived cells are formulas; inputs are blue cells on Inputs, Series and Scenarios. Sources and dates sit beside every input.

Sheet Inputs
A1: Armenia sovereign model | E1: built 26-Oct-26 by pipeline/sovereign_model.py from database/sovereigns/armenia.json
A2: Indicator | B2: Value | C2: Unit | D2: Period | E2: Source | F2: As of | G2: Definition
A3: policy_rate_pct | B3: 6.75 | C3: % | D3: Sep-26 | E3: Central Bank of Armenia, refinancing rate decision | F3: 15-Sep-26
A4: inflation_expectation_12m_pct | C4: %
A5: cpi_latest_yoy_pct | B5: 4.3 | C5: % | D5: Sep-26 | E5: Armstat, Consumer Price Index | F5: 30-Sep-26
A6: real_gdp_growth_pct | B6: 5.25 | C6: % | D6: 2026E | E6: IMF | F6: 30-Jun-26
A7: effective_interest_rate_pct | C7: %
A8: gov_debt_pct_gdp | B8: 50.6 | C8: % GDP | D8: 2026E | E8: IMF WEO | F8: 08-Oct-26 | G8: official annual series (filled automatically; a run's sourced point replaces it)
A9: primary_balance_pct_gdp | C9: % GDP
A10: fiscal_balance_pct_gdp | B10: -3.4 | C10: % GDP | D10: 2026 (tracking) | E10: Ministry of Finance, State Budget Execution | F10: 09-Oct-26
A11: revenue_pct_gdp | C11: % GDP
A12: interest_pct_revenue | C12: %
A13: gfn_pct_gdp | C13: % GDP
A14: current_account_pct_gdp | B14: -9.8 | C14: % GDP | D14: Q2-26 | E14: Armstat, Balance of Payments Q2 2026 | F14: 30-Jun-26
A15: fdi_net_pct_gdp | B15: 2.421 | C15: % GDP | D15: 2025 | E15: World Bank WDI | F15: 08-Oct-26 | G15: official annual series (filled automatically; a run's sourced point replaces it)
A16: gross_reserves_usd_bn | B16: 6.5 | C16: USD bn | D16: Sep-26 | E16: Central Bank of Armenia | F16: 30-Sep-26 | G16: CBA gross international reserves; reported as exceeding USD 6.5bn; gold treatment not stated
A17: net_reserves_usd_bn | C17: USD bn
A18: import_cover_months | B18: 5 | C18: months | D18: Sep-26 | E18: Central Bank of Armenia (reported as more than 5 months) | F18: 30-Sep-26
A19: short_term_external_debt_usd_bn | C19: USD bn
A20: external_debt_pct_gdp | C20: % GDP
A21: gefr_usd_bn | C21: USD bn
A22: nominal_gdp_usd_bn | B22: 31.873 | C22: USD bn | D22: 2026E | E22: IMF WEO | F22: 08-Oct-26 | G22: official annual series (filled automatically; a run's sourced point replaces it)
A23: eurobonds_outstanding_usd_bn | C23: USD bn
A24: eurobond_10y_spread_bp | C24: bp
A25: cds_5y_bp | C25: bp
A26: embi_gd_weight_pct | C26: %
A28: Ratings | B28: Rating | C28: Outlook | D28: Date
A29: fitch | B29: BB- | C29: Positive | D29: 10-Jul-26
A30: sp | B30: BB- | C30: Positive | D30: 21-Aug-26
A31: moodys | B31: Ba3 | C31: Positive | D31: 28-Jul-26
A33: IMF | B33: 3-year precautionary Stand-By Arrangement | D33: Dec-25

Sheet Series
A1: Series (annual) | B1: 2023 | C1: 2026E | D1: 2026F | E1: Source
A2: nominal_gdp_usd_bn
A3: real_gdp_growth_pct | C3: 5.25 | D3: 5.25 | E3: IMF, 30-Jun-26
A4: cpi_avg_pct
A5: current_account_pct_gdp
A6: fiscal_balance_pct_gdp | C6: -3.4 | E6: Ministry of Finance, 09-Oct-26
A7: primary_balance_pct_gdp
A8: gov_debt_pct_gdp
A9: external_debt_pct_gdp
A10: gross_reserves_usd_bn | B10: 3.6 | C10: 6.5 | E10: Central Bank of Armenia, late 2023 (as cited in adjudicated document, Oct-26)
A11: revenue_pct_gdp
A12: interest_pct_revenue

Sheet Calc
A1: Derived metric | B1: Formula result | C1: Formula / note
A2: Ex-ante real policy rate (%) | B2: =IF(Inputs!$B$4="",Inputs!$B$3-Inputs!$B$5,Inputs!$B$3-Inputs!$B$4) | C2: policy − 12m expected inflation (falls back to latest CPI)
A3: Nominal GDP growth proxy (%) | B3: =((1+Inputs!$B$6/100)*(1+Inputs!$B$5/100)-1)*100 | C3: (1+g)(1+π)−1
A4: Debt-stabilising primary balance (% GDP) | B4: =(Inputs!$B$7/100-B3/100)/(1+B3/100)*Inputs!$B$8 | C4: pb* = (r−g)/(1+g)·d
A5: Primary balance gap (% GDP) | B5: =Inputs!$B$9-B4 | C5: actual − pb*; negative = debt rising
A6: Reserves / short-term external debt (x) | B6: =IF(Inputs!$B$19>0,Inputs!$B$16/Inputs!$B$19,"") | C6: Greenspan-Guidotti; >1 is adequate
A7: GEFR / gross reserves (%) | B7: =IF(Inputs!$B$16>0,Inputs!$B$21/Inputs!$B$16*100,"")
A8: Interest / revenue check (%) | B8: =IF(AND(Inputs!$B$11>0,Inputs!$B$7>0),Inputs!$B$7/100*Inputs!$B$8/Inputs!$B$11*100,"") | C8: r·d/revenue; compare with reported interest/revenue
A9: Eurobonds / reserves (%) | B9: =IF(Inputs!$B$16>0,Inputs!$B$23/Inputs!$B$16*100,"")
A11: Debt projection (% GDP) | B11: Year 1 | C11: Year 2 | D11: Year 3 | E11: Year 4 | F11: Year 5 | G11: d(t+1) = d(t)·(1+r)/(1+g) − pb; r, g, pb from Inputs/Scenarios
A12: Baseline | B12: =Inputs!$B$8*(1+Inputs!$B$7/100)/(1+$B$3/100)-Inputs!$B$9 | C12: =B12*(1+Inputs!$B$7/100)/(1+$B$3/100)-Inputs!$B$9 | D12: =C12*(1+Inputs!$B$7/100)/(1+$B$3/100)-Inputs!$B$9 | E12: =D12*(1+Inputs!$B$7/100)/(1+$B$3/100)-Inputs!$B$9 | F12: =E12*(1+Inputs!$B$7/100)/(1+$B$3/100)-Inputs!$B$9
A13: Shock scenario | B13: =Inputs!$B$8*(1+(Inputs!$B$7+Scenarios!$B$3)/100)/(1+($B$3+Scenarios!$B$2)/100)-(Inputs!$B$9+Scenarios!$B$4) | C13: =B13*(1+(Inputs!$B$7+Scenarios!$B$3)/100)/(1+($B$3+Scenarios!$B$2)/100)-(Inputs!$B$9+Scenarios!$B$4) | D13: =C13*(1+(Inputs!$B$7+Scenarios!$B$3)/100)/(1+($B$3+Scenarios!$B$2)/100)-(Inputs!$B$9+Scenarios!$B$4) | E13: =D13*(1+(Inputs!$B$7+Scenarios!$B$3)/100)/(1+($B$3+Scenarios!$B$2)/100)-(Inputs!$B$9+Scenarios!$B$4) | F13: =E13*(1+(Inputs!$B$7+Scenarios!$B$3)/100)/(1+($B$3+Scenarios!$B$2)/100)-(Inputs!$B$9+Scenarios!$B$4)

Sheet Scenarios
A1: Shock inputs (edit the blue cells) | B1: Value | C1: Note
A2: Nominal growth shock (pp) | B2: -3 | C2: applied to nominal GDP growth
A3: Effective interest rate shock (pp) | B3: 2 | C3: refinancing at higher yields
A4: Primary balance shock (% GDP) | B4: -1.5 | C4: fiscal slippage
