Workbook

Sheet Annual and Quarterly
A1: €mm, Dec year-end | B1: FY18 | C1: FY19 | D1: FY20 | E1: FY21 | F1: FY22 | G1: FY23 | H1: FY24 | I1: FY25 | J1: LTM | K1: 1Q19 | L1: 2Q19 | M1: 3Q19 | N1: 4Q19 | O1: 1Q20 | P1: 2Q20 | Q1: 3Q20 | R1: 4Q20 | S1: 1Q21 | T1: 2Q21 | U1: 3Q21 | V1: 4Q21 | W1: 1Q22 | X1: 2Q22 | Y1: 3Q22 | Z1: 4Q22 | AA1: 1Q23 | AB1: 2Q23 | AC1: 3Q23 | AD1: 4Q23 | AE1: 1Q24 | AF1: 2Q24 | AG1: 3Q24 | AH1: 4Q24 | AI1: 1Q25 | AJ1: 2Q25 | AK1: 3Q25 | AL1: 4Q25 | AM1: 1Q26 | AN1: 2Q26 | AO1: Q/o/Q | AP1: Y/o/Y
A2: Income Statement
A3: Revenue | B3: 432.474 | C3: 607.3 | D3: 695.672 | E3: 1014.891 | F3: 1852.686 | G3: 2262.773 | H3: 2103.272 | I3: 2189.312 | J3: =I3+'Quarterly YTD'!AF3-'Quarterly YTD'!AB3 -> 2285.39 | K3: 93.496 | L3: ='Quarterly YTD'!D3-K3 -> 111.524 | M3: ='Quarterly YTD'!E3-'Quarterly YTD'!D3 -> 115.428 | N3: =C3-'Quarterly YTD'!E3 -> 286.852 | O3: 267.869 | P3: ='Quarterly YTD'!H3-O3 -> 132.978 | Q3: ='Quarterly YTD'!I3-'Quarterly YTD'!H3 -> 133.792 | R3: =D3-'Quarterly YTD'!I3 -> 161.033 | S3: 162.144 | T3: ='Quarterly YTD'!L3-S3 -> 206.427 | U3: ='Quarterly YTD'!M3-'Quarterly YTD'!L3 -> 299.715 | V3: =E3-'Quarterly YTD'!M3 -> 346.605 | W3: 317.129 | X3: ='Quarterly YTD'!P3-W3 -> 463.506 | Y3: ='Quarterly YTD'!Q3-'Quarterly YTD'!P3 -> 563.904 | Z3: =F3-'Quarterly YTD'!Q3 -> 508.147 | AA3: 404.776 | AB3: ='Quarterly YTD'!T3-AA3 -> 549.902 | AC3: ='Quarterly YTD'!U3-'Quarterly YTD'!T3 -> 687.535 | AD3: =G3-'Quarterly YTD'!U3 -> 620.56 | AE3: 508.778 | AF3: ='Quarterly YTD'!X3-AE3 -> 720.116 | AG3: ='Quarterly YTD'!Y3-'Quarterly YTD'!X3 -> 828.505 | AH3: =H3-'Quarterly YTD'!Y3 -> 45.873 | AI3: 457.491 | AJ3: ='Quarterly YTD'!AB3-AI3 -> 560.951 | AK3: ='Quarterly YTD'!AC3-'Quarterly YTD'!AB3+-164.005 -> 730.681 | AL3: =I3-'Quarterly YTD'!AC3 -> 276.184 | AM3: 522.848 | AN3: ='Quarterly YTD'!AF3-AM3 -> 591.672 | AO3: =IF(AND(AN3=0,AM3=0),0,IF(OR(AM3=0,AM3="NM",AN3="NM"),"NM",IF(AM3<0,-(AN3/AM3-1),AN3/AM3-1))) -> 0.1316329 | AP3: =IF(AND(AN3=0,AJ3=0),0,IF(OR(AJ3=0,AJ3="NM",AN3="NM"),"NM",IF(AJ3<0,-(AN3/AJ3-1),AN3/AJ3-1))) -> 0.054765924
A4: Other income | B4: 0.262 | C4: 0.879 | D4: 13.218 | E4: 3.332 | F4: 2.832 | G4: 3.466 | H4: 2.154 | I4: 6.403 | J4: =I4+'Quarterly YTD'!AF4-'Quarterly YTD'!AB4 -> 8.155 | K4: 0.16 | L4: ='Quarterly YTD'!D4-K4 -> 0.107 | M4: ='Quarterly YTD'!E4-'Quarterly YTD'!D4 -> 0.136 | N4: =C4-'Quarterly YTD'!E4 -> 0.476 | O4: 1.034 | P4: ='Quarterly YTD'!H4-O4 -> 11.009 | Q4: ='Quarterly YTD'!I4-'Quarterly YTD'!H4 -> 1.337 | R4: =D4-'Quarterly YTD'!I4 -> -0.162 | S4: 0.889 | T4: ='Quarterly YTD'!L4-S4 -> 1.869 | U4: ='Quarterly YTD'!M4-'Quarterly YTD'!L4 -> 1.428 | V4: =E4-'Quarterly YTD'!M4 -> -0.854 | W4: 0.746 | X4: ='Quarterly YTD'!P4-W4 -> 2.135 | Y4: ='Quarterly YTD'!Q4-'Quarterly YTD'!P4 -> 1.465 | Z4: =F4-'Quarterly YTD'!Q4 -> -1.514 | AA4: 0.783 | AB4: ='Quarterly YTD'!T4-AA4 -> 0.413 | AC4: ='Quarterly YTD'!U4-'Quarterly YTD'!T4 -> 3.566 | AD4: =G4-'Quarterly YTD'!U4 -> -1.296 | AE4: 1.109 | AF4: ='Quarterly YTD'!X4-AE4 -> 1.058 | AG4: ='Quarterly YTD'!Y4-'Quarterly YTD'!X4 -> 0.741 | AH4: =H4-'Quarterly YTD'!Y4 -> -0.754 | AI4: 0.771 | AJ4: ='Quarterly YTD'!AB4-AI4 -> 0.977 | AK4: ='Quarterly YTD'!AC4-'Quarterly YTD'!AB4+-0.332 -> 1.166 | AL4: =I4-'Quarterly YTD'!AC4 -> 3.157 | AM4: 1.269 | AN4: ='Quarterly YTD'!AF4-AM4 -> 2.231 | AO4: =IF(AND(AN4=0,AM4=0),0,IF(OR(AM4=0,AM4="NM",AN4="NM"),"NM",IF(AM4<0,-(AN4/AM4-1),AN4/AM4-1))) -> 0.75807723 | AP4: =IF(AND(AN4=0,AJ4=0),0,IF(OR(AJ4=0,AJ4="NM",AN4="NM"),"NM",IF(AJ4<0,-(AN4/AJ4-1),AN4/AJ4-1))) -> 1.283521
A5: Cost of services and goods | B5: -312.579 | C5: -412.602 | D5: -418.367 | E5: -615.285 | F5: -1193.407 | G5: -1406.56 | H5: -1187.448 | I5: -1202.791 | J5: =I5+'Quarterly YTD'!AF5-'Quarterly YTD'!AB5 -> -1321.335 | K5: -62.428 | L5: ='Quarterly YTD'!D5-K5 -> -75.67 | M5: ='Quarterly YTD'!E5-'Quarterly YTD'!D5 -> -80.875 | N5: =C5-'Quarterly YTD'!E5 -> -193.629 | O5: -185.272 | P5: ='Quarterly YTD'!H5-O5 -> -63.699 | Q5: ='Quarterly YTD'!I5-'Quarterly YTD'!H5 -> -74.874 | R5: =D5-'Quarterly YTD'!I5 -> -94.522 | S5: -95.058 | T5: ='Quarterly YTD'!L5-S5 -> -127.924 | U5: ='Quarterly YTD'!M5-'Quarterly YTD'!L5 -> -184.206 | V5: =E5-'Quarterly YTD'!M5 -> -208.097 | W5: -208.777 | X5: ='Quarterly YTD'!P5-W5 -> -307.233 | Y5: ='Quarterly YTD'!Q5-'Quarterly YTD'!P5 -> -347.418 | Z5: =F5-'Quarterly YTD'!Q5 -> -329.979 | AA5: -278.055 | AB5: ='Quarterly YTD'!T5-AA5 -> -327.317 | AC5: ='Quarterly YTD'!U5-'Quarterly YTD'!T5 -> -388.084 | AD5: =G5-'Quarterly YTD'!U5 -> -413.104 | AE5: -360.502 | AF5: ='Quarterly YTD'!X5-AE5 -> -402.589 | AG5: ='Quarterly YTD'!Y5-'Quarterly YTD'!X5 -> -444.051 | AH5: =H5-'Quarterly YTD'!Y5 -> 19.694 | AI5: -290.996 | AJ5: ='Quarterly YTD'!AB5-AI5 -> -290.214 | AK5: ='Quarterly YTD'!AC5-'Quarterly YTD'!AB5+152.816 -> -360.316 | AL5: =I5-'Quarterly YTD'!AC5 -> -108.449 | AM5: -327.944 | AN5: ='Quarterly YTD'!AF5-AM5 -> -371.81 | AO5: =IF(AND(AN5=0,AM5=0),0,IF(OR(AM5=0,AM5="NM",AN5="NM"),"NM",IF(AM5<0,(AN5/AM5-1),-(AN5/AM5-1)))) -> 0.13376064 | AP5: =IF(AND(AN5=0,AJ5=0),0,IF(OR(AJ5=0,AJ5="NM",AN5="NM"),"NM",IF(AJ5<0,(AN5/AJ5-1),-(AN5/AJ5-1)))) -> 0.28115804
A6: Depreciation and amortisation | B6: -6.853 | C6: -34.732 | D6: -99.205 | E6: -74.338 | F6: -114.781 | G6: -239.28 | H6: -220.229 | I6: -265.414 | J6: =I6+'Quarterly YTD'!AF6-'Quarterly YTD'!AB6 -> -268.039 | K6: -2.936 | L6: ='Quarterly YTD'!D6-K6 -> -3.23 | M6: ='Quarterly YTD'!E6-'Quarterly YTD'!D6 -> -3.427 | N6: =C6-'Quarterly YTD'!E6 -> -25.139 | O6: -26.639 | P6: ='Quarterly YTD'!H6-O6 -> -26.592 | Q6: ='Quarterly YTD'!I6-'Quarterly YTD'!H6 -> -24.388 | R6: =D6-'Quarterly YTD'!I6 -> -21.586 | S6: -18.04 | T6: ='Quarterly YTD'!L6-S6 -> -17.06 | U6: ='Quarterly YTD'!M6-'Quarterly YTD'!L6 -> -19.107 | V6: =E6-'Quarterly YTD'!M6 -> -20.131 | W6: -21.68 | X6: ='Quarterly YTD'!P6-W6 -> -26.51 | Y6: ='Quarterly YTD'!Q6-'Quarterly YTD'!P6 -> -36.201 | Z6: =F6-'Quarterly YTD'!Q6 -> -30.39 | AA6: -41.974 | AB6: ='Quarterly YTD'!T6-AA6 -> -50.043 | AC6: ='Quarterly YTD'!U6-'Quarterly YTD'!T6 -> -64.571 | AD6: =G6-'Quarterly YTD'!U6 -> -82.692 | AE6: -81.707 | AF6: ='Quarterly YTD'!X6-AE6 -> -89.611 | AG6: ='Quarterly YTD'!Y6-'Quarterly YTD'!X6 -> -93.959 | AH6: =H6-'Quarterly YTD'!Y6 -> 45.048 | AI6: -62.883 | AJ6: ='Quarterly YTD'!AB6-AI6 -> -60.352 | AK6: ='Quarterly YTD'!AC6-'Quarterly YTD'!AB6+69.598 -> -91.364 | AL6: =I6-'Quarterly YTD'!AC6 -> 18.783 | AM6: -72.539 | AN6: ='Quarterly YTD'!AF6-AM6 -> -53.321 | AO6: =IF(AND(AN6=0,AM6=0),0,IF(OR(AM6=0,AM6="NM",AN6="NM"),"NM",IF(AM6<0,(AN6/AM6-1),-(AN6/AM6-1)))) -> -0.26493335 | AP6: =IF(AND(AN6=0,AJ6=0),0,IF(OR(AJ6=0,AJ6="NM",AN6="NM"),"NM",IF(AJ6<0,(AN6/AJ6-1),-(AN6/AJ6-1)))) -> -0.11649987
A7: Employee related expenses | B7: -71.907 | C7: -96.702 | D7: -145.734 | E7: -200.189 | F7: -306.593 | G7: -395.763 | H7: -470.48 | I7: -519.925 | J7: =I7+'Quarterly YTD'!AF7-'Quarterly YTD'!AB7 -> -544.752 | K7: -20.556 | L7: ='Quarterly YTD'!D7-K7 -> -21.033 | M7: ='Quarterly YTD'!E7-'Quarterly YTD'!D7 -> -20.334 | N7: =C7-'Quarterly YTD'!E7 -> -34.779 | O7: -39.977 | P7: ='Quarterly YTD'!H7-O7 -> -32.471 | Q7: ='Quarterly YTD'!I7-'Quarterly YTD'!H7 -> -36.27 | R7: =D7-'Quarterly YTD'!I7 -> -37.016 | S7: -38.995 | T7: ='Quarterly YTD'!L7-S7 -> -43.33 | U7: ='Quarterly YTD'!M7-'Quarterly YTD'!L7 -> -51.99 | V7: =E7-'Quarterly YTD'!M7 -> -65.874 | W7: -66.068 | X7: ='Quarterly YTD'!P7-W7 -> -76.555 | Y7: ='Quarterly YTD'!Q7-'Quarterly YTD'!P7 -> -78.453 | Z7: =F7-'Quarterly YTD'!Q7 -> -85.517 | AA7: -85.755 | AB7: ='Quarterly YTD'!T7-AA7 -> -96.142 | AC7: ='Quarterly YTD'!U7-'Quarterly YTD'!T7 -> -101.075 | AD7: =G7-'Quarterly YTD'!U7 -> -112.791 | AE7: -115.571 | AF7: ='Quarterly YTD'!X7-AE7 -> -124.509 | AG7: ='Quarterly YTD'!Y7-'Quarterly YTD'!X7 -> -123.482 | AH7: =H7-'Quarterly YTD'!Y7 -> -106.918 | AI7: -128.452 | AJ7: ='Quarterly YTD'!AB7-AI7 -> -125.638 | AK7: ='Quarterly YTD'!AC7-'Quarterly YTD'!AB7+21.036 -> -127.091 | AL7: =I7-'Quarterly YTD'!AC7 -> -117.708 | AM7: -141.944 | AN7: ='Quarterly YTD'!AF7-AM7 -> -136.973 | AO7: =IF(AND(AN7=0,AM7=0),0,IF(OR(AM7=0,AM7="NM",AN7="NM"),"NM",IF(AM7<0,(AN7/AM7-1),-(AN7/AM7-1)))) -> -0.035020853 | AP7: =IF(AND(AN7=0,AJ7=0),0,IF(OR(AJ7=0,AJ7="NM",AN7="NM"),"NM",IF(AJ7<0,(AN7/AJ7-1),-(AN7/AJ7-1)))) -> 0.09021952
A8: Other operating expenses | B8: -22.952 | C8: -34.741 | D8: -46.596 | E8: -68.488 | F8: -79.919 | G8: -97.36 | H8: -121.492 | I8: -127.501 | J8: =I8+'Quarterly YTD'!AF8-'Quarterly YTD'!AB8 -> -124.382 | K8: -5.566 | L8: ='Quarterly YTD'!D8-K8 -> -6.585 | M8: ='Quarterly YTD'!E8-'Quarterly YTD'!D8 -> -6.353 | N8: =C8-'Quarterly YTD'!E8 -> -16.237 | O8: -12.328 | P8: ='Quarterly YTD'!H8-O8 -> -9.956 | Q8: ='Quarterly YTD'!I8-'Quarterly YTD'!H8 -> -10.507 | R8: =D8-'Quarterly YTD'!I8 -> -13.805 | S8: -11.52 | T8: ='Quarterly YTD'!L8-S8 -> -12.516 | U8: ='Quarterly YTD'!M8-'Quarterly YTD'!L8 -> -14.059 | V8: =E8-'Quarterly YTD'!M8 -> -30.393 | W8: -17.336 | X8: ='Quarterly YTD'!P8-W8 -> -17.552 | Y8: ='Quarterly YTD'!Q8-'Quarterly YTD'!P8 -> -23.516 | Z8: =F8-'Quarterly YTD'!Q8 -> -21.515 | AA8: -21.85 | AB8: ='Quarterly YTD'!T8-AA8 -> -19.899 | AC8: ='Quarterly YTD'!U8-'Quarterly YTD'!T8 -> -24.453 | AD8: =G8-'Quarterly YTD'!U8 -> -31.158 | AE8: -32.188 | AF8: ='Quarterly YTD'!X8-AE8 -> -31.398 | AG8: ='Quarterly YTD'!Y8-'Quarterly YTD'!X8 -> -34.249 | AH8: =H8-'Quarterly YTD'!Y8 -> -23.657 | AI8: -33.392 | AJ8: ='Quarterly YTD'!AB8-AI8 -> -23.246 | AK8: ='Quarterly YTD'!AC8-'Quarterly YTD'!AB8+12.706 -> -32.074 | AL8: =I8-'Quarterly YTD'!AC8 -> -26.083 | AM8: -26.695 | AN8: ='Quarterly YTD'!AF8-AM8 -> -26.824 | AO8: =IF(AND(AN8=0,AM8=0),0,IF(OR(AM8=0,AM8="NM",AN8="NM"),"NM",IF(AM8<0,(AN8/AM8-1),-(AN8/AM8-1)))) -> 0.0048323656 | AP8: =IF(AND(AN8=0,AJ8=0),0,IF(OR(AJ8=0,AJ8="NM",AN8="NM"),"NM",IF(AJ8<0,(AN8/AJ8-1),-(AN8/AJ8-1)))) -> 0.15391895
A9: (Increase)/decrease in the provision for impairment of financial assets | B9: -1.558 | C9: -1.389 | D9: -21.9 | E9: -12.438 | F9: -12.251 | G9: -0.919 | H9: -3.33 | I9: -159.559 | J9: =I9+'Quarterly YTD'!AF9-'Quarterly YTD'!AB9 -> -191.655 | K9: -0.219 | L9: ='Quarterly YTD'!D9-K9 -> 0.022 | M9: ='Quarterly YTD'!E9-'Quarterly YTD'!D9 -> -0.479 | N9: =C9-'Quarterly YTD'!E9 -> -0.713 | O9: -1.37 | P9: ='Quarterly YTD'!H9-O9 -> -6.218 | Q9: ='Quarterly YTD'!I9-'Quarterly YTD'!H9 -> -0.261 | R9: =D9-'Quarterly YTD'!I9 -> -14.051 | S9: -0.236 | T9: ='Quarterly YTD'!L9-S9 -> -1.563 | U9: ='Quarterly YTD'!M9-'Quarterly YTD'!L9 -> -0.6 | V9: =E9-'Quarterly YTD'!M9 -> -10.039 | W9: -9.311 | X9: ='Quarterly YTD'!P9-W9 -> -0.364 | Y9: ='Quarterly YTD'!Q9-'Quarterly YTD'!P9 -> 0.741 | Z9: =F9-'Quarterly YTD'!Q9 -> -3.317 | AA9: -0.133 | AB9: ='Quarterly YTD'!T9-AA9 -> 2.165 | AC9: ='Quarterly YTD'!U9-'Quarterly YTD'!T9 -> -1.828 | AD9: =G9-'Quarterly YTD'!U9 -> -1.123 | AE9: 1.105 | AF9: ='Quarterly YTD'!X9-AE9 -> -0.382 | AG9: ='Quarterly YTD'!Y9-'Quarterly YTD'!X9 -> -0.215 | AH9: =H9-'Quarterly YTD'!Y9 -> -3.838 | AI9: -2.974 | AJ9: ='Quarterly YTD'!AB9-AI9 -> 4.707 | AK9: ='Quarterly YTD'!AC9-'Quarterly YTD'!AB9+-6.357 -> -1.895 | AL9: =I9-'Quarterly YTD'!AC9 -> -165.754 | AM9: -1.113 | AN9: ='Quarterly YTD'!AF9-AM9 -> -29.25 | AO9: =IF(AND(AN9=0,AM9=0),0,IF(OR(AM9=0,AM9="NM",AN9="NM"),"NM",IF(AM9<0,(AN9/AM9-1),-(AN9/AM9-1)))) -> 25.280323 | AP9: =IF(AND(AN9=0,AJ9=0),0,IF(OR(AJ9=0,AJ9="NM",AN9="NM"),"NM",IF(AJ9<0,(AN9/AJ9-1),-(AN9/AJ9-1)))) -> 7.2141491
A10: (Increase)/decrease in the provision for impairment of non-financial assets | B10: -2.365 | C10: -3.536 | D10: -7.344 | E10: -5.714 | F10: -13.635 | G10: -3.303 | H10: -12.561 | I10: -4.535 | J10: =I10+'Quarterly YTD'!AF10-'Quarterly YTD'!AB10 -> -22.55 | K10: -0.407 | L10: ='Quarterly YTD'!D10-K10 -> -0.346 | M10: ='Quarterly YTD'!E10-'Quarterly YTD'!D10 -> -0.41 | N10: =C10-'Quarterly YTD'!E10 -> -2.373 | O10: -0.256 | P10: ='Quarterly YTD'!H10-O10 -> -2.263 | Q10: ='Quarterly YTD'!I10-'Quarterly YTD'!H10 -> -1.945 | R10: =D10-'Quarterly YTD'!I10 -> -2.88 | S10: -0.632 | T10: ='Quarterly YTD'!L10-S10 -> -0.624 | U10: ='Quarterly YTD'!M10-'Quarterly YTD'!L10 -> -0.335 | V10: =E10-'Quarterly YTD'!M10 -> -4.123 | W10: -6.106 | X10: ='Quarterly YTD'!P10-W10 -> 1.916 | Y10: ='Quarterly YTD'!Q10-'Quarterly YTD'!P10 -> -0.472 | Z10: =F10-'Quarterly YTD'!Q10 -> -8.973 | AA10: 0.017 | AB10: ='Quarterly YTD'!T10-AA10 -> -1.599 | AC10: ='Quarterly YTD'!U10-'Quarterly YTD'!T10 -> -0.426 | AD10: =G10-'Quarterly YTD'!U10 -> -1.295 | AE10: -0.82 | AF10: ='Quarterly YTD'!X10-AE10 -> -1.506 | AG10: ='Quarterly YTD'!Y10-'Quarterly YTD'!X10 -> -1.526 | AH10: =H10-'Quarterly YTD'!Y10 -> -8.709 | AI10: -0.225 | AJ10: ='Quarterly YTD'!AB10-AI10 -> 6.594 | AK10: ='Quarterly YTD'!AC10-'Quarterly YTD'!AB10+0.274 -> -4.774 | AL10: =I10-'Quarterly YTD'!AC10 -> -5.856 | AM10: -0.89 | AN10: ='Quarterly YTD'!AF10-AM10 -> -10.756 | AO10: =IF(AND(AN10=0,AM10=0),0,IF(OR(AM10=0,AM10="NM",AN10="NM"),"NM",IF(AM10<0,(AN10/AM10-1),-(AN10/AM10-1)))) -> 11.085393 | AP10: =IF(AND(AN10=0,AJ10=0),0,IF(OR(AJ10=0,AJ10="NM",AN10="NM"),"NM",IF(AJ10<0,(AN10/AJ10-1),-(AN10/AJ10-1)))) -> 2.6311799
A11: Other gains - net | B11: 0.016 | C11: 1.29 | D11: 12.021 | E11: 38.199 | F11: 27.045 | G11: 36.603 | H11: 3.219 | I11: 17.514 | J11: =I11+'Quarterly YTD'!AF11-'Quarterly YTD'!AB11 -> 26.043 | K11: 0.657 | L11: ='Quarterly YTD'!D11-K11 -> -0.068 | M11: ='Quarterly YTD'!E11-'Quarterly YTD'!D11 -> -0.132 | N11: =C11-'Quarterly YTD'!E11 -> 0.833 | O11: 0.377 | P11: ='Quarterly YTD'!H11-O11 -> 6.823 | Q11: ='Quarterly YTD'!I11-'Quarterly YTD'!H11 -> 3.439 | R11: =D11-'Quarterly YTD'!I11 -> 1.382 | S11: 13.473 | T11: ='Quarterly YTD'!L11-S11 -> 10.821 | U11: ='Quarterly YTD'!M11-'Quarterly YTD'!L11 -> 6.019 | V11: =E11-'Quarterly YTD'!M11 -> 7.886 | W11: 19.732 | X11: ='Quarterly YTD'!P11-W11 -> 7.784 | Y11: ='Quarterly YTD'!Q11-'Quarterly YTD'!P11 -> 14.526 | Z11: =F11-'Quarterly YTD'!Q11 -> -14.997 | AA11: 3.463 | AB11: ='Quarterly YTD'!T11-AA11 -> 3.992 | AC11: ='Quarterly YTD'!U11-'Quarterly YTD'!T11 -> 7.368 | AD11: =G11-'Quarterly YTD'!U11 -> 21.78 | AE11: 10.448 | AF11: ='Quarterly YTD'!X11-AE11 -> 5.899 | AG11: ='Quarterly YTD'!Y11-'Quarterly YTD'!X11 -> 2.2 | AH11: =H11-'Quarterly YTD'!Y11 -> -15.328 | AI11: -1.645 | AJ11: ='Quarterly YTD'!AB11-AI11 -> 3.756 | AK11: ='Quarterly YTD'!AC11-'Quarterly YTD'!AB11+-2.995 -> 4.889 | AL11: =I11-'Quarterly YTD'!AC11 -> 7.519 | AM11: 1.756 | AN11: ='Quarterly YTD'!AF11-AM11 -> 8.884 | AO11: =IF(AND(AN11=0,AM11=0),0,IF(OR(AM11=0,AM11="NM",AN11="NM"),"NM",IF(AM11<0,-(AN11/AM11-1),AN11/AM11-1))) -> 4.0592255 | AP11: =IF(AND(AN11=0,AJ11=0),0,IF(OR(AJ11=0,AJ11="NM",AN11="NM"),"NM",IF(AJ11<0,-(AN11/AJ11-1),AN11/AJ11-1))) -> 1.3652822
A12: Operating (loss)/profit | B12: =SUM(B3:B11) -> 14.538 | C12: =SUM(C3:C11) -> 25.767 | D12: =SUM(D3:D11) -> -18.235 | E12: =SUM(E3:E11) -> 79.97 | F12: =SUM(F3:F11) -> 161.977 | G12: =SUM(G3:G11) -> 159.657 | H12: =SUM(H3:H11) -> 93.105 | I12: =SUM(I3:I11) -> -66.496 | J12: =I12+'Quarterly YTD'!AF12-'Quarterly YTD'!AB12 -> -153.125 | K12: =SUM(K3:K11) -> 2.201 | L12: =SUM(L3:L11) -> 4.721 | M12: =SUM(M3:M11) -> 3.554 | N12: =SUM(N3:N11) -> 15.291 | O12: =SUM(O3:O11) -> 3.438 | P12: =SUM(P3:P11) -> 9.611 | Q12: =SUM(Q3:Q11) -> -9.677 | R12: =SUM(R3:R11) -> -21.607 | ... AN12: =SUM(AN3:AN11) -> -26.147 | AO12: =IF(AND(AN12=0,AM12=0),0,IF(OR(AM12=0,AM12="NM",AN12="NM"),"NM",IF(AM12<0,-(AN12/AM12-1),AN12/AM12-1))) -> 0.42219128 | AP12: =IF(AND(AN12=0,AJ12=0),0,IF(OR(AJ12=0,AJ12="NM",AN12="NM"),"NM",IF(AJ12<0,-(AN12/AJ12-1),AN12/AJ12-1))) -> -1.3372283
A13: Finance income | B13: 0.067 | C13: 3.05 | D13: 12.271 | E13: 2.919 | F13: 3.901 | G13: 24.747 | H13: 58.254 | I13: 15.295 | J13: =I13+'Quarterly YTD'!AF13-'Quarterly YTD'!AB13 -> -2.247 | K13: 0.003 | L13: ='Quarterly YTD'!D13-K13 -> 0.029 | M13: ='Quarterly YTD'!E13-'Quarterly YTD'!D13 -> 0.324 | N13: =C13-'Quarterly YTD'!E13 -> 2.694 | O13: 1.059 | P13: ='Quarterly YTD'!H13-O13 -> 4.12 | Q13: ='Quarterly YTD'!I13-'Quarterly YTD'!H13 -> -0.444 | R13: =D13-'Quarterly YTD'!I13 -> 7.536 | S13: 2.403 | T13: ='Quarterly YTD'!L13-S13 -> 0.767 | U13: ='Quarterly YTD'!M13-'Quarterly YTD'!L13 -> -0.503 | V13: =E13-'Quarterly YTD'!M13 -> 0.252 | W13: 0.094 | X13: ='Quarterly YTD'!P13-W13 -> 0.098 | Y13: ='Quarterly YTD'!Q13-'Quarterly YTD'!P13 -> 2.105 | Z13: =F13-'Quarterly YTD'!Q13 -> 1.604 | AA13: 6.358 | AB13: ='Quarterly YTD'!T13-AA13 -> 0.726 | AC13: ='Quarterly YTD'!U13-'Quarterly YTD'!T13 -> -2.508 | AD13: =G13-'Quarterly YTD'!U13 -> 20.171 | AE13: 0.593 | AF13: ='Quarterly YTD'!X13-AE13 -> 54.219 | AG13: ='Quarterly YTD'!Y13-'Quarterly YTD'!X13 -> 9.149 | AH13: =H13-'Quarterly YTD'!Y13 -> -5.707 | AI13: 7.109 | AJ13: ='Quarterly YTD'!AB13-AI13 -> 11.567 | AK13: ='Quarterly YTD'!AC13-'Quarterly YTD'!AB13+-2.071 -> 0.33 | AL13: =I13-'Quarterly YTD'!AC13 -> -5.782 | AM13: 0.412 | AN13: ='Quarterly YTD'!AF13-AM13 -> 0.722 | AO13: =IF(AND(AN13=0,AM13=0),0,IF(OR(AM13=0,AM13="NM",AN13="NM"),"NM",IF(AM13<0,-(AN13/AM13-1),AN13/AM13-1))) -> 0.75242718 | AP13: =IF(AND(AN13=0,AJ13=0),0,IF(OR(AJ13=0,AJ13="NM",AN13="NM"),"NM",IF(AJ13<0,-(AN13/AJ13-1),AN13/AJ13-1))) -> -0.93758105
A14: Finance costs | B14: -1.962 | C14: -9.948 | D14: -38.655 | E14: -39.719 | F14: -83.341 | G14: -114.979 | H14: -92.387 | I14: -93.369 | J14: =I14+'Quarterly YTD'!AF14-'Quarterly YTD'!AB14 -> -97.204 | K14: -1.155 | L14: ='Quarterly YTD'!D14-K14 -> -0.876 | M14: ='Quarterly YTD'!E14-'Quarterly YTD'!D14 -> -1.34 | N14: =C14-'Quarterly YTD'!E14 -> -6.577 | O14: -10.943 | P14: ='Quarterly YTD'!H14-O14 -> -9.827 | Q14: ='Quarterly YTD'!I14-'Quarterly YTD'!H14 -> -10.166 | R14: =D14-'Quarterly YTD'!I14 -> -7.719 | S14: -8.494 | T14: ='Quarterly YTD'!L14-S14 -> -7.849 | U14: ='Quarterly YTD'!M14-'Quarterly YTD'!L14 -> -10.5 | V14: =E14-'Quarterly YTD'!M14 -> -12.876 | W14: -18.259 | X14: ='Quarterly YTD'!P14-W14 -> -22.488 | Y14: ='Quarterly YTD'!Q14-'Quarterly YTD'!P14 -> -35.845 | Z14: =F14-'Quarterly YTD'!Q14 -> -6.749 | AA14: -24.175 | AB14: ='Quarterly YTD'!T14-AA14 -> -26.558 | AC14: ='Quarterly YTD'!U14-'Quarterly YTD'!T14 -> -34.404 | AD14: =G14-'Quarterly YTD'!U14 -> -29.842 | AE14: -41.744 | AF14: ='Quarterly YTD'!X14-AE14 -> -27.3 | AG14: ='Quarterly YTD'!Y14-'Quarterly YTD'!X14 -> -35.932 | AH14: =H14-'Quarterly YTD'!Y14 -> 12.589 | AI14: -23.988 | AJ14: ='Quarterly YTD'!AB14-AI14 -> -16.27 | AK14: ='Quarterly YTD'!AC14-'Quarterly YTD'!AB14+25.892 -> -27.691 | AL14: =I14-'Quarterly YTD'!AC14 -> 0.472 | AM14: -23.556 | AN14: ='Quarterly YTD'!AF14-AM14 -> -20.537 | AO14: =IF(AND(AN14=0,AM14=0),0,IF(OR(AM14=0,AM14="NM",AN14="NM"),"NM",IF(AM14<0,(AN14/AM14-1),-(AN14/AM14-1)))) -> -0.12816268 | AP14: =IF(AND(AN14=0,AJ14=0),0,IF(OR(AJ14=0,AJ14="NM",AN14="NM"),"NM",IF(AJ14<0,(AN14/AJ14-1),-(AN14/AJ14-1)))) -> 0.26226183
A15: Finance costs – net | B15: =SUM(B13:B14) -> -1.895 | C15: =SUM(C13:C14) -> -6.898 | D15: =SUM(D13:D14) -> -26.384 | E15: =SUM(E13:E14) -> -36.8 | F15: =SUM(F13:F14) -> -79.44 | G15: =SUM(G13:G14) -> -90.232 | H15: =SUM(H13:H14) -> -34.133 | I15: =SUM(I13:I14) -> -78.074 | ... AN15: =SUM(AN13:AN14) -> -19.815 | AO15: =IF(AND(AN15=0,AM15=0),0,IF(OR(AM15=0,AM15="NM",AN15="NM"),"NM",IF(AM15<0,(AN15/AM15-1),-(AN15/AM15-1)))) -> -0.14383858 | AP15: =IF(AND(AN15=0,AJ15=0),0,IF(OR(AJ15=0,AJ15="NM",AN15="NM"),"NM",IF(AJ15<0,(AN15/AJ15-1),-(AN15/AJ15-1)))) -> 3.2132681
A16: Share of profit of equity-accounted investees | B16: 0 | C16: -1.027 | D16: -1.19 | E16: 1.458 | F16: -55.091 | G16: 2.706 | H16: 0.013 | I16: -0.255 | J16: =I16+'Quarterly YTD'!AF16-'Quarterly YTD'!AB16 -> -0.262 | K16: -0.054 | L16: ='Quarterly YTD'!D16-K16 -> -0.025 | M16: ='Quarterly YTD'!E16-'Quarterly YTD'!D16 -> -0.859 | N16: =C16-'Quarterly YTD'!E16 -> -0.089 | O16: 0.84 | P16: ='Quarterly YTD'!H16-O16 -> 1.009 | Q16: ='Quarterly YTD'!I16-'Quarterly YTD'!H16 -> 1.562 | R16: =D16-'Quarterly YTD'!I16 -> -4.601 | S16: 0.022 | T16: ='Quarterly YTD'!L16-S16 -> -0.004 | U16: ='Quarterly YTD'!M16-'Quarterly YTD'!L16 -> -0.067 | V16: =E16-'Quarterly YTD'!M16 -> 1.507 | W16: 0.023 | X16: ='Quarterly YTD'!P16-W16 -> -0.03 | Y16: ='Quarterly YTD'!Q16-'Quarterly YTD'!P16 -> -0.006 | Z16: =F16-'Quarterly YTD'!Q16 -> -55.078 | AA16: 0.004 | AB16: ='Quarterly YTD'!T16-AA16 -> 2.093 | AC16: ='Quarterly YTD'!U16-'Quarterly YTD'!T16 -> 0.381 | AD16: =G16-'Quarterly YTD'!U16 -> 0.228 | AE16: 0.004 | AF16: ='Quarterly YTD'!X16-AE16 -> 0 | AG16: ='Quarterly YTD'!Y16-'Quarterly YTD'!X16 -> 0.001 | AH16: =H16-'Quarterly YTD'!Y16 -> 0.008 | AI16: 0 | AJ16: ='Quarterly YTD'!AB16-AI16 -> 0.012 | AK16: ='Quarterly YTD'!AC16-'Quarterly YTD'!AB16 -> 0 | AL16: =I16-'Quarterly YTD'!AC16 -> -0.267 | AM16: 0 | AN16: ='Quarterly YTD'!AF16-AM16 -> 0.005 | AO16: =IF(AND(AN16=0,AM16=0),0,IF(OR(AM16=0,AM16="NM",AN16="NM"),"NM",IF(AM16<0,-(AN16/AM16-1),AN16/AM16-1))) -> NM | AP16: =IF(AND(AN16=0,AJ16=0),0,IF(OR(AJ16=0,AJ16="NM",AN16="NM"),"NM",IF(AJ16<0,-(AN16/AJ16-1),AN16/AJ16-1))) -> -0.58333333
A17: Loss before income tax | B17: =B12+SUM(B15:B16) -> 12.643 | C17: =C12+SUM(C15:C16) -> 17.842 | D17: =D12+SUM(D15:D16) -> -45.809 | E17: =E12+SUM(E15:E16) -> 44.628 | F17: =F12+SUM(F15:F16) -> 27.446 | G17: =G12+SUM(G15:G16) -> 72.131 | H17: =H12+SUM(H15:H16) -> 58.985 | I17: =I12+SUM(I15:I16) -> -144.825 | ... AN17: =AN12+SUM(AN15:AN16) -> -45.957 | AO17: =IF(AND(AN17=0,AM17=0),0,IF(OR(AM17=0,AM17="NM",AN17="NM"),"NM",IF(AM17<0,-(AN17/AM17-1),AN17/AM17-1))) -> 0.32807474 | AP17: =IF(AND(AN17=0,AJ17=0),0,IF(OR(AJ17=0,AJ17="NM",AN17="NM"),"NM",IF(AJ17<0,-(AN17/AJ17-1),AN17/AJ17-1))) -> -1.6308962
A18: Income tax credit | B18: -2.952 | C18: -5.712 | D18: -5.796 | E18: -10.26 | F18: -15.779 | G18: -3.945 | H18: -4.73 | I18: -0.124 | J18: =I18+'Quarterly YTD'!AF18-'Quarterly YTD'!AB18 -> 9.975 | K18: -0.408 | L18: ='Quarterly YTD'!D18-K18 -> -0.799 | M18: ='Quarterly YTD'!E18-'Quarterly YTD'!D18 -> -0.529 | N18: =C18-'Quarterly YTD'!E18 -> -3.976 | O18: -1.795 | P18: ='Quarterly YTD'!H18-O18 -> -4.259 | Q18: ='Quarterly YTD'!I18-'Quarterly YTD'!H18 -> 0.902 | R18: =D18-'Quarterly YTD'!I18 -> -0.644 | S18: -4.202 | T18: ='Quarterly YTD'!L18-S18 -> 3.819 | U18: ='Quarterly YTD'!M18-'Quarterly YTD'!L18 -> -3.74 | V18: =E18-'Quarterly YTD'!M18 -> -6.137 | W18: -3.154 | X18: ='Quarterly YTD'!P18-W18 -> -6.655 | Y18: ='Quarterly YTD'!Q18-'Quarterly YTD'!P18 -> -10.666 | Z18: =F18-'Quarterly YTD'!Q18 -> 4.696 | AA18: 3 | AB18: ='Quarterly YTD'!T18-AA18 -> -7.123 | AC18: ='Quarterly YTD'!U18-'Quarterly YTD'!T18 -> -7.781 | AD18: =G18-'Quarterly YTD'!U18 -> 7.959 | AE18: 12.94 | AF18: ='Quarterly YTD'!X18-AE18 -> -7.471 | AG18: ='Quarterly YTD'!Y18-'Quarterly YTD'!X18 -> -22.827 | AH18: =H18-'Quarterly YTD'!Y18 -> 12.628 | AI18: 16.991 | AJ18: ='Quarterly YTD'!AB18-AI18 -> -15.524 | AK18: ='Quarterly YTD'!AC18-'Quarterly YTD'!AB18+-0.41 -> -20.878 | AL18: =I18-'Quarterly YTD'!AC18 -> 18.877 | AM18: 8.482 | AN18: ='Quarterly YTD'!AF18-AM18 -> 3.084 | AO18: =IF(AND(AN18=0,AM18=0),0,IF(OR(AM18=0,AM18="NM",AN18="NM"),"NM",IF(AM18<0,(AN18/AM18-1),-(AN18/AM18-1)))) -> 0.63640651 | AP18: =IF(AND(AN18=0,AJ18=0),0,IF(OR(AJ18=0,AJ18="NM",AN18="NM"),"NM",IF(AJ18<0,(AN18/AJ18-1),-(AN18/AJ18-1)))) -> -1.1986601
A19: Loss for the period | B19: =SUM(B17:B18) -> 9.691 | C19: =SUM(C17:C18) -> 12.13 | D19: =SUM(D17:D18) -> -51.605 | E19: =SUM(E17:E18) -> 34.368 | F19: =SUM(F17:F18) -> 11.667 | G19: =SUM(G17:G18) -> 68.186 | H19: =SUM(H17:H18) -> 54.255 | I19: =SUM(I17:I18) -> -144.949 | ... AN19: =SUM(AN17:AN18) -> -42.873 | AO19: =IF(AND(AN19=0,AM19=0),0,IF(OR(AM19=0,AM19="NM",AN19="NM"),"NM",IF(AM19<0,-(AN19/AM19-1),AN19/AM19-1))) -> 0.28442434 | AP19: =IF(AND(AN19=0,AJ19=0),0,IF(OR(AJ19=0,AJ19="NM",AN19="NM"),"NM",IF(AJ19<0,-(AN19/AJ19-1),AN19/AJ19-1))) -> -1.7479588
A20: Gain/(loss) for the period from discontinued operations | B20: 0 | C20: 0 | D20: 0 | E20: 0 | F20: 0 | G20: 0 | H20: -116.838 | I20: 81.382 | J20: =I20+'Quarterly YTD'!AF20-'Quarterly YTD'!AB20 -> 208.488 | K20: 0 | L20: ='Quarterly YTD'!D20-K20 -> 0 | M20: ='Quarterly YTD'!E20-'Quarterly YTD'!D20 -> 0 | N20: =C20-'Quarterly YTD'!E20 -> 0 | O20: 0 | P20: ='Quarterly YTD'!H20-O20 -> 0 | Q20: ='Quarterly YTD'!I20-'Quarterly YTD'!H20 -> 0 | R20: =D20-'Quarterly YTD'!I20 -> 0 | S20: 0 | T20: ='Quarterly YTD'!L20-S20 -> 0 | U20: ='Quarterly YTD'!M20-'Quarterly YTD'!L20 -> 0 | V20: =E20-'Quarterly YTD'!M20 -> 0 | W20: 0 | X20: ='Quarterly YTD'!P20-W20 -> 0 | Y20: ='Quarterly YTD'!Q20-'Quarterly YTD'!P20 -> 0 | Z20: =F20-'Quarterly YTD'!Q20 -> 0 | AA20: 0 | AB20: ='Quarterly YTD'!T20-AA20 -> 0 | AC20: ='Quarterly YTD'!U20-'Quarterly YTD'!T20 -> 0 | AD20: =G20-'Quarterly YTD'!U20 -> 0 | AE20: 0 | AF20: ='Quarterly YTD'!X20-AE20 -> 0 | AG20: ='Quarterly YTD'!Y20-'Quarterly YTD'!X20 -> 0 | AH20: =H20-'Quarterly YTD'!Y20 -> -116.838 | AI20: -59.905 | AJ20: ='Quarterly YTD'!AB20-AI20 -> -46.247 | AK20: ='Quarterly YTD'!AC20-'Quarterly YTD'!AB20+-106.152 -> 0 | AL20: =I20-'Quarterly YTD'!AC20 -> 81.382 | AM20: 0 | AN20: ='Quarterly YTD'!AF20-AM20 -> 20.954 | AO20: =IF(AND(AN20=0,AM20=0),0,IF(OR(AM20=0,AM20="NM",AN20="NM"),"NM",IF(AM20<0,-(AN20/AM20-1),AN20/AM20-1))) -> NM | AP20: =IF(AND(AN20=0,AJ20=0),0,IF(OR(AJ20=0,AJ20="NM",AN20="NM"),"NM",IF(AJ20<0,-(AN20/AJ20-1),AN20/AJ20-1))) -> 1.4530888
A21: Loss for the period | B21: =SUM(B19:B20) -> 9.691 | C21: =C19 -> 12.13 | D21: =D19 -> -51.605 | E21: =E19 -> 34.368 | F21: =F19 -> 11.667 | G21: =G19 -> 68.186 | H21: =SUM(H19:H20) -> -62.583 | I21: =SUM(I19:I20) -> -63.567 | J21: =SUM(J19:J20) -> -34.375 | K21: =K19 -> 0.587 | L21: =SUM(L19:L20) -> 3.05 | M21: =SUM(M19:M20) -> 1.15 | N21: =SUM(N19:N20) -> 7.343 | O21: =O19 -> -7.401 | P21: =SUM(P19:P20) -> 0.654 | Q21: =SUM(Q19:Q20) -> -17.823 | R21: =SUM(R19:R20) -> -27.035 | S21: =S19 -> 1.754 | T21: =SUM(T19:T20) -> 12.833 | U21: =SUM(U19:U20) -> 22.055 | V21: =SUM(V19:V20) -> -2.274 | W21: =W19 -> -12.967 | X21: =SUM(X19:X20) -> 18.052 | Y21: =SUM(Y19:Y20) -> 50.164 | Z21: =SUM(Z19:Z20) -> -43.582 | AA21: =AA19 -> -33.541 | AB21: =SUM(AB19:AB20) -> 30.61 | AC21: =SUM(AC19:AC20) -> 73.72 | AD21: =SUM(AD19:AD20) -> -2.603 | AE21: =AE19 -> -97.555 | AF21: =SUM(AF19:AF20) -> 96.526 | AG21: =SUM(AG19:AG20) -> 84.355 | AH21: =SUM(AH19:AH20) -> -145.909 | AI21: =SUM(AI19:AI20) -> -122.098 | AJ21: =SUM(AJ19:AJ20) -> 11.073 | AK21: =SUM(AK19:AK20) -> 70.983 | AL21: =SUM(AL19:AL20) -> -23.525 | AM21: =SUM(AM19:AM20) -> -59.914 | AN21: =SUM(AN19:AN20) -> -21.919 | AO21: =IF(AND(AN21=0,AM21=0),0,IF(OR(AM21=0,AM21="NM",AN21="NM"),"NM",IF(AM21<0,-(AN21/AM21-1),AN21/AM21-1))) -> 0.63415896 | AP21: =IF(AND(AN21=0,AJ21=0),0,IF(OR(AJ21=0,AJ21="NM",AN21="NM"),"NM",IF(AJ21<0,-(AN21/AJ21-1),AN21/AJ21-1))) -> -2.9794997
A23: Cash Flow Statement
A24: Loss for the period | B24: 9.691 | C24: 12.13 | D24: -51.605 | E24: 34.368 | F24: 11.667 | G24: 68.186 | H24: -62.583 | I24: -63.567 | J24: =I24+'Quarterly YTD'!AF24-'Quarterly YTD'!AB24 -> -34.375 | K24: 0.587 | L24: ='Quarterly YTD'!D24-K24 -> 3.05 | M24: ='Quarterly YTD'!E24-'Quarterly YTD'!D24 -> 1.15 | N24: =C24-'Quarterly YTD'!E24 -> 7.343 | O24: -7.401 | P24: ='Quarterly YTD'!H24-O24 -> 0.654 | Q24: ='Quarterly YTD'!I24-'Quarterly YTD'!H24 -> -17.823 | R24: =D24-'Quarterly YTD'!I24 -> -27.035 | S24: 1.754 | T24: ='Quarterly YTD'!L24-S24 -> 12.833 | U24: ='Quarterly YTD'!M24-'Quarterly YTD'!L24 -> 22.055 | V24: =E24-'Quarterly YTD'!M24 -> -2.274 | W24: -12.967 | X24: ='Quarterly YTD'!P24-W24 -> 18.052 | Y24: ='Quarterly YTD'!Q24-'Quarterly YTD'!P24 -> 50.164 | Z24: =F24-'Quarterly YTD'!Q24 -> -43.582 | AA24: -33.541 | AB24: ='Quarterly YTD'!T24-AA24 -> 30.61 | AC24: ='Quarterly YTD'!U24-'Quarterly YTD'!T24 -> 73.72 | AD24: =G24-'Quarterly YTD'!U24 -> -2.603 | AE24: -97.555 | AF24: ='Quarterly YTD'!X24-AE24 -> 96.525 | AG24: ='Quarterly YTD'!Y24-'Quarterly YTD'!X24 -> 84.356 | AH24: =H24-'Quarterly YTD'!Y24 -> -145.909 | AI24: -122.098 | AJ24: ='Quarterly YTD'!AB24-AI24 -> 11.073 | AK24: ='Quarterly YTD'!AC24-'Quarterly YTD'!AB24 -> 70.983 | AL24: =I24-'Quarterly YTD'!AC24 -> -23.525 | AM24: -59.914 | AN24: ='Quarterly YTD'!AF24-AM24 -> -21.919
A25: Income tax (credit) | B25: 2.952 | C25: 5.712 | D25: 5.796 | E25: 10.26 | F25: 15.779 | G25: 3.945 | H25: -2.197 | I25: 3.712 | J25: =I25+'Quarterly YTD'!AF25-'Quarterly YTD'!AB25 -> -1.707 | K25: 0.408 | L25: ='Quarterly YTD'!D25-K25 -> 0.799 | M25: ='Quarterly YTD'!E25-'Quarterly YTD'!D25 -> 0.529 | N25: =C25-'Quarterly YTD'!E25 -> 3.976 | O25: 1.795 | P25: ='Quarterly YTD'!H25-O25 -> 4.259 | Q25: ='Quarterly YTD'!I25-'Quarterly YTD'!H25 -> -0.902 | R25: =D25-'Quarterly YTD'!I25 -> 0.644 | S25: 4.202 | T25: ='Quarterly YTD'!L25-S25 -> -3.819 | U25: ='Quarterly YTD'!M25-'Quarterly YTD'!L25 -> 3.74 | V25: =E25-'Quarterly YTD'!M25 -> 6.137 | W25: 3.154 | X25: ='Quarterly YTD'!P25-W25 -> 6.655 | Y25: ='Quarterly YTD'!Q25-'Quarterly YTD'!P25 -> 10.666 | Z25: =F25-'Quarterly YTD'!Q25 -> -4.696 | AA25: -3 | AB25: ='Quarterly YTD'!T25-AA25 -> 7.123 | AC25: ='Quarterly YTD'!U25-'Quarterly YTD'!T25 -> 7.781 | AD25: =G25-'Quarterly YTD'!U25 -> -7.959 | AE25: -12.94 | AF25: ='Quarterly YTD'!X25-AE25 -> 7.471 | AG25: ='Quarterly YTD'!Y25-'Quarterly YTD'!X25 -> 22.827 | AH25: =H25-'Quarterly YTD'!Y25 -> -19.555 | AI25: -16.582 | AJ25: ='Quarterly YTD'!AB25-AI25 -> 14.705 | AK25: ='Quarterly YTD'!AC25-'Quarterly YTD'!AB25 -> 20.878 | AL25: =I25-'Quarterly YTD'!AC25 -> -15.289 | AM25: -8.482 | AN25: ='Quarterly YTD'!AF25-AM25 -> 1.186
A26: Depreciation and amortisation | B26: 6.853 | C26: 34.732 | D26: 99.205 | E26: 74.338 | F26: 114.781 | G26: 239.28 | H26: 364.599 | I26: 353.946 | J26: =I26+'Quarterly YTD'!AF26-'Quarterly YTD'!AB26 -> 292.857 | K26: 2.936 | L26: ='Quarterly YTD'!D26-K26 -> 3.23 | M26: ='Quarterly YTD'!E26-'Quarterly YTD'!D26 -> 3.427 | N26: =C26-'Quarterly YTD'!E26 -> 25.139 | O26: 26.639 | P26: ='Quarterly YTD'!H26-O26 -> 26.592 | Q26: ='Quarterly YTD'!I26-'Quarterly YTD'!H26 -> 24.388 | R26: =D26-'Quarterly YTD'!I26 -> 21.586 | S26: 18.04 | T26: ='Quarterly YTD'!L26-S26 -> 17.06 | U26: ='Quarterly YTD'!M26-'Quarterly YTD'!L26 -> 19.107 | V26: =E26-'Quarterly YTD'!M26 -> 20.131 | W26: 21.68 | X26: ='Quarterly YTD'!P26-W26 -> 26.51 | Y26: ='Quarterly YTD'!Q26-'Quarterly YTD'!P26 -> 36.201 | Z26: =F26-'Quarterly YTD'!Q26 -> 30.39 | AA26: 41.974 | AB26: ='Quarterly YTD'!T26-AA26 -> 50.043 | AC26: ='Quarterly YTD'!U26-'Quarterly YTD'!T26 -> 64.571 | AD26: =G26-'Quarterly YTD'!U26 -> 82.692 | AE26: 81.707 | AF26: ='Quarterly YTD'!X26-AE26 -> 89.611 | AG26: ='Quarterly YTD'!Y26-'Quarterly YTD'!X26 -> 93.959 | AH26: =H26-'Quarterly YTD'!Y26 -> 99.322 | AI26: 102.318 | AJ26: ='Quarterly YTD'!AB26-AI26 -> 90.515 | AK26: ='Quarterly YTD'!AC26-'Quarterly YTD'!AB26 -> 91.364 | AL26: =I26-'Quarterly YTD'!AC26 -> 69.749 | AM26: 72.539 | AN26: ='Quarterly YTD'!AF26-AM26 -> 59.205
A27: Increase/(decrease) in the provision for impairment of financial and non-financial assets | B27: 3.923 | C27: 4.925 | D27: 29.244 | E27: 18.152 | F27: 25.886 | G27: 4.222 | H27: 64.234 | I27: 161.607 | J27: =I27+'Quarterly YTD'!AF27-'Quarterly YTD'!AB27 -> 225.411 | K27: 0.626 | L27: ='Quarterly YTD'!D27-K27 -> 0.324 | M27: ='Quarterly YTD'!E27-'Quarterly YTD'!D27 -> 0.889 | N27: =C27-'Quarterly YTD'!E27 -> 3.086 | O27: 1.626 | P27: ='Quarterly YTD'!H27-O27 -> 8.481 | Q27: ='Quarterly YTD'!I27-'Quarterly YTD'!H27 -> 2.206 | R27: =D27-'Quarterly YTD'!I27 -> 16.931 | S27: 0.868 | T27: ='Quarterly YTD'!L27-S27 -> 2.187 | U27: ='Quarterly YTD'!M27-'Quarterly YTD'!L27 -> 0.935 | V27: =E27-'Quarterly YTD'!M27 -> 14.162 | W27: 15.417 | X27: ='Quarterly YTD'!P27-W27 -> -1.552 | Y27: ='Quarterly YTD'!Q27-'Quarterly YTD'!P27 -> -0.269 | Z27: =F27-'Quarterly YTD'!Q27 -> 12.29 | AA27: 0.116 | AB27: ='Quarterly YTD'!T27-AA27 -> -0.566 | AC27: ='Quarterly YTD'!U27-'Quarterly YTD'!T27 -> 2.254 | AD27: =G27-'Quarterly YTD'!U27 -> 2.418 | AE27: -0.285 | AF27: ='Quarterly YTD'!X27-AE27 -> 1.888 | AG27: ='Quarterly YTD'!Y27-'Quarterly YTD'!X27 -> 1.741 | AH27: =H27-'Quarterly YTD'!Y27 -> 60.89 | AI27: -3.851 | AJ27: ='Quarterly YTD'!AB27-AI27 -> -10.334 | AK27: ='Quarterly YTD'!AC27-'Quarterly YTD'!AB27 -> 6.669 | AL27: =I27-'Quarterly YTD'!AC27 -> 169.123 | AM27: 2.003 | AN27: ='Quarterly YTD'!AF27-AM27 -> 47.616
A28: Interest expenses | B28: 1.512 | C28: 8.969 | D28: 38.784 | E28: 33.432 | F28: 47.69 | G28: 82.481 | H28: 137.997 | I28: 114.609 | J28: =I28+'Quarterly YTD'!AF28-'Quarterly YTD'!AB28 -> 93.373 | K28: 0.833 | L28: ='Quarterly YTD'!D28-K28 -> 0.83 | M28: ='Quarterly YTD'!E28-'Quarterly YTD'!D28 -> 0.975 | N28: =C28-'Quarterly YTD'!E28 -> 6.331 | O28: 9.986 | P28: ='Quarterly YTD'!H28-O28 -> 9.192 | Q28: ='Quarterly YTD'!I28-'Quarterly YTD'!H28 -> 10.406 | R28: =D28-'Quarterly YTD'!I28 -> 9.2 | S28: 8.209 | T28: ='Quarterly YTD'!L28-S28 -> 7.375 | U28: ='Quarterly YTD'!M28-'Quarterly YTD'!L28 -> 9.239 | V28: =E28-'Quarterly YTD'!M28 -> 8.609 | W28: 10.146 | X28: ='Quarterly YTD'!P28-W28 -> 11.42 | Y28: ='Quarterly YTD'!Q28-'Quarterly YTD'!P28 -> 13.087 | Z28: =F28-'Quarterly YTD'!Q28 -> 13.037 | AA28: 16.243 | AB28: ='Quarterly YTD'!T28-AA28 -> 18.467 | AC28: ='Quarterly YTD'!U28-'Quarterly YTD'!T28 -> 23.285 | AD28: =G28-'Quarterly YTD'!U28 -> 24.486 | AE28: 29.16 | AF28: ='Quarterly YTD'!X28-AE28 -> 35.895 | AG28: ='Quarterly YTD'!Y28-'Quarterly YTD'!X28 -> 36.123 | AH28: =H28-'Quarterly YTD'!Y28 -> 36.819 | AI28: 35.468 | AJ28: ='Quarterly YTD'!AB28-AI28 -> 29.417 | AK28: ='Quarterly YTD'!AC28-'Quarterly YTD'!AB28 -> 27.632 | AL28: =I28-'Quarterly YTD'!AC28 -> 22.092 | AM28: 22.628 | AN28: ='Quarterly YTD'!AF28-AM28 -> 21.021
A29: Foreign exchange loss | B29: -0.04 | C29: -2.354 | D29: -15.434 | E29: 14.492 | F29: 7.001 | G29: -16.743 | H29: 7.308 | I29: -11.84 | J29: =I29+'Quarterly YTD'!AF29-'Quarterly YTD'!AB29 -> 2.802 | K29: 0.352 | L29: ='Quarterly YTD'!D29-K29 -> -0.549 | M29: ='Quarterly YTD'!E29-'Quarterly YTD'!D29 -> 0.359 | N29: =C29-'Quarterly YTD'!E29 -> -2.516 | O29: 2.687 | P29: ='Quarterly YTD'!H29-O29 -> -3.103 | Q29: ='Quarterly YTD'!I29-'Quarterly YTD'!H29 -> -4.435 | R29: =D29-'Quarterly YTD'!I29 -> -10.583 | S29: 6.477 | T29: ='Quarterly YTD'!L29-S29 -> -3.794 | U29: ='Quarterly YTD'!M29-'Quarterly YTD'!L29 -> 4.813 | V29: =E29-'Quarterly YTD'!M29 -> 6.996 | W29: 0.659 | X29: ='Quarterly YTD'!P29-W29 -> 18.179 | Y29: ='Quarterly YTD'!Q29-'Quarterly YTD'!P29 -> 26.379 | Z29: =F29-'Quarterly YTD'!Q29 -> -38.216 | AA29: -8.876 | AB29: ='Quarterly YTD'!T29-AA29 -> 4.988 | AC29: ='Quarterly YTD'!U29-'Quarterly YTD'!T29 -> 10.772 | AD29: =G29-'Quarterly YTD'!U29 -> -23.627 | AE29: 3.824 | AF29: ='Quarterly YTD'!X29-AE29 -> 1.755 | AG29: ='Quarterly YTD'!Y29-'Quarterly YTD'!X29 -> -12.949 | AH29: =H29-'Quarterly YTD'!Y29 -> 14.678 | AI29: 1.148 | AJ29: ='Quarterly YTD'!AB29-AI29 -> -12.753 | AK29: ='Quarterly YTD'!AC29-'Quarterly YTD'!AB29 -> -2.11 | AL29: =I29-'Quarterly YTD'!AC29 -> 1.875 | AM29: 1.791 | AN29: ='Quarterly YTD'!AF29-AM29 -> 1.246
A30: Discounting effect on financial assets | B30: 0.008 | C30: 0.29 | D30: -0.812 | E30: -1.281 | F30: 3.26 | G30: 3.01 | H30: 2.566 | I30: -0.804 | J30: =I30+'Quarterly YTD'!AF30-'Quarterly YTD'!AB30 -> 0.103 | K30: 0.002 | L30: ='Quarterly YTD'!D30-K30 -> 0 | M30: ='Quarterly YTD'!E30-'Quarterly YTD'!D30 -> 0.113 | N30: =C30-'Quarterly YTD'!E30 -> 0.175 | O30: -0.073 | P30: ='Quarterly YTD'!H30-O30 -> -0.441 | Q30: ='Quarterly YTD'!I30-'Quarterly YTD'!H30 -> -0.049 | R30: =D30-'Quarterly YTD'!I30 -> -0.249 | S30: -0.287 | T30: ='Quarterly YTD'!L30-S30 -> 0.201 | U30: ='Quarterly YTD'!M30-'Quarterly YTD'!L30 -> 0.177 | V30: =E30-'Quarterly YTD'!M30 -> -1.372 | W30: 0.769 | X30: ='Quarterly YTD'!P30-W30 -> 0.432 | Y30: ='Quarterly YTD'!Q30-'Quarterly YTD'!P30 -> 1.939 | Z30: =F30-'Quarterly YTD'!Q30 -> 0.12 | AA30: 1.391 | AB30: ='Quarterly YTD'!T30-AA30 -> 1.398 | AC30: ='Quarterly YTD'!U30-'Quarterly YTD'!T30 -> 0.74 | AD30: =G30-'Quarterly YTD'!U30 -> -0.519 | AE30: 1.308 | AF30: ='Quarterly YTD'!X30-AE30 -> 0.184 | AG30: ='Quarterly YTD'!Y30-'Quarterly YTD'!X30 -> 0.529 | AH30: =H30-'Quarterly YTD'!Y30 -> 0.545 | AI30: -0.006 | AJ30: ='Quarterly YTD'!AB30-AI30 -> -2.4 | AK30: ='Quarterly YTD'!AC30-'Quarterly YTD'!AB30 -> -0.139 | AL30: =I30-'Quarterly YTD'!AC30 -> 1.741 | AM30: -0.252 | AN30: ='Quarterly YTD'!AF30-AM30 -> -1.247
A31: Fair value loss on derivative financial instruments | B31: 0 | C31: 0 | D31: 0 | E31: 0 | F31: 0 | G31: 0 | H31: 0 | I31: 0 | J31: =I31+'Quarterly YTD'!AF31-'Quarterly YTD'!AB31 -> 0 | K31: 0 | L31: ='Quarterly YTD'!D31-K31 -> 0 | M31: ='Quarterly YTD'!E31-'Quarterly YTD'!D31 -> 0 | N31: =C31-'Quarterly YTD'!E31 -> 0 | O31: 0 | P31: ='Quarterly YTD'!H31-O31 -> 0 | Q31: ='Quarterly YTD'!I31-'Quarterly YTD'!H31 -> 0 | R31: =D31-'Quarterly YTD'!I31 -> 0 | S31: 0 | T31: ='Quarterly YTD'!L31-S31 -> 0 | U31: ='Quarterly YTD'!M31-'Quarterly YTD'!L31 -> 0 | V31: =E31-'Quarterly YTD'!M31 -> 0 | W31: 0 | X31: ='Quarterly YTD'!P31-W31 -> 0 | Y31: ='Quarterly YTD'!Q31-'Quarterly YTD'!P31 -> 0 | Z31: =F31-'Quarterly YTD'!Q31 -> 0 | AA31: 0 | AB31: ='Quarterly YTD'!T31-AA31 -> 0 | AC31: ='Quarterly YTD'!U31-'Quarterly YTD'!T31 -> 0 | AD31: =G31-'Quarterly YTD'!U31 -> 0 | AE31: 0 | AF31: ='Quarterly YTD'!X31-AE31 -> 0 | AG31: ='Quarterly YTD'!Y31-'Quarterly YTD'!X31 -> 0 | AH31: =H31-'Quarterly YTD'!Y31 -> 0 | AI31: 0 | AJ31: ='Quarterly YTD'!AB31-AI31 -> 0 | AK31: ='Quarterly YTD'!AC31-'Quarterly YTD'!AB31 -> 0 | AL31: =I31-'Quarterly YTD'!AC31 -> 0 | AM31: 0 | AN31: ='Quarterly YTD'!AF31-AM31 -> 0
A32: Fair value loss | B32: 0.002 | C32: -0.003 | D32: -0.66 | E32: -0.474 | F32: 26.441 | G32: 26.685 | H32: -52.388 | I32: 0.01 | J32: =I32+'Quarterly YTD'!AF32-'Quarterly YTD'!AB32 -> -0.761 | K32: 0 | L32: ='Quarterly YTD'!D32-K32 -> 0 | M32: ='Quarterly YTD'!E32-'Quarterly YTD'!D32 -> 0 | N32: =C32-'Quarterly YTD'!E32 -> -0.003 | O32: 0 | P32: ='Quarterly YTD'!H32-O32 -> 0 | Q32: ='Quarterly YTD'!I32-'Quarterly YTD'!H32 -> -0.003 | R32: =D32-'Quarterly YTD'!I32 -> -0.657 | S32: -1.958 | T32: ='Quarterly YTD'!L32-S32 -> -0.44 | U32: ='Quarterly YTD'!M32-'Quarterly YTD'!L32 -> -0.08 | V32: =E32-'Quarterly YTD'!M32 -> 2.004 | W32: 5.983 | X32: ='Quarterly YTD'!P32-W32 -> 6.122 | Y32: ='Quarterly YTD'!Q32-'Quarterly YTD'!P32 -> 6.36 | Z32: =F32-'Quarterly YTD'!Q32 -> 7.976 | AA32: 6.425 | AB32: ='Quarterly YTD'!T32-AA32 -> 6.625 | AC32: ='Quarterly YTD'!U32-'Quarterly YTD'!T32 -> 6.757 | AD32: =G32-'Quarterly YTD'!U32 -> 6.878 | AE32: 7.032 | AF32: ='Quarterly YTD'!X32-AE32 -> -59.608 | AG32: ='Quarterly YTD'!Y32-'Quarterly YTD'!X32 -> 0 | AH32: =H32-'Quarterly YTD'!Y32 -> 0.188 | AI32: 0.009 | AJ32: ='Quarterly YTD'!AB32-AI32 -> 0.794 | AK32: ='Quarterly YTD'!AC32-'Quarterly YTD'!AB32 -> -0.425 | AL32: =I32-'Quarterly YTD'!AC32 -> -0.368 | AM32: 0.033 | AN32: ='Quarterly YTD'!AF32-AM32 -> -0.001
A33: Hedging initial transaction costs | B33: 0 | C33: 0 | D33: 0 | E33: 0 | F33: 0 | G33: 0 | H33: 1.574 | I33: 1.137 | J33: =I33+'Quarterly YTD'!AF33-'Quarterly YTD'!AB33 -> 0 | K33: 0 | L33: ='Quarterly YTD'!D33-K33 -> 0 | M33: ='Quarterly YTD'!E33-'Quarterly YTD'!D33 -> 0 | N33: =C33-'Quarterly YTD'!E33 -> 0 | O33: 0 | P33: ='Quarterly YTD'!H33-O33 -> 0 | Q33: ='Quarterly YTD'!I33-'Quarterly YTD'!H33 -> 0 | R33: =D33-'Quarterly YTD'!I33 -> 0 | S33: 0 | T33: ='Quarterly YTD'!L33-S33 -> 0 | U33: ='Quarterly YTD'!M33-'Quarterly YTD'!L33 -> 0 | V33: =E33-'Quarterly YTD'!M33 -> 0 | W33: 0 | X33: ='Quarterly YTD'!P33-W33 -> 0 | Y33: ='Quarterly YTD'!Q33-'Quarterly YTD'!P33 -> 0 | Z33: =F33-'Quarterly YTD'!Q33 -> 0 | AA33: 0 | AB33: ='Quarterly YTD'!T33-AA33 -> 0 | AC33: ='Quarterly YTD'!U33-'Quarterly YTD'!T33 -> 0 | AD33: =G33-'Quarterly YTD'!U33 -> 0 | AE33: 0 | AF33: ='Quarterly YTD'!X33-AE33 -> 0 | AG33: ='Quarterly YTD'!Y33-'Quarterly YTD'!X33 -> 1.511 | AH33: =H33-'Quarterly YTD'!Y33 -> 0.063 | AI33: 1.137 | AJ33: ='Quarterly YTD'!AB33-AI33 -> 0 | AK33: ='Quarterly YTD'!AC33-'Quarterly YTD'!AB33 -> 0 | AL33: =I33-'Quarterly YTD'!AC33 -> 0 | AM33: 0 | AN33: ='Quarterly YTD'!AF33-AM33 -> 0
A34: Changes in other reserves | B34: 0 | C34: 0.06 | D34: 0.271 | E34: 0.265 | F34: 0.265 | G34: 1.134 | H34: 0 | I34: 0 | J34: =I34+'Quarterly YTD'!AF34-'Quarterly YTD'!AB34 -> 0 | K34: 0 | L34: ='Quarterly YTD'!D34-K34 -> 0 | M34: ='Quarterly YTD'!E34-'Quarterly YTD'!D34 -> -0.002 | N34: =C34-'Quarterly YTD'!E34 -> 0.062 | O34: 0.072 | P34: ='Quarterly YTD'!H34-O34 -> 0.066 | Q34: ='Quarterly YTD'!I34-'Quarterly YTD'!H34 -> 0.067 | R34: =D34-'Quarterly YTD'!I34 -> 0.066 | S34: 0.066 | T34: ='Quarterly YTD'!L34-S34 -> 0.066 | U34: ='Quarterly YTD'!M34-'Quarterly YTD'!L34 -> 0.067 | V34: =E34-'Quarterly YTD'!M34 -> 0.066 | W34: 0.066 | X34: ='Quarterly YTD'!P34-W34 -> 0.066 | Y34: ='Quarterly YTD'!Q34-'Quarterly YTD'!P34 -> 0.067 | Z34: =F34-'Quarterly YTD'!Q34 -> 0.066 | AA34: 0.066 | AB34: ='Quarterly YTD'!T34-AA34 -> 0.067 | AC34: ='Quarterly YTD'!U34-'Quarterly YTD'!T34 -> 0.066 | AD34: =G34-'Quarterly YTD'!U34 -> 0.935 | AE34: 0.204 | AF34: ='Quarterly YTD'!X34-AE34 -> 0.203 | AG34: ='Quarterly YTD'!Y34-'Quarterly YTD'!X34 -> 0.205 | AH34: =H34-'Quarterly YTD'!Y34 -> -0.612 | AI34: 0 | AJ34: ='Quarterly YTD'!AB34-AI34 -> 0 | AK34: ='Quarterly YTD'!AC34-'Quarterly YTD'!AB34 -> 0 | AL34: =I34-'Quarterly YTD'!AC34 -> 0 | AM34: 0 | AN34: ='Quarterly YTD'!AF34-AM34 -> 0
A35: (Gain)/loss on property, plant and equipment disposals and write-offs | B35: 0.108 | C35: -0.879 | D35: 0.588 | E35: -4.902 | F35: -14.615 | G35: -8.391 | H35: -14.771 | I35: -1.151 | J35: =I35+'Quarterly YTD'!AF35-'Quarterly YTD'!AB35 -> 1.131 | K35: -0.272 | L35: ='Quarterly YTD'!D35-K35 -> 0.449 | M35: ='Quarterly YTD'!E35-'Quarterly YTD'!D35 -> -0.55 | N35: =C35-'Quarterly YTD'!E35 -> -0.506 | O35: 0.289 | P35: ='Quarterly YTD'!H35-O35 -> -0.183 | Q35: ='Quarterly YTD'!I35-'Quarterly YTD'!H35 -> 1.216 | R35: =D35-'Quarterly YTD'!I35 -> -0.734 | S35: 0.445 | T35: ='Quarterly YTD'!L35-S35 -> 0.184 | U35: ='Quarterly YTD'!M35-'Quarterly YTD'!L35 -> 3.033 | V35: =E35-'Quarterly YTD'!M35 -> -8.564 | W35: -15.095 | X35: ='Quarterly YTD'!P35-W35 -> 0.014 | Y35: ='Quarterly YTD'!Q35-'Quarterly YTD'!P35 -> -13.925 | Z35: =F35-'Quarterly YTD'!Q35 -> 14.391 | AA35: 0.366 | AB35: ='Quarterly YTD'!T35-AA35 -> -0.194 | AC35: ='Quarterly YTD'!U35-'Quarterly YTD'!T35 -> 0.352 | AD35: =G35-'Quarterly YTD'!U35 -> -8.915 | AE35: -8.902 | AF35: ='Quarterly YTD'!X35-AE35 -> -2.798 | AG35: ='Quarterly YTD'!Y35-'Quarterly YTD'!X35 -> -4.446 | AH35: =H35-'Quarterly YTD'!Y35 -> 1.375 | AI35: 0.018 | AJ35: ='Quarterly YTD'!AB35-AI35 -> -2.739 | AK35: ='Quarterly YTD'!AC35-'Quarterly YTD'!AB35 -> 0.412 | AL35: =I35-'Quarterly YTD'!AC35 -> 1.158 | AM35: -0.162 | AN35: ='Quarterly YTD'!AF35-AM35 -> -0.277
... A54: Security deposits received | B54: 0.014 | C54: 1.345 | D54: 1.965 | E54: 2.677 | F54: 9.332 | G54: 10.664 | H54: 15.497 | I54: 12.113 | J54: =I54+'Quarterly YTD'!AF54-'Quarterly YTD'!AB54 -> 10.807 | K54: 0.036 | L54: ='Quarterly YTD'!D54-K54 -> 0.288 | M54: ='Quarterly YTD'!E54-'Quarterly YTD'!D54 -> 0.143 | N54: =C54-'Quarterly YTD'!E54 -> 0.878 | O54: 1.434 | P54: ='Quarterly YTD'!H54-O54 -> 0.691 | Q54: ='Quarterly YTD'!I54-'Quarterly YTD'!H54 -> -0.425 | R54: =D54-'Quarterly YTD'!I54 -> 0.265 | S54: 0.041 | T54: ='Quarterly YTD'!L54-S54 -> 2.629 | U54: ='Quarterly YTD'!M54-'Quarterly YTD'!L54 -> -0.799 | V54: =E54-'Quarterly YTD'!M54 -> 0.806 | W54: 4.128 | X54: ='Quarterly YTD'!P54-W54 -> 4.05 | Y54: ='Quarterly YTD'!Q54-'Quarterly YTD'!P54 -> 2.992 | Z54: =F54-'Quarterly YTD'!Q54 -> -1.838 | AA54: 4.345 | AB54: ='Quarterly YTD'!T54-AA54 -> 9.912 | AC54: ='Quarterly YTD'!U54-'Quarterly YTD'!T54 -> -1.408 | AD54: =G54-'Quarterly YTD'!U54 -> -2.185 | AE54: 21.742 | AF54: ='Quarterly YTD'!X54-AE54 -> -10.244 | AG54: ='Quarterly YTD'!Y54-'Quarterly YTD'!X54 -> 2.833 | AH54: =H54-'Quarterly YTD'!Y54 -> 1.166 | AI54: 1.585 | AJ54: ='Quarterly YTD'!AB54-AI54 -> 5.475 | AK54: ='Quarterly YTD'!AC54-'Quarterly YTD'!AB54 -> 1.886 | AL54: =I54-'Quarterly YTD'!AC54 -> 3.167 | AM54: 4.438 | AN54: ='Quarterly YTD'!AF54-AM54 -> 1.316
A55: Cash generated from operating activities | B55: =SUM(B24:B30)+B32+SUM(B34:B35)+B43+SUM(B45:B46)+SUM(B48:B54) -> 22.857 | C55: =SUM(C24:C30)+C32+SUM(C34:C35)+SUM(C37:C38)+SUM(C42:C43)+SUM(C45:C46)+SUM(C48:C54) -> 50.447 | D55: =SUM(D24:D30)+D32+SUM(D34:D35)+SUM(D37:D38)+SUM(D42:D43)+SUM(D45:D46)+SUM(D48:D54) -> 132.888 | E55: =SUM(E24:E30)+E32+SUM(E34:E35)+SUM(E37:E38)+SUM(E42:E43)+SUM(E45:E46)+SUM(E48:E54) -> 84.745 | F55: =SUM(F24:F30)+F32+SUM(F34:F35)+SUM(F37:F38)+SUM(F42:F43)+SUM(F45:F46)+SUM(F48:F54) -> 235.793 | G55: =SUM(G24:G30)+SUM(G32:G35)+G38+SUM(G40:G43)+SUM(G45:G46)+SUM(G48:G54) -> 367.304 | H55: =SUM(H24:H30)+SUM(H32:H33)+H35+H38+SUM(H40:H41)+H43+SUM(H45:H47)+SUM(H49:H51)+SUM(H53:H54) -> 431.774 | I55: =SUM(I24:I30)+SUM(I32:I33)+I35+I38+SUM(I40:I41)+I43+SUM(I45:I47)+SUM(I49:I51)+SUM(I53:I54) -> 370.204 | J55: =I55+'Quarterly YTD'!AF55-'Quarterly YTD'!AB55 -> 292.216 | K55: =SUM(K24:K30)+SUM(K34:K35)+SUM(K45:K46)+SUM(K48:K50)+SUM(K52:K54) -> 6.971 | L55: =SUM(L24:L54) -> 6.297 | M55: =SUM(M24:M54) -> -2.32 | N55: =SUM(N24:N54) -> 39.499 | O55: =SUM(O24:O30)+O32+SUM(O34:O35)+O38+O42+SUM(O45:O46)+SUM(O48:O54) -> 61.513 | P55: =SUM(P24:P54) -> 72.297 | Q55: =SUM(Q24:Q54) -> -40.216 | R55: =SUM(R24:R54) -> 39.294 | S55: =SUM(S24:S30)+S32+SUM(S34:S35)+SUM(S38:S39)+SUM(S42:S43)+SUM(S45:S46)+SUM(S48:S54) -> 18.472 | T55: =SUM(T24:T54) -> 14.883 | U55: =SUM(U24:U54) -> 27.682 | V55: =SUM(V24:V54) -> 23.708 | W55: =SUM(W24:W30)+W32+SUM(W34:W35)+W38+SUM(W42:W43)+SUM(W45:W46)+SUM(W48:W54) -> 49.747 | X55: =SUM(X24:X54) -> 48.655 | Y55: =SUM(Y24:Y54) -> 102.353 | Z55: =SUM(Z24:Z54) -> 35.038 | AA55: =SUM(AA24:AA30)+AA32+SUM(AA34:AA35)+AA38+AA43+SUM(AA45:AA46)+SUM(AA48:AA54) -> 24.817 | AB55: =SUM(AB24:AB54) -> 116.7 | AC55: =SUM(AC24:AC54) -> 130.213 | AD55: =SUM(AD24:AD54) -> 95.574 | AE55: =SUM(AE24:AE30)+SUM(AE32:AE35)+AE38+AE41+AE46+SUM(AE48:AE51)+SUM(AE53:AE54) -> 85.338 | AF55: =SUM(AF24:AF54) -> 133.14 | AG55: =SUM(AG24:AG54) -> 176.844 | AH55: =SUM(AH24:AH54) -> 36.452 | AI55: =SUM(AI24:AI30)+SUM(AI32:AI33)+AI35+AI38+AI41+SUM(AI45:AI46)+SUM(AI49:AI51)+SUM(AI53:AI54) -> 52.193 | AJ55: =SUM(AJ24:AJ54) -> 157.087 | AK55: =SUM(AK24:AK54) -> 181.991 | AL55: =SUM(AL24:AL54) -> -21.067 | AM55: =SUM(AM24:AM30)+SUM(AM32:AM33)+AM35+AM38+AM41+SUM(AM45:AM46)+SUM(AM49:AM51)+SUM(AM53:AM54) -> 51.785 | AN55: =SUM(AN24:AN54) -> 79.507
A56: Interest received | B56: 0.001 | C56: 0.002 | D56: 0.952 | E56: 1.711 | F56: 2.337 | G56: 5.272 | H56: 7.141 | I56: 2.114 | J56: =I56+'Quarterly YTD'!AF56-'Quarterly YTD'!AB56 -> 1.455 | K56: 0 | L56: ='Quarterly YTD'!D56-K56 -> 0.027 | M56: ='Quarterly YTD'!E56-'Quarterly YTD'!D56 -> 0.001 | N56: =C56-'Quarterly YTD'!E56 -> -0.026 | O56: 0 | P56: ='Quarterly YTD'!H56-O56 -> 0.397 | Q56: ='Quarterly YTD'!I56-'Quarterly YTD'!H56 -> 0.029 | R56: =D56-'Quarterly YTD'!I56 -> 0.526 | S56: -2.072 | T56: ='Quarterly YTD'!L56-S56 -> 2.909 | U56: ='Quarterly YTD'!M56-'Quarterly YTD'!L56 -> 0.009 | V56: =E56-'Quarterly YTD'!M56 -> 0.865 | W56: 0.095 | X56: ='Quarterly YTD'!P56-W56 -> -0.082 | Y56: ='Quarterly YTD'!Q56-'Quarterly YTD'!P56 -> 1.466 | Z56: =F56-'Quarterly YTD'!Q56 -> 0.858 | AA56: 0.192 | AB56: ='Quarterly YTD'!T56-AA56 -> 0.065 | AC56: ='Quarterly YTD'!U56-'Quarterly YTD'!T56 -> 0.017 | AD56: =G56-'Quarterly YTD'!U56 -> 4.998 | AE56: 0.607 | AF56: ='Quarterly YTD'!X56-AE56 -> 2.544 | AG56: ='Quarterly YTD'!Y56-'Quarterly YTD'!X56 -> 1.454 | AH56: =H56-'Quarterly YTD'!Y56 -> 2.536 | AI56: 0.65 | AJ56: ='Quarterly YTD'!AB56-AI56 -> 0.368 | AK56: ='Quarterly YTD'!AC56-'Quarterly YTD'!AB56 -> 0.632 | AL56: =I56-'Quarterly YTD'!AC56 -> 0.464 | AM56: 0.18 | AN56: ='Quarterly YTD'!AF56-AM56 -> 0.179
A57: Interest paid | B57: -1.456 | C57: -7.718 | D57: -29.584 | E57: -27.567 | F57: -44.188 | G57: -79.833 | H57: -131.204 | I57: -110.568 | J57: =I57+'Quarterly YTD'!AF57-'Quarterly YTD'!AB57 -> -89.314 | K57: -0.726 | L57: ='Quarterly YTD'!D57-K57 -> -0.414 | M57: ='Quarterly YTD'!E57-'Quarterly YTD'!D57 -> -0.705 | N57: =C57-'Quarterly YTD'!E57 -> -5.873 | O57: -4.566 | P57: ='Quarterly YTD'!H57-O57 -> -14.899 | Q57: ='Quarterly YTD'!I57-'Quarterly YTD'!H57 -> 3.757 | R57: =D57-'Quarterly YTD'!I57 -> -13.876 | S57: 0.005 | T57: ='Quarterly YTD'!L57-S57 -> -13.42 | U57: ='Quarterly YTD'!M57-'Quarterly YTD'!L57 -> -3.06 | V57: =E57-'Quarterly YTD'!M57 -> -11.092 | W57: -3.275 | X57: ='Quarterly YTD'!P57-W57 -> -14.314 | Y57: ='Quarterly YTD'!Q57-'Quarterly YTD'!P57 -> -8.762 | Z57: =F57-'Quarterly YTD'!Q57 -> -17.837 | AA57: -9.784 | AB57: ='Quarterly YTD'!T57-AA57 -> -22.233 | AC57: ='Quarterly YTD'!U57-'Quarterly YTD'!T57 -> -16.214 | AD57: =G57-'Quarterly YTD'!U57 -> -31.602 | AE57: -24.293 | AF57: ='Quarterly YTD'!X57-AE57 -> -33.548 | AG57: ='Quarterly YTD'!Y57-'Quarterly YTD'!X57 -> -29.518 | AH57: =H57-'Quarterly YTD'!Y57 -> -43.845 | AI57: -25.054 | AJ57: ='Quarterly YTD'!AB57-AI57 -> -37.196 | AK57: ='Quarterly YTD'!AC57-'Quarterly YTD'!AB57 -> -20.744 | AL57: =I57-'Quarterly YTD'!AC57 -> -27.574 | AM57: -13.015 | AN57: ='Quarterly YTD'!AF57-AM57 -> -27.981
A58: Income tax paid | B58: -0.931 | C58: -3.536 | D58: -6.885 | E58: -16.208 | F58: -20.421 | G58: -24.529 | H58: -14.017 | I58: -17.702 | J58: =I58+'Quarterly YTD'!AF58-'Quarterly YTD'!AB58 -> -13.607 | K58: -0.067 | L58: ='Quarterly YTD'!D58-K58 -> -1.61 | M58: ='Quarterly YTD'!E58-'Quarterly YTD'!D58 -> 0.11 | N58: =C58-'Quarterly YTD'!E58 -> -1.969 | O58: -0.16 | P58: ='Quarterly YTD'!H58-O58 -> -0.814 | Q58: ='Quarterly YTD'!I58-'Quarterly YTD'!H58 -> -0.354 | R58: =D58-'Quarterly YTD'!I58 -> -5.557 | S58: -4.986 | T58: ='Quarterly YTD'!L58-S58 -> -1.939 | U58: ='Quarterly YTD'!M58-'Quarterly YTD'!L58 -> -10.076 | V58: =E58-'Quarterly YTD'!M58 -> 0.793 | W58: -3.411 | X58: ='Quarterly YTD'!P58-W58 -> -6.827 | Y58: ='Quarterly YTD'!Q58-'Quarterly YTD'!P58 -> -4.432 | Z58: =F58-'Quarterly YTD'!Q58 -> -5.751 | AA58: -11.307 | AB58: ='Quarterly YTD'!T58-AA58 -> 3.794 | AC58: ='Quarterly YTD'!U58-'Quarterly YTD'!T58 -> -12.193 | AD58: =G58-'Quarterly YTD'!U58 -> -4.823 | AE58: -2.367 | AF58: ='Quarterly YTD'!X58-AE58 -> -2.469 | AG58: ='Quarterly YTD'!Y58-'Quarterly YTD'!X58 -> -4.594 | AH58: =H58-'Quarterly YTD'!Y58 -> -4.587 | AI58: -1.631 | AJ58: ='Quarterly YTD'!AB58-AI58 -> -7.657 | AK58: ='Quarterly YTD'!AC58-'Quarterly YTD'!AB58 -> -4.444 | AL58: =I58-'Quarterly YTD'!AC58 -> -3.97 | AM58: -1.405 | AN58: ='Quarterly YTD'!AF58-AM58 -> -3.788
A59: Net cash generated from (used in) operating activities from continuing operations | B59: =SUM(B55:B58) -> 20.471 | C59: =SUM(C55:C58) -> 39.195 | D59: =SUM(D55:D58) -> 97.371 | E59: =SUM(E55:E58) -> 42.681 | F59: =SUM(F55:F58) -> 173.521 | G59: =SUM(G55:G58) -> 268.214 | H59: =SUM(H55:H58) -> 293.694 | I59: =SUM(I55:I58) -> 244.048 | J59: =SUM(J55:J58) -> 190.75 | K59: =K55+SUM(K57:K58) -> 6.178 | L59: =SUM(L55:L58) -> 4.3 | M59: =SUM(M55:M58) -> -2.914 | N59: =SUM(N55:N58) -> 31.631 | O59: =SUM(O55:O58) -> 56.787 | P59: =SUM(P55:P58) -> 56.981 | Q59: =SUM(Q55:Q58) -> -36.784 | R59: =SUM(R55:R58) -> 20.387 | S59: =SUM(S55:S58) -> 11.419 | ... AN59: =SUM(AN55:AN58) -> 47.917
A60: Net cash generated from operating activities | B60: =B59 -> 20.471 | C60: =C59 -> 39.195 | D60: =D59 -> 97.371 | E60: =E59 -> 42.681 | F60: =F59 -> 173.521 | G60: =G59 -> 268.214 | H60: =H59 -> 293.694 | I60: =I59 -> 244.048 | ... AN60: =AN59 -> 47.917 | AO60: =IF(AND(AN60=0,AM60=0),0,IF(OR(AM60=0,AM60="NM",AN60="NM"),"NM",IF(AM60<0,-(AN60/AM60-1),AN60/AM60-1))) -> 0.27625516 | AP60: =IF(AND(AN60=0,AJ60=0),0,IF(OR(AJ60=0,AJ60="NM",AN60="NM"),"NM",IF(AJ60<0,-(AN60/AJ60-1),AN60/AJ60-1))) -> -0.57445694
A61: Purchase of property, plant and equipment | B61: -25.222 | C61: -39.674 | D61: -93.132 | E61: -70.253 | F61: -154.722 | G61: -204.822 | H61: -230.833 | I61: -162.507 | J61: =I61+'Quarterly YTD'!AF61-'Quarterly YTD'!AB61 -> -155.115 | K61: -3.532 | L61: ='Quarterly YTD'!D61-K61 -> -13.197 | M61: ='Quarterly YTD'!E61-'Quarterly YTD'!D61 -> 12.707 | N61: =C61-'Quarterly YTD'!E61 -> -35.652 | O61: -18.545 | P61: ='Quarterly YTD'!H61-O61 -> -30.936 | Q61: ='Quarterly YTD'!I61-'Quarterly YTD'!H61 -> -19.794 | R61: =D61-'Quarterly YTD'!I61 -> -23.857 | S61: -26.252 | T61: ='Quarterly YTD'!L61-S61 -> -12.095 | U61: ='Quarterly YTD'!M61-'Quarterly YTD'!L61 -> -11.268 | V61: =E61-'Quarterly YTD'!M61 -> -20.638 | W61: -21.649 | X61: ='Quarterly YTD'!P61-W61 -> -18.101 | Y61: ='Quarterly YTD'!Q61-'Quarterly YTD'!P61 -> -20.731 | Z61: =F61-'Quarterly YTD'!Q61 -> -94.241 | AA61: -34.387 | AB61: ='Quarterly YTD'!T61-AA61 -> -55.834 | AC61: ='Quarterly YTD'!U61-'Quarterly YTD'!T61 -> -32.57 | AD61: =G61-'Quarterly YTD'!U61 -> -82.031 | AE61: -42.935 | AF61: ='Quarterly YTD'!X61-AE61 -> -40.025 | AG61: ='Quarterly YTD'!Y61-'Quarterly YTD'!X61 -> -72.69 | AH61: =H61-'Quarterly YTD'!Y61 -> -75.183 | AI61: -47.439 | AJ61: ='Quarterly YTD'!AB61-AI61 -> -29.473 | AK61: ='Quarterly YTD'!AC61-'Quarterly YTD'!AB61 -> -35.433 | AL61: =I61-'Quarterly YTD'!AC61 -> -50.162 | AM61: -12.02 | AN61: ='Quarterly YTD'!AF61-AM61 -> -57.5
A62: Purchase of intangible assets | B62: 0 | C62: 0 | D62: 0 | E62: 0 | F62: -4.348 | G62: -8.962 | H62: -9.512 | I62: -6.608 | J62: =I62+'Quarterly YTD'!AF62-'Quarterly YTD'!AB62 -> -7.432 | K62: 0 | L62: ='Quarterly YTD'!D62-K62 -> 0 | M62: ='Quarterly YTD'!E62-'Quarterly YTD'!D62 -> 0 | N62: =C62-'Quarterly YTD'!E62 -> 0 | O62: 0 | P62: ='Quarterly YTD'!H62-O62 -> 0 | Q62: ='Quarterly YTD'!I62-'Quarterly YTD'!H62 -> 0 | R62: =D62-'Quarterly YTD'!I62 -> 0 | S62: 0 | T62: ='Quarterly YTD'!L62-S62 -> 0 | U62: ='Quarterly YTD'!M62-'Quarterly YTD'!L62 -> 0 | V62: =E62-'Quarterly YTD'!M62 -> 0 | W62: 0 | X62: ='Quarterly YTD'!P62-W62 -> 0 | Y62: ='Quarterly YTD'!Q62-'Quarterly YTD'!P62 -> 0 | Z62: =F62-'Quarterly YTD'!Q62 -> -4.348 | AA62: -2.179 | AB62: ='Quarterly YTD'!T62-AA62 -> -2.386 | AC62: ='Quarterly YTD'!U62-'Quarterly YTD'!T62 -> -1.801 | AD62: =G62-'Quarterly YTD'!U62 -> -2.596 | AE62: -1.957 | AF62: ='Quarterly YTD'!X62-AE62 -> -2.39 | AG62: ='Quarterly YTD'!Y62-'Quarterly YTD'!X62 -> -2.694 | AH62: =H62-'Quarterly YTD'!Y62 -> -2.471 | AI62: -1.302 | AJ62: ='Quarterly YTD'!AB62-AI62 -> -1.096 | AK62: ='Quarterly YTD'!AC62-'Quarterly YTD'!AB62 -> -1.403 | AL62: =I62-'Quarterly YTD'!AC62 -> -2.807 | AM62: -1.481 | AN62: ='Quarterly YTD'!AF62-AM62 -> -1.741
A63: Proceeds from the disposal of property, plant and equipment and intangible assets | B63: 0.215 | C63: 3.422 | D63: 9.145 | E63: 4.129 | F63: 3.9 | G63: 21.152 | H63: 6.519 | I63: 18.903 | J63: =I63+'Quarterly YTD'!AF63-'Quarterly YTD'!AB63 -> 5.833 | K63: 0.328 | L63: ='Quarterly YTD'!D63-K63 -> 0.17 | M63: ='Quarterly YTD'!E63-'Quarterly YTD'!D63 -> 0.03 | N63: =C63-'Quarterly YTD'!E63 -> 2.894 | O63: 0.433 | P63: ='Quarterly YTD'!H63-O63 -> 0.265 | Q63: ='Quarterly YTD'!I63-'Quarterly YTD'!H63 -> -0.033 | R63: =D63-'Quarterly YTD'!I63 -> 8.48 | S63: 0.05 | T63: ='Quarterly YTD'!L63-S63 -> 0.347 | U63: ='Quarterly YTD'!M63-'Quarterly YTD'!L63 -> 0.19 | V63: =E63-'Quarterly YTD'!M63 -> 3.542 | W63: 1.976 | X63: ='Quarterly YTD'!P63-W63 -> 0.048 | Y63: ='Quarterly YTD'!Q63-'Quarterly YTD'!P63 -> 21.262 | Z63: =F63-'Quarterly YTD'!Q63 -> -19.386 | AA63: 0.053 | AB63: ='Quarterly YTD'!T63-AA63 -> -0.052 | AC63: ='Quarterly YTD'!U63-'Quarterly YTD'!T63 -> 0.103 | AD63: =G63-'Quarterly YTD'!U63 -> 21.048 | AE63: 0.041 | AF63: ='Quarterly YTD'!X63-AE63 -> 1.314 | AG63: ='Quarterly YTD'!Y63-'Quarterly YTD'!X63 -> 3.979 | AH63: =H63-'Quarterly YTD'!Y63 -> 1.185 | AI63: 9.265 | AJ63: ='Quarterly YTD'!AB63-AI63 -> 6.385 | AK63: ='Quarterly YTD'!AC63-'Quarterly YTD'!AB63 -> -4.158 | AL63: =I63-'Quarterly YTD'!AC63 -> 7.411 | AM63: 0.297 | AN63: ='Quarterly YTD'!AF63-AM63 -> 2.283
A64: Net proceeds from aircraft sale leaseback | B64: 0 | C64: 0 | D64: 0 | E64: 0 | F64: 0 | G64: 0 | H64: 0 | I64: 0 | J64: =I64+'Quarterly YTD'!AF64-'Quarterly YTD'!AB64 -> 0 | K64: 0 | L64: ='Quarterly YTD'!D64-K64 -> 0 | M64: ='Quarterly YTD'!E64-'Quarterly YTD'!D64 -> 0 | N64: =C64-'Quarterly YTD'!E64 -> 0 | O64: 0 | P64: ='Quarterly YTD'!H64-O64 -> 0 | Q64: ='Quarterly YTD'!I64-'Quarterly YTD'!H64 -> 0 | R64: =D64-'Quarterly YTD'!I64 -> 0 | S64: 0 | T64: ='Quarterly YTD'!L64-S64 -> 0 | U64: ='Quarterly YTD'!M64-'Quarterly YTD'!L64 -> 0 | V64: =E64-'Quarterly YTD'!M64 -> 0 | W64: 0 | X64: ='Quarterly YTD'!P64-W64 -> 0 | Y64: ='Quarterly YTD'!Q64-'Quarterly YTD'!P64 -> 0 | Z64: =F64-'Quarterly YTD'!Q64 -> 0 | AA64: 0 | AB64: ='Quarterly YTD'!T64-AA64 -> 0 | AC64: ='Quarterly YTD'!U64-'Quarterly YTD'!T64 -> 0 | AD64: =G64-'Quarterly YTD'!U64 -> 0 | AE64: 0 | AF64: ='Quarterly YTD'!X64-AE64 -> 0 | AG64: ='Quarterly YTD'!Y64-'Quarterly YTD'!X64 -> 0 | AH64: =H64-'Quarterly YTD'!Y64 -> 0 | AI64: 0 | AJ64: ='Quarterly YTD'!AB64-AI64 -> 0 | AK64: ='Quarterly YTD'!AC64-'Quarterly YTD'!AB64 -> 0 | AL64: =I64-'Quarterly YTD'!AC64 -> 0 | AM64: 0 | AN64: ='Quarterly YTD'!AF64-AM64 -> 0
A65: Acquired aircrafts in relation to sale leaseback | B65: 0 | C65: 0 | D65: 0 | E65: 0 | F65: -81.411 | G65: 0 | H65: 0 | I65: 0 | J65: =I65+'Quarterly YTD'!AF65-'Quarterly YTD'!AB65 -> 0 | K65: 0 | L65: ='Quarterly YTD'!D65-K65 -> 0 | M65: ='Quarterly YTD'!E65-'Quarterly YTD'!D65 -> 0 | N65: =C65-'Quarterly YTD'!E65 -> 0 | O65: 0 | P65: ='Quarterly YTD'!H65-O65 -> 0 | Q65: ='Quarterly YTD'!I65-'Quarterly YTD'!H65 -> 0 | R65: =D65-'Quarterly YTD'!I65 -> 0 | S65: 0 | T65: ='Quarterly YTD'!L65-S65 -> 0 | U65: ='Quarterly YTD'!M65-'Quarterly YTD'!L65 -> 0 | V65: =E65-'Quarterly YTD'!M65 -> 0 | W65: 0 | X65: ='Quarterly YTD'!P65-W65 -> 0 | Y65: ='Quarterly YTD'!Q65-'Quarterly YTD'!P65 -> 0 | Z65: =F65-'Quarterly YTD'!Q65 -> -81.411 | AA65: 0 | AB65: ='Quarterly YTD'!T65-AA65 -> 0 | AC65: ='Quarterly YTD'!U65-'Quarterly YTD'!T65 -> 0 | AD65: =G65-'Quarterly YTD'!U65 -> 0 | AE65: 0 | AF65: ='Quarterly YTD'!X65-AE65 -> 0 | AG65: ='Quarterly YTD'!Y65-'Quarterly YTD'!X65 -> 0 | AH65: =H65-'Quarterly YTD'!Y65 -> 0 | AI65: 0 | AJ65: ='Quarterly YTD'!AB65-AI65 -> 0 | AK65: ='Quarterly YTD'!AC65-'Quarterly YTD'!AB65 -> 0 | AL65: =I65-'Quarterly YTD'!AC65 -> 0 | AM65: 0 | AN65: ='Quarterly YTD'!AF65-AM65 -> 0
A66: Proceeds from aircraft sale leaseback | B66: 0 | C66: 0 | D66: 0 | E66: 0 | F66: 98.738 | G66: 6.621 | H66: 57.737 | I66: 27.5 | J66: =I66+'Quarterly YTD'!AF66-'Quarterly YTD'!AB66 -> 6.494 | K66: 0 | L66: ='Quarterly YTD'!D66-K66 -> 0 | M66: ='Quarterly YTD'!E66-'Quarterly YTD'!D66 -> 0 | N66: =C66-'Quarterly YTD'!E66 -> 0 | O66: 0 | P66: ='Quarterly YTD'!H66-O66 -> 0 | Q66: ='Quarterly YTD'!I66-'Quarterly YTD'!H66 -> 0 | R66: =D66-'Quarterly YTD'!I66 -> 0 | S66: 0 | T66: ='Quarterly YTD'!L66-S66 -> 0 | U66: ='Quarterly YTD'!M66-'Quarterly YTD'!L66 -> 0 | V66: =E66-'Quarterly YTD'!M66 -> 0 | W66: 0 | X66: ='Quarterly YTD'!P66-W66 -> 0 | Y66: ='Quarterly YTD'!Q66-'Quarterly YTD'!P66 -> 0 | Z66: =F66-'Quarterly YTD'!Q66 -> 98.738 | AA66: 0 | AB66: ='Quarterly YTD'!T66-AA66 -> 0 | AC66: ='Quarterly YTD'!U66-'Quarterly YTD'!T66 -> 0 | AD66: =G66-'Quarterly YTD'!U66 -> 6.621 | AE66: 33.24 | AF66: ='Quarterly YTD'!X66-AE66 -> 9.15 | AG66: ='Quarterly YTD'!Y66-'Quarterly YTD'!X66 -> 1.706 | AH66: =H66-'Quarterly YTD'!Y66 -> 13.641 | AI66: 12.077 | AJ66: ='Quarterly YTD'!AB66-AI66 -> 15.732 | AK66: ='Quarterly YTD'!AC66-'Quarterly YTD'!AB66 -> -0.126 | AL66: =I66-'Quarterly YTD'!AC66 -> -0.183 | AM66: 6.695 | AN66: ='Quarterly YTD'!AF66-AM66 -> 0.108
A67: Purchase of other investment | B67: 0 | C67: 0 | D67: -0.57 | E67: -6.626 | F67: -0.607 | G67: 0 | H67: 0 | I67: 0 | J67: =I67+'Quarterly YTD'!AF67-'Quarterly YTD'!AB67 -> 0 | K67: 0 | L67: ='Quarterly YTD'!D67-K67 -> -2.868 | M67: ='Quarterly YTD'!E67-'Quarterly YTD'!D67 -> 2.868 | N67: =C67-'Quarterly YTD'!E67 -> 0 | O67: 0 | P67: ='Quarterly YTD'!H67-O67 -> -0.468 | Q67: ='Quarterly YTD'!I67-'Quarterly YTD'!H67 -> 0.025 | R67: =D67-'Quarterly YTD'!I67 -> -0.127 | S67: 0 | T67: ='Quarterly YTD'!L67-S67 -> -0.831 | U67: ='Quarterly YTD'!M67-'Quarterly YTD'!L67 -> -2.28 | V67: =E67-'Quarterly YTD'!M67 -> -3.515 | W67: -0.305 | X67: ='Quarterly YTD'!P67-W67 -> -0.008 | Y67: ='Quarterly YTD'!Q67-'Quarterly YTD'!P67 -> 0.313 | Z67: =F67-'Quarterly YTD'!Q67 -> -0.607 | AA67: 0 | AB67: ='Quarterly YTD'!T67-AA67 -> 0 | AC67: ='Quarterly YTD'!U67-'Quarterly YTD'!T67 -> 0 | AD67: =G67-'Quarterly YTD'!U67 -> 0 | AE67: 0 | AF67: ='Quarterly YTD'!X67-AE67 -> 0 | AG67: ='Quarterly YTD'!Y67-'Quarterly YTD'!X67 -> 0 | AH67: =H67-'Quarterly YTD'!Y67 -> 0 | AI67: 0 | AJ67: ='Quarterly YTD'!AB67-AI67 -> 0 | AK67: ='Quarterly YTD'!AC67-'Quarterly YTD'!AB67 -> 0 | AL67: =I67-'Quarterly YTD'!AC67 -> 0 | AM67: 0 | AN67: ='Quarterly YTD'!AF67-AM67 -> 0
A68: Disposal of other investments | B68: 0 | C68: 0 | D68: 2.117 | E68: 6.37 | F68: 0.287 | G68: 0.209 | H68: 5.107 | I68: 6.773 | J68: =I68+'Quarterly YTD'!AF68-'Quarterly YTD'!AB68 -> -0.438 | K68: 0 | L68: ='Quarterly YTD'!D68-K68 -> 0 | M68: ='Quarterly YTD'!E68-'Quarterly YTD'!D68 -> 0 | N68: =C68-'Quarterly YTD'!E68 -> 0 | O68: 0 | P68: ='Quarterly YTD'!H68-O68 -> 0 | Q68: ='Quarterly YTD'!I68-'Quarterly YTD'!H68 -> 0 | R68: =D68-'Quarterly YTD'!I68 -> 2.117 | S68: 0 | T68: ='Quarterly YTD'!L68-S68 -> 0 | U68: ='Quarterly YTD'!M68-'Quarterly YTD'!L68 -> 2.275 | V68: =E68-'Quarterly YTD'!M68 -> 4.095 | W68: 0.269 | X68: ='Quarterly YTD'!P68-W68 -> 0.007 | Y68: ='Quarterly YTD'!Q68-'Quarterly YTD'!P68 -> 0.008 | Z68: =F68-'Quarterly YTD'!Q68 -> 0.003 | AA68: 0 | AB68: ='Quarterly YTD'!T68-AA68 -> 0.487 | AC68: ='Quarterly YTD'!U68-'Quarterly YTD'!T68 -> -0.167 | AD68: =G68-'Quarterly YTD'!U68 -> -0.111 | AE68: 0.061 | AF68: ='Quarterly YTD'!X68-AE68 -> -0.002 | AG68: ='Quarterly YTD'!Y68-'Quarterly YTD'!X68 -> 3.573 | AH68: =H68-'Quarterly YTD'!Y68 -> 1.475 | AI68: 0.001 | AJ68: ='Quarterly YTD'!AB68-AI68 -> 7.219 | AK68: ='Quarterly YTD'!AC68-'Quarterly YTD'!AB68 -> 0.025 | AL68: =I68-'Quarterly YTD'!AC68 -> -0.472 | AM68: 0 | AN68: ='Quarterly YTD'!AF68-AM68 -> 0.009
A69: Loans granted | B69: -1.471 | C69: -2.729 | D69: -4.733 | E69: -10.733 | F69: -5.108 | G69: -4.541 | H69: -6.028 | I69: -1.797 | J69: =I69+'Quarterly YTD'!AF69-'Quarterly YTD'!AB69 -> -7.039 | K69: -0.586 | L69: ='Quarterly YTD'!D69-K69 -> -0.069 | M69: ='Quarterly YTD'!E69-'Quarterly YTD'!D69 -> -0.164 | N69: =C69-'Quarterly YTD'!E69 -> -1.91 | O69: -0.511 | P69: ='Quarterly YTD'!H69-O69 -> -3.023 | Q69: ='Quarterly YTD'!I69-'Quarterly YTD'!H69 -> -0.698 | R69: =D69-'Quarterly YTD'!I69 -> -0.501 | S69: -2.131 | T69: ='Quarterly YTD'!L69-S69 -> -1.496 | U69: ='Quarterly YTD'!M69-'Quarterly YTD'!L69 -> -6.972 | V69: =E69-'Quarterly YTD'!M69 -> -0.134 | W69: -0.729 | X69: ='Quarterly YTD'!P69-W69 -> -3.283 | Y69: ='Quarterly YTD'!Q69-'Quarterly YTD'!P69 -> -10.104 | Z69: =F69-'Quarterly YTD'!Q69 -> 9.008 | AA69: -0.011 | AB69: ='Quarterly YTD'!T69-AA69 -> -4.019 | AC69: ='Quarterly YTD'!U69-'Quarterly YTD'!T69 -> -0.006 | AD69: =G69-'Quarterly YTD'!U69 -> -0.505 | AE69: -4.437 | AF69: ='Quarterly YTD'!X69-AE69 -> -0.074 | AG69: ='Quarterly YTD'!Y69-'Quarterly YTD'!X69 -> -0.538 | AH69: =H69-'Quarterly YTD'!Y69 -> -0.979 | AI69: -0.035 | AJ69: ='Quarterly YTD'!AB69-AI69 -> -1.229 | AK69: ='Quarterly YTD'!AC69-'Quarterly YTD'!AB69 -> -0.006 | AL69: =I69-'Quarterly YTD'!AC69 -> -0.527 | AM69: -2.965 | AN69: ='Quarterly YTD'!AF69-AM69 -> -3.541
A70: Repayment of loans granted | B70: 1.023 | C70: 0.312 | D70: 0.182 | E70: 1.311 | F70: 3.139 | G70: 2.876 | H70: 1.835 | I70: 1.482 | J70: =I70+'Quarterly YTD'!AF70-'Quarterly YTD'!AB70 -> 0.665 | K70: 0.313 | L70: ='Quarterly YTD'!D70-K70 -> -0.298 | M70: ='Quarterly YTD'!E70-'Quarterly YTD'!D70 -> 0 | N70: =C70-'Quarterly YTD'!E70 -> 0.297 | O70: 0.177 | P70: ='Quarterly YTD'!H70-O70 -> -0.02 | Q70: ='Quarterly YTD'!I70-'Quarterly YTD'!H70 -> 0.01 | R70: =D70-'Quarterly YTD'!I70 -> 0.015 | S70: 0.008 | T70: ='Quarterly YTD'!L70-S70 -> 0 | U70: ='Quarterly YTD'!M70-'Quarterly YTD'!L70 -> 1.171 | V70: =E70-'Quarterly YTD'!M70 -> 0.132 | W70: 1.785 | X70: ='Quarterly YTD'!P70-W70 -> 0.648 | Y70: ='Quarterly YTD'!Q70-'Quarterly YTD'!P70 -> 0.666 | Z70: =F70-'Quarterly YTD'!Q70 -> 0.04 | AA70: 0.027 | AB70: ='Quarterly YTD'!T70-AA70 -> 2.195 | AC70: ='Quarterly YTD'!U70-'Quarterly YTD'!T70 -> 0.003 | AD70: =G70-'Quarterly YTD'!U70 -> 0.651 | AE70: 0.047 | AF70: ='Quarterly YTD'!X70-AE70 -> 0.345 | AG70: ='Quarterly YTD'!Y70-'Quarterly YTD'!X70 -> 0.55 | AH70: =H70-'Quarterly YTD'!Y70 -> 0.893 | AI70: 0.358 | AJ70: ='Quarterly YTD'!AB70-AI70 -> 1.025 | AK70: ='Quarterly YTD'!AC70-'Quarterly YTD'!AB70 -> 0.043 | AL70: =I70-'Quarterly YTD'!AC70 -> 0.056 | AM70: 0.079 | AN70: ='Quarterly YTD'!AF70-AM70 -> 0.487
A71: Bank deposits repaid | B71: 0 | C71: -84.994 | D71: -363.039 | E71: -225.941 | F71: -1.553 | G71: -1.5 | H71: -0.581 | I71: 2.142 | J71: =I71+'Quarterly YTD'!AF71-'Quarterly YTD'!AB71 -> -6.881 | K71: -0.567 | L71: ='Quarterly YTD'!D71-K71 -> 0.567 | M71: ='Quarterly YTD'!E71-'Quarterly YTD'!D71 -> 0 | N71: =C71-'Quarterly YTD'!E71 -> -84.994 | O71: -141.549 | P71: ='Quarterly YTD'!H71-O71 -> -134.554 | Q71: ='Quarterly YTD'!I71-'Quarterly YTD'!H71 -> -21.477 | R71: =D71-'Quarterly YTD'!I71 -> -65.459 | S71: -0.374 | T71: ='Quarterly YTD'!L71-S71 -> -0.539 | U71: ='Quarterly YTD'!M71-'Quarterly YTD'!L71 -> -0.017 | V71: =E71-'Quarterly YTD'!M71 -> -225.011 | W71: -0.026 | X71: ='Quarterly YTD'!P71-W71 -> -1.424 | Y71: ='Quarterly YTD'!Q71-'Quarterly YTD'!P71 -> 1.45 | Z71: =F71-'Quarterly YTD'!Q71 -> -1.553 | AA71: 1.398 | AB71: ='Quarterly YTD'!T71-AA71 -> -0.016 | AC71: ='Quarterly YTD'!U71-'Quarterly YTD'!T71 -> -0.069 | AD71: =G71-'Quarterly YTD'!U71 -> -2.813 | AE71: 2.175 | AF71: ='Quarterly YTD'!X71-AE71 -> -11.422 | AG71: ='Quarterly YTD'!Y71-'Quarterly YTD'!X71 -> -9.452 | AH71: =H71-'Quarterly YTD'!Y71 -> 18.118 | AI71: 2.998 | AJ71: ='Quarterly YTD'!AB71-AI71 -> -0.234 | AK71: ='Quarterly YTD'!AC71-'Quarterly YTD'!AB71 -> 0.772 | AL71: =I71-'Quarterly YTD'!AC71 -> -1.394 | AM71: -0.444 | AN71: ='Quarterly YTD'!AF71-AM71 -> -5.815
A72: Repayments of bank deposits placed | B72: 0 | C72: 0 | D72: 418.311 | E72: 26.471 | F72: 226.651 | G72: 0 | H72: 0 | I72: 0 | J72: =I72+'Quarterly YTD'!AF72-'Quarterly YTD'!AB72 -> 0 | K72: 0.047 | L72: ='Quarterly YTD'!D72-K72 -> -0.047 | M72: ='Quarterly YTD'!E72-'Quarterly YTD'!D72 -> 0 | N72: =C72-'Quarterly YTD'!E72 -> 0 | O72: 54.407 | P72: ='Quarterly YTD'!H72-O72 -> 233.408 | Q72: ='Quarterly YTD'!I72-'Quarterly YTD'!H72 -> 66.164 | R72: =D72-'Quarterly YTD'!I72 -> 64.332 | S72: 0.913 | T72: ='Quarterly YTD'!L72-S72 -> 25.065 | U72: ='Quarterly YTD'!M72-'Quarterly YTD'!L72 -> 0.196 | V72: =E72-'Quarterly YTD'!M72 -> 0.297 | W72: 90.073 | X72: ='Quarterly YTD'!P72-W72 -> 49.512 | Y72: ='Quarterly YTD'!Q72-'Quarterly YTD'!P72 -> -65.673 | Z72: =F72-'Quarterly YTD'!Q72 -> 152.739 | AA72: 0 | AB72: ='Quarterly YTD'!T72-AA72 -> 0 | AC72: ='Quarterly YTD'!U72-'Quarterly YTD'!T72 -> 0 | AD72: =G72-'Quarterly YTD'!U72 -> 0 | AE72: 0 | AF72: ='Quarterly YTD'!X72-AE72 -> 0 | AG72: ='Quarterly YTD'!Y72-'Quarterly YTD'!X72 -> 0 | AH72: =H72-'Quarterly YTD'!Y72 -> 0 | AI72: 0 | AJ72: ='Quarterly YTD'!AB72-AI72 -> 0 | AK72: ='Quarterly YTD'!AC72-'Quarterly YTD'!AB72 -> 0 | AL72: =I72-'Quarterly YTD'!AC72 -> 0 | AM72: 0 | AN72: ='Quarterly YTD'!AF72-AM72 -> 0
... A74: Repayments of security deposits placed | B74: 0 | C74: 0 | D74: 0 | E74: 0 | F74: 0 | G74: 0 | H74: 0 | I74: 0 | J74: =I74+'Quarterly YTD'!AF74-'Quarterly YTD'!AB74 -> 0 | K74: 0 | L74: ='Quarterly YTD'!D74-K74 -> 0.052 | M74: ='Quarterly YTD'!E74-'Quarterly YTD'!D74 -> 0.08 | N74: =C74-'Quarterly YTD'!E74 -> -0.132 | O74: 0 | P74: ='Quarterly YTD'!H74-O74 -> 2.981 | Q74: ='Quarterly YTD'!I74-'Quarterly YTD'!H74 -> -0.366 | R74: =D74-'Quarterly YTD'!I74 -> -2.615 | S74: 0 | T74: ='Quarterly YTD'!L74-S74 -> 0 | U74: ='Quarterly YTD'!M74-'Quarterly YTD'!L74 -> 0 | V74: =E74-'Quarterly YTD'!M74 -> 0 | W74: 0 | X74: ='Quarterly YTD'!P74-W74 -> 0 | Y74: ='Quarterly YTD'!Q74-'Quarterly YTD'!P74 -> 0 | Z74: =F74-'Quarterly YTD'!Q74 -> 0 | AA74: 0 | AB74: ='Quarterly YTD'!T74-AA74 -> 0 | AC74: ='Quarterly YTD'!U74-'Quarterly YTD'!T74 -> 0 | AD74: =G74-'Quarterly YTD'!U74 -> 0 | AE74: 0 | AF74: ='Quarterly YTD'!X74-AE74 -> 0 | AG74: ='Quarterly YTD'!Y74-'Quarterly YTD'!X74 -> 0 | AH74: =H74-'Quarterly YTD'!Y74 -> 0 | AI74: 0 | AJ74: ='Quarterly YTD'!AB74-AI74 -> 0 | AK74: ='Quarterly YTD'!AC74-'Quarterly YTD'!AB74 -> 0 | AL74: =I74-'Quarterly YTD'!AC74 -> 0 | AM74: 0 | AN74: ='Quarterly YTD'!AF74-AM74 -> 0
A75: Purchase of subsidiaries (net of cash acquired) | B75: -3.239 | C75: 83.741 | D75: -21.351 | E75: -22.826 | F75: 0 | G75: -9.473 | H75: -11.888 | I75: 0 | J75: =I75+'Quarterly YTD'!AF75-'Quarterly YTD'!AB75 -> -24.812 | K75: 0 | L75: ='Quarterly YTD'!D75-K75 -> 0.164 | M75: ='Quarterly YTD'!E75-'Quarterly YTD'!D75 -> 0 | N75: =C75-'Quarterly YTD'!E75 -> 83.577 | O75: -3.925 | P75: ='Quarterly YTD'!H75-O75 -> -1.838 | Q75: ='Quarterly YTD'!I75-'Quarterly YTD'!H75 -> -0.027 | R75: =D75-'Quarterly YTD'!I75 -> -15.561 | S75: -3.605 | T75: ='Quarterly YTD'!L75-S75 -> 0 | U75: ='Quarterly YTD'!M75-'Quarterly YTD'!L75 -> -6.513 | V75: =E75-'Quarterly YTD'!M75 -> -12.708 | W75: 0 | X75: ='Quarterly YTD'!P75-W75 -> 0 | Y75: ='Quarterly YTD'!Q75-'Quarterly YTD'!P75 -> 9.631 | Z75: =F75-'Quarterly YTD'!Q75 -> -9.631 | AA75: -2.008 | AB75: ='Quarterly YTD'!T75-AA75 -> -4.393 | AC75: ='Quarterly YTD'!U75-'Quarterly YTD'!T75 -> -3.869 | AD75: =G75-'Quarterly YTD'!U75 -> 0.797 | AE75: -5.729 | AF75: ='Quarterly YTD'!X75-AE75 -> 2.873 | AG75: ='Quarterly YTD'!Y75-'Quarterly YTD'!X75 -> -4.368 | AH75: =H75-'Quarterly YTD'!Y75 -> -4.664 | AI75: 0 | AJ75: ='Quarterly YTD'!AB75-AI75 -> -0.012 | AK75: ='Quarterly YTD'!AC75-'Quarterly YTD'!AB75+-0.012 -> 0 | AL75: =I75-'Quarterly YTD'!AC75 -> 0 | AM75: -27.788 | AN75: ='Quarterly YTD'!AF75-AM75 -> 2.964
A76: Net cash generated from (used in) investing activities from continued operations | B76: =B61+B63+SUM(B69:B71)+B75+SUM(B77:B78) -> -30.78 | C76: =C61+C63+SUM(C67:C71)+C75+SUM(C77:C79) -> -41.352 | D76: =D61+D63+SUM(D67:D72)+D75+SUM(D77:D79) -> -84.247 | E76: =E61+SUM(E63:E64)+SUM(E67:E72)+E75+SUM(E77:E78) -> -292.192 | F76: =SUM(F61:F63)+SUM(F65:F72)+F75+F77+F79 -> 84.892 | G76: =SUM(G61:G63)+G66+SUM(G68:G71)+G75+G77+G79 -> -180.123 | H76: =SUM(H61:H63)+H66+SUM(H68:H71)+H75+H77+SUM(H79:H80) -> -190.521 | I76: =SUM(I61:I63)+I66+SUM(I68:I71)+I75+I77+SUM(I79:I80) -> -114.056 | J76: =SUM(J61:J75)+SUM(J77:J80) -> -192.585 | K76: =K61+K63+SUM(K69:K72)+K75+SUM(K78:K79) -> -8.236 | L76: =SUM(L61:L75)+SUM(L77:L80) -> -15.969 | M76: =SUM(M61:M75)+SUM(M77:M80) -> 14.877 | N76: =SUM(N61:N75)+SUM(N77:N80) -> -32.024 | O76: =O61+O63+SUM(O69:O72)+O75+SUM(O78:O79) -> -121.293 | P76: =SUM(P61:P75)+SUM(P77:P80) -> 61.258 | Q76: =SUM(Q61:Q75)+SUM(Q77:Q80) -> 25.066 | R76: =SUM(R61:R75)+SUM(R77:R80) -> -49.278 | S76: =S61+S63+S67+SUM(S69:S72)+S75+S77 -> -31.391 | T76: =SUM(T61:T75)+SUM(T77:T80) -> 10.451 | U76: =SUM(U61:U75)+SUM(U77:U80) -> -16.805 | V76: =SUM(V61:V75)+SUM(V77:V80) -> -254.447 | W76: =W61+W63+SUM(W67:W72)+W75+W77 -> 71.352 | X76: =SUM(X61:X75)+SUM(X77:X80) -> 27.386 | Y76: =SUM(Y61:Y75)+SUM(Y77:Y80) -> -63.178 | Z76: =SUM(Z61:Z75)+SUM(Z77:Z80) -> 49.332 | AA76: =SUM(AA61:AA63)+AA66+SUM(AA68:AA71)+AA75+AA77+AA79 -> -16.845 | AB76: =SUM(AB61:AB75)+SUM(AB77:AB80) -> -64.133 | AC76: =SUM(AC61:AC75)+SUM(AC77:AC80) -> -40.246 | AD76: =SUM(AD61:AD75)+SUM(AD77:AD80) -> -58.899 | AE76: =SUM(AE61:AE63)+AE66+SUM(AE68:AE71)+AE75+AE79 -> -22.324 | AF76: =SUM(AF61:AF75)+SUM(AF77:AF80) -> -40.231 | AG76: =SUM(AG61:AG75)+SUM(AG77:AG80) -> -79.979 | AH76: =SUM(AH61:AH75)+SUM(AH77:AH80) -> -47.987 | AI76: =SUM(AI61:AI63)+AI66+SUM(AI68:AI71)+AI75+AI79 -> -24.077 | AJ76: =SUM(AJ61:AJ75)+SUM(AJ77:AJ80) -> -0.908 | AK76: =SUM(AK61:AK75)+SUM(AK77:AK80) -> -40.649 | AL76: =SUM(AL61:AL75)+SUM(AL77:AL80) -> -48.422 | AM76: =SUM(AM61:AM63)+AM66+SUM(AM68:AM71)+AM75+AM79 -> -42.446 | AN76: =SUM(AN61:AN75)+SUM(AN77:AN80) -> -61.068
A77: Sales of subsidiaries (net of cash disposed) | B77: -1.983 | C77: 0 | D77: -5.951 | E77: 6.413 | F77: -0.074 | G77: 20.137 | H77: 0 | I77: -0.719 | J77: =I77+'Quarterly YTD'!AF77-'Quarterly YTD'!AB77 -> 0.92 | K77: 0 | L77: ='Quarterly YTD'!D77-K77 -> 0 | M77: ='Quarterly YTD'!E77-'Quarterly YTD'!D77 -> 0 | N77: =C77-'Quarterly YTD'!E77 -> 0 | O77: 0 | P77: ='Quarterly YTD'!H77-O77 -> 0.038 | Q77: ='Quarterly YTD'!I77-'Quarterly YTD'!H77 -> 0 | R77: =D77-'Quarterly YTD'!I77 -> -5.989 | S77: 0 | T77: ='Quarterly YTD'!L77-S77 -> 0 | U77: ='Quarterly YTD'!M77-'Quarterly YTD'!L77 -> 6.413 | V77: =E77-'Quarterly YTD'!M77 -> 0 | W77: -0.042 | X77: ='Quarterly YTD'!P77-W77 -> -0.013 | Y77: ='Quarterly YTD'!Q77-'Quarterly YTD'!P77 -> 0 | Z77: =F77-'Quarterly YTD'!Q77 -> -0.019 | AA77: 20.262 | AB77: ='Quarterly YTD'!T77-AA77 -> -0.115 | AC77: ='Quarterly YTD'!U77-'Quarterly YTD'!T77 -> -0.05 | AD77: =G77-'Quarterly YTD'!U77 -> 0.04 | AE77: 0 | AF77: ='Quarterly YTD'!X77-AE77 -> 0 | AG77: ='Quarterly YTD'!Y77-'Quarterly YTD'!X77 -> 0 | AH77: =H77-'Quarterly YTD'!Y77 -> 0 | AI77: 0 | AJ77: ='Quarterly YTD'!AB77-AI77 -> 0 | AK77: ='Quarterly YTD'!AC77-'Quarterly YTD'!AB77 -> -0.363 | AL77: =I77-'Quarterly YTD'!AC77 -> -0.356 | AM77: 0 | AN77: ='Quarterly YTD'!AF77-AM77 -> 1.639
A78: Investment into joint venture | B78: -0.103 | C78: -1.43 | D78: -1.658 | E78: -0.507 | F78: 0 | G78: 0 | H78: 0 | I78: 0 | J78: =I78+'Quarterly YTD'!AF78-'Quarterly YTD'!AB78 -> 0 | K78: -4.239 | L78: ='Quarterly YTD'!D78-K78 -> 2.893 | M78: ='Quarterly YTD'!E78-'Quarterly YTD'!D78 -> -0.087 | N78: =C78-'Quarterly YTD'!E78 -> 0.003 | O78: -0.272 | P78: ='Quarterly YTD'!H78-O78 -> -1.386 | Q78: ='Quarterly YTD'!I78-'Quarterly YTD'!H78 -> 0 | R78: =D78-'Quarterly YTD'!I78 -> 0 | S78: 0 | T78: ='Quarterly YTD'!L78-S78 -> 0 | U78: ='Quarterly YTD'!M78-'Quarterly YTD'!L78 -> 0 | V78: =E78-'Quarterly YTD'!M78 -> -0.507 | W78: 0 | X78: ='Quarterly YTD'!P78-W78 -> 0 | Y78: ='Quarterly YTD'!Q78-'Quarterly YTD'!P78 -> 0 | Z78: =F78-'Quarterly YTD'!Q78 -> 0 | AA78: 0 | AB78: ='Quarterly YTD'!T78-AA78 -> 0 | AC78: ='Quarterly YTD'!U78-'Quarterly YTD'!T78 -> 0 | AD78: =G78-'Quarterly YTD'!U78 -> 0 | AE78: 0 | AF78: ='Quarterly YTD'!X78-AE78 -> 0 | AG78: ='Quarterly YTD'!Y78-'Quarterly YTD'!X78 -> 0 | AH78: =H78-'Quarterly YTD'!Y78 -> 0 | AI78: 0 | AJ78: ='Quarterly YTD'!AB78-AI78 -> 0 | AK78: ='Quarterly YTD'!AC78-'Quarterly YTD'!AB78 -> 0 | AL78: =I78-'Quarterly YTD'!AC78 -> 0 | AM78: 0 | AN78: ='Quarterly YTD'!AF78-AM78 -> 0
A79: Payments for financial assets at amortised cost | B79: 0 | C79: 0 | D79: -23.568 | E79: 0 | F79: 0 | G79: -1.82 | H79: -2.877 | I79: 0 | J79: =I79+'Quarterly YTD'!AF79-'Quarterly YTD'!AB79 -> -4.832 | K79: 0 | L79: ='Quarterly YTD'!D79-K79 -> 0 | M79: ='Quarterly YTD'!E79-'Quarterly YTD'!D79 -> 0 | N79: =C79-'Quarterly YTD'!E79 -> 0 | O79: -11.508 | P79: ='Quarterly YTD'!H79-O79 -> -0.06 | Q79: ='Quarterly YTD'!I79-'Quarterly YTD'!H79 -> 0 | R79: =D79-'Quarterly YTD'!I79 -> -12 | S79: 0 | T79: ='Quarterly YTD'!L79-S79 -> 0 | U79: ='Quarterly YTD'!M79-'Quarterly YTD'!L79 -> 0 | V79: =E79-'Quarterly YTD'!M79 -> 0 | W79: 0 | X79: ='Quarterly YTD'!P79-W79 -> 0 | Y79: ='Quarterly YTD'!Q79-'Quarterly YTD'!P79 -> 0 | Z79: =F79-'Quarterly YTD'!Q79 -> 0 | AA79: 0 | AB79: ='Quarterly YTD'!T79-AA79 -> 0 | AC79: ='Quarterly YTD'!U79-'Quarterly YTD'!T79 -> -1.82 | AD79: =G79-'Quarterly YTD'!U79 -> 0 | AE79: -2.83 | AF79: ='Quarterly YTD'!X79-AE79 -> 0 | AG79: ='Quarterly YTD'!Y79-'Quarterly YTD'!X79 -> -0.045 | AH79: =H79-'Quarterly YTD'!Y79 -> -0.002 | AI79: 0 | AJ79: ='Quarterly YTD'!AB79-AI79 -> 0 | AK79: ='Quarterly YTD'!AC79-'Quarterly YTD'!AB79+0.012 -> 0 | AL79: =I79-'Quarterly YTD'!AC79 -> 0.012 | AM79: -4.819 | AN79: ='Quarterly YTD'!AF79-AM79 -> -0.013
A80: Receipt of government grants | B80: 0 | C80: 0 | D80: 0 | E80: 0 | F80: 0 | G80: 0 | H80: 0 | I80: 0.775 | J80: =I80+'Quarterly YTD'!AF80-'Quarterly YTD'!AB80 -> 0.052 | K80: 0 | L80: ='Quarterly YTD'!D80-K80 -> 0 | M80: ='Quarterly YTD'!E80-'Quarterly YTD'!D80 -> 0 | N80: =C80-'Quarterly YTD'!E80 -> 0 | O80: 0 | P80: ='Quarterly YTD'!H80-O80 -> 0 | Q80: ='Quarterly YTD'!I80-'Quarterly YTD'!H80 -> 0 | R80: =D80-'Quarterly YTD'!I80 -> 0 | S80: 0 | T80: ='Quarterly YTD'!L80-S80 -> 0 | U80: ='Quarterly YTD'!M80-'Quarterly YTD'!L80 -> 0 | V80: =E80-'Quarterly YTD'!M80 -> 0 | W80: 0 | X80: ='Quarterly YTD'!P80-W80 -> 0 | Y80: ='Quarterly YTD'!Q80-'Quarterly YTD'!P80 -> 0 | Z80: =F80-'Quarterly YTD'!Q80 -> 0 | AA80: 0 | AB80: ='Quarterly YTD'!T80-AA80 -> 0 | AC80: ='Quarterly YTD'!U80-'Quarterly YTD'!T80 -> 0 | AD80: =G80-'Quarterly YTD'!U80 -> 0 | AE80: 0 | AF80: ='Quarterly YTD'!X80-AE80 -> 0 | AG80: ='Quarterly YTD'!Y80-'Quarterly YTD'!X80 -> 0 | AH80: =H80-'Quarterly YTD'!Y80 -> 0 | AI80: 0 | AJ80: ='Quarterly YTD'!AB80-AI80 -> 0.775 | AK80: ='Quarterly YTD'!AC80-'Quarterly YTD'!AB80 -> 0 | AL80: =I80-'Quarterly YTD'!AC80 -> 0 | AM80: 0 | AN80: ='Quarterly YTD'!AF80-AM80 -> 0.052
A81: Net cash used in investing activities | B81: =B76 -> -30.78 | C81: =C76 -> -41.352 | D81: =D76 -> -84.247 | E81: =E76 -> -292.192 | F81: =F76 -> 84.892 | G81: =G76 -> -180.123 | H81: =H76 -> -190.521 | I81: =I76 -> -114.056 | ... AN81: =AN76 -> -61.068 | AO81: =IF(AND(AN81=0,AM81=0),0,IF(OR(AM81=0,AM81="NM",AN81="NM"),"NM",IF(AM81<0,(AN81/AM81-1),-(AN81/AM81-1)))) -> 0.43872214 | AP81: =IF(AND(AN81=0,AJ81=0),0,IF(OR(AJ81=0,AJ81="NM",AN81="NM"),"NM",IF(AJ81<0,(AN81/AJ81-1),-(AN81/AJ81-1)))) -> 66.255507
A82: Acquisition of interest in a subsidiary | B82: -0.049 | C82: 0 | D82: 0 | E82: 0 | F82: 0 | G82: 0 | H82: 0 | I82: 0 | J82: =I82+'Quarterly YTD'!AF82-'Quarterly YTD'!AB82 -> 0 | K82: 0 | L82: ='Quarterly YTD'!D82-K82 -> -0.005 | M82: ='Quarterly YTD'!E82-'Quarterly YTD'!D82 -> 0 | N82: =C82-'Quarterly YTD'!E82 -> 0.005 | O82: 0 | P82: ='Quarterly YTD'!H82-O82 -> 0 | Q82: ='Quarterly YTD'!I82-'Quarterly YTD'!H82 -> 0 | R82: =D82-'Quarterly YTD'!I82 -> 0 | S82: 0 | T82: ='Quarterly YTD'!L82-S82 -> 0 | U82: ='Quarterly YTD'!M82-'Quarterly YTD'!L82 -> 0 | V82: =E82-'Quarterly YTD'!M82 -> 0 | W82: 0 | X82: ='Quarterly YTD'!P82-W82 -> 0 | Y82: ='Quarterly YTD'!Q82-'Quarterly YTD'!P82 -> 0 | Z82: =F82-'Quarterly YTD'!Q82 -> 0 | AA82: 0 | AB82: ='Quarterly YTD'!T82-AA82 -> 0 | AC82: ='Quarterly YTD'!U82-'Quarterly YTD'!T82 -> 0 | AD82: =G82-'Quarterly YTD'!U82 -> 0 | AE82: 0 | AF82: ='Quarterly YTD'!X82-AE82 -> 0 | AG82: ='Quarterly YTD'!Y82-'Quarterly YTD'!X82 -> 0 | AH82: =H82-'Quarterly YTD'!Y82 -> 0 | AI82: 0 | AJ82: ='Quarterly YTD'!AB82-AI82 -> 0 | AK82: ='Quarterly YTD'!AC82-'Quarterly YTD'!AB82 -> 0 | AL82: =I82-'Quarterly YTD'!AC82 -> 0 | AM82: 0 | AN82: ='Quarterly YTD'!AF82-AM82 -> 0
A83: Dividends paid | B83: 0 | C83: 0 | D83: -0.675 | E83: -0.293 | F83: -30.328 | G83: -25.995 | H83: -1.492 | I83: -2.097 | J83: =I83+'Quarterly YTD'!AF83-'Quarterly YTD'!AB83 -> -2.92 | K83: 0 | L83: ='Quarterly YTD'!D83-K83 -> 0 | M83: ='Quarterly YTD'!E83-'Quarterly YTD'!D83 -> 0 | N83: =C83-'Quarterly YTD'!E83 -> 0 | O83: 0 | P83: ='Quarterly YTD'!H83-O83 -> 0 | Q83: ='Quarterly YTD'!I83-'Quarterly YTD'!H83 -> 0 | R83: =D83-'Quarterly YTD'!I83 -> -0.675 | S83: -0.293 | T83: ='Quarterly YTD'!L83-S83 -> 0 | U83: ='Quarterly YTD'!M83-'Quarterly YTD'!L83 -> 0 | V83: =E83-'Quarterly YTD'!M83 -> 0 | W83: 0 | X83: ='Quarterly YTD'!P83-W83 -> -29.764 | Y83: ='Quarterly YTD'!Q83-'Quarterly YTD'!P83 -> -0.529 | Z83: =F83-'Quarterly YTD'!Q83 -> -0.035 | AA83: 0 | AB83: ='Quarterly YTD'!T83-AA83 -> -0.572 | AC83: ='Quarterly YTD'!U83-'Quarterly YTD'!T83 -> -0.736 | AD83: =G83-'Quarterly YTD'!U83 -> -24.687 | AE83: -0.07 | AF83: ='Quarterly YTD'!X83-AE83 -> -0.665 | AG83: ='Quarterly YTD'!Y83-'Quarterly YTD'!X83 -> -0.289 | AH83: =H83-'Quarterly YTD'!Y83 -> -0.468 | AI83: -0.148 | AJ83: ='Quarterly YTD'!AB83-AI83 -> -0.105 | AK83: ='Quarterly YTD'!AC83-'Quarterly YTD'!AB83 -> -1.844 | AL83: =I83-'Quarterly YTD'!AC83 -> 0 | AM83: -0.155 | AN83: ='Quarterly YTD'!AF83-AM83 -> -0.921
A84: Issuance of convertible preferred shares | B84: 0 | C84: 0 | D84: 0 | E84: 300 | F84: 0 | G84: 0 | H84: 0 | I84: 0 | J84: =I84+'Quarterly YTD'!AF84-'Quarterly YTD'!AB84 -> 0 | K84: 0 | L84: ='Quarterly YTD'!D84-K84 -> 0 | M84: ='Quarterly YTD'!E84-'Quarterly YTD'!D84 -> 0 | N84: =C84-'Quarterly YTD'!E84 -> 0 | O84: 0 | P84: ='Quarterly YTD'!H84-O84 -> 0 | Q84: ='Quarterly YTD'!I84-'Quarterly YTD'!H84 -> 0 | R84: =D84-'Quarterly YTD'!I84 -> 0 | S84: 0 | T84: ='Quarterly YTD'!L84-S84 -> 0 | U84: ='Quarterly YTD'!M84-'Quarterly YTD'!L84 -> 0 | V84: =E84-'Quarterly YTD'!M84 -> 300 | W84: 0 | X84: ='Quarterly YTD'!P84-W84 -> 0 | Y84: ='Quarterly YTD'!Q84-'Quarterly YTD'!P84 -> 0 | Z84: =F84-'Quarterly YTD'!Q84 -> 0 | AA84: 0 | AB84: ='Quarterly YTD'!T84-AA84 -> 0 | AC84: ='Quarterly YTD'!U84-'Quarterly YTD'!T84 -> 0 | AD84: =G84-'Quarterly YTD'!U84 -> 0 | AE84: 0 | AF84: ='Quarterly YTD'!X84-AE84 -> 0 | AG84: ='Quarterly YTD'!Y84-'Quarterly YTD'!X84 -> 0 | AH84: =H84-'Quarterly YTD'!Y84 -> 0 | AI84: 0 | AJ84: ='Quarterly YTD'!AB84-AI84 -> 0 | AK84: ='Quarterly YTD'!AC84-'Quarterly YTD'!AB84 -> 0 | AL84: =I84-'Quarterly YTD'!AC84 -> 0 | AM84: 0 | AN84: ='Quarterly YTD'!AF84-AM84 -> 0
A85: Acquisition of interest in asubsidiary (no change in control) | B85: 0 | C85: -0.004 | D85: -2.905 | E85: 0 | F85: 0 | G85: 0 | H85: 0 | I85: 0 | J85: =I85+'Quarterly YTD'!AF85-'Quarterly YTD'!AB85 -> 0 | K85: 0 | L85: ='Quarterly YTD'!D85-K85 -> 0 | M85: ='Quarterly YTD'!E85-'Quarterly YTD'!D85 -> 0 | N85: =C85-'Quarterly YTD'!E85 -> -0.004 | O85: 0 | P85: ='Quarterly YTD'!H85-O85 -> 0 | Q85: ='Quarterly YTD'!I85-'Quarterly YTD'!H85 -> 0 | R85: =D85-'Quarterly YTD'!I85 -> -2.905 | S85: 0 | T85: ='Quarterly YTD'!L85-S85 -> 0 | U85: ='Quarterly YTD'!M85-'Quarterly YTD'!L85 -> 0 | V85: =E85-'Quarterly YTD'!M85 -> 0 | W85: 0 | X85: ='Quarterly YTD'!P85-W85 -> 0 | Y85: ='Quarterly YTD'!Q85-'Quarterly YTD'!P85 -> 0 | Z85: =F85-'Quarterly YTD'!Q85 -> 0 | AA85: 0 | AB85: ='Quarterly YTD'!T85-AA85 -> 0 | AC85: ='Quarterly YTD'!U85-'Quarterly YTD'!T85 -> 0 | AD85: =G85-'Quarterly YTD'!U85 -> 0 | AE85: 0 | AF85: ='Quarterly YTD'!X85-AE85 -> 0 | AG85: ='Quarterly YTD'!Y85-'Quarterly YTD'!X85 -> 0 | AH85: =H85-'Quarterly YTD'!Y85 -> 0 | AI85: 0 | AJ85: ='Quarterly YTD'!AB85-AI85 -> 0 | AK85: ='Quarterly YTD'!AC85-'Quarterly YTD'!AB85 -> 0 | AL85: =I85-'Quarterly YTD'!AC85 -> 0 | AM85: 0 | AN85: ='Quarterly YTD'!AF85-AM85 -> 0
A86: Disposal of interest in a subsidiary (no change in control) | B86: 0 | C86: 0 | D86: 0 | E86: 0 | F86: 0 | G86: 0 | H86: 0 | I86: 0 | J86: =I86+'Quarterly YTD'!AF86-'Quarterly YTD'!AB86 -> 0 | K86: 0 | L86: ='Quarterly YTD'!D86-K86 -> 0 | M86: ='Quarterly YTD'!E86-'Quarterly YTD'!D86 -> 0 | N86: =C86-'Quarterly YTD'!E86 -> 0 | O86: 0 | P86: ='Quarterly YTD'!H86-O86 -> 0 | Q86: ='Quarterly YTD'!I86-'Quarterly YTD'!H86 -> 0 | R86: =D86-'Quarterly YTD'!I86 -> 0 | S86: 0 | T86: ='Quarterly YTD'!L86-S86 -> 0 | U86: ='Quarterly YTD'!M86-'Quarterly YTD'!L86 -> 0 | V86: =E86-'Quarterly YTD'!M86 -> 0 | W86: 0 | X86: ='Quarterly YTD'!P86-W86 -> 0 | Y86: ='Quarterly YTD'!Q86-'Quarterly YTD'!P86 -> 0 | Z86: =F86-'Quarterly YTD'!Q86 -> 0 | AA86: 0 | AB86: ='Quarterly YTD'!T86-AA86 -> 0 | AC86: ='Quarterly YTD'!U86-'Quarterly YTD'!T86 -> 0 | AD86: =G86-'Quarterly YTD'!U86 -> 0 | AE86: 0 | AF86: ='Quarterly YTD'!X86-AE86 -> 0 | AG86: ='Quarterly YTD'!Y86-'Quarterly YTD'!X86 -> 0 | AH86: =H86-'Quarterly YTD'!Y86 -> 0 | AI86: 0 | AJ86: ='Quarterly YTD'!AB86-AI86 -> 0 | AK86: ='Quarterly YTD'!AC86-'Quarterly YTD'!AB86 -> 0 | AL86: =I86-'Quarterly YTD'!AC86 -> 0 | AM86: 0 | AN86: ='Quarterly YTD'!AF86-AM86 -> 0
A87: Increase on non-controlling interest (no change in control) | B87: 0 | C87: 0 | D87: 0 | E87: 0 | F87: -0.048 | G87: -0.359 | H87: 0 | I87: 0 | J87: =I87+'Quarterly YTD'!AF87-'Quarterly YTD'!AB87 -> 0 | K87: 0 | L87: ='Quarterly YTD'!D87-K87 -> 0 | M87: ='Quarterly YTD'!E87-'Quarterly YTD'!D87 -> 0 | N87: =C87-'Quarterly YTD'!E87 -> 0 | O87: 0 | P87: ='Quarterly YTD'!H87-O87 -> 0 | Q87: ='Quarterly YTD'!I87-'Quarterly YTD'!H87 -> 0 | R87: =D87-'Quarterly YTD'!I87 -> 0 | S87: 0 | T87: ='Quarterly YTD'!L87-S87 -> 0 | U87: ='Quarterly YTD'!M87-'Quarterly YTD'!L87 -> 0 | V87: =E87-'Quarterly YTD'!M87 -> 0 | W87: 0 | X87: ='Quarterly YTD'!P87-W87 -> 0 | Y87: ='Quarterly YTD'!Q87-'Quarterly YTD'!P87 -> 0 | Z87: =F87-'Quarterly YTD'!Q87 -> -0.048 | AA87: 0 | AB87: ='Quarterly YTD'!T87-AA87 -> 0 | AC87: ='Quarterly YTD'!U87-'Quarterly YTD'!T87 -> 0 | AD87: =G87-'Quarterly YTD'!U87 -> -0.359 | AE87: 0 | AF87: ='Quarterly YTD'!X87-AE87 -> 0 | AG87: ='Quarterly YTD'!Y87-'Quarterly YTD'!X87 -> 0 | AH87: =H87-'Quarterly YTD'!Y87 -> 0 | AI87: 0 | AJ87: ='Quarterly YTD'!AB87-AI87 -> 0 | AK87: ='Quarterly YTD'!AC87-'Quarterly YTD'!AB87 -> 0 | AL87: =I87-'Quarterly YTD'!AC87 -> 0 | AM87: 0 | AN87: ='Quarterly YTD'!AF87-AM87 -> 0
A88: Bank borrowings received | B88: 14.047 | C88: 5.728 | D88: 8.658 | E88: 22.118 | F88: 11.094 | G88: 1.11 | H88: 33.158 | I88: 80.896 | J88: =I88+'Quarterly YTD'!AF88-'Quarterly YTD'!AB88 -> 156.099 | K88: 0.731 | L88: ='Quarterly YTD'!D88-K88 -> 1.358 | M88: ='Quarterly YTD'!E88-'Quarterly YTD'!D88 -> 0.551 | N88: =C88-'Quarterly YTD'!E88 -> 3.088 | O88: 1.455 | P88: ='Quarterly YTD'!H88-O88 -> 0.001 | Q88: ='Quarterly YTD'!I88-'Quarterly YTD'!H88 -> 0.24 | R88: =D88-'Quarterly YTD'!I88 -> 6.962 | S88: 0.714 | T88: ='Quarterly YTD'!L88-S88 -> 15.843 | U88: ='Quarterly YTD'!M88-'Quarterly YTD'!L88 -> 9.564 | V88: =E88-'Quarterly YTD'!M88 -> -4.003 | W88: 5.426 | X88: ='Quarterly YTD'!P88-W88 -> 5.203 | Y88: ='Quarterly YTD'!Q88-'Quarterly YTD'!P88 -> 0.453 | Z88: =F88-'Quarterly YTD'!Q88 -> 0.012 | AA88: 0 | AB88: ='Quarterly YTD'!T88-AA88 -> 0.276 | AC88: ='Quarterly YTD'!U88-'Quarterly YTD'!T88 -> 1.705 | AD88: =G88-'Quarterly YTD'!U88 -> -0.871 | AE88: 0.839 | AF88: ='Quarterly YTD'!X88-AE88 -> 15.021 | AG88: ='Quarterly YTD'!Y88-'Quarterly YTD'!X88 -> 0.07 | AH88: =H88-'Quarterly YTD'!Y88 -> 17.228 | AI88: 28.516 | AJ88: ='Quarterly YTD'!AB88-AI88 -> 22.791 | AK88: ='Quarterly YTD'!AC88-'Quarterly YTD'!AB88 -> 2.485 | AL88: =I88-'Quarterly YTD'!AC88 -> 27.104 | AM88: 54.916 | AN88: ='Quarterly YTD'!AF88-AM88 -> 71.594
A89: Repayment of bank borrowings | B89: -8.976 | C89: -9.493 | D89: -0.842 | E89: -4.121 | F89: -3.891 | G89: -3.875 | H89: -14.861 | I89: -10.148 | J89: =I89+'Quarterly YTD'!AF89-'Quarterly YTD'!AB89 -> -26.255 | K89: -1.053 | L89: ='Quarterly YTD'!D89-K89 -> -1.475 | M89: ='Quarterly YTD'!E89-'Quarterly YTD'!D89 -> -1.413 | N89: =C89-'Quarterly YTD'!E89 -> -5.552 | O89: -1.082 | P89: ='Quarterly YTD'!H89-O89 -> -0.163 | Q89: ='Quarterly YTD'!I89-'Quarterly YTD'!H89 -> -0.424 | R89: =D89-'Quarterly YTD'!I89 -> 0.827 | S89: -0.584 | T89: ='Quarterly YTD'!L89-S89 -> -0.796 | U89: ='Quarterly YTD'!M89-'Quarterly YTD'!L89 -> -3.473 | V89: =E89-'Quarterly YTD'!M89 -> 0.732 | W89: -0.65 | X89: ='Quarterly YTD'!P89-W89 -> -0.423 | Y89: ='Quarterly YTD'!Q89-'Quarterly YTD'!P89 -> -2.428 | Z89: =F89-'Quarterly YTD'!Q89 -> -0.39 | AA89: -1.314 | AB89: ='Quarterly YTD'!T89-AA89 -> -0.554 | AC89: ='Quarterly YTD'!U89-'Quarterly YTD'!T89 -> -1.359 | AD89: =G89-'Quarterly YTD'!U89 -> -0.648 | AE89: -1.435 | AF89: ='Quarterly YTD'!X89-AE89 -> -0.785 | AG89: ='Quarterly YTD'!Y89-'Quarterly YTD'!X89 -> -2.009 | AH89: =H89-'Quarterly YTD'!Y89 -> -10.632 | AI89: -1.59 | AJ89: ='Quarterly YTD'!AB89-AI89 -> -0.91 | AK89: ='Quarterly YTD'!AC89-'Quarterly YTD'!AB89 -> -3.616 | AL89: =I89-'Quarterly YTD'!AC89 -> -4.032 | AM89: -14.123 | AN89: ='Quarterly YTD'!AF89-AM89 -> -4.484
A90: Borrowings from related parties received | B90: 2.434 | C90: 7.699 | D90: 0 | E90: 0 | F90: 0 | G90: 0 | H90: 0 | I90: 0 | J90: =I90+'Quarterly YTD'!AF90-'Quarterly YTD'!AB90 -> 0 | K90: 2.905 | L90: ='Quarterly YTD'!D90-K90 -> 11.467 | M90: ='Quarterly YTD'!E90-'Quarterly YTD'!D90 -> -0.734 | N90: =C90-'Quarterly YTD'!E90 -> -5.939 | O90: 0 | P90: ='Quarterly YTD'!H90-O90 -> 0 | Q90: ='Quarterly YTD'!I90-'Quarterly YTD'!H90 -> 0 | R90: =D90-'Quarterly YTD'!I90 -> 0 | S90: 0 | T90: ='Quarterly YTD'!L90-S90 -> 0 | U90: ='Quarterly YTD'!M90-'Quarterly YTD'!L90 -> 0 | V90: =E90-'Quarterly YTD'!M90 -> 0 | W90: 0 | X90: ='Quarterly YTD'!P90-W90 -> 0 | Y90: ='Quarterly YTD'!Q90-'Quarterly YTD'!P90 -> 0 | Z90: =F90-'Quarterly YTD'!Q90 -> 0 | AA90: 0 | AB90: ='Quarterly YTD'!T90-AA90 -> 0 | AC90: ='Quarterly YTD'!U90-'Quarterly YTD'!T90 -> 0 | AD90: =G90-'Quarterly YTD'!U90 -> 0 | AE90: 0 | AF90: ='Quarterly YTD'!X90-AE90 -> 0 | AG90: ='Quarterly YTD'!Y90-'Quarterly YTD'!X90 -> 0 | AH90: =H90-'Quarterly YTD'!Y90 -> 0 | AI90: 0 | AJ90: ='Quarterly YTD'!AB90-AI90 -> 0 | AK90: ='Quarterly YTD'!AC90-'Quarterly YTD'!AB90 -> 0 | AL90: =I90-'Quarterly YTD'!AC90 -> 0 | AM90: 0 | AN90: ='Quarterly YTD'!AF90-AM90 -> 0
A91: Repayments of borrowings from related parties | B91: -0.193 | C91: -6.634 | D91: 0 | E91: 0 | F91: 0 | G91: 0 | H91: 0 | I91: 0 | J91: =I91+'Quarterly YTD'!AF91-'Quarterly YTD'!AB91 -> 0 | K91: 0 | L91: ='Quarterly YTD'!D91-K91 -> 0 | M91: ='Quarterly YTD'!E91-'Quarterly YTD'!D91 -> 0 | N91: =C91-'Quarterly YTD'!E91 -> -6.634 | O91: 0 | P91: ='Quarterly YTD'!H91-O91 -> 0 | Q91: ='Quarterly YTD'!I91-'Quarterly YTD'!H91 -> 0 | R91: =D91-'Quarterly YTD'!I91 -> 0 | S91: 0 | T91: ='Quarterly YTD'!L91-S91 -> 0 | U91: ='Quarterly YTD'!M91-'Quarterly YTD'!L91 -> 0 | V91: =E91-'Quarterly YTD'!M91 -> 0 | W91: 0 | X91: ='Quarterly YTD'!P91-W91 -> 0 | Y91: ='Quarterly YTD'!Q91-'Quarterly YTD'!P91 -> 0 | Z91: =F91-'Quarterly YTD'!Q91 -> 0 | AA91: 0 | AB91: ='Quarterly YTD'!T91-AA91 -> 0 | AC91: ='Quarterly YTD'!U91-'Quarterly YTD'!T91 -> 0 | AD91: =G91-'Quarterly YTD'!U91 -> 0 | AE91: 0 | AF91: ='Quarterly YTD'!X91-AE91 -> 0 | AG91: ='Quarterly YTD'!Y91-'Quarterly YTD'!X91 -> 0 | AH91: =H91-'Quarterly YTD'!Y91 -> 0 | AI91: 0 | AJ91: ='Quarterly YTD'!AB91-AI91 -> 0 | AK91: ='Quarterly YTD'!AC91-'Quarterly YTD'!AB91 -> 0 | AL91: =I91-'Quarterly YTD'!AC91 -> 0 | AM91: 0 | AN91: ='Quarterly YTD'!AF91-AM91 -> 0
A92: Other borrowings received | B92: 0 | C92: 0 | D92: 1.878 | E92: 8.383 | F92: 1.63 | G92: 1.035 | H92: 1.22 | I92: 3.75 | J92: =I92+'Quarterly YTD'!AF92-'Quarterly YTD'!AB92 -> 2.69 | K92: 0 | L92: ='Quarterly YTD'!D92-K92 -> 0 | M92: ='Quarterly YTD'!E92-'Quarterly YTD'!D92 -> 0 | N92: =C92-'Quarterly YTD'!E92 -> 0 | O92: 0 | P92: ='Quarterly YTD'!H92-O92 -> 0 | Q92: ='Quarterly YTD'!I92-'Quarterly YTD'!H92 -> 0 | R92: =D92-'Quarterly YTD'!I92 -> 1.878 | S92: 0.449 | T92: ='Quarterly YTD'!L92-S92 -> 0.382 | U92: ='Quarterly YTD'!M92-'Quarterly YTD'!L92 -> 2.189 | V92: =E92-'Quarterly YTD'!M92 -> 5.363 | W92: 0 | X92: ='Quarterly YTD'!P92-W92 -> 0 | Y92: ='Quarterly YTD'!Q92-'Quarterly YTD'!P92 -> 0.043 | Z92: =F92-'Quarterly YTD'!Q92 -> 1.587 | AA92: 0 | AB92: ='Quarterly YTD'!T92-AA92 -> 0 | AC92: ='Quarterly YTD'!U92-'Quarterly YTD'!T92 -> 1.03 | AD92: =G92-'Quarterly YTD'!U92 -> 0.005 | AE92: 0 | AF92: ='Quarterly YTD'!X92-AE92 -> 0 | AG92: ='Quarterly YTD'!Y92-'Quarterly YTD'!X92 -> 0 | AH92: =H92-'Quarterly YTD'!Y92 -> 1.22 | AI92: 0 | AJ92: ='Quarterly YTD'!AB92-AI92 -> 1.419 | AK92: ='Quarterly YTD'!AC92-'Quarterly YTD'!AB92 -> -0.13 | AL92: =I92-'Quarterly YTD'!AC92 -> 2.461 | AM92: 0 | AN92: ='Quarterly YTD'!AF92-AM92 -> 0.359
A93: Repayment of other borrowings | B93: 0 | C93: 0 | D93: -0.096 | E93: -0.115 | F93: -1.898 | G93: -9.238 | H93: -4.733 | I93: -3.704 | J93: =I93+'Quarterly YTD'!AF93-'Quarterly YTD'!AB93 -> -14.048 | K93: 0 | L93: ='Quarterly YTD'!D93-K93 -> 0 | M93: ='Quarterly YTD'!E93-'Quarterly YTD'!D93 -> -6.634 | N93: =C93-'Quarterly YTD'!E93 -> 6.634 | O93: -0.1 | P93: ='Quarterly YTD'!H93-O93 -> 0.1 | Q93: ='Quarterly YTD'!I93-'Quarterly YTD'!H93 -> 0 | R93: =D93-'Quarterly YTD'!I93 -> -0.096 | S93: -0.109 | T93: ='Quarterly YTD'!L93-S93 -> 0.092 | U93: ='Quarterly YTD'!M93-'Quarterly YTD'!L93 -> 0.017 | V93: =E93-'Quarterly YTD'!M93 -> -0.115 | W93: -4.43 | X93: ='Quarterly YTD'!P93-W93 -> 1.31 | Y93: ='Quarterly YTD'!Q93-'Quarterly YTD'!P93 -> 1.18 | Z93: =F93-'Quarterly YTD'!Q93 -> 0.042 | AA93: -3.734 | AB93: ='Quarterly YTD'!T93-AA93 -> -10.408 | AC93: ='Quarterly YTD'!U93-'Quarterly YTD'!T93 -> 5.037 | AD93: =G93-'Quarterly YTD'!U93 -> -0.133 | AE93: -0.845 | AF93: ='Quarterly YTD'!X93-AE93 -> -0.954 | AG93: ='Quarterly YTD'!Y93-'Quarterly YTD'!X93 -> -2.587 | AH93: =H93-'Quarterly YTD'!Y93 -> -0.347 | AI93: -2.277 | AJ93: ='Quarterly YTD'!AB93-AI93 -> -1.198 | AK93: ='Quarterly YTD'!AC93-'Quarterly YTD'!AB93 -> -0.693 | AL93: =I93-'Quarterly YTD'!AC93 -> 0.464 | AM93: -13.573 | AN93: ='Quarterly YTD'!AF93-AM93 -> -0.246
... A99: Repayment of lease liabilities | B99: -2.072 | C99: -30.873 | D99: -37.801 | E99: -37.939 | F99: -63.864 | G99: -151.442 | H99: -242.596 | I99: -252.388 | J99: =I99+'Quarterly YTD'!AF99-'Quarterly YTD'!AB99 -> -192.443 | K99: -1.543 | L99: ='Quarterly YTD'!D99-K99 -> -1.477 | M99: ='Quarterly YTD'!E99-'Quarterly YTD'!D99 -> -1.711 | N99: =C99-'Quarterly YTD'!E99 -> -26.142 | O99: -16.841 | P99: ='Quarterly YTD'!H99-O99 -> -23.732 | Q99: ='Quarterly YTD'!I99-'Quarterly YTD'!H99 -> 8.235 | R99: =D99-'Quarterly YTD'!I99 -> -5.463 | S99: -6.749 | T99: ='Quarterly YTD'!L99-S99 -> -8.659 | U99: ='Quarterly YTD'!M99-'Quarterly YTD'!L99 -> -11.178 | V99: =E99-'Quarterly YTD'!M99 -> -11.353 | W99: -11.958 | X99: ='Quarterly YTD'!P99-W99 -> -7.823 | Y99: ='Quarterly YTD'!Q99-'Quarterly YTD'!P99 -> -19.376 | Z99: =F99-'Quarterly YTD'!Q99 -> -24.707 | AA99: -21.097 | AB99: ='Quarterly YTD'!T99-AA99 -> -28.759 | AC99: ='Quarterly YTD'!U99-'Quarterly YTD'!T99 -> -43.527 | AD99: =G99-'Quarterly YTD'!U99 -> -58.059 | AE99: -50.913 | AF99: ='Quarterly YTD'!X99-AE99 -> -65.648 | AG99: ='Quarterly YTD'!Y99-'Quarterly YTD'!X99 -> -71.169 | AH99: =H99-'Quarterly YTD'!Y99 -> -54.866 | AI99: -78.083 | AJ99: ='Quarterly YTD'!AB99-AI99 -> -62.351 | AK99: ='Quarterly YTD'!AC99-'Quarterly YTD'!AB99 -> -66.02 | AL99: =I99-'Quarterly YTD'!AC99 -> -45.934 | AM99: -41.338 | AN99: ='Quarterly YTD'!AF99-AM99 -> -39.151
A100: Net cash generated from (used in) financing activities from continued operations | B100: =B82+SUM(B88:B91)+B94+B99 -> 5.191 | C100: =C83+C85+SUM(C88:C94)+C97+C99 -> 230.88 | D100: =SUM(D83:D85)+SUM(D88:D93)+D97+D99 -> -47.361 | E100: =SUM(E83:E84)+E86+SUM(E88:E89)+SUM(E92:E93)+E97+E99 -> 287.524 | F100: =F83+SUM(F87:F89)+SUM(F92:F93)+F97+F99 -> -152.007 | G100: =G83+SUM(G87:G89)+SUM(G92:G93)+SUM(G95:G97)+G99 -> -208.611 | H100: =H83+SUM(H88:H89)+SUM(H92:H93)+SUM(H95:H97)+H99 -> -125.341 | I100: =I83+SUM(I88:I89)+SUM(I92:I93)+SUM(I95:I97)+I99 -> -183.715 | J100: =SUM(J82:J99) -> -77.031 | K100: =SUM(K88:K90)+K93+K99 -> 1.04 | L100: =SUM(L82:L99) -> 9.868 | M100: =SUM(M82:M99) -> -9.941 | N100: =SUM(N82:N99) -> 229.913 | O100: =O83+SUM(O88:O89)+SUM(O92:O93)+O97+O99 -> -16.568 | P100: =SUM(P82:P99) -> -29.022 | Q100: =SUM(Q82:Q99) -> 6.128 | R100: =SUM(R82:R99) -> -7.899 | S100: =S83+SUM(S88:S89)+SUM(S92:S93)+S97+S99 -> -7.072 | T100: =SUM(T82:T99) -> 6.862 | U100: =SUM(U82:U99) -> -2.884 | V100: =SUM(V82:V99) -> 290.618 | W100: =W83+SUM(W88:W89)+W93+W97+W99 -> -12.465 | X100: =SUM(X82:X99) -> -41.348 | Y100: =SUM(Y82:Y99) -> -65.545 | Z100: =SUM(Z82:Z99) -> -32.649 | AA100: =AA83+SUM(AA88:AA89)+AA93+AA99 -> -26.145 | AB100: =SUM(AB82:AB99) -> -59.875 | AC100: =SUM(AC82:AC99) -> -37.803 | AD100: =SUM(AD82:AD99) -> -84.788 | AE100: =AE83+SUM(AE88:AE89)+AE93+AE99 -> -52.424 | AF100: =SUM(AF82:AF99) -> 50.705 | AG100: =SUM(AG82:AG99) -> -75.734 | AH100: =SUM(AH82:AH99) -> -47.888 | AI100: =AI83+SUM(AI88:AI89)+AI93+AI95+AI99 -> -53.582 | AJ100: =SUM(AJ82:AJ99) -> -40.354 | AK100: =SUM(AK82:AK99) -> -69.818 | AL100: =SUM(AL82:AL99) -> -19.961 | AM100: =AM83+SUM(AM88:AM89)+AM93+AM95+AM99 -> -14.403 | AN100: =SUM(AN82:AN99) -> 27.151
A101: Net cash from (used in) financing activities | B101: =B100 -> 5.191 | C101: =C100 -> 230.88 | D101: =D100 -> -47.361 | E101: =E100 -> 287.524 | F101: =F100 -> -152.007 | G101: =G100 -> -208.611 | H101: =H100 -> -125.341 | I101: =I100 -> -183.715 | ... AN101: =AN100 -> 27.151 | AO101: =IF(AND(AN101=0,AM101=0),0,IF(OR(AM101=0,AM101="NM",AN101="NM"),"NM",IF(AM101<0,-(AN101/AM101-1),AN101/AM101-1))) -> 2.8850934 | AP101: =IF(AND(AN101=0,AJ101=0),0,IF(OR(AJ101=0,AJ101="NM",AN101="NM"),"NM",IF(AJ101<0,-(AN101/AJ101-1),AN101/AJ101-1))) -> 1.6728205
A102: Currency translation difference | B102: 0 | C102: 0 | D102: 0 | E102: 0 | F102: 2.336 | G102: -3.534 | H102: 6.316 | I102: -8.323 | J102: =I102+'Quarterly YTD'!AF102-'Quarterly YTD'!AB102 -> 1.105 | K102: 0 | L102: ='Quarterly YTD'!D102-K102 -> 0 | M102: ='Quarterly YTD'!E102-'Quarterly YTD'!D102 -> 0 | N102: =C102-'Quarterly YTD'!E102 -> 0 | O102: 0 | P102: ='Quarterly YTD'!H102-O102 -> 0 | Q102: ='Quarterly YTD'!I102-'Quarterly YTD'!H102 -> 0 | R102: =D102-'Quarterly YTD'!I102 -> 0 | S102: 0 | T102: ='Quarterly YTD'!L102-S102 -> 0 | U102: ='Quarterly YTD'!M102-'Quarterly YTD'!L102 -> 0 | V102: =E102-'Quarterly YTD'!M102 -> 0 | W102: 0 | X102: ='Quarterly YTD'!P102-W102 -> 0 | Y102: ='Quarterly YTD'!Q102-'Quarterly YTD'!P102 -> 0 | Z102: =F102-'Quarterly YTD'!Q102 -> 2.336 | AA102: 0 | AB102: ='Quarterly YTD'!T102-AA102 -> 0 | AC102: ='Quarterly YTD'!U102-'Quarterly YTD'!T102 -> 0 | AD102: =G102-'Quarterly YTD'!U102 -> -3.534 | AE102: 1.883 | AF102: ='Quarterly YTD'!X102-AE102 -> 1.577 | AG102: ='Quarterly YTD'!Y102-'Quarterly YTD'!X102 -> -8.429 | AH102: =H102-'Quarterly YTD'!Y102 -> 11.285 | AI102: -2.587 | AJ102: ='Quarterly YTD'!AB102-AI102 -> -6.238 | AK102: ='Quarterly YTD'!AC102-'Quarterly YTD'!AB102 -> -0.549 | AL102: =I102-'Quarterly YTD'!AC102 -> 1.051 | AM102: 0.781 | AN102: ='Quarterly YTD'!AF102-AM102 -> -0.178
A103: At beginning of year | B103: -11.516 | C103: -16.634 | D103: 212.089 | E103: 177.852 | F103: 215.865 | G103: 324.607 | H103: 200.553 | I103: ='Quarterly YTD'!AB103 -> 184.701 | J103: ='Quarterly YTD'!AB105 -> 195.715 | K103: =C103 -> -16.634 | L103: =K105 -> -17.652 | M103: ='Quarterly YTD'!D105 -> -19.453 | N103: ='Quarterly YTD'!E105 -> -17.431 | O103: =D103 -> 212.089 | P103: =O105 -> 131.015 | Q103: ='Quarterly YTD'!H105 -> 220.232 | R103: ='Quarterly YTD'!I105 -> 214.642 | S103: =E103 -> 177.852 | T103: =S105 -> 150.808 | U103: ='Quarterly YTD'!L105 -> 170.554 | V103: ='Quarterly YTD'!M105 -> 165.42 | W103: =F103 -> 215.865 | X103: =W105 -> 317.908 | Y103: ='Quarterly YTD'!P105 -> 331.378 | Z103: ='Quarterly YTD'!Q105 -> 293.28 | AA103: =G103 -> 324.607 | AB103: =AA105 -> 285.535 | AC103: ='Quarterly YTD'!T105 -> 259.853 | AD103: ='Quarterly YTD'!U105 -> 283.627 | AE103: =H103 -> 200.553 | AF103: =AE105 -> 186.973 | AG103: ='Quarterly YTD'!X105 -> 298.691 | AH103: ='Quarterly YTD'!Y105 -> 278.735 | AI103: ='Quarterly YTD'!AB103 -> 184.701 | AJ103: =AI105 -> 130.613 | AK103: ='Quarterly YTD'!AB105 -> 195.715 | AL103: ='Quarterly YTD'!AC105 -> 242.134 | AM103: ='Quarterly YTD'!AF103 -> 122.655 | AN103: =AM105 -> 104.132 | AO103: =IF(AND(AN103=0,AM103=0),0,IF(OR(AM103=0,AM103="NM",AN103="NM"),"NM",IF(AM103<0,-(AN103/AM103-1),AN103/AM103-1))) -> -0.15101708 | AP103: =IF(AND(AN103=0,AJ103=0),0,IF(OR(AJ103=0,AJ103="NM",AN103="NM"),"NM",IF(AJ103<0,-(AN103/AJ103-1),AN103/AJ103-1))) -> -0.20274398
A104: Decrease in cash and cash equivalents | B104: =B60+B81+B101 -> -5.118 | C104: =C60+C81+C101 -> 228.723 | D104: =D60+D81+D101 -> -34.237 | E104: =E60+E81+E101 -> 38.013 | F104: =F60+F81+SUM(F101:F102) -> 108.742 | G104: =G60+G81+SUM(G101:G102) -> -124.054 | H104: =H60+H81+SUM(H101:H102) -> -15.852 | I104: =I60+I81+SUM(I101:I102) -> -62.046 | J104: =I104+'Quarterly YTD'!AF104-'Quarterly YTD'!AB104 -> -77.761 | K104: =K60+K81+K101 -> -1.018 | L104: =L60+L81+SUM(L101:L102) -> -1.801 | M104: =M60+M81+SUM(M101:M102) -> 2.022 | N104: =N60+N81+SUM(N101:N102) -> 229.52 | O104: =O60+O81+O101 -> -81.074 | P104: =P60+P81+SUM(P101:P102) -> 89.217 | Q104: =Q60+Q81+SUM(Q101:Q102) -> -5.59 | R104: =R60+R81+SUM(R101:R102) -> -36.79 | S104: =S60+S81+S101 -> -27.044 | T104: =T60+T81+SUM(T101:T102) -> 19.746 | U104: =U60+U81+SUM(U101:U102) -> -5.134 | V104: =V60+V81+SUM(V101:V102) -> 50.445 | W104: =W60+W81+W101 -> 102.043 | X104: =X60+X81+SUM(X101:X102) -> 13.47 | Y104: =Y60+Y81+SUM(Y101:Y102) -> -38.098 | Z104: =Z60+Z81+SUM(Z101:Z102) -> 31.327 | AA104: =AA60+AA81+SUM(AA101:AA102) -> -39.072 | AB104: =AB60+AB81+SUM(AB101:AB102) -> -25.682 | AC104: =AC60+AC81+SUM(AC101:AC102) -> 23.774 | AD104: =AD60+AD81+SUM(AD101:AD102) -> -83.074 | AE104: =AE60+AE81+SUM(AE101:AE102) -> -13.58 | ... AN104: =AN60+AN81+SUM(AN101:AN102) -> 13.822 | AO104: =IF(AND(AN104=0,AM104=0),0,IF(OR(AM104=0,AM104="NM",AN104="NM"),"NM",IF(AM104<0,-(AN104/AM104-1),AN104/AM104-1))) -> 1.7462074 | AP104: =IF(AND(AN104=0,AJ104=0),0,IF(OR(AJ104=0,AJ104="NM",AN104="NM"),"NM",IF(AJ104<0,-(AN104/AJ104-1),AN104/AJ104-1))) -> -0.78768701
A105: At end of period | B105: =SUM(B103:B104) -> -16.634 | C105: =SUM(C103:C104) -> 212.089 | D105: =SUM(D103:D104) -> 177.852 | E105: =SUM(E103:E104) -> 215.865 | F105: =SUM(F103:F104) -> 324.607 | G105: =SUM(G103:G104) -> 200.553 | H105: =SUM(H103:H104) -> 184.701 | I105: =SUM(I103:I104) -> 122.655 | ... AN105: =SUM(AN103:AN104) -> 117.954 | AO105: =IF(AND(AN105=0,AM105=0),0,IF(OR(AM105=0,AM105="NM",AN105="NM"),"NM",IF(AM105<0,-(AN105/AM105-1),AN105/AM105-1))) -> 0.13273537 | AP105: =IF(AND(AN105=0,AJ105=0),0,IF(OR(AJ105=0,AJ105="NM",AN105="NM"),"NM",IF(AJ105<0,-(AN105/AJ105-1),AN105/AJ105-1))) -> -0.39731753
A107: Balance Sheet
A108: Property, plant and equipment | B108: 62.449 | C108: 363.286 | D108: 352.931 | E108: 414.443 | F108: 776.321 | G108: 1410.635 | H108: 1723.662 | I108: 1084.449 | J108: =AN108 -> 939.053 | N108: 363.286 | O108: 405.787 | P108: 388.096 | Q108: 380.535 | R108: 352.931 | S108: 364.592 | T108: 380.509 | U108: 396.674 | V108: 414.443 | W108: 464.724 | X108: 573.566 | Y108: 752.719 | Z108: 776.321 | AA108: 953.524 | AB108: 1144.169 | AC108: 1299.404 | AD108: 1410.635 | AE108: 1584.065 | AF108: 1670.091 | AG108: 1671.461 | AH108: 1723.662 | AI108: 1604.095 | AJ108: 1403.598 | AK108: 1340.629 | AL108: 1084.449 | AM108: 1106.064 | AN108: 939.053 | AO108: =IF(AND(AN108=0,AM108=0),0,IF(OR(AM108=0,AM108="NM",AN108="NM"),"NM",IF(AM108<0,-(AN108/AM108-1),AN108/AM108-1))) -> -0.15099578 | AP108: =IF(AND(AN108=0,AJ108=0),0,IF(OR(AJ108=0,AJ108="NM",AN108="NM"),"NM",IF(AJ108<0,-(AN108/AJ108-1),AN108/AJ108-1))) -> -0.33096727
A109: Investment property | B109: 0 | C109: 11.842 | D109: 10.132 | E109: 31.03 | F109: 41.64 | G109: 41.151 | H109: 59.644 | I109: 53.604 | J109: =AN109 -> 52.892 | N109: 11.842 | O109: 12.645 | P109: 10.851 | Q109: 10.473 | R109: 10.132 | S109: 13.356 | T109: 10.5 | U109: 11.599 | V109: 31.03 | W109: 27.166 | X109: 28.21 | Y109: 38.728 | Z109: 41.64 | AA109: 43.62 | AB109: 43.159 | AC109: 41.398 | AD109: 41.151 | AE109: 64.49 | AF109: 60.761 | AG109: 60.181 | AH109: 59.644 | AI109: 58.938 | AJ109: 55.613 | AK109: 54.886 | AL109: 53.604 | AM109: 53.268 | AN109: 52.892 | AO109: =IF(AND(AN109=0,AM109=0),0,IF(OR(AM109=0,AM109="NM",AN109="NM"),"NM",IF(AM109<0,-(AN109/AM109-1),AN109/AM109-1))) -> -0.0070586468 | AP109: =IF(AND(AN109=0,AJ109=0),0,IF(OR(AJ109=0,AJ109="NM",AN109="NM"),"NM",IF(AJ109<0,-(AN109/AJ109-1),AN109/AJ109-1))) -> -0.048927409
A110: Intangible assets | B110: 6.963 | C110: 74.412 | D110: 102.777 | E110: 113.584 | F110: 110.215 | G110: 139.622 | H110: 151.848 | I110: 133.318 | J110: =AN110 -> 132.969 | N110: 74.412 | O110: 94.381 | P110: 95.323 | Q110: 94.424 | R110: 102.777 | S110: 107.53 | T110: 107.253 | U110: 108.882 | V110: 113.584 | W110: 116.219 | X110: 117.558 | Y110: 115.845 | Z110: 110.215 | AA110: 110.473 | AB110: 130.668 | AC110: 136.333 | AD110: 139.622 | AE110: 146.163 | AF110: 147.907 | AG110: 148.537 | AH110: 151.848 | AI110: 150.29 | AJ110: 145.31 | AK110: 144.14 | AL110: 133.318 | AM110: 134.15 | AN110: 132.969 | AO110: =IF(AND(AN110=0,AM110=0),0,IF(OR(AM110=0,AM110="NM",AN110="NM"),"NM",IF(AM110<0,-(AN110/AM110-1),AN110/AM110-1))) -> -0.0088035781 | AP110: =IF(AND(AN110=0,AJ110=0),0,IF(OR(AJ110=0,AJ110="NM",AN110="NM"),"NM",IF(AJ110<0,-(AN110/AJ110-1),AN110/AJ110-1))) -> -0.084928773
A111: Investments accounted for using the equity method | B111: 0.103 | C111: 47.034 | D111: 43.68 | E111: 51.602 | F111: 0.349 | G111: 0.348 | H111: 0.368 | I111: 0.086 | J111: =AN111 -> 0.103 | N111: 47.034 | O111: 48.816 | P111: 50.254 | Q111: 50.101 | R111: 43.68 | S111: 46.333 | T111: 46.338 | U111: 48.208 | V111: 51.602 | W111: 52.664 | X111: 56.224 | Y111: 59.877 | Z111: 0.349 | AA111: 0.349 | AB111: 0.358 | AC111: 0.358 | AD111: 0.348 | AE111: 0.356 | AF111: 0.354 | AG111: 0 | AH111: 0.368 | AI111: 0.359 | AJ111: 0.353 | AK111: 0.352 | AL111: 0.086 | AM111: 0.093 | AN111: 0.103 | AO111: =IF(AND(AN111=0,AM111=0),0,IF(OR(AM111=0,AM111="NM",AN111="NM"),"NM",IF(AM111<0,-(AN111/AM111-1),AN111/AM111-1))) -> 0.10752688 | AP111: =IF(AND(AN111=0,AJ111=0),0,IF(OR(AJ111=0,AJ111="NM",AN111="NM"),"NM",IF(AJ111<0,-(AN111/AJ111-1),AN111/AJ111-1))) -> -0.7082153
A112: Deferred tax assets | B112: 6.914 | C112: 9.615 | D112: 17.161 | E112: 16.728 | F112: 17.646 | G112: 38.486 | H112: 72.029 | I112: 64.647 | J112: =AN112 -> 84.819 | N112: 9.615 | O112: 15.222 | P112: 17.666 | Q112: 22.331 | R112: 17.161 | S112: 18.559 | T112: 16.317 | U112: 16.438 | V112: 16.728 | W112: 18.975 | X112: 17.458 | Y112: 18.065 | Z112: 17.646 | AA112: 25.679 | AB112: 24.404 | AC112: 30.234 | AD112: 38.486 | AE112: 57.412 | AF112: 52.405 | AG112: 43.533 | AH112: 72.029 | AI112: 84.194 | AJ112: 66.137 | AK112: 52.719 | AL112: 64.647 | AM112: 80.672 | AN112: 84.819 | AO112: =IF(AND(AN112=0,AM112=0),0,IF(OR(AM112=0,AM112="NM",AN112="NM"),"NM",IF(AM112<0,-(AN112/AM112-1),AN112/AM112-1))) -> 0.051405692 | AP112: =IF(AND(AN112=0,AJ112=0),0,IF(OR(AJ112=0,AJ112="NM",AN112="NM"),"NM",IF(AJ112<0,-(AN112/AJ112-1),AN112/AJ112-1))) -> 0.28247426
A113: Other investment | B113: 0 | C113: 0 | D113: 0 | E113: 0 | F113: 0 | G113: 0 | H113: 0 | I113: 0 | J113: =AN113 -> 0.012 | N113: 0 | O113: 0 | P113: 0.468 | Q113: 1.289 | R113: 0 | S113: 3.246 | T113: 3.909 | U113: 5.334 | V113: 0 | W113: 0 | X113: 0 | Y113: 0 | Z113: 0 | AA113: 0 | AB113: 0 | AC113: 0 | AD113: 0 | AE113: 0 | AF113: 0 | AG113: 0 | AH113: 0 | AI113: 0 | AJ113: 0 | AK113: 0 | AL113: 0 | AM113: 0 | AN113: 0.012 | AO113: =IF(AND(AN113=0,AM113=0),0,IF(OR(AM113=0,AM113="NM",AN113="NM"),"NM",IF(AM113<0,-(AN113/AM113-1),AN113/AM113-1))) -> NM | AP113: =IF(AND(AN113=0,AJ113=0),0,IF(OR(AJ113=0,AJ113="NM",AN113="NM"),"NM",IF(AJ113<0,-(AN113/AJ113-1),AN113/AJ113-1))) -> NM
A114: Financial assets at fair value through profit or loss | B114: 0 | C114: 0 | D114: 1.231 | E114: 2.924 | F114: 1.649 | G114: 1.289 | H114: 0.01 | I114: 0 | J114: =AN114 -> 0.54 | N114: 0 | O114: 0 | P114: 0 | Q114: 0 | R114: 1.231 | S114: 0 | T114: 0 | U114: 0 | V114: 2.924 | W114: 2.967 | X114: 2.967 | Y114: 2.977 | Z114: 1.649 | AA114: 1.531 | AB114: 1.507 | AC114: 1.506 | AD114: 1.289 | AE114: 1.311 | AF114: 1.324 | AG114: 1.617 | AH114: 0.01 | AI114: 0 | AJ114: 0 | AK114: 0.002 | AL114: 0 | AM114: 0.54 | AN114: 0.54 | AO114: =IF(AND(AN114=0,AM114=0),0,IF(OR(AM114=0,AM114="NM",AN114="NM"),"NM",IF(AM114<0,-(AN114/AM114-1),AN114/AM114-1))) -> 0 | AP114: =IF(AND(AN114=0,AJ114=0),0,IF(OR(AJ114=0,AJ114="NM",AN114="NM"),"NM",IF(AJ114<0,-(AN114/AJ114-1),AN114/AJ114-1))) -> NM
A115: Derivative financial instruments | B115: 0 | C115: 3.672 | D115: 3.563 | E115: 4.667 | F115: 5.513 | G115: 2.774 | H115: 6.023 | I115: 0 | J115: =AN115 -> 0 | N115: 3.672 | O115: 7.665 | P115: 6.48 | Q115: 5.321 | R115: 3.563 | S115: 4.707 | T115: 3.828 | U115: 4.471 | V115: 4.667 | W115: 4.995 | X115: 7.577 | Y115: 15.864 | Z115: 5.513 | AA115: 4.719 | AB115: 3.854 | AC115: 6.568 | AD115: 2.774 | AE115: 4.092 | AF115: 1.579 | AG115: 0 | AH115: 6.023 | AI115: 0 | AJ115: 0 | AK115: 0 | AL115: 0 | AM115: 0 | AN115: 0 | AO115: =IF(AND(AN115=0,AM115=0),0,IF(OR(AM115=0,AM115="NM",AN115="NM"),"NM",IF(AM115<0,-(AN115/AM115-1),AN115/AM115-1))) -> 0 | AP115: =IF(AND(AN115=0,AJ115=0),0,IF(OR(AJ115=0,AJ115="NM",AN115="NM"),"NM",IF(AJ115<0,-(AN115/AJ115-1),AN115/AJ115-1))) -> 0
A116: Long-term bank deposits | B116: 0 | C116: 0.983 | D116: 1.226 | E116: 2.297 | F116: 0.859 | G116: 0.865 | H116: 0.362 | I116: 1.762 | J116: =AN116 -> 3.397 | N116: 0.983 | O116: 0.997 | P116: 0.975 | Q116: 0.94 | R116: 1.226 | S116: 1.523 | T116: 2.18 | U116: 2.244 | V116: 2.297 | W116: 2.338 | X116: 0.895 | Y116: 0.946 | Z116: 0.859 | AA116: 0.854 | AB116: 0.858 | AC116: 0.866 | AD116: 0.865 | AE116: 0.875 | AF116: 0.878 | AG116: 0.866 | AH116: 0.362 | AI116: 0.006 | AJ116: 0 | AK116: 0.106 | AL116: 1.762 | AM116: 0.645 | AN116: 3.397 | AO116: =IF(AND(AN116=0,AM116=0),0,IF(OR(AM116=0,AM116="NM",AN116="NM"),"NM",IF(AM116<0,-(AN116/AM116-1),AN116/AM116-1))) -> 4.2666667 | AP116: =IF(AND(AN116=0,AJ116=0),0,IF(OR(AJ116=0,AJ116="NM",AN116="NM"),"NM",IF(AJ116<0,-(AN116/AJ116-1),AN116/AJ116-1))) -> NM
A117: Trade and other receivables | B117: 4.052 | C117: 40.319 | D117: 42.091 | E117: 49.725 | F117: 81.12 | G117: 112.618 | H117: 134.58 | I117: 81.777 | J117: =AN117 -> 75.186 | N117: 40.319 | O117: 47.791 | P117: 47.104 | Q117: 45.451 | R117: 42.091 | S117: 43.301 | T117: 47.009 | U117: 55.884 | V117: 49.725 | W117: 53.375 | X117: 59.674 | Y117: 80.256 | Z117: 81.12 | AA117: 92.223 | AB117: 106.504 | AC117: 111.652 | AD117: 112.618 | AE117: 120.322 | AF117: 136.818 | AG117: 147.712 | AH117: 134.58 | AI117: 114.172 | AJ117: 107.278 | AK117: 106.819 | AL117: 81.777 | AM117: 84.641 | AN117: 75.186 | AO117: =IF(AND(AN117=0,AM117=0),0,IF(OR(AM117=0,AM117="NM",AN117="NM"),"NM",IF(AM117<0,-(AN117/AM117-1),AN117/AM117-1))) -> -0.11170709 | AP117: =IF(AND(AN117=0,AJ117=0),0,IF(OR(AJ117=0,AJ117="NM",AN117="NM"),"NM",IF(AJ117<0,-(AN117/AJ117-1),AN117/AJ117-1))) -> -0.29914801
A118: Non-current assets | B118: =SUM(B108:B112)+SUM(B115:B117) -> 80.481 | C118: =SUM(C108:C112)+SUM(C114:C117) -> 551.163 | D118: =SUM(D108:D112)+SUM(D114:D117) -> 574.792 | E118: =SUM(E108:E112)+SUM(E114:E117) -> 687 | F118: =SUM(F108:F112)+SUM(F114:F117) -> 1035.312 | G118: =SUM(G108:G112)+SUM(G114:G117) -> 1747.788 | H118: =SUM(H108:H112)+SUM(H114:H117) -> 2148.526 | I118: =SUM(I108:I114)+SUM(I116:I117) -> 1419.643 | J118: =AN118 -> 1288.971 | N118: =SUM(N108:N112)+SUM(N114:N117) -> 551.163 | O118: =SUM(O108:O112)+SUM(O115:O117) -> 633.304 | P118: =SUM(P108:P113)+SUM(P115:P117) -> 617.217 | Q118: =SUM(Q108:Q113)+SUM(Q115:Q117) -> 610.865 | R118: =SUM(R108:R112)+SUM(R114:R117) -> 574.792 | S118: =SUM(S108:S113)+SUM(S115:S117) -> 603.147 | T118: =SUM(T108:T113)+SUM(T115:T117) -> 617.843 | U118: =SUM(U108:U113)+SUM(U115:U117) -> 649.734 | V118: =SUM(V108:V112)+SUM(V114:V117) -> 687 | W118: =SUM(W108:W112)+SUM(W114:W117) -> 743.423 | X118: =SUM(X108:X112)+SUM(X114:X117) -> 864.129 | Y118: =SUM(Y108:Y112)+SUM(Y114:Y117) -> 1085.277 | Z118: =SUM(Z108:Z112)+SUM(Z114:Z117) -> 1035.312 | AA118: =SUM(AA108:AA112)+SUM(AA114:AA117) -> 1232.972 | AB118: =SUM(AB108:AB112)+SUM(AB114:AB117) -> 1455.481 | AC118: =SUM(AC108:AC112)+SUM(AC114:AC117) -> 1628.319 | ... AK118: =SUM(AK108:AK112)+SUM(AK114:AK117) -> 1699.653 | AL118: =SUM(AL108:AL114)+SUM(AL116:AL117) -> 1419.643 | AM118: =SUM(AM108:AM112)+AM114+SUM(AM116:AM117) -> 1460.073 | AN118: =SUM(AN108:AN114)+SUM(AN116:AN117) -> 1288.971 | AO118: =IF(AND(AN118=0,AM118=0),0,IF(OR(AM118=0,AM118="NM",AN118="NM"),"NM",IF(AM118<0,-(AN118/AM118-1),AN118/AM118-1))) -> -0.11718729 | AP118: =IF(AND(AN118=0,AJ118=0),0,IF(OR(AJ118=0,AJ118="NM",AN118="NM"),"NM",IF(AJ118<0,-(AN118/AJ118-1),AN118/AJ118-1))) -> -0.27516225
A119: Inventories | B119: 26.709 | C119: 95.847 | D119: 38.976 | E119: 73.551 | F119: 89.855 | G119: 125.745 | H119: 248.835 | I119: 221.047 | J119: =AN119 -> 190.585 | N119: 95.847 | O119: 39.111 | P119: 39.443 | Q119: 41.206 | R119: 38.976 | S119: 44.288 | T119: 62.885 | U119: 77.206 | V119: 73.551 | W119: 76.52 | X119: 110.29 | Y119: 126.329 | Z119: 89.855 | AA119: 94.526 | AB119: 109.463 | AC119: 133.908 | AD119: 125.745 | AE119: 151.759 | AF119: 159.693 | AG119: 200.006 | AH119: 248.835 | AI119: 223.859 | AJ119: 209.073 | AK119: 201.883 | AL119: 221.047 | AM119: 199.391 | AN119: 190.585 | AO119: =IF(AND(AN119=0,AM119=0),0,IF(OR(AM119=0,AM119="NM",AN119="NM"),"NM",IF(AM119<0,-(AN119/AM119-1),AN119/AM119-1))) -> -0.044164481 | AP119: =IF(AND(AN119=0,AJ119=0),0,IF(OR(AJ119=0,AJ119="NM",AN119="NM"),"NM",IF(AJ119<0,-(AN119/AJ119-1),AN119/AJ119-1))) -> -0.088428444
A120: Trade and other receivables | B120: 65.585 | C120: 142.85 | D120: 116.824 | E120: 247.093 | F120: 259.04 | G120: 327.359 | H120: 335.482 | I120: 317.267 | J120: =AN120 -> 335.079 | N120: 142.85 | O120: 183.817 | P120: 150.231 | Q120: 152.414 | R120: 116.824 | S120: 140.147 | T120: 159.232 | U120: 203.359 | V120: 247.093 | W120: 242.44 | X120: 269.332 | Y120: 289.9 | Z120: 259.04 | AA120: 305.529 | AB120: 338.024 | AC120: 340.762 | AD120: 327.359 | AE120: 371.961 | AF120: 398.356 | AG120: 383.022 | AH120: 335.482 | AI120: 354.854 | AJ120: 349.648 | AK120: 338.015 | AL120: 317.267 | AM120: 369.281 | AN120: 335.079 | AO120: =IF(AND(AN120=0,AM120=0),0,IF(OR(AM120=0,AM120="NM",AN120="NM"),"NM",IF(AM120<0,-(AN120/AM120-1),AN120/AM120-1))) -> -0.092617817 | AP120: =IF(AND(AN120=0,AJ120=0),0,IF(OR(AJ120=0,AJ120="NM",AN120="NM"),"NM",IF(AJ120<0,-(AN120/AJ120-1),AN120/AJ120-1))) -> -0.04166762
A121: Derivative financial instruments | B121: 0 | C121: 0.377 | D121: 0 | E121: 0 | F121: 0 | G121: 0 | H121: 0 | I121: 0 | J121: =AN121 -> 0 | N121: 0.377 | O121: 0 | P121: 0 | Q121: 0 | R121: 0 | S121: 0 | T121: 0 | U121: 0 | V121: 0 | W121: 0 | X121: 0 | Y121: 0 | Z121: 0 | AA121: 0 | AB121: 0 | AC121: 0 | AD121: 0 | AE121: 0 | AF121: 0 | AG121: 0 | AH121: 0 | AI121: 0 | AJ121: 0 | AK121: 0 | AL121: 0 | AM121: 0 | AN121: 0 | AO121: =IF(AND(AN121=0,AM121=0),0,IF(OR(AM121=0,AM121="NM",AN121="NM"),"NM",IF(AM121<0,-(AN121/AM121-1),AN121/AM121-1))) -> 0 | AP121: =IF(AND(AN121=0,AJ121=0),0,IF(OR(AJ121=0,AJ121="NM",AN121="NM"),"NM",IF(AJ121<0,-(AN121/AJ121-1),AN121/AJ121-1))) -> 0
A122: Financial assets at fair value through profit or loss | B122: 0 | C122: 0 | D122: 0 | E122: 0.313 | F122: 0.6 | G122: 0.371 | H122: 0.016 | I122: 0.071 | J122: =AN122 -> 0.07 | N122: 0 | O122: 0 | P122: 0 | Q122: 0 | R122: 0 | S122: 0 | T122: 0 | U122: 0 | V122: 0.313 | W122: 0.308 | X122: 0 | Y122: 0 | Z122: 0.6 | AA122: 0.588 | AB122: 0.118 | AC122: 0.272 | AD122: 0.371 | AE122: 0.324 | AF122: 0.33 | AG122: 0.316 | AH122: 0.016 | AI122: 0.016 | AJ122: 0.079 | AK122: 0.064 | AL122: 0.071 | AM122: 0.063 | AN122: 0.07 | AO122: =IF(AND(AN122=0,AM122=0),0,IF(OR(AM122=0,AM122="NM",AN122="NM"),"NM",IF(AM122<0,-(AN122/AM122-1),AN122/AM122-1))) -> 0.11111111 | AP122: =IF(AND(AN122=0,AJ122=0),0,IF(OR(AJ122=0,AJ122="NM",AN122="NM"),"NM",IF(AJ122<0,-(AN122/AJ122-1),AN122/AJ122-1))) -> -0.11392405
A123: Contract assets | B123: 3.047 | C123: 7.376 | D123: 10.128 | E123: 20.676 | F123: 24.701 | G123: 35.986 | H123: 41.957 | I123: 15.053 | J123: =AN123 -> 24.2 | N123: 7.376 | O123: 10.924 | P123: 11.541 | Q123: 10.546 | R123: 10.128 | S123: 18.258 | T123: 20.594 | U123: 18.908 | V123: 20.676 | W123: 23.954 | X123: 21.026 | Y123: 26.936 | Z123: 24.701 | AA123: 23.512 | AB123: 29.142 | AC123: 28.263 | AD123: 35.986 | AE123: 36.744 | AF123: 34.093 | AG123: 29.294 | AH123: 41.957 | AI123: 24.748 | AJ123: 20.555 | AK123: 18.267 | AL123: 15.053 | AM123: 31.702 | AN123: 24.2 | AO123: =IF(AND(AN123=0,AM123=0),0,IF(OR(AM123=0,AM123="NM",AN123="NM"),"NM",IF(AM123<0,-(AN123/AM123-1),AN123/AM123-1))) -> -0.23664122 | AP123: =IF(AND(AN123=0,AJ123=0),0,IF(OR(AJ123=0,AJ123="NM",AN123="NM"),"NM",IF(AJ123<0,-(AN123/AJ123-1),AN123/AJ123-1))) -> 0.17732912
A124: Current financial assets at fair value through profit & loss | B124: 0 | C124: 0 | D124: 0 | E124: 0 | F124: 0 | G124: 0 | H124: 0 | I124: 0 | J124: =AN124 -> 0 | N124: 0 | O124: 0 | P124: 0 | Q124: 0 | R124: 0 | S124: 0 | T124: 0.701 | U124: 0.642 | V124: 0 | W124: 0 | X124: 0 | Y124: 0 | Z124: 0 | AA124: 0 | AB124: 0 | AC124: 0 | AD124: 0 | AE124: 0 | AF124: 0 | AG124: 0 | AH124: 0 | AI124: 0 | AJ124: 0 | AK124: 0 | AL124: 0 | AM124: 0 | AN124: 0 | AO124: =IF(AND(AN124=0,AM124=0),0,IF(OR(AM124=0,AM124="NM",AN124="NM"),"NM",IF(AM124<0,-(AN124/AM124-1),AN124/AM124-1))) -> 0 | AP124: =IF(AND(AN124=0,AJ124=0),0,IF(OR(AJ124=0,AJ124="NM",AN124="NM"),"NM",IF(AJ124<0,-(AN124/AJ124-1),AN124/AJ124-1))) -> 0
A125: Prepaid income tax | B125: 1.022 | C125: 1.156 | D125: 1.699 | E125: 1.739 | F125: 4.41 | G125: 3.729 | H125: 0 | I125: 0 | J125: =AN125 -> 0 | N125: 1.156 | O125: 2.494 | P125: 1.656 | Q125: 1.768 | R125: 1.699 | S125: 1.696 | T125: 2.066 | U125: 2.038 | V125: 1.739 | W125: 0.945 | X125: 1.163 | Y125: 1.594 | Z125: 4.41 | AA125: 2.086 | AB125: 2.091 | AC125: 4.242 | AD125: 3.729 | AE125: 5.769 | AF125: 7.348 | AG125: 5.781 | AH125: 0 | AI125: 3.563 | AJ125: 5.5 | AK125: 6.525 | AL125: 0 | AM125: 0 | AN125: 0 | AO125: =IF(AND(AN125=0,AM125=0),0,IF(OR(AM125=0,AM125="NM",AN125="NM"),"NM",IF(AM125<0,-(AN125/AM125-1),AN125/AM125-1))) -> 0 | AP125: =IF(AND(AN125=0,AJ125=0),0,IF(OR(AJ125=0,AJ125="NM",AN125="NM"),"NM",IF(AJ125<0,-(AN125/AJ125-1),AN125/AJ125-1))) -> -1
A126: Short-term bank deposit | B126: 0 | C126: 84.011 | D126: 25.519 | E126: 0 | F126: 0 | G126: 0 | H126: 0 | I126: 0 | J126: =AN126 -> 0 | N126: 84.011 | O126: 172.597 | P126: 72.161 | Q126: 26.862 | R126: 25.519 | S126: 25.881 | T126: 0 | U126: 0.009 | V126: 0 | W126: 135.032 | X126: 88.51 | Y126: 154.814 | Z126: 0 | AA126: 0 | AB126: 0 | AC126: 0 | AD126: 0 | AE126: 0 | AF126: 0 | AG126: 0 | AH126: 0 | AI126: 0 | AJ126: 0 | AK126: 0 | AL126: 0 | AM126: 0 | AN126: 0 | AO126: =IF(AND(AN126=0,AM126=0),0,IF(OR(AM126=0,AM126="NM",AN126="NM"),"NM",IF(AM126<0,-(AN126/AM126-1),AN126/AM126-1))) -> 0 | AP126: =IF(AND(AN126=0,AJ126=0),0,IF(OR(AJ126=0,AJ126="NM",AN126="NM"),"NM",IF(AJ126<0,-(AN126/AJ126-1),AN126/AJ126-1))) -> 0
...

Sheet Quarterly YTD
A1: €mm, Dec year-end | B1: FY18 | C1: 1Q19 | D1: 1H19 | E1: 3Q19 | F1: FY19 | G1: 1Q20 | H1: 1H20 | I1: 3Q20 | J1: FY20 | K1: 1Q21 | L1: 1H21 | M1: 3Q21 | N1: FY21 | O1: 1Q22 | P1: 1H22 | Q1: 3Q22 | R1: FY22 | S1: 1Q23 | T1: 1H23 | U1: 3Q23 | V1: FY23 | W1: 1Q24 | X1: 1H24 | Y1: 3Q24 | Z1: FY24 | AA1: 1Q25 | AB1: 1H25 | AC1: 3Q25 | AD1: FY25 | AE1: 1Q26 | AF1: 1H26
A2: Income Statement
A3: Revenue | B3: 432.474 | C3: 93.496 | D3: 205.02 | E3: 320.448 | F3: 607.3 | G3: 267.869 | H3: 400.847 | I3: 534.639 | J3: 695.672 | K3: 162.144 | L3: 368.571 | M3: 668.286 | N3: 1014.891 | O3: 317.129 | P3: 780.635 | Q3: 1344.539 | R3: 1852.686 | S3: 404.776 | T3: 954.678 | U3: 1642.213 | V3: 2262.773 | W3: 508.778 | X3: 1228.894 | Y3: 2057.399 | Z3: 2103.272 | AA3: 457.491 | AB3: 1018.442 | AC3: 1913.128 | AD3: 2189.312 | AE3: 522.848 | AF3: 1114.52
A4: Other income | B4: 0.262 | C4: 0.16 | D4: 0.267 | E4: 0.403 | F4: 0.879 | G4: 1.034 | H4: 12.043 | I4: 13.38 | J4: 13.218 | K4: 0.889 | L4: 2.758 | M4: 4.186 | N4: 3.332 | O4: 0.746 | P4: 2.881 | Q4: 4.346 | R4: 2.832 | S4: 0.783 | T4: 1.196 | U4: 4.762 | V4: 3.466 | W4: 1.109 | X4: 2.167 | Y4: 2.908 | Z4: 2.154 | AA4: 0.771 | AB4: 1.748 | AC4: 3.246 | AD4: 6.403 | AE4: 1.269 | AF4: 3.5
A5: Cost of services and goods | B5: -312.579 | C5: -62.428 | D5: -138.098 | E5: -218.973 | F5: -412.602 | G5: -185.272 | H5: -248.971 | I5: -323.845 | J5: -418.367 | K5: -95.058 | L5: -222.982 | M5: -407.188 | N5: -615.285 | O5: -208.777 | P5: -516.01 | Q5: -863.428 | R5: -1193.407 | S5: -278.055 | T5: -605.372 | U5: -993.456 | V5: -1406.56 | W5: -360.502 | X5: -763.091 | Y5: -1207.142 | Z5: -1187.448 | AA5: -290.996 | AB5: -581.21 | AC5: -1094.342 | AD5: -1202.791 | AE5: -327.944 | AF5: -699.754
A6: Depreciation and amortisation | B6: -6.853 | C6: -2.936 | D6: -6.166 | E6: -9.593 | F6: -34.732 | G6: -26.639 | H6: -53.231 | I6: -77.619 | J6: -99.205 | K6: -18.04 | L6: -35.1 | M6: -54.207 | N6: -74.338 | O6: -21.68 | P6: -48.19 | Q6: -84.391 | R6: -114.781 | S6: -41.974 | T6: -92.017 | U6: -156.588 | V6: -239.28 | W6: -81.707 | X6: -171.318 | Y6: -265.277 | Z6: -220.229 | AA6: -62.883 | AB6: -123.235 | AC6: -284.197 | AD6: -265.414 | AE6: -72.539 | AF6: -125.86
A7: Employee related expenses | B7: -71.907 | C7: -20.556 | D7: -41.589 | E7: -61.923 | F7: -96.702 | G7: -39.977 | H7: -72.448 | I7: -108.718 | J7: -145.734 | K7: -38.995 | L7: -82.325 | M7: -134.315 | N7: -200.189 | O7: -66.068 | P7: -142.623 | Q7: -221.076 | R7: -306.593 | S7: -85.755 | T7: -181.897 | U7: -282.972 | V7: -395.763 | W7: -115.571 | X7: -240.08 | Y7: -363.562 | Z7: -470.48 | AA7: -128.452 | AB7: -254.09 | AC7: -402.217 | AD7: -519.925 | AE7: -141.944 | AF7: -278.917
A8: Other operating expenses | B8: -22.952 | C8: -5.566 | D8: -12.151 | E8: -18.504 | F8: -34.741 | G8: -12.328 | H8: -22.284 | I8: -32.791 | J8: -46.596 | K8: -11.52 | L8: -24.036 | M8: -38.095 | N8: -68.488 | O8: -17.336 | P8: -34.888 | Q8: -58.404 | R8: -79.919 | S8: -21.85 | T8: -41.749 | U8: -66.202 | V8: -97.36 | W8: -32.188 | X8: -63.586 | Y8: -97.835 | Z8: -121.492 | AA8: -33.392 | AB8: -56.638 | AC8: -101.418 | AD8: -127.501 | AE8: -26.695 | AF8: -53.519
A9: (Increase)/decrease in the provision for impairment of financial assets | B9: -1.558 | C9: -0.219 | D9: -0.197 | E9: -0.676 | F9: -1.389 | G9: -1.37 | H9: -7.588 | I9: -7.849 | J9: -21.9 | K9: -0.236 | L9: -1.799 | M9: -2.399 | N9: -12.438 | O9: -9.311 | P9: -9.675 | Q9: -8.934 | R9: -12.251 | S9: -0.133 | T9: 2.032 | U9: 0.204 | V9: -0.919 | W9: 1.105 | X9: 0.723 | Y9: 0.508 | Z9: -3.33 | AA9: -2.974 | AB9: 1.733 | AC9: 6.195 | AD9: -159.559 | AE9: -1.113 | AF9: -30.363
A10: (Increase)/decrease in the provision for impairment of non-financial assets | B10: -2.365 | C10: -0.407 | D10: -0.753 | E10: -1.163 | F10: -3.536 | G10: -0.256 | H10: -2.519 | I10: -4.464 | J10: -7.344 | K10: -0.632 | L10: -1.256 | M10: -1.591 | N10: -5.714 | O10: -6.106 | P10: -4.19 | Q10: -4.662 | R10: -13.635 | S10: 0.017 | T10: -1.582 | U10: -2.008 | V10: -3.303 | W10: -0.82 | X10: -2.326 | Y10: -3.852 | Z10: -12.561 | AA10: -0.225 | AB10: 6.369 | AC10: 1.321 | AD10: -4.535 | AE10: -0.89 | AF10: -11.646
A11: Other gains - net | B11: 0.016 | C11: 0.657 | D11: 0.589 | E11: 0.457 | F11: 1.29 | G11: 0.377 | H11: 7.2 | I11: 10.639 | J11: 12.021 | K11: 13.473 | L11: 24.294 | M11: 30.313 | N11: 38.199 | O11: 19.732 | P11: 27.516 | Q11: 42.042 | R11: 27.045 | S11: 3.463 | T11: 7.455 | U11: 14.823 | V11: 36.603 | W11: 10.448 | X11: 16.347 | Y11: 18.547 | Z11: 3.219 | AA11: -1.645 | AB11: 2.111 | AC11: 9.995 | AD11: 17.514 | AE11: 1.756 | AF11: 10.64
A12: Operating (loss)/profit | B12: =SUM(B3:B11) -> 14.538 | C12: =SUM(C3:C11) -> 2.201 | D12: =SUM(D3:D11) -> 6.922 | E12: =SUM(E3:E11) -> 10.476 | F12: =SUM(F3:F11) -> 25.767 | G12: =SUM(G3:G11) -> 3.438 | H12: =SUM(H3:H11) -> 13.049 | I12: =SUM(I3:I11) -> 3.372 | ... AF12: =SUM(AF3:AF11) -> -71.399
A13: Finance income | B13: 0.067 | C13: 0.003 | D13: 0.032 | E13: 0.356 | F13: 3.05 | G13: 1.059 | H13: 5.179 | I13: 4.735 | J13: 12.271 | K13: 2.403 | L13: 3.17 | M13: 2.667 | N13: 2.919 | O13: 0.094 | P13: 0.192 | Q13: 2.297 | R13: 3.901 | S13: 6.358 | T13: 7.084 | U13: 4.576 | V13: 24.747 | W13: 0.593 | X13: 54.812 | Y13: 63.961 | Z13: 58.254 | AA13: 7.109 | AB13: 18.676 | AC13: 21.077 | AD13: 15.295 | AE13: 0.412 | AF13: 1.134
A14: Finance costs | B14: -1.962 | C14: -1.155 | D14: -2.031 | E14: -3.371 | F14: -9.948 | G14: -10.943 | H14: -20.77 | I14: -30.936 | J14: -38.655 | K14: -8.494 | L14: -16.343 | M14: -26.843 | N14: -39.719 | O14: -18.259 | P14: -40.747 | Q14: -76.592 | R14: -83.341 | S14: -24.175 | T14: -50.733 | U14: -85.137 | V14: -114.979 | W14: -41.744 | X14: -69.044 | Y14: -104.976 | Z14: -92.387 | AA14: -23.988 | AB14: -40.258 | AC14: -93.841 | AD14: -93.369 | AE14: -23.556 | AF14: -44.093
A15: Finance costs – net | B15: =SUM(B13:B14) -> -1.895 | C15: =SUM(C13:C14) -> -1.152 | D15: =SUM(D13:D14) -> -1.999 | E15: =SUM(E13:E14) -> -3.015 | F15: =SUM(F13:F14) -> -6.898 | G15: =SUM(G13:G14) -> -9.884 | H15: =SUM(H13:H14) -> -15.591 | I15: =SUM(I13:I14) -> -26.201 | ... AF15: =SUM(AF13:AF14) -> -42.959
A16: Share of profit of equity-accounted investees | B16: 0 | C16: -0.054 | D16: -0.079 | E16: -0.938 | F16: -1.027 | G16: 0.84 | H16: 1.849 | I16: 3.411 | J16: -1.19 | K16: 0.022 | L16: 0.018 | M16: -0.049 | N16: 1.458 | O16: 0.023 | P16: -0.007 | Q16: -0.013 | R16: -55.091 | S16: 0.004 | T16: 2.097 | U16: 2.478 | V16: 2.706 | W16: 0.004 | X16: 0.004 | Y16: 0.005 | Z16: 0.013 | AA16: 0 | AB16: 0.012 | AC16: 0.012 | AD16: -0.255 | AE16: 0 | AF16: 0.005
A17: Loss before income tax | B17: =B12+SUM(B15:B16) -> 12.643 | C17: =C12+SUM(C15:C16) -> 0.995 | D17: =D12+SUM(D15:D16) -> 4.844 | E17: =E12+SUM(E15:E16) -> 6.523 | F17: =F12+SUM(F15:F16) -> 17.842 | G17: =G12+SUM(G15:G16) -> -5.606 | H17: =H12+SUM(H15:H16) -> -0.693 | I17: =I12+SUM(I15:I16) -> -19.418 | ... AF17: =AF12+SUM(AF15:AF16) -> -114.353
A18: Income tax credit | B18: -2.952 | C18: -0.408 | D18: -1.207 | E18: -1.736 | F18: -5.712 | G18: -1.795 | H18: -6.054 | I18: -5.152 | J18: -5.796 | K18: -4.202 | L18: -0.383 | M18: -4.123 | N18: -10.26 | O18: -3.154 | P18: -9.809 | Q18: -20.475 | R18: -15.779 | S18: 3 | T18: -4.123 | U18: -11.904 | V18: -3.945 | W18: 12.94 | X18: 5.469 | Y18: -17.358 | Z18: -4.73 | AA18: 16.991 | AB18: 1.467 | AC18: -19.001 | AD18: -0.124 | AE18: 8.482 | AF18: 11.566
A19: Loss for the period | B19: =SUM(B17:B18) -> 9.691 | C19: =SUM(C17:C18) -> 0.587 | D19: =SUM(D17:D18) -> 3.637 | E19: =SUM(E17:E18) -> 4.787 | F19: =SUM(F17:F18) -> 12.13 | G19: =SUM(G17:G18) -> -7.401 | H19: =SUM(H17:H18) -> -6.747 | I19: =SUM(I17:I18) -> -24.57 | ... AF19: =SUM(AF17:AF18) -> -102.787
A20: Gain/(loss) for the period from discontinued operations | B20: 0 | C20: 0 | D20: 0 | E20: 0 | F20: 0 | G20: 0 | H20: 0 | I20: 0 | J20: 0 | K20: 0 | L20: 0 | M20: 0 | N20: 0 | O20: 0 | P20: 0 | Q20: 0 | R20: 0 | S20: 0 | T20: 0 | U20: 0 | V20: 0 | W20: 0 | X20: 0 | Y20: 0 | Z20: -116.838 | AA20: -59.905 | AB20: -106.152 | AC20: 0 | AD20: 81.382 | AE20: 0 | AF20: 20.954
A21: Loss for the period | B21: =SUM(B19:B20) -> 9.691 | C21: =C19 -> 0.587 | D21: =D19 -> 3.637 | E21: =E19 -> 4.787 | F21: =F19 -> 12.13 | G21: =G19 -> -7.401 | H21: =H19 -> -6.747 | I21: =I19 -> -24.57 | J21: =J19 -> -51.605 | ... Y21: =Y19 -> 83.326 | Z21: =SUM(Z19:Z20) -> -62.583 | AA21: =SUM(AA19:AA20) -> -122.098 | AB21: =SUM(AB19:AB20) -> -111.025 | AC21: =AC19 -> -40.042 | AD21: =SUM(AD19:AD20) -> -63.567 | AE21: =SUM(AE19:AE20) -> -59.914 | AF21: =SUM(AF19:AF20) -> -81.833
A23: Cash Flow Statement
A24: Loss for the period | B24: 9.691 | C24: 0.587 | D24: 3.637 | E24: 4.787 | F24: 12.13 | G24: -7.401 | H24: -6.747 | I24: -24.57 | J24: -51.605 | K24: 1.754 | L24: 14.587 | M24: 36.642 | N24: 34.368 | O24: -12.967 | P24: 5.085 | Q24: 55.249 | R24: 11.667 | S24: -33.541 | T24: -2.931 | U24: 70.789 | V24: 68.186 | W24: -97.555 | X24: -1.03 | Y24: 83.326 | Z24: -62.583 | AA24: -122.098 | AB24: -111.025 | AC24: -40.042 | AD24: -63.567 | AE24: -59.914 | AF24: -81.833
A25: Income tax (credit) | B25: 2.952 | C25: 0.408 | D25: 1.207 | E25: 1.736 | F25: 5.712 | G25: 1.795 | H25: 6.054 | I25: 5.152 | J25: 5.796 | K25: 4.202 | L25: 0.383 | M25: 4.123 | N25: 10.26 | O25: 3.154 | P25: 9.809 | Q25: 20.475 | R25: 15.779 | S25: -3 | T25: 4.123 | U25: 11.904 | V25: 3.945 | W25: -12.94 | X25: -5.469 | Y25: 17.358 | Z25: -2.197 | AA25: -16.582 | AB25: -1.877 | AC25: 19.001 | AD25: 3.712 | AE25: -8.482 | AF25: -7.296
A26: Depreciation and amortisation | B26: 6.853 | C26: 2.936 | D26: 6.166 | E26: 9.593 | F26: 34.732 | G26: 26.639 | H26: 53.231 | I26: 77.619 | J26: 99.205 | K26: 18.04 | L26: 35.1 | M26: 54.207 | N26: 74.338 | O26: 21.68 | P26: 48.19 | Q26: 84.391 | R26: 114.781 | S26: 41.974 | T26: 92.017 | U26: 156.588 | V26: 239.28 | W26: 81.707 | X26: 171.318 | Y26: 265.277 | Z26: 364.599 | AA26: 102.318 | AB26: 192.833 | AC26: 284.197 | AD26: 353.946 | AE26: 72.539 | AF26: 131.744
A27: Increase/(decrease) in the provision for impairment of financial and non-financial assets | B27: 3.923 | C27: 0.626 | D27: 0.95 | E27: 1.839 | F27: 4.925 | G27: 1.626 | H27: 10.107 | I27: 12.313 | J27: 29.244 | K27: 0.868 | L27: 3.055 | M27: 3.99 | N27: 18.152 | O27: 15.417 | P27: 13.865 | Q27: 13.596 | R27: 25.886 | S27: 0.116 | T27: -0.45 | U27: 1.804 | V27: 4.222 | W27: -0.285 | X27: 1.603 | Y27: 3.344 | Z27: 64.234 | AA27: -3.851 | AB27: -14.185 | AC27: -7.516 | AD27: 161.607 | AE27: 2.003 | AF27: 49.619
A28: Interest expenses | B28: 1.512 | C28: 0.833 | D28: 1.663 | E28: 2.638 | F28: 8.969 | G28: 9.986 | H28: 19.178 | I28: 29.584 | J28: 38.784 | K28: 8.209 | L28: 15.584 | M28: 24.823 | N28: 33.432 | O28: 10.146 | P28: 21.566 | Q28: 34.653 | R28: 47.69 | S28: 16.243 | T28: 34.71 | U28: 57.995 | V28: 82.481 | W28: 29.16 | X28: 65.055 | Y28: 101.178 | Z28: 137.997 | AA28: 35.468 | AB28: 64.885 | AC28: 92.517 | AD28: 114.609 | AE28: 22.628 | AF28: 43.649
A29: Foreign exchange loss | B29: -0.04 | C29: 0.352 | D29: -0.197 | E29: 0.162 | F29: -2.354 | G29: 2.687 | H29: -0.416 | I29: -4.851 | J29: -15.434 | K29: 6.477 | L29: 2.683 | M29: 7.496 | N29: 14.492 | O29: 0.659 | P29: 18.838 | Q29: 45.217 | R29: 7.001 | S29: -8.876 | T29: -3.888 | U29: 6.884 | V29: -16.743 | W29: 3.824 | X29: 5.579 | Y29: -7.37 | Z29: 7.308 | AA29: 1.148 | AB29: -11.605 | AC29: -13.715 | AD29: -11.84 | AE29: 1.791 | AF29: 3.037
A30: Discounting effect on financial assets | B30: 0.008 | C30: 0.002 | D30: 0.002 | E30: 0.115 | F30: 0.29 | G30: -0.073 | H30: -0.514 | I30: -0.563 | J30: -0.812 | K30: -0.287 | L30: -0.086 | M30: 0.091 | N30: -1.281 | O30: 0.769 | P30: 1.201 | Q30: 3.14 | R30: 3.26 | S30: 1.391 | T30: 2.789 | U30: 3.529 | V30: 3.01 | W30: 1.308 | X30: 1.492 | Y30: 2.021 | Z30: 2.566 | AA30: -0.006 | AB30: -2.406 | AC30: -2.545 | AD30: -0.804 | AE30: -0.252 | AF30: -1.499
A31: Fair value loss on derivative financial instruments | B31: 0 | C31: 0 | D31: 0 | E31: 0 | F31: 0 | G31: 0 | H31: 0 | I31: 0 | J31: 0 | K31: 0 | L31: 0 | M31: 0 | N31: 0 | O31: 0 | P31: 0 | Q31: 0 | R31: 0 | S31: 0 | T31: 0 | U31: 0 | V31: 0 | W31: 0 | X31: 0 | Y31: 0 | Z31: 0 | AA31: 0 | AB31: 0 | AC31: 0 | AD31: 0 | AE31: 0 | AF31: 0
A32: Fair value loss | B32: 0.002 | C32: 0 | D32: 0 | E32: 0 | F32: -0.003 | G32: 0 | H32: 0 | I32: -0.003 | J32: -0.66 | K32: -1.958 | L32: -2.398 | M32: -2.478 | N32: -0.474 | O32: 5.983 | P32: 12.105 | Q32: 18.465 | R32: 26.441 | S32: 6.425 | T32: 13.05 | U32: 19.807 | V32: 26.685 | W32: 7.032 | X32: -52.576 | Y32: -52.576 | Z32: -52.388 | AA32: 0.009 | AB32: 0.803 | AC32: 0.378 | AD32: 0.01 | AE32: 0.033 | AF32: 0.032
A33: Hedging initial transaction costs | B33: 0 | C33: 0 | D33: 0 | E33: 0 | F33: 0 | G33: 0 | H33: 0 | I33: 0 | J33: 0 | K33: 0 | L33: 0 | M33: 0 | N33: 0 | O33: 0 | P33: 0 | Q33: 0 | R33: 0 | S33: 0 | T33: 0 | U33: 0 | V33: 0 | W33: 0 | X33: 0 | Y33: 1.511 | Z33: 1.574 | AA33: 1.137 | AB33: 1.137 | AC33: 1.137 | AD33: 1.137 | AE33: 0 | AF33: 0
A34: Changes in other reserves | B34: 0 | C34: 0 | D34: 0 | E34: -0.002 | F34: 0.06 | G34: 0.072 | H34: 0.138 | I34: 0.205 | J34: 0.271 | K34: 0.066 | L34: 0.132 | M34: 0.199 | N34: 0.265 | O34: 0.066 | P34: 0.132 | Q34: 0.199 | R34: 0.265 | S34: 0.066 | T34: 0.133 | U34: 0.199 | V34: 1.134 | W34: 0.204 | X34: 0.407 | Y34: 0.612 | Z34: 0 | AA34: 0 | AB34: 0 | AC34: 0 | AD34: 0 | AE34: 0 | AF34: 0
A35: (Gain)/loss on property, plant and equipment disposals and write-offs | B35: 0.108 | C35: -0.272 | D35: 0.177 | E35: -0.373 | F35: -0.879 | G35: 0.289 | H35: 0.106 | I35: 1.322 | J35: 0.588 | K35: 0.445 | L35: 0.629 | M35: 3.662 | N35: -4.902 | O35: -15.095 | P35: -15.081 | Q35: -29.006 | R35: -14.615 | S35: 0.366 | T35: 0.172 | U35: 0.524 | V35: -8.391 | W35: -8.902 | X35: -11.7 | Y35: -16.146 | Z35: -14.771 | AA35: 0.018 | AB35: -2.721 | AC35: -2.309 | AD35: -1.151 | AE35: -0.162 | AF35: -0.439
... A54: Security deposits received | B54: 0.014 | C54: 0.036 | D54: 0.324 | E54: 0.467 | F54: 1.345 | G54: 1.434 | H54: 2.125 | I54: 1.7 | J54: 1.965 | K54: 0.041 | L54: 2.67 | M54: 1.871 | N54: 2.677 | O54: 4.128 | P54: 8.178 | Q54: 11.17 | R54: 9.332 | S54: 4.345 | T54: 14.257 | U54: 12.849 | V54: 10.664 | W54: 21.742 | X54: 11.498 | Y54: 14.331 | Z54: 15.497 | AA54: 1.585 | AB54: 7.06 | AC54: 8.946 | AD54: 12.113 | AE54: 4.438 | AF54: 5.754
A55: Cash generated from operating activities | B55: =SUM(B24:B30)+B32+SUM(B34:B35)+B43+SUM(B45:B46)+SUM(B48:B54) -> 22.857 | C55: =SUM(C24:C30)+SUM(C34:C35)+SUM(C45:C46)+SUM(C48:C50)+SUM(C52:C54) -> 6.971 | D55: =SUM(D24:D30)+SUM(D34:D36)+SUM(D42:D43)+SUM(D45:D46)+SUM(D48:D50)+SUM(D52:D54) -> 13.268 | E55: =SUM(E24:E31)+SUM(E34:E35)+E38+SUM(E42:E43)+SUM(E45:E46)+SUM(E48:E50)+SUM(E52:E54) -> 10.948 | F55: =SUM(F24:F30)+F32+SUM(F34:F35)+SUM(F37:F38)+SUM(F42:F43)+SUM(F45:F46)+SUM(F48:F54) -> 50.447 | G55: =SUM(G24:G30)+G32+SUM(G34:G35)+G38+G42+SUM(G45:G46)+SUM(G48:G54) -> 61.513 | H55: =SUM(H24:H30)+H32+SUM(H34:H36)+SUM(H42:H43)+SUM(H45:H46)+SUM(H48:H54) -> 133.81 | I55: =SUM(I24:I30)+I32+SUM(I34:I36)+SUM(I42:I43)+SUM(I45:I46)+SUM(I48:I54) -> 93.594 | J55: =SUM(J24:J30)+J32+SUM(J34:J35)+SUM(J37:J38)+SUM(J42:J43)+SUM(J45:J46)+SUM(J48:J54) -> 132.888 | K55: =SUM(K24:K30)+K32+SUM(K34:K35)+SUM(K38:K39)+SUM(K42:K43)+SUM(K45:K46)+SUM(K48:K54) -> 18.472 | L55: =SUM(L24:L30)+L32+SUM(L34:L35)+SUM(L38:L39)+SUM(L42:L43)+SUM(L45:L46)+SUM(L48:L54) -> 33.355 | M55: =SUM(M24:M30)+M32+SUM(M34:M35)+M38+SUM(M42:M43)+SUM(M45:M46)+SUM(M48:M54) -> 61.037 | N55: =SUM(N24:N30)+N32+SUM(N34:N35)+SUM(N37:N38)+SUM(N42:N43)+SUM(N45:N46)+SUM(N48:N54) -> 84.745 | O55: =SUM(O24:O30)+O32+SUM(O34:O35)+O38+SUM(O42:O43)+SUM(O45:O46)+SUM(O48:O54) -> 49.747 | P55: =SUM(P24:P30)+P32+SUM(P34:P35)+P38+SUM(P42:P43)+SUM(P45:P46)+SUM(P48:P54) -> 98.402 | Q55: =SUM(Q24:Q30)+Q32+SUM(Q34:Q35)+Q38+SUM(Q42:Q43)+SUM(Q45:Q46)+SUM(Q48:Q54) -> 200.755 | R55: =SUM(R24:R30)+R32+SUM(R34:R35)+SUM(R37:R38)+SUM(R42:R43)+SUM(R45:R46)+SUM(R48:R54) -> 235.793 | S55: =SUM(S24:S30)+S32+SUM(S34:S35)+S38+S43+SUM(S45:S46)+SUM(S48:S54) -> 24.817 | T55: =SUM(T24:T30)+T32+SUM(T34:T35)+T38+SUM(T41:T43)+SUM(T45:T46)+SUM(T48:T54) -> 141.517 | U55: =SUM(U24:U30)+SUM(U32:U35)+U38+SUM(U41:U43)+SUM(U45:U46)+SUM(U48:U54) -> 271.73 | V55: =SUM(V24:V30)+SUM(V32:V35)+V38+SUM(V40:V43)+SUM(V45:V46)+SUM(V48:V54) -> 367.304 | W55: =SUM(W24:W30)+SUM(W32:W35)+W38+W41+W46+SUM(W48:W51)+SUM(W53:W54) -> 85.338 | X55: =SUM(X24:X30)+SUM(X32:X35)+X38+X41+SUM(X45:X46)+SUM(X48:X54) -> 218.478 | Y55: =SUM(Y24:Y30)+SUM(Y32:Y35)+Y38+Y41+Y43+SUM(Y45:Y46)+SUM(Y48:Y54) -> 395.322 | Z55: =SUM(Z24:Z30)+SUM(Z32:Z33)+Z35+Z38+SUM(Z40:Z41)+Z43+SUM(Z45:Z47)+SUM(Z49:Z51)+SUM(Z53:Z54) -> 431.774 | AA55: =SUM(AA24:AA30)+SUM(AA32:AA33)+AA35+AA38+AA41+SUM(AA45:AA46)+SUM(AA49:AA51)+SUM(AA53:AA54) -> 52.193 | AB55: =SUM(AB24:AB30)+SUM(AB32:AB33)+AB35+AB38+AB41+SUM(AB43:AB46)+SUM(AB48:AB51)+SUM(AB53:AB54) -> 209.28 | AC55: =SUM(AC24:AC30)+SUM(AC32:AC35)+AC38+AC41+AC43+SUM(AC45:AC46)+SUM(AC48:AC54) -> 391.271 | AD55: =SUM(AD24:AD30)+SUM(AD32:AD33)+AD35+AD38+SUM(AD40:AD41)+AD43+SUM(AD45:AD47)+SUM(AD49:AD51)+SUM(AD53:AD54) -> 370.204 | AE55: =SUM(AE24:AE30)+SUM(AE32:AE33)+AE35+AE38+AE41+SUM(AE45:AE46)+SUM(AE49:AE51)+SUM(AE53:AE54) -> 51.785 | AF55: =SUM(AF24:AF30)+SUM(AF32:AF33)+AF35+AF38+AF41+SUM(AF43:AF46)+SUM(AF48:AF51)+SUM(AF53:AF54) -> 131.292
A56: Interest received | B56: 0.001 | C56: 0 | D56: 0.027 | E56: 0.028 | F56: 0.002 | G56: 0 | H56: 0.397 | I56: 0.426 | J56: 0.952 | K56: -2.072 | L56: 0.837 | M56: 0.846 | N56: 1.711 | O56: 0.095 | P56: 0.013 | Q56: 1.479 | R56: 2.337 | S56: 0.192 | T56: 0.257 | U56: 0.274 | V56: 5.272 | W56: 0.607 | X56: 3.151 | Y56: 4.605 | Z56: 7.141 | AA56: 0.65 | AB56: 1.018 | AC56: 1.65 | AD56: 2.114 | AE56: 0.18 | AF56: 0.359
A57: Interest paid | B57: -1.456 | C57: -0.726 | D57: -1.14 | E57: -1.845 | F57: -7.718 | G57: -4.566 | H57: -19.465 | I57: -15.708 | J57: -29.584 | K57: 0.005 | L57: -13.415 | M57: -16.475 | N57: -27.567 | O57: -3.275 | P57: -17.589 | Q57: -26.351 | R57: -44.188 | S57: -9.784 | T57: -32.017 | U57: -48.231 | V57: -79.833 | W57: -24.293 | X57: -57.841 | Y57: -87.359 | Z57: -131.204 | AA57: -25.054 | AB57: -62.25 | AC57: -82.994 | AD57: -110.568 | AE57: -13.015 | AF57: -40.996
A58: Income tax paid | B58: -0.931 | C58: -0.067 | D58: -1.677 | E58: -1.567 | F58: -3.536 | G58: -0.16 | H58: -0.974 | I58: -1.328 | J58: -6.885 | K58: -4.986 | L58: -6.925 | M58: -17.001 | N58: -16.208 | O58: -3.411 | P58: -10.238 | Q58: -14.67 | R58: -20.421 | S58: -11.307 | T58: -7.513 | U58: -19.706 | V58: -24.529 | W58: -2.367 | X58: -4.836 | Y58: -9.43 | Z58: -14.017 | AA58: -1.631 | AB58: -9.288 | AC58: -13.732 | AD58: -17.702 | AE58: -1.405 | AF58: -5.193
A59: Net cash generated from (used in) operating activities from continuing operations | B59: =SUM(B55:B58) -> 20.471 | C59: =C55+SUM(C57:C58) -> 6.178 | D59: =SUM(D55:D58) -> 10.478 | E59: =SUM(E55:E58) -> 7.564 | F59: =SUM(F55:F58) -> 39.195 | G59: =SUM(G55:G58) -> 56.787 | H59: =SUM(H55:H58) -> 113.768 | I59: =SUM(I55:I58) -> 76.984 | J59: =SUM(J55:J58) -> 97.371 | K59: =SUM(K55:K58) -> 11.419 | ... AF59: =SUM(AF55:AF58) -> 85.462
A60: Net cash generated from operating activities | B60: =B59 -> 20.471 | C60: =C59 -> 6.178 | D60: =D59 -> 10.478 | E60: =E59 -> 7.564 | F60: =F59 -> 39.195 | G60: =G59 -> 56.787 | H60: =H59 -> 113.768 | I60: =I59 -> 76.984 | ... AF60: =AF59 -> 85.462
A61: Purchase of property, plant and equipment | B61: -25.222 | C61: -3.532 | D61: -16.729 | E61: -4.022 | F61: -39.674 | G61: -18.545 | H61: -49.481 | I61: -69.275 | J61: -93.132 | K61: -26.252 | L61: -38.347 | M61: -49.615 | N61: -70.253 | O61: -21.649 | P61: -39.75 | Q61: -60.481 | R61: -154.722 | S61: -34.387 | T61: -90.221 | U61: -122.791 | V61: -204.822 | W61: -42.935 | X61: -82.96 | Y61: -155.65 | Z61: -230.833 | AA61: -47.439 | AB61: -76.912 | AC61: -112.345 | AD61: -162.507 | AE61: -12.02 | AF61: -69.52
A62: Purchase of intangible assets | B62: 0 | C62: 0 | D62: 0 | E62: 0 | F62: 0 | G62: 0 | H62: 0 | I62: 0 | J62: 0 | K62: 0 | L62: 0 | M62: 0 | N62: 0 | O62: 0 | P62: 0 | Q62: 0 | R62: -4.348 | S62: -2.179 | T62: -4.565 | U62: -6.366 | V62: -8.962 | W62: -1.957 | X62: -4.347 | Y62: -7.041 | Z62: -9.512 | AA62: -1.302 | AB62: -2.398 | AC62: -3.801 | AD62: -6.608 | AE62: -1.481 | AF62: -3.222
A63: Proceeds from the disposal of property, plant and equipment and intangible assets | B63: 0.215 | C63: 0.328 | D63: 0.498 | E63: 0.528 | F63: 3.422 | G63: 0.433 | H63: 0.698 | I63: 0.665 | J63: 9.145 | K63: 0.05 | L63: 0.397 | M63: 0.587 | N63: 4.129 | O63: 1.976 | P63: 2.024 | Q63: 23.286 | R63: 3.9 | S63: 0.053 | T63: 0.001 | U63: 0.104 | V63: 21.152 | W63: 0.041 | X63: 1.355 | Y63: 5.334 | Z63: 6.519 | AA63: 9.265 | AB63: 15.65 | AC63: 11.492 | AD63: 18.903 | AE63: 0.297 | AF63: 2.58
A64: Net proceeds from aircraft sale leaseback | B64: 0 | C64: 0 | D64: 0 | E64: 0 | F64: 0 | G64: 0 | H64: 0 | I64: 0 | J64: 0 | K64: 0 | L64: 0 | M64: 0 | N64: 0 | O64: 0 | P64: 0 | Q64: 0 | R64: 0 | S64: 0 | T64: 0 | U64: 0 | V64: 0 | W64: 0 | X64: 0 | Y64: 0 | Z64: 0 | AA64: 0 | AB64: 0 | AC64: 0 | AD64: 0 | AE64: 0 | AF64: 0
A65: Acquired aircrafts in relation to sale leaseback | B65: 0 | C65: 0 | D65: 0 | E65: 0 | F65: 0 | G65: 0 | H65: 0 | I65: 0 | J65: 0 | K65: 0 | L65: 0 | M65: 0 | N65: 0 | O65: 0 | P65: 0 | Q65: 0 | R65: -81.411 | S65: 0 | T65: 0 | U65: 0 | V65: 0 | W65: 0 | X65: 0 | Y65: 0 | Z65: 0 | AA65: 0 | AB65: 0 | AC65: 0 | AD65: 0 | AE65: 0 | AF65: 0
A66: Proceeds from aircraft sale leaseback | B66: 0 | C66: 0 | D66: 0 | E66: 0 | F66: 0 | G66: 0 | H66: 0 | I66: 0 | J66: 0 | K66: 0 | L66: 0 | M66: 0 | N66: 0 | O66: 0 | P66: 0 | Q66: 0 | R66: 98.738 | S66: 0 | T66: 0 | U66: 0 | V66: 6.621 | W66: 33.24 | X66: 42.39 | Y66: 44.096 | Z66: 57.737 | AA66: 12.077 | AB66: 27.809 | AC66: 27.683 | AD66: 27.5 | AE66: 6.695 | AF66: 6.803
A67: Purchase of other investment | B67: 0 | C67: 0 | D67: -2.868 | E67: 0 | F67: 0 | G67: 0 | H67: -0.468 | I67: -0.443 | J67: -0.57 | K67: 0 | L67: -0.831 | M67: -3.111 | N67: -6.626 | O67: -0.305 | P67: -0.313 | Q67: 0 | R67: -0.607 | S67: 0 | T67: 0 | U67: 0 | V67: 0 | W67: 0 | X67: 0 | Y67: 0 | Z67: 0 | AA67: 0 | AB67: 0 | AC67: 0 | AD67: 0 | AE67: 0 | AF67: 0
A68: Disposal of other investments | B68: 0 | C68: 0 | D68: 0 | E68: 0 | F68: 0 | G68: 0 | H68: 0 | I68: 0 | J68: 2.117 | K68: 0 | L68: 0 | M68: 2.275 | N68: 6.37 | O68: 0.269 | P68: 0.276 | Q68: 0.284 | R68: 0.287 | S68: 0 | T68: 0.487 | U68: 0.32 | V68: 0.209 | W68: 0.061 | X68: 0.059 | Y68: 3.632 | Z68: 5.107 | AA68: 0.001 | AB68: 7.22 | AC68: 7.245 | AD68: 6.773 | AE68: 0 | AF68: 0.009
A69: Loans granted | B69: -1.471 | C69: -0.586 | D69: -0.655 | E69: -0.819 | F69: -2.729 | G69: -0.511 | H69: -3.534 | I69: -4.232 | J69: -4.733 | K69: -2.131 | L69: -3.627 | M69: -10.599 | N69: -10.733 | O69: -0.729 | P69: -4.012 | Q69: -14.116 | R69: -5.108 | S69: -0.011 | T69: -4.03 | U69: -4.036 | V69: -4.541 | W69: -4.437 | X69: -4.511 | Y69: -5.049 | Z69: -6.028 | AA69: -0.035 | AB69: -1.264 | AC69: -1.27 | AD69: -1.797 | AE69: -2.965 | AF69: -6.506
A70: Repayment of loans granted | B70: 1.023 | C70: 0.313 | D70: 0.015 | E70: 0.015 | F70: 0.312 | G70: 0.177 | H70: 0.157 | I70: 0.167 | J70: 0.182 | K70: 0.008 | L70: 0.008 | M70: 1.179 | N70: 1.311 | O70: 1.785 | P70: 2.433 | Q70: 3.099 | R70: 3.139 | S70: 0.027 | T70: 2.222 | U70: 2.225 | V70: 2.876 | W70: 0.047 | X70: 0.392 | Y70: 0.942 | Z70: 1.835 | AA70: 0.358 | AB70: 1.383 | AC70: 1.426 | AD70: 1.482 | AE70: 0.079 | AF70: 0.566
A71: Bank deposits repaid | B71: 0 | C71: -0.567 | D71: 0 | E71: 0 | F71: -84.994 | G71: -141.549 | H71: -276.103 | I71: -297.58 | J71: -363.039 | K71: -0.374 | L71: -0.913 | M71: -0.93 | N71: -225.941 | O71: -0.026 | P71: -1.45 | Q71: 0 | R71: -1.553 | S71: 1.398 | T71: 1.382 | U71: 1.313 | V71: -1.5 | W71: 2.175 | X71: -9.247 | Y71: -18.699 | Z71: -0.581 | AA71: 2.998 | AB71: 2.764 | AC71: 3.536 | AD71: 2.142 | AE71: -0.444 | AF71: -6.259
A72: Repayments of bank deposits placed | B72: 0 | C72: 0.047 | D72: 0 | E72: 0 | F72: 0 | G72: 54.407 | H72: 287.815 | I72: 353.979 | J72: 418.311 | K72: 0.913 | L72: 25.978 | M72: 26.174 | N72: 26.471 | O72: 90.073 | P72: 139.585 | Q72: 73.912 | R72: 226.651 | S72: 0 | T72: 0 | U72: 0 | V72: 0 | W72: 0 | X72: 0 | Y72: 0 | Z72: 0 | AA72: 0 | AB72: 0 | AC72: 0 | AD72: 0 | AE72: 0 | AF72: 0
... A75: Purchase of subsidiaries (net of cash acquired) | B75: -3.239 | C75: 0 | D75: 0.164 | E75: 0.164 | F75: 83.741 | G75: -3.925 | H75: -5.763 | I75: -5.79 | J75: -21.351 | K75: -3.605 | L75: -3.605 | M75: -10.118 | N75: -22.826 | O75: 0 | P75: 0 | Q75: 9.631 | R75: 0 | S75: -2.008 | T75: -6.401 | U75: -10.27 | V75: -9.473 | W75: -5.729 | X75: -2.856 | Y75: -7.224 | Z75: -11.888 | AA75: 0 | AB75: -0.012 | AC75: 0 | AD75: 0 | AE75: -27.788 | AF75: -24.824
A76: Net cash generated from (used in) investing activities from continued operations | B76: =B61+B63+SUM(B69:B71)+B75+SUM(B77:B78) -> -30.78 | C76: =C61+C63+SUM(C69:C72)+C75+SUM(C78:C79) -> -8.236 | D76: =D61+D63+D67+SUM(D69:D75)+SUM(D77:D79) -> -24.205 | E76: =E61+E63+E67+SUM(E69:E75)+SUM(E77:E79) -> -9.328 | F76: =F61+F63+SUM(F67:F71)+F75+SUM(F77:F79) -> -41.352 | G76: =G61+G63+SUM(G69:G72)+G75+SUM(G78:G79) -> -121.293 | H76: =H61+H63+H67+SUM(H69:H75)+SUM(H77:H79) -> -60.035 | I76: =I61+I63+SUM(I67:I75)+SUM(I77:I79) -> -34.969 | J76: =J61+J63+SUM(J67:J72)+J75+SUM(J77:J79) -> -84.247 | K76: =K61+K63+K67+SUM(K69:K72)+K75+K77 -> -31.391 | L76: =L61+L63+SUM(L67:L72)+L75+L77 -> -20.94 | M76: =M61+M63+SUM(M67:M72)+M75+M77 -> -37.745 | N76: =N61+SUM(N63:N64)+SUM(N67:N72)+N75+SUM(N77:N78) -> -292.192 | O76: =O61+O63+SUM(O67:O72)+O75+O77 -> 71.352 | P76: =P61+P63+SUM(P67:P72)+P75+P77 -> 98.738 | Q76: =Q61+Q63+SUM(Q67:Q70)+Q72+Q75+Q77+Q79 -> 35.56 | R76: =SUM(R61:R63)+SUM(R65:R72)+R75+R77+R79 -> 84.892 | S76: =SUM(S61:S63)+S66+SUM(S68:S71)+S75+S77+S79 -> -16.845 | T76: =SUM(T61:T63)+T66+SUM(T68:T71)+T75+T77+T79 -> -80.978 | U76: =SUM(U61:U63)+U66+SUM(U68:U71)+U75+U77+U79 -> -121.224 | V76: =SUM(V61:V63)+V66+SUM(V68:V71)+V75+V77+V79 -> -180.123 | W76: =SUM(W61:W63)+W66+SUM(W68:W71)+W75+W79 -> -22.324 | X76: =SUM(X61:X63)+X66+SUM(X68:X71)+X75+SUM(X79:X80) -> -62.555 | Y76: =SUM(Y61:Y63)+Y66+SUM(Y68:Y71)+Y75+Y77+SUM(Y79:Y80) -> -142.534 | Z76: =SUM(Z61:Z63)+Z66+SUM(Z68:Z71)+Z75+Z77+SUM(Z79:Z80) -> -190.521 | AA76: =SUM(AA61:AA63)+AA66+SUM(AA68:AA71)+AA75+AA79 -> -24.077 | AB76: =SUM(AB61:AB63)+AB66+SUM(AB68:AB71)+AB75+AB77+SUM(AB79:AB80) -> -24.985 | AC76: =SUM(AC61:AC63)+AC66+SUM(AC68:AC71)+AC75+AC77+SUM(AC79:AC80) -> -65.634 | AD76: =SUM(AD61:AD63)+AD66+SUM(AD68:AD71)+AD75+AD77+SUM(AD79:AD80) -> -114.056 | AE76: =SUM(AE61:AE63)+AE66+SUM(AE68:AE71)+AE75+AE79 -> -42.446 | AF76: =SUM(AF61:AF63)+AF66+SUM(AF68:AF71)+AF75+AF77+SUM(AF79:AF80) -> -103.514
A77: Sales of subsidiaries (net of cash disposed) | B77: -1.983 | C77: 0 | D77: 0 | E77: 0 | F77: 0 | G77: 0 | H77: 0.038 | I77: 0.038 | J77: -5.951 | K77: 0 | L77: 0 | M77: 6.413 | N77: 6.413 | O77: -0.042 | P77: -0.055 | Q77: -0.055 | R77: -0.074 | S77: 20.262 | T77: 20.147 | U77: 20.097 | V77: 20.137 | W77: 0 | X77: 0 | Y77: 0 | Z77: 0 | AA77: 0 | AB77: 0 | AC77: -0.363 | AD77: -0.719 | AE77: 0 | AF77: 1.639
A78: Investment into joint venture | B78: -0.103 | C78: -4.239 | D78: -1.346 | E78: -1.433 | F78: -1.43 | G78: -0.272 | H78: -1.658 | I78: -1.658 | J78: -1.658 | K78: 0 | L78: 0 | M78: 0 | N78: -0.507 | O78: 0 | P78: 0 | Q78: 0 | R78: 0 | S78: 0 | T78: 0 | U78: 0 | V78: 0 | W78: 0 | X78: 0 | Y78: 0 | Z78: 0 | AA78: 0 | AB78: 0 | AC78: 0 | AD78: 0 | AE78: 0 | AF78: 0
A79: Payments for financial assets at amortised cost | B79: 0 | C79: 0 | D79: 0 | E79: 0 | F79: 0 | G79: -11.508 | H79: -11.568 | I79: -11.568 | J79: -23.568 | K79: 0 | L79: 0 | M79: 0 | N79: 0 | O79: 0 | P79: 0 | Q79: 0 | R79: 0 | S79: 0 | T79: 0 | U79: -1.82 | V79: -1.82 | W79: -2.83 | X79: -2.83 | Y79: -2.875 | Z79: -2.877 | AA79: 0 | AB79: 0 | AC79: -0.012 | AD79: 0 | AE79: -4.819 | AF79: -4.832
A80: Receipt of government grants | B80: 0 | C80: 0 | D80: 0 | E80: 0 | F80: 0 | G80: 0 | H80: 0 | I80: 0 | J80: 0 | K80: 0 | L80: 0 | M80: 0 | N80: 0 | O80: 0 | P80: 0 | Q80: 0 | R80: 0 | S80: 0 | T80: 0 | U80: 0 | V80: 0 | W80: 0 | X80: 0 | Y80: 0 | Z80: 0 | AA80: 0 | AB80: 0.775 | AC80: 0.775 | AD80: 0.775 | AE80: 0 | AF80: 0.052
A81: Net cash used in investing activities | B81: =B76 -> -30.78 | C81: =C76 -> -8.236 | D81: =D76 -> -24.205 | E81: =E76 -> -9.328 | F81: =F76 -> -41.352 | G81: =G76 -> -121.293 | H81: =H76 -> -60.035 | I81: =I76 -> -34.969 | ... AF81: =AF76 -> -103.514
A82: Acquisition of interest in a subsidiary | B82: -0.049 | C82: 0 | D82: -0.005 | E82: -0.005 | F82: 0 | G82: 0 | H82: 0 | I82: 0 | J82: 0 | K82: 0 | L82: 0 | M82: 0 | N82: 0 | O82: 0 | P82: 0 | Q82: 0 | R82: 0 | S82: 0 | T82: 0 | U82: 0 | V82: 0 | W82: 0 | X82: 0 | Y82: 0 | Z82: 0 | AA82: 0 | AB82: 0 | AC82: 0 | AD82: 0 | AE82: 0 | AF82: 0
A83: Dividends paid | B83: 0 | C83: 0 | D83: 0 | E83: 0 | F83: 0 | G83: 0 | H83: 0 | I83: 0 | J83: -0.675 | K83: -0.293 | L83: -0.293 | M83: -0.293 | N83: -0.293 | O83: 0 | P83: -29.764 | Q83: -30.293 | R83: -30.328 | S83: 0 | T83: -0.572 | U83: -1.308 | V83: -25.995 | W83: -0.07 | X83: -0.735 | Y83: -1.024 | Z83: -1.492 | AA83: -0.148 | AB83: -0.253 | AC83: -2.097 | AD83: -2.097 | AE83: -0.155 | AF83: -1.076
A84: Issuance of convertible preferred shares | B84: 0 | C84: 0 | D84: 0 | E84: 0 | F84: 0 | G84: 0 | H84: 0 | I84: 0 | J84: 0 | K84: 0 | L84: 0 | M84: 0 | N84: 300 | O84: 0 | P84: 0 | Q84: 0 | R84: 0 | S84: 0 | T84: 0 | U84: 0 | V84: 0 | W84: 0 | X84: 0 | Y84: 0 | Z84: 0 | AA84: 0 | AB84: 0 | AC84: 0 | AD84: 0 | AE84: 0 | AF84: 0
A85: Acquisition of interest in asubsidiary (no change in control) | B85: 0 | C85: 0 | D85: 0 | E85: 0 | F85: -0.004 | G85: 0 | H85: 0 | I85: 0 | J85: -2.905 | K85: 0 | L85: 0 | M85: 0 | N85: 0 | O85: 0 | P85: 0 | Q85: 0 | R85: 0 | S85: 0 | T85: 0 | U85: 0 | V85: 0 | W85: 0 | X85: 0 | Y85: 0 | Z85: 0 | AA85: 0 | AB85: 0 | AC85: 0 | AD85: 0 | AE85: 0 | AF85: 0
A86: Disposal of interest in a subsidiary (no change in control) | B86: 0 | C86: 0 | D86: 0 | E86: 0 | F86: 0 | G86: 0 | H86: 0 | I86: 0 | J86: 0 | K86: 0 | L86: 0 | M86: 0 | N86: 0 | O86: 0 | P86: 0 | Q86: 0 | R86: 0 | S86: 0 | T86: 0 | U86: 0 | V86: 0 | W86: 0 | X86: 0 | Y86: 0 | Z86: 0 | AA86: 0 | AB86: 0 | AC86: 0 | AD86: 0 | AE86: 0 | AF86: 0
A87: Increase on non-controlling interest (no change in control) | B87: 0 | C87: 0 | D87: 0 | E87: 0 | F87: 0 | G87: 0 | H87: 0 | I87: 0 | J87: 0 | K87: 0 | L87: 0 | M87: 0 | N87: 0 | O87: 0 | P87: 0 | Q87: 0 | R87: -0.048 | S87: 0 | T87: 0 | U87: 0 | V87: -0.359 | W87: 0 | X87: 0 | Y87: 0 | Z87: 0 | AA87: 0 | AB87: 0 | AC87: 0 | AD87: 0 | AE87: 0 | AF87: 0
A88: Bank borrowings received | B88: 14.047 | C88: 0.731 | D88: 2.089 | E88: 2.64 | F88: 5.728 | G88: 1.455 | H88: 1.456 | I88: 1.696 | J88: 8.658 | K88: 0.714 | L88: 16.557 | M88: 26.121 | N88: 22.118 | O88: 5.426 | P88: 10.629 | Q88: 11.082 | R88: 11.094 | S88: 0 | T88: 0.276 | U88: 1.981 | V88: 1.11 | W88: 0.839 | X88: 15.86 | Y88: 15.93 | Z88: 33.158 | AA88: 28.516 | AB88: 51.307 | AC88: 53.792 | AD88: 80.896 | AE88: 54.916 | AF88: 126.51
A89: Repayment of bank borrowings | B89: -8.976 | C89: -1.053 | D89: -2.528 | E89: -3.941 | F89: -9.493 | G89: -1.082 | H89: -1.245 | I89: -1.669 | J89: -0.842 | K89: -0.584 | L89: -1.38 | M89: -4.853 | N89: -4.121 | O89: -0.65 | P89: -1.073 | Q89: -3.501 | R89: -3.891 | S89: -1.314 | T89: -1.868 | U89: -3.227 | V89: -3.875 | W89: -1.435 | X89: -2.22 | Y89: -4.229 | Z89: -14.861 | AA89: -1.59 | AB89: -2.5 | AC89: -6.116 | AD89: -10.148 | AE89: -14.123 | AF89: -18.607
A90: Borrowings from related parties received | B90: 2.434 | C90: 2.905 | D90: 14.372 | E90: 13.638 | F90: 7.699 | G90: 0 | H90: 0 | I90: 0 | J90: 0 | K90: 0 | L90: 0 | M90: 0 | N90: 0 | O90: 0 | P90: 0 | Q90: 0 | R90: 0 | S90: 0 | T90: 0 | U90: 0 | V90: 0 | W90: 0 | X90: 0 | Y90: 0 | Z90: 0 | AA90: 0 | AB90: 0 | AC90: 0 | AD90: 0 | AE90: 0 | AF90: 0
A91: Repayments of borrowings from related parties | B91: -0.193 | C91: 0 | D91: 0 | E91: 0 | F91: -6.634 | G91: 0 | H91: 0 | I91: 0 | J91: 0 | K91: 0 | L91: 0 | M91: 0 | N91: 0 | O91: 0 | P91: 0 | Q91: 0 | R91: 0 | S91: 0 | T91: 0 | U91: 0 | V91: 0 | W91: 0 | X91: 0 | Y91: 0 | Z91: 0 | AA91: 0 | AB91: 0 | AC91: 0 | AD91: 0 | AE91: 0 | AF91: 0
A92: Other borrowings received | B92: 0 | C92: 0 | D92: 0 | E92: 0 | F92: 0 | G92: 0 | H92: 0 | I92: 0 | J92: 1.878 | K92: 0.449 | L92: 0.831 | M92: 3.02 | N92: 8.383 | O92: 0 | P92: 0 | Q92: 0.043 | R92: 1.63 | S92: 0 | T92: 0 | U92: 1.03 | V92: 1.035 | W92: 0 | X92: 0 | Y92: 0 | Z92: 1.22 | AA92: 0 | AB92: 1.419 | AC92: 1.289 | AD92: 3.75 | AE92: 0 | AF92: 0.359
A93: Repayment of other borrowings | B93: 0 | C93: 0 | D93: 0 | E93: -6.634 | F93: 0 | G93: -0.1 | H93: 0 | I93: 0 | J93: -0.096 | K93: -0.109 | L93: -0.017 | M93: 0 | N93: -0.115 | O93: -4.43 | P93: -3.12 | Q93: -1.94 | R93: -1.898 | S93: -3.734 | T93: -14.142 | U93: -9.105 | V93: -9.238 | W93: -0.845 | X93: -1.799 | Y93: -4.386 | Z93: -4.733 | AA93: -2.277 | AB93: -3.475 | AC93: -4.168 | AD93: -3.704 | AE93: -13.573 | AF93: -13.819
... A99: Repayment of lease liabilities | B99: -2.072 | C99: -1.543 | D99: -3.02 | E99: -4.731 | F99: -30.873 | G99: -16.841 | H99: -40.573 | I99: -32.338 | J99: -37.801 | K99: -6.749 | L99: -15.408 | M99: -26.586 | N99: -37.939 | O99: -11.958 | P99: -19.781 | Q99: -39.157 | R99: -63.864 | S99: -21.097 | T99: -49.856 | U99: -93.383 | V99: -151.442 | W99: -50.913 | X99: -116.561 | Y99: -187.73 | Z99: -242.596 | AA99: -78.083 | AB99: -140.434 | AC99: -206.454 | AD99: -252.388 | AE99: -41.338 | AF99: -80.489
A100: Net cash generated from (used in) financing activities from continued operations | B100: =B82+SUM(B88:B91)+B94+B99 -> 5.191 | C100: =SUM(C88:C90)+C93+C99 -> 1.04 | D100: =D82+SUM(D88:D90)+D93+D97+D99 -> 10.908 | E100: =E82+SUM(E88:E90)+E93+E97+E99 -> 0.967 | F100: =F83+F85+SUM(F88:F94)+F97+F99 -> 230.88 | G100: =G83+SUM(G88:G89)+SUM(G92:G93)+G97+G99 -> -16.568 | H100: =H83+SUM(H88:H89)+SUM(H92:H93)+H97+H99 -> -45.59 | I100: =I83+SUM(I88:I89)+I92+I97+I99 -> -39.462 | J100: =SUM(J83:J85)+SUM(J88:J93)+J97+J99 -> -47.361 | K100: =K83+SUM(K88:K89)+SUM(K92:K93)+K97+K99 -> -7.072 | L100: =L83+SUM(L88:L89)+SUM(L92:L93)+L97+L99 -> -0.21 | M100: =M83+SUM(M88:M89)+SUM(M92:M93)+M97+M99 -> -3.094 | N100: =SUM(N83:N84)+N86+SUM(N88:N89)+SUM(N92:N93)+N97+N99 -> 287.524 | O100: =O83+SUM(O88:O89)+O93+O97+O99 -> -12.465 | P100: =P83+SUM(P88:P89)+P93+P97+P99 -> -53.813 | Q100: =Q83+SUM(Q88:Q89)+SUM(Q92:Q93)+Q97+Q99 -> -119.358 | R100: =R83+SUM(R87:R89)+SUM(R92:R93)+R97+R99 -> -152.007 | S100: =S83+SUM(S88:S89)+S93+S99 -> -26.145 | T100: =T83+SUM(T88:T89)+T93+SUM(T95:T97)+T99 -> -86.02 | U100: =U83+SUM(U88:U89)+SUM(U92:U93)+SUM(U95:U97)+U99 -> -123.823 | V100: =V83+SUM(V87:V89)+SUM(V92:V93)+SUM(V95:V97)+V99 -> -208.611 | W100: =W83+SUM(W88:W89)+W93+W99 -> -52.424 | X100: =X83+SUM(X88:X89)+SUM(X92:X93)+SUM(X95:X97)+X99 -> -1.719 | Y100: =Y83+SUM(Y88:Y89)+SUM(Y92:Y93)+SUM(Y95:Y97)+Y99 -> -77.453 | Z100: =Z83+SUM(Z88:Z89)+SUM(Z92:Z93)+SUM(Z95:Z97)+Z99 -> -125.341 | AA100: =AA83+SUM(AA88:AA89)+AA93+AA95+AA99 -> -53.582 | AB100: =AB83+SUM(AB88:AB89)+SUM(AB92:AB93)+SUM(AB98:AB99) -> -93.936 | AC100: =AC83+SUM(AC88:AC89)+SUM(AC92:AC93)+SUM(AC95:AC97)+AC99 -> -163.754 | AD100: =AD83+SUM(AD88:AD89)+SUM(AD92:AD93)+SUM(AD95:AD97)+AD99 -> -183.715 | AE100: =AE83+SUM(AE88:AE89)+AE93+AE95+AE99 -> -14.403 | AF100: =AF83+SUM(AF88:AF89)+SUM(AF92:AF93)+SUM(AF98:AF99) -> 12.748
A101: Net cash from (used in) financing activities | B101: =B100 -> 5.191 | C101: =C100 -> 1.04 | D101: =D100 -> 10.908 | E101: =E100 -> 0.967 | F101: =F100 -> 230.88 | G101: =G100 -> -16.568 | H101: =H100 -> -45.59 | I101: =I100 -> -39.462 | ... AF101: =AF100 -> 12.748
A102: Currency translation difference | B102: 0 | C102: 0 | D102: 0 | E102: 0 | F102: 0 | G102: 0 | H102: 0 | I102: 0 | J102: 0 | K102: 0 | L102: 0 | M102: 0 | N102: 0 | O102: 0 | P102: 0 | Q102: 0 | R102: 2.336 | S102: 0 | T102: 0 | U102: 0 | V102: -3.534 | W102: 1.883 | X102: 3.46 | Y102: -4.969 | Z102: 6.316 | AA102: -2.587 | AB102: -8.825 | AC102: -9.374 | AD102: -8.323 | AE102: 0.781 | AF102: 0.603
A103: At beginning of year | B103: -11.516 | C103: =F103 -> -16.634 | D103: =F103 -> -16.634 | E103: =F103 -> -16.634 | F103: -16.634 | G103: =J103 -> 212.089 | H103: =J103 -> 212.089 | I103: =J103 -> 212.089 | J103: 212.089 | K103: =N103 -> 177.852 | L103: =N103 -> 177.852 | M103: =N103 -> 177.852 | N103: 177.852 | O103: =R103 -> 215.865 | P103: =R103 -> 215.865 | Q103: =R103 -> 215.865 | R103: 215.865 | S103: =V103 -> 324.607 | T103: =V103 -> 324.607 | U103: =V103 -> 324.607 | V103: 324.607 | W103: =Z103 -> 200.553 | X103: =Z103 -> 200.553 | Y103: =Z103 -> 200.553 | Z103: 200.553 | AA103: =AB103 -> 184.701 | AB103: 184.701 | AC103: =AB103 -> 184.701 | AD103: =AB103 -> 184.701 | AE103: =AF103 -> 122.655 | AF103: 122.655
A104: Decrease in cash and cash equivalents | B104: =B60+B81+B101 -> -5.118 | C104: =C60+C81+C101 -> -1.018 | D104: =D60+D81+D101 -> -2.819 | E104: =E60+E81+E101 -> -0.797 | F104: =F60+F81+F101 -> 228.723 | G104: =G60+G81+G101 -> -81.074 | H104: =H60+H81+H101 -> 8.143 | I104: =I60+I81+I101 -> 2.553 | ... O104: =O60+O81+O101 -> 102.043 | P104: =P60+P81+SUM(P101:P102) -> 115.513 | Q104: =Q60+Q81+Q101 -> 77.415 | R104: =R60+R81+SUM(R101:R102) -> 108.742 | S104: =S60+S81+SUM(S101:S102) -> -39.072 | T104: =T60+T81+SUM(T101:T102) -> -64.754 | U104: =U60+U81+SUM(U101:U102) -> -40.98 | V104: =V60+V81+SUM(V101:V102) -> -124.054 | W104: =W60+W81+SUM(W101:W102) -> -13.58 | X104: =X60+X81+SUM(X101:X102) -> 98.138 | Y104: =Y60+Y81+SUM(Y101:Y102) -> 78.182 | ... AF104: =AF60+AF81+SUM(AF101:AF102) -> -4.701
A105: At end of period | B105: =SUM(B103:B104) -> -16.634 | C105: =SUM(C103:C104) -> -17.652 | D105: =SUM(D103:D104) -> -19.453 | E105: =SUM(E103:E104) -> -17.431 | F105: =SUM(F103:F104) -> 212.089 | G105: =SUM(G103:G104) -> 131.015 | H105: =SUM(H103:H104) -> 220.232 | I105: =SUM(I103:I104) -> 214.642 | ... AF105: =SUM(AF103:AF104) -> 117.954
A107: Balance Sheet
A108: Property, plant and equipment | B108: 62.449 | F108: 363.286 | G108: 405.787 | H108: ='Annual and Quarterly'!P108 -> 388.096 | I108: ='Annual and Quarterly'!Q108 -> 380.535 | J108: 352.931 | K108: 364.592 | L108: ='Annual and Quarterly'!T108 -> 380.509 | M108: ='Annual and Quarterly'!U108 -> 396.674 | N108: 414.443 | O108: 464.724 | P108: ='Annual and Quarterly'!X108 -> 573.566 | Q108: ='Annual and Quarterly'!Y108 -> 752.719 | R108: 776.321 | S108: 953.524 | T108: ='Annual and Quarterly'!AB108 -> 1144.169 | U108: ='Annual and Quarterly'!AC108 -> 1299.404 | V108: 1410.635 | W108: 1584.065 | X108: ='Annual and Quarterly'!AF108 -> 1670.091 | Y108: ='Annual and Quarterly'!AG108 -> 1671.461 | Z108: 1723.662 | AA108: 1604.095 | AB108: ='Annual and Quarterly'!AJ108 -> 1403.598 | AC108: ='Annual and Quarterly'!AK108 -> 1340.629 | AD108: 1084.449 | AE108: 1106.064 | AF108: ='Annual and Quarterly'!AN108 -> 939.053
A109: Investment property | B109: 0 | F109: 11.842 | G109: 12.645 | H109: ='Annual and Quarterly'!P109 -> 10.851 | I109: ='Annual and Quarterly'!Q109 -> 10.473 | J109: 10.132 | K109: 13.356 | L109: ='Annual and Quarterly'!T109 -> 10.5 | M109: ='Annual and Quarterly'!U109 -> 11.599 | N109: 31.03 | O109: 27.166 | P109: ='Annual and Quarterly'!X109 -> 28.21 | Q109: ='Annual and Quarterly'!Y109 -> 38.728 | R109: 41.64 | S109: 43.62 | T109: ='Annual and Quarterly'!AB109 -> 43.159 | U109: ='Annual and Quarterly'!AC109 -> 41.398 | V109: 41.151 | W109: 64.49 | X109: ='Annual and Quarterly'!AF109 -> 60.761 | Y109: ='Annual and Quarterly'!AG109 -> 60.181 | Z109: 59.644 | AA109: 58.938 | AB109: ='Annual and Quarterly'!AJ109 -> 55.613 | AC109: ='Annual and Quarterly'!AK109 -> 54.886 | AD109: 53.604 | AE109: 53.268 | AF109: ='Annual and Quarterly'!AN109 -> 52.892
A110: Intangible assets | B110: 6.963 | F110: 74.412 | G110: 94.381 | H110: ='Annual and Quarterly'!P110 -> 95.323 | I110: ='Annual and Quarterly'!Q110 -> 94.424 | J110: 102.777 | K110: 107.53 | L110: ='Annual and Quarterly'!T110 -> 107.253 | M110: ='Annual and Quarterly'!U110 -> 108.882 | N110: 113.584 | O110: 116.219 | P110: ='Annual and Quarterly'!X110 -> 117.558 | Q110: ='Annual and Quarterly'!Y110 -> 115.845 | R110: 110.215 | S110: 110.473 | T110: ='Annual and Quarterly'!AB110 -> 130.668 | U110: ='Annual and Quarterly'!AC110 -> 136.333 | V110: 139.622 | W110: 146.163 | X110: ='Annual and Quarterly'!AF110 -> 147.907 | Y110: ='Annual and Quarterly'!AG110 -> 148.537 | Z110: 151.848 | AA110: 150.29 | AB110: ='Annual and Quarterly'!AJ110 -> 145.31 | AC110: ='Annual and Quarterly'!AK110 -> 144.14 | AD110: 133.318 | AE110: 134.15 | AF110: ='Annual and Quarterly'!AN110 -> 132.969
A111: Investments accounted for using the equity method | B111: 0.103 | F111: 47.034 | G111: 48.816 | H111: ='Annual and Quarterly'!P111 -> 50.254 | I111: ='Annual and Quarterly'!Q111 -> 50.101 | J111: 43.68 | K111: 46.333 | L111: ='Annual and Quarterly'!T111 -> 46.338 | M111: ='Annual and Quarterly'!U111 -> 48.208 | N111: 51.602 | O111: 52.664 | P111: ='Annual and Quarterly'!X111 -> 56.224 | Q111: ='Annual and Quarterly'!Y111 -> 59.877 | R111: 0.349 | S111: 0.349 | T111: ='Annual and Quarterly'!AB111 -> 0.358 | U111: ='Annual and Quarterly'!AC111 -> 0.358 | V111: 0.348 | W111: 0.356 | X111: ='Annual and Quarterly'!AF111 -> 0.354 | Y111: ='Annual and Quarterly'!AG111 -> 0 | Z111: 0.368 | AA111: 0.359 | AB111: ='Annual and Quarterly'!AJ111 -> 0.353 | AC111: ='Annual and Quarterly'!AK111 -> 0.352 | AD111: 0.086 | AE111: 0.093 | AF111: ='Annual and Quarterly'!AN111 -> 0.103
A112: Deferred tax assets | B112: 6.914 | F112: 9.615 | G112: 15.222 | H112: ='Annual and Quarterly'!P112 -> 17.666 | I112: ='Annual and Quarterly'!Q112 -> 22.331 | J112: 17.161 | K112: 18.559 | L112: ='Annual and Quarterly'!T112 -> 16.317 | M112: ='Annual and Quarterly'!U112 -> 16.438 | N112: 16.728 | O112: 18.975 | P112: ='Annual and Quarterly'!X112 -> 17.458 | Q112: ='Annual and Quarterly'!Y112 -> 18.065 | R112: 17.646 | S112: 25.679 | T112: ='Annual and Quarterly'!AB112 -> 24.404 | U112: ='Annual and Quarterly'!AC112 -> 30.234 | V112: 38.486 | W112: 57.412 | X112: ='Annual and Quarterly'!AF112 -> 52.405 | Y112: ='Annual and Quarterly'!AG112 -> 43.533 | Z112: 72.029 | AA112: 84.194 | AB112: ='Annual and Quarterly'!AJ112 -> 66.137 | AC112: ='Annual and Quarterly'!AK112 -> 52.719 | AD112: 64.647 | AE112: 80.672 | AF112: ='Annual and Quarterly'!AN112 -> 84.819
A113: Other investment | B113: 0 | F113: 0 | G113: 0 | H113: ='Annual and Quarterly'!P113 -> 0.468 | I113: ='Annual and Quarterly'!Q113 -> 1.289 | J113: 0 | K113: 3.246 | L113: ='Annual and Quarterly'!T113 -> 3.909 | M113: ='Annual and Quarterly'!U113 -> 5.334 | N113: 0 | O113: 0 | P113: ='Annual and Quarterly'!X113 -> 0 | Q113: ='Annual and Quarterly'!Y113 -> 0 | R113: 0 | S113: 0 | T113: ='Annual and Quarterly'!AB113 -> 0 | U113: ='Annual and Quarterly'!AC113 -> 0 | V113: 0 | W113: 0 | X113: ='Annual and Quarterly'!AF113 -> 0 | Y113: ='Annual and Quarterly'!AG113 -> 0 | Z113: 0 | AA113: 0 | AB113: ='Annual and Quarterly'!AJ113 -> 0 | AC113: ='Annual and Quarterly'!AK113 -> 0 | AD113: 0 | AE113: 0 | AF113: ='Annual and Quarterly'!AN113 -> 0.012
A114: Financial assets at fair value through profit or loss | B114: 0 | F114: 0 | G114: 0 | H114: ='Annual and Quarterly'!P114 -> 0 | I114: ='Annual and Quarterly'!Q114 -> 0 | J114: 1.231 | K114: 0 | L114: ='Annual and Quarterly'!T114 -> 0 | M114: ='Annual and Quarterly'!U114 -> 0 | N114: 2.924 | O114: 2.967 | P114: ='Annual and Quarterly'!X114 -> 2.967 | Q114: ='Annual and Quarterly'!Y114 -> 2.977 | R114: 1.649 | S114: 1.531 | T114: ='Annual and Quarterly'!AB114 -> 1.507 | U114: ='Annual and Quarterly'!AC114 -> 1.506 | V114: 1.289 | W114: 1.311 | X114: ='Annual and Quarterly'!AF114 -> 1.324 | Y114: ='Annual and Quarterly'!AG114 -> 1.617 | Z114: 0.01 | AA114: 0 | AB114: ='Annual and Quarterly'!AJ114 -> 0 | AC114: ='Annual and Quarterly'!AK114 -> 0.002 | AD114: 0 | AE114: 0.54 | AF114: ='Annual and Quarterly'!AN114 -> 0.54
A115: Derivative financial instruments | B115: 0 | F115: 3.672 | G115: 7.665 | H115: ='Annual and Quarterly'!P115 -> 6.48 | I115: ='Annual and Quarterly'!Q115 -> 5.321 | J115: 3.563 | K115: 4.707 | L115: ='Annual and Quarterly'!T115 -> 3.828 | M115: ='Annual and Quarterly'!U115 -> 4.471 | N115: 4.667 | O115: 4.995 | P115: ='Annual and Quarterly'!X115 -> 7.577 | Q115: ='Annual and Quarterly'!Y115 -> 15.864 | R115: 5.513 | S115: 4.719 | T115: ='Annual and Quarterly'!AB115 -> 3.854 | U115: ='Annual and Quarterly'!AC115 -> 6.568 | V115: 2.774 | W115: 4.092 | X115: ='Annual and Quarterly'!AF115 -> 1.579 | Y115: ='Annual and Quarterly'!AG115 -> 0 | Z115: 6.023 | AA115: 0 | AB115: ='Annual and Quarterly'!AJ115 -> 0 | AC115: ='Annual and Quarterly'!AK115 -> 0 | AD115: 0 | AE115: 0 | AF115: ='Annual and Quarterly'!AN115 -> 0
A116: Long-term bank deposits | B116: 0 | F116: 0.983 | G116: 0.997 | H116: ='Annual and Quarterly'!P116 -> 0.975 | I116: ='Annual and Quarterly'!Q116 -> 0.94 | J116: 1.226 | K116: 1.523 | L116: ='Annual and Quarterly'!T116 -> 2.18 | M116: ='Annual and Quarterly'!U116 -> 2.244 | N116: 2.297 | O116: 2.338 | P116: ='Annual and Quarterly'!X116 -> 0.895 | Q116: ='Annual and Quarterly'!Y116 -> 0.946 | R116: 0.859 | S116: 0.854 | T116: ='Annual and Quarterly'!AB116 -> 0.858 | U116: ='Annual and Quarterly'!AC116 -> 0.866 | V116: 0.865 | W116: 0.875 | X116: ='Annual and Quarterly'!AF116 -> 0.878 | Y116: ='Annual and Quarterly'!AG116 -> 0.866 | Z116: 0.362 | AA116: 0.006 | AB116: ='Annual and Quarterly'!AJ116 -> 0 | AC116: ='Annual and Quarterly'!AK116 -> 0.106 | AD116: 1.762 | AE116: 0.645 | AF116: ='Annual and Quarterly'!AN116 -> 3.397
A117: Trade and other receivables | B117: 4.052 | F117: 40.319 | G117: 47.791 | H117: ='Annual and Quarterly'!P117 -> 47.104 | I117: ='Annual and Quarterly'!Q117 -> 45.451 | J117: 42.091 | K117: 43.301 | L117: ='Annual and Quarterly'!T117 -> 47.009 | M117: ='Annual and Quarterly'!U117 -> 55.884 | N117: 49.725 | O117: 53.375 | P117: ='Annual and Quarterly'!X117 -> 59.674 | Q117: ='Annual and Quarterly'!Y117 -> 80.256 | R117: 81.12 | S117: 92.223 | T117: ='Annual and Quarterly'!AB117 -> 106.504 | U117: ='Annual and Quarterly'!AC117 -> 111.652 | V117: 112.618 | W117: 120.322 | X117: ='Annual and Quarterly'!AF117 -> 136.818 | Y117: ='Annual and Quarterly'!AG117 -> 147.712 | Z117: 134.58 | AA117: 114.172 | AB117: ='Annual and Quarterly'!AJ117 -> 107.278 | AC117: ='Annual and Quarterly'!AK117 -> 106.819 | AD117: 81.777 | AE117: 84.641 | AF117: ='Annual and Quarterly'!AN117 -> 75.186
A118: Non-current assets | B118: =SUM(B108:B112)+SUM(B115:B117) -> 80.481 | F118: =SUM(F108:F112)+SUM(F114:F117) -> 551.163 | G118: =SUM(G108:G112)+SUM(G115:G117) -> 633.304 | H118: ='Annual and Quarterly'!P118 -> 617.217 | I118: ='Annual and Quarterly'!Q118 -> 610.865 | J118: =SUM(J108:J112)+SUM(J114:J117) -> 574.792 | K118: =SUM(K108:K113)+SUM(K115:K117) -> 603.147 | L118: ='Annual and Quarterly'!T118 -> 617.843 | M118: ='Annual and Quarterly'!U118 -> 649.734 | N118: =SUM(N108:N112)+SUM(N114:N117) -> 687 | O118: =SUM(O108:O112)+SUM(O114:O117) -> 743.423 | P118: ='Annual and Quarterly'!X118 -> 864.129 | Q118: ='Annual and Quarterly'!Y118 -> 1085.277 | R118: =SUM(R108:R112)+SUM(R114:R117) -> 1035.312 | S118: =SUM(S108:S112)+SUM(S114:S117) -> 1232.972 | T118: ='Annual and Quarterly'!AB118 -> 1455.481 | U118: ='Annual and Quarterly'!AC118 -> 1628.319 | V118: =SUM(V108:V112)+SUM(V114:V117) -> 1747.788 | W118: =SUM(W108:W112)+SUM(W114:W117) -> 1979.086 | X118: ='Annual and Quarterly'!AF118 -> 2072.117 | Y118: ='Annual and Quarterly'!AG118 -> 2073.907 | Z118: =SUM(Z108:Z112)+SUM(Z114:Z117) -> 2148.526 | AA118: =SUM(AA108:AA112)+SUM(AA114:AA117) -> 2012.054 | AB118: ='Annual and Quarterly'!AJ118 -> 1778.289 | AC118: ='Annual and Quarterly'!AK118 -> 1699.653 | AD118: =SUM(AD108:AD114)+SUM(AD116:AD117) -> 1419.643 | AE118: =SUM(AE108:AE112)+AE114+SUM(AE116:AE117) -> 1460.073 | AF118: ='Annual and Quarterly'!AN118 -> 1288.971
A119: Inventories | B119: 26.709 | F119: 95.847 | G119: 39.111 | H119: ='Annual and Quarterly'!P119 -> 39.443 | I119: ='Annual and Quarterly'!Q119 -> 41.206 | J119: 38.976 | K119: 44.288 | L119: ='Annual and Quarterly'!T119 -> 62.885 | M119: ='Annual and Quarterly'!U119 -> 77.206 | N119: 73.551 | O119: 76.52 | P119: ='Annual and Quarterly'!X119 -> 110.29 | Q119: ='Annual and Quarterly'!Y119 -> 126.329 | R119: 89.855 | S119: 94.526 | T119: ='Annual and Quarterly'!AB119 -> 109.463 | U119: ='Annual and Quarterly'!AC119 -> 133.908 | V119: 125.745 | W119: 151.759 | X119: ='Annual and Quarterly'!AF119 -> 159.693 | Y119: ='Annual and Quarterly'!AG119 -> 200.006 | Z119: 248.835 | AA119: 223.859 | AB119: ='Annual and Quarterly'!AJ119 -> 209.073 | AC119: ='Annual and Quarterly'!AK119 -> 201.883 | AD119: 221.047 | AE119: 199.391 | AF119: ='Annual and Quarterly'!AN119 -> 190.585
A120: Trade and other receivables | B120: 65.585 | F120: 142.85 | G120: 183.817 | H120: ='Annual and Quarterly'!P120 -> 150.231 | I120: ='Annual and Quarterly'!Q120 -> 152.414 | J120: 116.824 | K120: 140.147 | L120: ='Annual and Quarterly'!T120 -> 159.232 | M120: ='Annual and Quarterly'!U120 -> 203.359 | N120: 247.093 | O120: 242.44 | P120: ='Annual and Quarterly'!X120 -> 269.332 | Q120: ='Annual and Quarterly'!Y120 -> 289.9 | R120: 259.04 | S120: 305.529 | T120: ='Annual and Quarterly'!AB120 -> 338.024 | U120: ='Annual and Quarterly'!AC120 -> 340.762 | V120: 327.359 | W120: 371.961 | X120: ='Annual and Quarterly'!AF120 -> 398.356 | Y120: ='Annual and Quarterly'!AG120 -> 383.022 | Z120: 335.482 | AA120: 354.854 | AB120: ='Annual and Quarterly'!AJ120 -> 349.648 | AC120: ='Annual and Quarterly'!AK120 -> 338.015 | AD120: 317.267 | AE120: 369.281 | AF120: ='Annual and Quarterly'!AN120 -> 335.079
A121: Derivative financial instruments | B121: 0 | F121: 0.377 | G121: 0 | H121: ='Annual and Quarterly'!P121 -> 0 | I121: ='Annual and Quarterly'!Q121 -> 0 | J121: 0 | K121: 0 | L121: ='Annual and Quarterly'!T121 -> 0 | M121: ='Annual and Quarterly'!U121 -> 0 | N121: 0 | O121: 0 | P121: ='Annual and Quarterly'!X121 -> 0 | Q121: ='Annual and Quarterly'!Y121 -> 0 | R121: 0 | S121: 0 | T121: ='Annual and Quarterly'!AB121 -> 0 | U121: ='Annual and Quarterly'!AC121 -> 0 | V121: 0 | W121: 0 | X121: ='Annual and Quarterly'!AF121 -> 0 | Y121: ='Annual and Quarterly'!AG121 -> 0 | Z121: 0 | AA121: 0 | AB121: ='Annual and Quarterly'!AJ121 -> 0 | AC121: ='Annual and Quarterly'!AK121 -> 0 | AD121: 0 | AE121: 0 | AF121: ='Annual and Quarterly'!AN121 -> 0
A122: Financial assets at fair value through profit or loss | B122: 0 | F122: 0 | G122: 0 | H122: ='Annual and Quarterly'!P122 -> 0 | I122: ='Annual and Quarterly'!Q122 -> 0 | J122: 0 | K122: 0 | L122: ='Annual and Quarterly'!T122 -> 0 | M122: ='Annual and Quarterly'!U122 -> 0 | N122: 0.313 | O122: 0.308 | P122: ='Annual and Quarterly'!X122 -> 0 | Q122: ='Annual and Quarterly'!Y122 -> 0 | R122: 0.6 | S122: 0.588 | T122: ='Annual and Quarterly'!AB122 -> 0.118 | U122: ='Annual and Quarterly'!AC122 -> 0.272 | V122: 0.371 | W122: 0.324 | X122: ='Annual and Quarterly'!AF122 -> 0.33 | Y122: ='Annual and Quarterly'!AG122 -> 0.316 | Z122: 0.016 | AA122: 0.016 | AB122: ='Annual and Quarterly'!AJ122 -> 0.079 | AC122: ='Annual and Quarterly'!AK122 -> 0.064 | AD122: 0.071 | AE122: 0.063 | AF122: ='Annual and Quarterly'!AN122 -> 0.07
A123: Contract assets | B123: 3.047 | F123: 7.376 | G123: 10.924 | H123: ='Annual and Quarterly'!P123 -> 11.541 | I123: ='Annual and Quarterly'!Q123 -> 10.546 | J123: 10.128 | K123: 18.258 | L123: ='Annual and Quarterly'!T123 -> 20.594 | M123: ='Annual and Quarterly'!U123 -> 18.908 | N123: 20.676 | O123: 23.954 | P123: ='Annual and Quarterly'!X123 -> 21.026 | Q123: ='Annual and Quarterly'!Y123 -> 26.936 | R123: 24.701 | S123: 23.512 | T123: ='Annual and Quarterly'!AB123 -> 29.142 | U123: ='Annual and Quarterly'!AC123 -> 28.263 | V123: 35.986 | W123: 36.744 | X123: ='Annual and Quarterly'!AF123 -> 34.093 | Y123: ='Annual and Quarterly'!AG123 -> 29.294 | Z123: 41.957 | AA123: 24.748 | AB123: ='Annual and Quarterly'!AJ123 -> 20.555 | AC123: ='Annual and Quarterly'!AK123 -> 18.267 | AD123: 15.053 | AE123: 31.702 | AF123: ='Annual and Quarterly'!AN123 -> 24.2
A124: Current financial assets at fair value through profit & loss | B124: 0 | F124: 0 | G124: 0 | H124: ='Annual and Quarterly'!P124 -> 0 | I124: ='Annual and Quarterly'!Q124 -> 0 | J124: 0 | K124: 0 | L124: ='Annual and Quarterly'!T124 -> 0.701 | M124: ='Annual and Quarterly'!U124 -> 0.642 | N124: 0 | O124: 0 | P124: ='Annual and Quarterly'!X124 -> 0 | Q124: ='Annual and Quarterly'!Y124 -> 0 | R124: 0 | S124: 0 | T124: ='Annual and Quarterly'!AB124 -> 0 | U124: ='Annual and Quarterly'!AC124 -> 0 | V124: 0 | W124: 0 | X124: ='Annual and Quarterly'!AF124 -> 0 | Y124: ='Annual and Quarterly'!AG124 -> 0 | Z124: 0 | AA124: 0 | AB124: ='Annual and Quarterly'!AJ124 -> 0 | AC124: ='Annual and Quarterly'!AK124 -> 0 | AD124: 0 | AE124: 0 | AF124: ='Annual and Quarterly'!AN124 -> 0
A125: Prepaid income tax | B125: 1.022 | F125: 1.156 | G125: 2.494 | H125: ='Annual and Quarterly'!P125 -> 1.656 | I125: ='Annual and Quarterly'!Q125 -> 1.768 | J125: 1.699 | K125: 1.696 | L125: ='Annual and Quarterly'!T125 -> 2.066 | M125: ='Annual and Quarterly'!U125 -> 2.038 | N125: 1.739 | O125: 0.945 | P125: ='Annual and Quarterly'!X125 -> 1.163 | Q125: ='Annual and Quarterly'!Y125 -> 1.594 | R125: 4.41 | S125: 2.086 | T125: ='Annual and Quarterly'!AB125 -> 2.091 | U125: ='Annual and Quarterly'!AC125 -> 4.242 | V125: 3.729 | W125: 5.769 | X125: ='Annual and Quarterly'!AF125 -> 7.348 | Y125: ='Annual and Quarterly'!AG125 -> 5.781 | Z125: 0 | AA125: 3.563 | AB125: ='Annual and Quarterly'!AJ125 -> 5.5 | AC125: ='Annual and Quarterly'!AK125 -> 6.525 | AD125: 0 | AE125: 0 | AF125: ='Annual and Quarterly'!AN125 -> 0
A126: Short-term bank deposit | B126: 0 | F126: 84.011 | G126: 172.597 | H126: ='Annual and Quarterly'!P126 -> 72.161 | I126: ='Annual and Quarterly'!Q126 -> 26.862 | J126: 25.519 | K126: 25.881 | L126: ='Annual and Quarterly'!T126 -> 0 | M126: ='Annual and Quarterly'!U126 -> 0.009 | N126: 0 | O126: 135.032 | P126: ='Annual and Quarterly'!X126 -> 88.51 | Q126: ='Annual and Quarterly'!Y126 -> 154.814 | R126: 0 | S126: 0 | T126: ='Annual and Quarterly'!AB126 -> 0 | U126: ='Annual and Quarterly'!AC126 -> 0 | V126: 0 | W126: 0 | X126: ='Annual and Quarterly'!AF126 -> 0 | Y126: ='Annual and Quarterly'!AG126 -> 0 | Z126: 0 | AA126: 0 | AB126: ='Annual and Quarterly'!AJ126 -> 0 | AC126: ='Annual and Quarterly'!AK126 -> 0 | AD126: 0 | AE126: 0 | AF126: ='Annual and Quarterly'!AN126 -> 0
A127: Prepaid income | B127: 0 | F127: 0 | G127: 0 | H127: ='Annual and Quarterly'!P127 -> 0 | I127: ='Annual and Quarterly'!Q127 -> 0 | J127: 0 | K127: 0 | L127: ='Annual and Quarterly'!T127 -> 0 | M127: ='Annual and Quarterly'!U127 -> 0 | N127: 0 | O127: 0 | P127: ='Annual and Quarterly'!X127 -> 0 | Q127: ='Annual and Quarterly'!Y127 -> 0 | R127: 0 | S127: 0 | T127: ='Annual and Quarterly'!AB127 -> 0 | U127: ='Annual and Quarterly'!AC127 -> 0 | V127: 0 | W127: 0 | X127: ='Annual and Quarterly'!AF127 -> 0 | Y127: ='Annual and Quarterly'!AG127 -> 0 | Z127: 3.123 | AA127: 0 | AB127: ='Annual and Quarterly'!AJ127 -> 0 | AC127: ='Annual and Quarterly'!AK127 -> 0 | AD127: 2.553 | AE127: 3.996 | AF127: ='Annual and Quarterly'!AN127 -> 4.307
...

Sheet Rolling LTM
A1: €mm, Dec year-end | B1: FY18 | C1: 1Q19 | D1: 2Q19 | E1: 3Q19 | F1: FY19 | G1: 1Q20 | H1: 2Q20 | I1: 3Q20 | J1: FY20 | K1: 1Q21 | L1: 2Q21 | M1: 3Q21 | N1: FY21 | O1: 1Q22 | P1: 2Q22 | Q1: 3Q22 | R1: FY22 | S1: 1Q23 | T1: 2Q23 | U1: 3Q23 | V1: FY23 | W1: 1Q24 | X1: 2Q24 | Y1: 3Q24 | Z1: FY24 | AA1: 1Q25 | AB1: 2Q25 | AC1: 3Q25 | AD1: FY25 | AE1: 1Q26 | AF1: 2Q26
A2: Income Statement
A3: Revenue | B3: 432.474 | F3: 607.3 | G3: =F3+'Quarterly YTD'!G3-'Quarterly YTD'!C3 -> 781.673 | H3: =F3+'Quarterly YTD'!H3-'Quarterly YTD'!D3 -> 803.127 | I3: =F3+'Quarterly YTD'!I3-'Quarterly YTD'!E3 -> 821.491 | J3: 695.672 | K3: =J3+'Quarterly YTD'!K3-'Quarterly YTD'!G3 -> 589.947 | L3: =J3+'Quarterly YTD'!L3-'Quarterly YTD'!H3 -> 663.396 | M3: =J3+'Quarterly YTD'!M3-'Quarterly YTD'!I3 -> 829.319 | N3: 1014.891 | O3: =N3+'Quarterly YTD'!O3-'Quarterly YTD'!K3 -> 1169.876 | P3: =N3+'Quarterly YTD'!P3-'Quarterly YTD'!L3 -> 1426.955 | Q3: =N3+'Quarterly YTD'!Q3-'Quarterly YTD'!M3 -> 1691.144 | R3: 1852.686 | S3: =R3+'Quarterly YTD'!S3-'Quarterly YTD'!O3 -> 1940.333 | T3: =R3+'Quarterly YTD'!T3-'Quarterly YTD'!P3 -> 2026.729 | U3: =R3+'Quarterly YTD'!U3-'Quarterly YTD'!Q3 -> 2150.36 | V3: 2262.773 | W3: =V3+'Quarterly YTD'!W3-'Quarterly YTD'!S3 -> 2366.775 | X3: =V3+'Quarterly YTD'!X3-'Quarterly YTD'!T3 -> 2536.989 | Y3: =V3+'Quarterly YTD'!Y3-'Quarterly YTD'!U3 -> 2677.959 | Z3: 2103.272 | AA3: =Z3+'Quarterly YTD'!AA3-'Quarterly YTD'!W3 -> 2051.985 | AB3: =Z3+'Quarterly YTD'!AB3-'Quarterly YTD'!X3 -> 1892.82 | AC3: =Z3+'Quarterly YTD'!AC3-'Quarterly YTD'!Y3 -> 1959.001 | AD3: 2189.312 | AE3: =AD3+'Quarterly YTD'!AE3-'Quarterly YTD'!AA3 -> 2254.669 | AF3: =AD3+'Quarterly YTD'!AF3-'Quarterly YTD'!AB3 -> 2285.39
A4: Other income | B4: 0.262 | F4: 0.879 | G4: =F4+'Quarterly YTD'!G4-'Quarterly YTD'!C4 -> 1.753 | H4: =F4+'Quarterly YTD'!H4-'Quarterly YTD'!D4 -> 12.655 | I4: =F4+'Quarterly YTD'!I4-'Quarterly YTD'!E4 -> 13.856 | J4: 13.218 | K4: =J4+'Quarterly YTD'!K4-'Quarterly YTD'!G4 -> 13.073 | L4: =J4+'Quarterly YTD'!L4-'Quarterly YTD'!H4 -> 3.933 | M4: =J4+'Quarterly YTD'!M4-'Quarterly YTD'!I4 -> 4.024 | N4: 3.332 | O4: =N4+'Quarterly YTD'!O4-'Quarterly YTD'!K4 -> 3.189 | P4: =N4+'Quarterly YTD'!P4-'Quarterly YTD'!L4 -> 3.455 | Q4: =N4+'Quarterly YTD'!Q4-'Quarterly YTD'!M4 -> 3.492 | R4: 2.832 | S4: =R4+'Quarterly YTD'!S4-'Quarterly YTD'!O4 -> 2.869 | T4: =R4+'Quarterly YTD'!T4-'Quarterly YTD'!P4 -> 1.147 | U4: =R4+'Quarterly YTD'!U4-'Quarterly YTD'!Q4 -> 3.248 | V4: 3.466 | W4: =V4+'Quarterly YTD'!W4-'Quarterly YTD'!S4 -> 3.792 | X4: =V4+'Quarterly YTD'!X4-'Quarterly YTD'!T4 -> 4.437 | Y4: =V4+'Quarterly YTD'!Y4-'Quarterly YTD'!U4 -> 1.612 | Z4: 2.154 | AA4: =Z4+'Quarterly YTD'!AA4-'Quarterly YTD'!W4 -> 1.816 | AB4: =Z4+'Quarterly YTD'!AB4-'Quarterly YTD'!X4 -> 1.735 | AC4: =Z4+'Quarterly YTD'!AC4-'Quarterly YTD'!Y4 -> 2.492 | AD4: 6.403 | AE4: =AD4+'Quarterly YTD'!AE4-'Quarterly YTD'!AA4 -> 6.901 | AF4: =AD4+'Quarterly YTD'!AF4-'Quarterly YTD'!AB4 -> 8.155
A5: Cost of services and goods | B5: -312.579 | F5: -412.602 | G5: =F5+'Quarterly YTD'!G5-'Quarterly YTD'!C5 -> -535.446 | H5: =F5+'Quarterly YTD'!H5-'Quarterly YTD'!D5 -> -523.475 | I5: =F5+'Quarterly YTD'!I5-'Quarterly YTD'!E5 -> -517.474 | J5: -418.367 | K5: =J5+'Quarterly YTD'!K5-'Quarterly YTD'!G5 -> -328.153 | L5: =J5+'Quarterly YTD'!L5-'Quarterly YTD'!H5 -> -392.378 | M5: =J5+'Quarterly YTD'!M5-'Quarterly YTD'!I5 -> -501.71 | N5: -615.285 | O5: =N5+'Quarterly YTD'!O5-'Quarterly YTD'!K5 -> -729.004 | P5: =N5+'Quarterly YTD'!P5-'Quarterly YTD'!L5 -> -908.313 | Q5: =N5+'Quarterly YTD'!Q5-'Quarterly YTD'!M5 -> -1071.525 | R5: -1193.407 | S5: =R5+'Quarterly YTD'!S5-'Quarterly YTD'!O5 -> -1262.685 | T5: =R5+'Quarterly YTD'!T5-'Quarterly YTD'!P5 -> -1282.769 | U5: =R5+'Quarterly YTD'!U5-'Quarterly YTD'!Q5 -> -1323.435 | V5: -1406.56 | W5: =V5+'Quarterly YTD'!W5-'Quarterly YTD'!S5 -> -1489.007 | X5: =V5+'Quarterly YTD'!X5-'Quarterly YTD'!T5 -> -1564.279 | Y5: =V5+'Quarterly YTD'!Y5-'Quarterly YTD'!U5 -> -1620.246 | Z5: -1187.448 | AA5: =Z5+'Quarterly YTD'!AA5-'Quarterly YTD'!W5 -> -1117.942 | AB5: =Z5+'Quarterly YTD'!AB5-'Quarterly YTD'!X5 -> -1005.567 | AC5: =Z5+'Quarterly YTD'!AC5-'Quarterly YTD'!Y5 -> -1074.648 | AD5: -1202.791 | AE5: =AD5+'Quarterly YTD'!AE5-'Quarterly YTD'!AA5 -> -1239.739 | AF5: =AD5+'Quarterly YTD'!AF5-'Quarterly YTD'!AB5 -> -1321.335
A6: Depreciation and amortisation | B6: -6.853 | F6: -34.732 | G6: =F6+'Quarterly YTD'!G6-'Quarterly YTD'!C6 -> -58.435 | H6: =F6+'Quarterly YTD'!H6-'Quarterly YTD'!D6 -> -81.797 | I6: =F6+'Quarterly YTD'!I6-'Quarterly YTD'!E6 -> -102.758 | J6: -99.205 | K6: =J6+'Quarterly YTD'!K6-'Quarterly YTD'!G6 -> -90.606 | L6: =J6+'Quarterly YTD'!L6-'Quarterly YTD'!H6 -> -81.074 | M6: =J6+'Quarterly YTD'!M6-'Quarterly YTD'!I6 -> -75.793 | N6: -74.338 | O6: =N6+'Quarterly YTD'!O6-'Quarterly YTD'!K6 -> -77.978 | P6: =N6+'Quarterly YTD'!P6-'Quarterly YTD'!L6 -> -87.428 | Q6: =N6+'Quarterly YTD'!Q6-'Quarterly YTD'!M6 -> -104.522 | R6: -114.781 | S6: =R6+'Quarterly YTD'!S6-'Quarterly YTD'!O6 -> -135.075 | T6: =R6+'Quarterly YTD'!T6-'Quarterly YTD'!P6 -> -158.608 | U6: =R6+'Quarterly YTD'!U6-'Quarterly YTD'!Q6 -> -186.978 | V6: -239.28 | W6: =V6+'Quarterly YTD'!W6-'Quarterly YTD'!S6 -> -279.013 | X6: =V6+'Quarterly YTD'!X6-'Quarterly YTD'!T6 -> -318.581 | Y6: =V6+'Quarterly YTD'!Y6-'Quarterly YTD'!U6 -> -347.969 | Z6: -220.229 | AA6: =Z6+'Quarterly YTD'!AA6-'Quarterly YTD'!W6 -> -201.405 | AB6: =Z6+'Quarterly YTD'!AB6-'Quarterly YTD'!X6 -> -172.146 | AC6: =Z6+'Quarterly YTD'!AC6-'Quarterly YTD'!Y6 -> -239.149 | AD6: -265.414 | AE6: =AD6+'Quarterly YTD'!AE6-'Quarterly YTD'!AA6 -> -275.07 | AF6: =AD6+'Quarterly YTD'!AF6-'Quarterly YTD'!AB6 -> -268.039
A7: Employee related expenses | B7: -71.907 | F7: -96.702 | G7: =F7+'Quarterly YTD'!G7-'Quarterly YTD'!C7 -> -116.123 | H7: =F7+'Quarterly YTD'!H7-'Quarterly YTD'!D7 -> -127.561 | I7: =F7+'Quarterly YTD'!I7-'Quarterly YTD'!E7 -> -143.497 | J7: -145.734 | K7: =J7+'Quarterly YTD'!K7-'Quarterly YTD'!G7 -> -144.752 | L7: =J7+'Quarterly YTD'!L7-'Quarterly YTD'!H7 -> -155.611 | M7: =J7+'Quarterly YTD'!M7-'Quarterly YTD'!I7 -> -171.331 | N7: -200.189 | O7: =N7+'Quarterly YTD'!O7-'Quarterly YTD'!K7 -> -227.262 | P7: =N7+'Quarterly YTD'!P7-'Quarterly YTD'!L7 -> -260.487 | Q7: =N7+'Quarterly YTD'!Q7-'Quarterly YTD'!M7 -> -286.95 | R7: -306.593 | S7: =R7+'Quarterly YTD'!S7-'Quarterly YTD'!O7 -> -326.28 | T7: =R7+'Quarterly YTD'!T7-'Quarterly YTD'!P7 -> -345.867 | U7: =R7+'Quarterly YTD'!U7-'Quarterly YTD'!Q7 -> -368.489 | V7: -395.763 | W7: =V7+'Quarterly YTD'!W7-'Quarterly YTD'!S7 -> -425.579 | X7: =V7+'Quarterly YTD'!X7-'Quarterly YTD'!T7 -> -453.946 | Y7: =V7+'Quarterly YTD'!Y7-'Quarterly YTD'!U7 -> -476.353 | Z7: -470.48 | AA7: =Z7+'Quarterly YTD'!AA7-'Quarterly YTD'!W7 -> -483.361 | AB7: =Z7+'Quarterly YTD'!AB7-'Quarterly YTD'!X7 -> -484.49 | AC7: =Z7+'Quarterly YTD'!AC7-'Quarterly YTD'!Y7 -> -509.135 | AD7: -519.925 | AE7: =AD7+'Quarterly YTD'!AE7-'Quarterly YTD'!AA7 -> -533.417 | AF7: =AD7+'Quarterly YTD'!AF7-'Quarterly YTD'!AB7 -> -544.752
A8: Other operating expenses | B8: -22.952 | F8: -34.741 | G8: =F8+'Quarterly YTD'!G8-'Quarterly YTD'!C8 -> -41.503 | H8: =F8+'Quarterly YTD'!H8-'Quarterly YTD'!D8 -> -44.874 | I8: =F8+'Quarterly YTD'!I8-'Quarterly YTD'!E8 -> -49.028 | J8: -46.596 | K8: =J8+'Quarterly YTD'!K8-'Quarterly YTD'!G8 -> -45.788 | L8: =J8+'Quarterly YTD'!L8-'Quarterly YTD'!H8 -> -48.348 | M8: =J8+'Quarterly YTD'!M8-'Quarterly YTD'!I8 -> -51.9 | N8: -68.488 | O8: =N8+'Quarterly YTD'!O8-'Quarterly YTD'!K8 -> -74.304 | P8: =N8+'Quarterly YTD'!P8-'Quarterly YTD'!L8 -> -79.34 | Q8: =N8+'Quarterly YTD'!Q8-'Quarterly YTD'!M8 -> -88.797 | R8: -79.919 | S8: =R8+'Quarterly YTD'!S8-'Quarterly YTD'!O8 -> -84.433 | T8: =R8+'Quarterly YTD'!T8-'Quarterly YTD'!P8 -> -86.78 | U8: =R8+'Quarterly YTD'!U8-'Quarterly YTD'!Q8 -> -87.717 | V8: -97.36 | W8: =V8+'Quarterly YTD'!W8-'Quarterly YTD'!S8 -> -107.698 | X8: =V8+'Quarterly YTD'!X8-'Quarterly YTD'!T8 -> -119.197 | Y8: =V8+'Quarterly YTD'!Y8-'Quarterly YTD'!U8 -> -128.993 | Z8: -121.492 | AA8: =Z8+'Quarterly YTD'!AA8-'Quarterly YTD'!W8 -> -122.696 | AB8: =Z8+'Quarterly YTD'!AB8-'Quarterly YTD'!X8 -> -114.544 | AC8: =Z8+'Quarterly YTD'!AC8-'Quarterly YTD'!Y8 -> -125.075 | AD8: -127.501 | AE8: =AD8+'Quarterly YTD'!AE8-'Quarterly YTD'!AA8 -> -120.804 | AF8: =AD8+'Quarterly YTD'!AF8-'Quarterly YTD'!AB8 -> -124.382
A9: (Increase)/decrease in the provision for impairment of financial assets | B9: -1.558 | F9: -1.389 | G9: =F9+'Quarterly YTD'!G9-'Quarterly YTD'!C9 -> -2.54 | H9: =F9+'Quarterly YTD'!H9-'Quarterly YTD'!D9 -> -8.78 | I9: =F9+'Quarterly YTD'!I9-'Quarterly YTD'!E9 -> -8.562 | J9: -21.9 | K9: =J9+'Quarterly YTD'!K9-'Quarterly YTD'!G9 -> -20.766 | L9: =J9+'Quarterly YTD'!L9-'Quarterly YTD'!H9 -> -16.111 | M9: =J9+'Quarterly YTD'!M9-'Quarterly YTD'!I9 -> -16.45 | N9: -12.438 | O9: =N9+'Quarterly YTD'!O9-'Quarterly YTD'!K9 -> -21.513 | P9: =N9+'Quarterly YTD'!P9-'Quarterly YTD'!L9 -> -20.314 | Q9: =N9+'Quarterly YTD'!Q9-'Quarterly YTD'!M9 -> -18.973 | R9: -12.251 | S9: =R9+'Quarterly YTD'!S9-'Quarterly YTD'!O9 -> -3.073 | T9: =R9+'Quarterly YTD'!T9-'Quarterly YTD'!P9 -> -0.544 | U9: =R9+'Quarterly YTD'!U9-'Quarterly YTD'!Q9 -> -3.113 | V9: -0.919 | W9: =V9+'Quarterly YTD'!W9-'Quarterly YTD'!S9 -> 0.319 | X9: =V9+'Quarterly YTD'!X9-'Quarterly YTD'!T9 -> -2.228 | Y9: =V9+'Quarterly YTD'!Y9-'Quarterly YTD'!U9 -> -0.615 | Z9: -3.33 | AA9: =Z9+'Quarterly YTD'!AA9-'Quarterly YTD'!W9 -> -7.409 | AB9: =Z9+'Quarterly YTD'!AB9-'Quarterly YTD'!X9 -> -2.32 | AC9: =Z9+'Quarterly YTD'!AC9-'Quarterly YTD'!Y9 -> 2.357 | AD9: -159.559 | AE9: =AD9+'Quarterly YTD'!AE9-'Quarterly YTD'!AA9 -> -157.698 | AF9: =AD9+'Quarterly YTD'!AF9-'Quarterly YTD'!AB9 -> -191.655
A10: (Increase)/decrease in the provision for impairment of non-financial assets | B10: -2.365 | F10: -3.536 | G10: =F10+'Quarterly YTD'!G10-'Quarterly YTD'!C10 -> -3.385 | H10: =F10+'Quarterly YTD'!H10-'Quarterly YTD'!D10 -> -5.302 | I10: =F10+'Quarterly YTD'!I10-'Quarterly YTD'!E10 -> -6.837 | J10: -7.344 | K10: =J10+'Quarterly YTD'!K10-'Quarterly YTD'!G10 -> -7.72 | L10: =J10+'Quarterly YTD'!L10-'Quarterly YTD'!H10 -> -6.081 | M10: =J10+'Quarterly YTD'!M10-'Quarterly YTD'!I10 -> -4.471 | N10: -5.714 | O10: =N10+'Quarterly YTD'!O10-'Quarterly YTD'!K10 -> -11.188 | P10: =N10+'Quarterly YTD'!P10-'Quarterly YTD'!L10 -> -8.648 | Q10: =N10+'Quarterly YTD'!Q10-'Quarterly YTD'!M10 -> -8.785 | R10: -13.635 | S10: =R10+'Quarterly YTD'!S10-'Quarterly YTD'!O10 -> -7.512 | T10: =R10+'Quarterly YTD'!T10-'Quarterly YTD'!P10 -> -11.027 | U10: =R10+'Quarterly YTD'!U10-'Quarterly YTD'!Q10 -> -10.981 | V10: -3.303 | W10: =V10+'Quarterly YTD'!W10-'Quarterly YTD'!S10 -> -4.14 | X10: =V10+'Quarterly YTD'!X10-'Quarterly YTD'!T10 -> -4.047 | Y10: =V10+'Quarterly YTD'!Y10-'Quarterly YTD'!U10 -> -5.147 | Z10: -12.561 | AA10: =Z10+'Quarterly YTD'!AA10-'Quarterly YTD'!W10 -> -11.966 | AB10: =Z10+'Quarterly YTD'!AB10-'Quarterly YTD'!X10 -> -3.866 | AC10: =Z10+'Quarterly YTD'!AC10-'Quarterly YTD'!Y10 -> -7.388 | AD10: -4.535 | AE10: =AD10+'Quarterly YTD'!AE10-'Quarterly YTD'!AA10 -> -5.2 | AF10: =AD10+'Quarterly YTD'!AF10-'Quarterly YTD'!AB10 -> -22.55
A11: Other gains - net | B11: 0.016 | F11: 1.29 | G11: =F11+'Quarterly YTD'!G11-'Quarterly YTD'!C11 -> 1.01 | H11: =F11+'Quarterly YTD'!H11-'Quarterly YTD'!D11 -> 7.901 | I11: =F11+'Quarterly YTD'!I11-'Quarterly YTD'!E11 -> 11.472 | J11: 12.021 | K11: =J11+'Quarterly YTD'!K11-'Quarterly YTD'!G11 -> 25.117 | L11: =J11+'Quarterly YTD'!L11-'Quarterly YTD'!H11 -> 29.115 | M11: =J11+'Quarterly YTD'!M11-'Quarterly YTD'!I11 -> 31.695 | N11: 38.199 | O11: =N11+'Quarterly YTD'!O11-'Quarterly YTD'!K11 -> 44.458 | P11: =N11+'Quarterly YTD'!P11-'Quarterly YTD'!L11 -> 41.421 | Q11: =N11+'Quarterly YTD'!Q11-'Quarterly YTD'!M11 -> 49.928 | R11: 27.045 | S11: =R11+'Quarterly YTD'!S11-'Quarterly YTD'!O11 -> 10.776 | T11: =R11+'Quarterly YTD'!T11-'Quarterly YTD'!P11 -> 6.984 | U11: =R11+'Quarterly YTD'!U11-'Quarterly YTD'!Q11 -> -0.174 | V11: 36.603 | W11: =V11+'Quarterly YTD'!W11-'Quarterly YTD'!S11 -> 43.588 | X11: =V11+'Quarterly YTD'!X11-'Quarterly YTD'!T11 -> 45.495 | Y11: =V11+'Quarterly YTD'!Y11-'Quarterly YTD'!U11 -> 40.327 | Z11: 3.219 | AA11: =Z11+'Quarterly YTD'!AA11-'Quarterly YTD'!W11 -> -8.874 | AB11: =Z11+'Quarterly YTD'!AB11-'Quarterly YTD'!X11 -> -11.017 | AC11: =Z11+'Quarterly YTD'!AC11-'Quarterly YTD'!Y11 -> -5.333 | AD11: 17.514 | AE11: =AD11+'Quarterly YTD'!AE11-'Quarterly YTD'!AA11 -> 20.915 | AF11: =AD11+'Quarterly YTD'!AF11-'Quarterly YTD'!AB11 -> 26.043
A12: Operating (loss)/profit | B12: =SUM(B3:B11) -> 14.538 | F12: =SUM(F3:F11) -> 25.767 | G12: =F12+'Quarterly YTD'!G12-'Quarterly YTD'!C12 -> 27.004 | H12: =F12+'Quarterly YTD'!H12-'Quarterly YTD'!D12 -> 31.894 | I12: =F12+'Quarterly YTD'!I12-'Quarterly YTD'!E12 -> 18.663 | J12: =SUM(J3:J11) -> -18.235 | K12: =J12+'Quarterly YTD'!K12-'Quarterly YTD'!G12 -> -9.648 | L12: =J12+'Quarterly YTD'!L12-'Quarterly YTD'!H12 -> -3.159 | M12: =J12+'Quarterly YTD'!M12-'Quarterly YTD'!I12 -> 43.383 | N12: =SUM(N3:N11) -> 79.97 | O12: =N12+'Quarterly YTD'!O12-'Quarterly YTD'!K12 -> 76.274 | P12: =N12+'Quarterly YTD'!P12-'Quarterly YTD'!L12 -> 107.301 | Q12: =N12+'Quarterly YTD'!Q12-'Quarterly YTD'!M12 -> 165.012 | R12: =SUM(R3:R11) -> 161.977 | S12: =R12+'Quarterly YTD'!S12-'Quarterly YTD'!O12 -> 134.92 | T12: =R12+'Quarterly YTD'!T12-'Quarterly YTD'!P12 -> 149.265 | U12: =R12+'Quarterly YTD'!U12-'Quarterly YTD'!Q12 -> 172.721 | V12: =SUM(V3:V11) -> 159.657 | W12: =V12+'Quarterly YTD'!W12-'Quarterly YTD'!S12 -> 109.037 | X12: =V12+'Quarterly YTD'!X12-'Quarterly YTD'!T12 -> 124.643 | Y12: =V12+'Quarterly YTD'!Y12-'Quarterly YTD'!U12 -> 140.575 | Z12: =SUM(Z3:Z11) -> 93.105 | AA12: =Z12+'Quarterly YTD'!AA12-'Quarterly YTD'!W12 -> 100.148 | AB12: =Z12+'Quarterly YTD'!AB12-'Quarterly YTD'!X12 -> 100.605 | AC12: =Z12+'Quarterly YTD'!AC12-'Quarterly YTD'!Y12 -> 3.122 | AD12: =SUM(AD3:AD11) -> -66.496 | AE12: =AD12+'Quarterly YTD'!AE12-'Quarterly YTD'!AA12 -> -49.443 | AF12: =AD12+'Quarterly YTD'!AF12-'Quarterly YTD'!AB12 -> -153.125
A13: Finance income | B13: 0.067 | F13: 3.05 | G13: =F13+'Quarterly YTD'!G13-'Quarterly YTD'!C13 -> 4.106 | H13: =F13+'Quarterly YTD'!H13-'Quarterly YTD'!D13 -> 8.197 | I13: =F13+'Quarterly YTD'!I13-'Quarterly YTD'!E13 -> 7.429 | J13: 12.271 | K13: =J13+'Quarterly YTD'!K13-'Quarterly YTD'!G13 -> 13.615 | L13: =J13+'Quarterly YTD'!L13-'Quarterly YTD'!H13 -> 10.262 | M13: =J13+'Quarterly YTD'!M13-'Quarterly YTD'!I13 -> 10.203 | N13: 2.919 | O13: =N13+'Quarterly YTD'!O13-'Quarterly YTD'!K13 -> 0.61 | P13: =N13+'Quarterly YTD'!P13-'Quarterly YTD'!L13 -> -0.059 | Q13: =N13+'Quarterly YTD'!Q13-'Quarterly YTD'!M13 -> 2.549 | R13: 3.901 | S13: =R13+'Quarterly YTD'!S13-'Quarterly YTD'!O13 -> 10.165 | T13: =R13+'Quarterly YTD'!T13-'Quarterly YTD'!P13 -> 10.793 | U13: =R13+'Quarterly YTD'!U13-'Quarterly YTD'!Q13 -> 6.18 | V13: 24.747 | W13: =V13+'Quarterly YTD'!W13-'Quarterly YTD'!S13 -> 18.982 | X13: =V13+'Quarterly YTD'!X13-'Quarterly YTD'!T13 -> 72.475 | Y13: =V13+'Quarterly YTD'!Y13-'Quarterly YTD'!U13 -> 84.132 | Z13: 58.254 | AA13: =Z13+'Quarterly YTD'!AA13-'Quarterly YTD'!W13 -> 64.77 | AB13: =Z13+'Quarterly YTD'!AB13-'Quarterly YTD'!X13 -> 22.118 | AC13: =Z13+'Quarterly YTD'!AC13-'Quarterly YTD'!Y13 -> 15.37 | AD13: 15.295 | AE13: =AD13+'Quarterly YTD'!AE13-'Quarterly YTD'!AA13 -> 8.598 | AF13: =AD13+'Quarterly YTD'!AF13-'Quarterly YTD'!AB13 -> -2.247
A14: Finance costs | B14: -1.962 | F14: -9.948 | G14: =F14+'Quarterly YTD'!G14-'Quarterly YTD'!C14 -> -19.736 | H14: =F14+'Quarterly YTD'!H14-'Quarterly YTD'!D14 -> -28.687 | I14: =F14+'Quarterly YTD'!I14-'Quarterly YTD'!E14 -> -37.513 | J14: -38.655 | K14: =J14+'Quarterly YTD'!K14-'Quarterly YTD'!G14 -> -36.206 | L14: =J14+'Quarterly YTD'!L14-'Quarterly YTD'!H14 -> -34.228 | M14: =J14+'Quarterly YTD'!M14-'Quarterly YTD'!I14 -> -34.562 | N14: -39.719 | O14: =N14+'Quarterly YTD'!O14-'Quarterly YTD'!K14 -> -49.484 | P14: =N14+'Quarterly YTD'!P14-'Quarterly YTD'!L14 -> -64.123 | Q14: =N14+'Quarterly YTD'!Q14-'Quarterly YTD'!M14 -> -89.468 | R14: -83.341 | S14: =R14+'Quarterly YTD'!S14-'Quarterly YTD'!O14 -> -89.257 | T14: =R14+'Quarterly YTD'!T14-'Quarterly YTD'!P14 -> -93.327 | U14: =R14+'Quarterly YTD'!U14-'Quarterly YTD'!Q14 -> -91.886 | V14: -114.979 | W14: =V14+'Quarterly YTD'!W14-'Quarterly YTD'!S14 -> -132.548 | X14: =V14+'Quarterly YTD'!X14-'Quarterly YTD'!T14 -> -133.29 | Y14: =V14+'Quarterly YTD'!Y14-'Quarterly YTD'!U14 -> -134.818 | Z14: -92.387 | AA14: =Z14+'Quarterly YTD'!AA14-'Quarterly YTD'!W14 -> -74.631 | AB14: =Z14+'Quarterly YTD'!AB14-'Quarterly YTD'!X14 -> -63.601 | AC14: =Z14+'Quarterly YTD'!AC14-'Quarterly YTD'!Y14 -> -81.252 | AD14: -93.369 | AE14: =AD14+'Quarterly YTD'!AE14-'Quarterly YTD'!AA14 -> -92.937 | AF14: =AD14+'Quarterly YTD'!AF14-'Quarterly YTD'!AB14 -> -97.204
A15: Finance costs – net | B15: =SUM(B13:B14) -> -1.895 | F15: =SUM(F13:F14) -> -6.898 | G15: =SUM(G13:G14) -> -15.63 | H15: =SUM(H13:H14) -> -20.49 | I15: =SUM(I13:I14) -> -30.084 | J15: =SUM(J13:J14) -> -26.384 | K15: =SUM(K13:K14) -> -22.591 | L15: =SUM(L13:L14) -> -23.966 | M15: =SUM(M13:M14) -> -24.359 | ... AF15: =SUM(AF13:AF14) -> -99.451
A16: Share of profit of equity-accounted investees | B16: 0 | F16: -1.027 | G16: =F16+'Quarterly YTD'!G16-'Quarterly YTD'!C16 -> -0.133 | H16: =F16+'Quarterly YTD'!H16-'Quarterly YTD'!D16 -> 0.901 | I16: =F16+'Quarterly YTD'!I16-'Quarterly YTD'!E16 -> 3.322 | J16: -1.19 | K16: =J16+'Quarterly YTD'!K16-'Quarterly YTD'!G16 -> -2.008 | L16: =J16+'Quarterly YTD'!L16-'Quarterly YTD'!H16 -> -3.021 | M16: =J16+'Quarterly YTD'!M16-'Quarterly YTD'!I16 -> -4.65 | N16: 1.458 | O16: =N16+'Quarterly YTD'!O16-'Quarterly YTD'!K16 -> 1.459 | P16: =N16+'Quarterly YTD'!P16-'Quarterly YTD'!L16 -> 1.433 | Q16: =N16+'Quarterly YTD'!Q16-'Quarterly YTD'!M16 -> 1.494 | R16: -55.091 | S16: =R16+'Quarterly YTD'!S16-'Quarterly YTD'!O16 -> -55.11 | T16: =R16+'Quarterly YTD'!T16-'Quarterly YTD'!P16 -> -52.987 | U16: =R16+'Quarterly YTD'!U16-'Quarterly YTD'!Q16 -> -52.6 | V16: 2.706 | W16: =V16+'Quarterly YTD'!W16-'Quarterly YTD'!S16 -> 2.706 | X16: =V16+'Quarterly YTD'!X16-'Quarterly YTD'!T16 -> 0.613 | Y16: =V16+'Quarterly YTD'!Y16-'Quarterly YTD'!U16 -> 0.233 | Z16: 0.013 | AA16: =Z16+'Quarterly YTD'!AA16-'Quarterly YTD'!W16 -> 0.009 | AB16: =Z16+'Quarterly YTD'!AB16-'Quarterly YTD'!X16 -> 0.021 | AC16: =Z16+'Quarterly YTD'!AC16-'Quarterly YTD'!Y16 -> 0.02 | AD16: -0.255 | AE16: =AD16+'Quarterly YTD'!AE16-'Quarterly YTD'!AA16 -> -0.255 | AF16: =AD16+'Quarterly YTD'!AF16-'Quarterly YTD'!AB16 -> -0.262
A17: Loss before income tax | B17: =B12+SUM(B15:B16) -> 12.643 | F17: =F12+SUM(F15:F16) -> 17.842 | G17: =G12+SUM(G15:G16) -> 11.241 | H17: =H12+SUM(H15:H16) -> 12.305 | I17: =I12+SUM(I15:I16) -> -8.099 | J17: =J12+SUM(J15:J16) -> -45.809 | K17: =K12+SUM(K15:K16) -> -34.247 | L17: =L12+SUM(L15:L16) -> -30.146 | M17: =M12+SUM(M15:M16) -> 14.374 | ... AF17: =AF12+SUM(AF15:AF16) -> -252.838
A18: Income tax credit | B18: -2.952 | F18: -5.712 | G18: =F18+'Quarterly YTD'!G18-'Quarterly YTD'!C18 -> -7.099 | H18: =F18+'Quarterly YTD'!H18-'Quarterly YTD'!D18 -> -10.559 | I18: =F18+'Quarterly YTD'!I18-'Quarterly YTD'!E18 -> -9.128 | J18: -5.796 | K18: =J18+'Quarterly YTD'!K18-'Quarterly YTD'!G18 -> -8.203 | L18: =J18+'Quarterly YTD'!L18-'Quarterly YTD'!H18 -> -0.125 | M18: =J18+'Quarterly YTD'!M18-'Quarterly YTD'!I18 -> -4.767 | N18: -10.26 | O18: =N18+'Quarterly YTD'!O18-'Quarterly YTD'!K18 -> -9.212 | P18: =N18+'Quarterly YTD'!P18-'Quarterly YTD'!L18 -> -19.686 | Q18: =N18+'Quarterly YTD'!Q18-'Quarterly YTD'!M18 -> -26.612 | R18: -15.779 | S18: =R18+'Quarterly YTD'!S18-'Quarterly YTD'!O18 -> -9.625 | T18: =R18+'Quarterly YTD'!T18-'Quarterly YTD'!P18 -> -10.093 | U18: =R18+'Quarterly YTD'!U18-'Quarterly YTD'!Q18 -> -7.208 | V18: -3.945 | W18: =V18+'Quarterly YTD'!W18-'Quarterly YTD'!S18 -> 5.995 | X18: =V18+'Quarterly YTD'!X18-'Quarterly YTD'!T18 -> 5.647 | Y18: =V18+'Quarterly YTD'!Y18-'Quarterly YTD'!U18 -> -9.399 | Z18: -4.73 | AA18: =Z18+'Quarterly YTD'!AA18-'Quarterly YTD'!W18 -> -0.679 | AB18: =Z18+'Quarterly YTD'!AB18-'Quarterly YTD'!X18 -> -8.732 | AC18: =Z18+'Quarterly YTD'!AC18-'Quarterly YTD'!Y18 -> -6.373 | AD18: -0.124 | AE18: =AD18+'Quarterly YTD'!AE18-'Quarterly YTD'!AA18 -> -8.633 | AF18: =AD18+'Quarterly YTD'!AF18-'Quarterly YTD'!AB18 -> 9.975
A19: Loss for the period | B19: =SUM(B17:B18) -> 9.691 | F19: =SUM(F17:F18) -> 12.13 | G19: =SUM(G17:G18) -> 4.142 | H19: =SUM(H17:H18) -> 1.746 | I19: =SUM(I17:I18) -> -17.227 | J19: =SUM(J17:J18) -> -51.605 | K19: =SUM(K17:K18) -> -42.45 | L19: =SUM(L17:L18) -> -30.271 | M19: =SUM(M17:M18) -> 9.607 | ... AF19: =SUM(AF17:AF18) -> -242.863
A20: Gain/(loss) for the period from discontinued operations | B20: 0 | F20: 0 | G20: =F20+'Quarterly YTD'!G20-'Quarterly YTD'!C20 -> 0 | H20: =F20+'Quarterly YTD'!H20-'Quarterly YTD'!D20 -> 0 | I20: =F20+'Quarterly YTD'!I20-'Quarterly YTD'!E20 -> 0 | J20: 0 | K20: =J20+'Quarterly YTD'!K20-'Quarterly YTD'!G20 -> 0 | L20: =J20+'Quarterly YTD'!L20-'Quarterly YTD'!H20 -> 0 | M20: =J20+'Quarterly YTD'!M20-'Quarterly YTD'!I20 -> 0 | N20: 0 | O20: =N20+'Quarterly YTD'!O20-'Quarterly YTD'!K20 -> 0 | P20: =N20+'Quarterly YTD'!P20-'Quarterly YTD'!L20 -> 0 | Q20: =N20+'Quarterly YTD'!Q20-'Quarterly YTD'!M20 -> 0 | R20: 0 | S20: =R20+'Quarterly YTD'!S20-'Quarterly YTD'!O20 -> 0 | T20: =R20+'Quarterly YTD'!T20-'Quarterly YTD'!P20 -> 0 | U20: =R20+'Quarterly YTD'!U20-'Quarterly YTD'!Q20 -> 0 | V20: 0 | W20: =V20+'Quarterly YTD'!W20-'Quarterly YTD'!S20 -> 0 | X20: =V20+'Quarterly YTD'!X20-'Quarterly YTD'!T20 -> 0 | Y20: =V20+'Quarterly YTD'!Y20-'Quarterly YTD'!U20 -> 0 | Z20: -116.838 | AA20: =Z20+'Quarterly YTD'!AA20-'Quarterly YTD'!W20 -> -176.743 | AB20: =Z20+'Quarterly YTD'!AB20-'Quarterly YTD'!X20 -> -222.99 | AC20: =Z20+'Quarterly YTD'!AC20-'Quarterly YTD'!Y20 -> -116.838 | AD20: 81.382 | AE20: =AD20+'Quarterly YTD'!AE20-'Quarterly YTD'!AA20 -> 141.287 | AF20: =AD20+'Quarterly YTD'!AF20-'Quarterly YTD'!AB20 -> 208.488
A21: Loss for the period | B21: =SUM(B19:B20) -> 9.691 | F21: =F19 -> 12.13 | G21: =SUM(G19:G20) -> 4.142 | H21: =SUM(H19:H20) -> 1.746 | I21: =SUM(I19:I20) -> -17.227 | J21: =J19 -> -51.605 | K21: =SUM(K19:K20) -> -42.45 | L21: =SUM(L19:L20) -> -30.271 | M21: =SUM(M19:M20) -> 9.607 | N21: =N19 -> 34.368 | O21: =SUM(O19:O20) -> 19.647 | P21: =SUM(P19:P20) -> 24.866 | Q21: =SUM(Q19:Q20) -> 52.975 | R21: =R19 -> 11.667 | S21: =SUM(S19:S20) -> -8.907 | T21: =SUM(T19:T20) -> 3.651 | U21: =SUM(U19:U20) -> 27.207 | V21: =V19 -> 68.186 | W21: =SUM(W19:W20) -> 4.172 | X21: =SUM(X19:X20) -> 70.088 | Y21: =SUM(Y19:Y20) -> 80.723 | Z21: =SUM(Z19:Z20) -> -62.583 | AA21: =SUM(AA19:AA20) -> -87.126 | AB21: =SUM(AB19:AB20) -> -172.579 | AC21: =SUM(AC19:AC20) -> -185.951 | AD21: =SUM(AD19:AD20) -> -63.567 | ... AF21: =SUM(AF19:AF20) -> -34.375
A23: Cash Flow Statement
A24: Loss for the period | B24: 9.691 | F24: 12.13 | G24: =F24+'Quarterly YTD'!G24-'Quarterly YTD'!C24 -> 4.142 | H24: =F24+'Quarterly YTD'!H24-'Quarterly YTD'!D24 -> 1.746 | I24: =F24+'Quarterly YTD'!I24-'Quarterly YTD'!E24 -> -17.227 | J24: -51.605 | K24: =J24+'Quarterly YTD'!K24-'Quarterly YTD'!G24 -> -42.45 | L24: =J24+'Quarterly YTD'!L24-'Quarterly YTD'!H24 -> -30.271 | M24: =J24+'Quarterly YTD'!M24-'Quarterly YTD'!I24 -> 9.607 | N24: 34.368 | O24: =N24+'Quarterly YTD'!O24-'Quarterly YTD'!K24 -> 19.647 | P24: =N24+'Quarterly YTD'!P24-'Quarterly YTD'!L24 -> 24.866 | Q24: =N24+'Quarterly YTD'!Q24-'Quarterly YTD'!M24 -> 52.975 | R24: 11.667 | S24: =R24+'Quarterly YTD'!S24-'Quarterly YTD'!O24 -> -8.907 | T24: =R24+'Quarterly YTD'!T24-'Quarterly YTD'!P24 -> 3.651 | U24: =R24+'Quarterly YTD'!U24-'Quarterly YTD'!Q24 -> 27.207 | V24: 68.186 | W24: =V24+'Quarterly YTD'!W24-'Quarterly YTD'!S24 -> 4.172 | X24: =V24+'Quarterly YTD'!X24-'Quarterly YTD'!T24 -> 70.087 | Y24: =V24+'Quarterly YTD'!Y24-'Quarterly YTD'!U24 -> 80.723 | Z24: -62.583 | AA24: =Z24+'Quarterly YTD'!AA24-'Quarterly YTD'!W24 -> -87.126 | AB24: =Z24+'Quarterly YTD'!AB24-'Quarterly YTD'!X24 -> -172.578 | AC24: =Z24+'Quarterly YTD'!AC24-'Quarterly YTD'!Y24 -> -185.951 | AD24: -63.567 | AE24: =AD24+'Quarterly YTD'!AE24-'Quarterly YTD'!AA24 -> -1.383 | AF24: =AD24+'Quarterly YTD'!AF24-'Quarterly YTD'!AB24 -> -34.375
A25: Income tax (credit) | B25: 2.952 | F25: 5.712 | G25: =F25+'Quarterly YTD'!G25-'Quarterly YTD'!C25 -> 7.099 | H25: =F25+'Quarterly YTD'!H25-'Quarterly YTD'!D25 -> 10.559 | I25: =F25+'Quarterly YTD'!I25-'Quarterly YTD'!E25 -> 9.128 | J25: 5.796 | K25: =J25+'Quarterly YTD'!K25-'Quarterly YTD'!G25 -> 8.203 | L25: =J25+'Quarterly YTD'!L25-'Quarterly YTD'!H25 -> 0.125 | M25: =J25+'Quarterly YTD'!M25-'Quarterly YTD'!I25 -> 4.767 | N25: 10.26 | O25: =N25+'Quarterly YTD'!O25-'Quarterly YTD'!K25 -> 9.212 | P25: =N25+'Quarterly YTD'!P25-'Quarterly YTD'!L25 -> 19.686 | Q25: =N25+'Quarterly YTD'!Q25-'Quarterly YTD'!M25 -> 26.612 | R25: 15.779 | S25: =R25+'Quarterly YTD'!S25-'Quarterly YTD'!O25 -> 9.625 | T25: =R25+'Quarterly YTD'!T25-'Quarterly YTD'!P25 -> 10.093 | U25: =R25+'Quarterly YTD'!U25-'Quarterly YTD'!Q25 -> 7.208 | V25: 3.945 | W25: =V25+'Quarterly YTD'!W25-'Quarterly YTD'!S25 -> -5.995 | X25: =V25+'Quarterly YTD'!X25-'Quarterly YTD'!T25 -> -5.647 | Y25: =V25+'Quarterly YTD'!Y25-'Quarterly YTD'!U25 -> 9.399 | Z25: -2.197 | AA25: =Z25+'Quarterly YTD'!AA25-'Quarterly YTD'!W25 -> -5.839 | AB25: =Z25+'Quarterly YTD'!AB25-'Quarterly YTD'!X25 -> 1.395 | AC25: =Z25+'Quarterly YTD'!AC25-'Quarterly YTD'!Y25 -> -0.554 | AD25: 3.712 | AE25: =AD25+'Quarterly YTD'!AE25-'Quarterly YTD'!AA25 -> 11.812 | AF25: =AD25+'Quarterly YTD'!AF25-'Quarterly YTD'!AB25 -> -1.707
