Workbook

Sheet Annual and Quarterly
A1: $mm, Dec year-end | B1: FY22 | C1: FY23 | D1: FY24 | E1: FY25 | F1: LTM | G1: 3Q23 | H1: 4Q23 | I1: 1Q24 | J1: 2Q24 | K1: 3Q24 | L1: 4Q24 | M1: 1Q25 | N1: 2Q25 | O1: 3Q25 | P1: 4Q25 | Q1: 1Q26 | R1: 2Q26 | S1: Q/o/Q | T1: Y/o/Y
A2: Income Statement
A3: Revenues | B3: 308.10876 | C3: 356.19708 | D3: 355.99368 | E3: 408.64877 | F3: =E3+'Quarterly YTD'!O3-'Quarterly YTD'!K3 -> 445.67177 | G3: 71.173501 | H3: =C3-'Quarterly YTD'!D3 -> 92.106065 | I3: 85.804548 | J3: 88.795866 | K3: 88.056758 | L3: =D3-'Quarterly YTD'!H3 -> 93.33651 | M3: 93.498313 | N3: 100.30978 | O3: 106.75608 | P3: =E3-'Quarterly YTD'!L3 -> 108.0846 | Q3: 114.34153 | R3: 116.48956 | S3: =IF(AND(R3=0,Q3=0),0,IF(OR(Q3=0,Q3="NM",R3="NM"),"NM",IF(Q3<0,-(R3/Q3-1),R3/Q3-1))) -> 0.018786061 | T3: =IF(AND(R3=0,N3=0),0,IF(OR(N3=0,N3="NM",R3="NM"),"NM",IF(N3<0,-(R3/N3-1),R3/N3-1))) -> 0.16129816
A4: Operating costs and commissions | B4: -136.08515 | C4: -139.63505 | D4: -145.86452 | E4: -144.11926 | F4: =E4+'Quarterly YTD'!O4-'Quarterly YTD'!K4 -> -149.35098 | G4: -29.166475 | H4: =C4-'Quarterly YTD'!D4 -> -31.506634 | I4: -31.334551 | J4: -37.769739 | K4: -41.459787 | L4: =D4-'Quarterly YTD'!H4 -> -35.30044 | M4: -34.165761 | N4: -35.956565 | O4: -35.515765 | P4: =E4-'Quarterly YTD'!L4 -> -38.481171 | Q4: -37.420421 | R4: -37.933622 | S4: =IF(AND(R4=0,Q4=0),0,IF(OR(Q4=0,Q4="NM",R4="NM"),"NM",IF(Q4<0,(R4/Q4-1),-(R4/Q4-1)))) -> 0.013714464 | T4: =IF(AND(R4=0,N4=0),0,IF(OR(N4=0,N4="NM",R4="NM"),"NM",IF(N4<0,(R4/N4-1),-(R4/N4-1)))) -> 0.05498459
A5: Administrative, marketing and selling expenses | B5: -108.12485 | C5: -115.29811 | D5: -130.95791 | E5: -130.081 | F5: =E5+'Quarterly YTD'!O5-'Quarterly YTD'!K5 -> -142.36757 | G5: -20.450035 | H5: =C5-'Quarterly YTD'!D5 -> -35.695191 | I5: -28.487093 | J5: -28.482691 | K5: -31.407928 | L5: =D5-'Quarterly YTD'!H5 -> -42.580194 | M5: -30.456847 | N5: -34.716748 | O5: -26.436797 | P5: =E5-'Quarterly YTD'!L5 -> -38.470608 | Q5: -37.877638 | R5: -39.582525 | S5: =IF(AND(R5=0,Q5=0),0,IF(OR(Q5=0,Q5="NM",R5="NM"),"NM",IF(Q5<0,(R5/Q5-1),-(R5/Q5-1)))) -> 0.045010383 | T5: =IF(AND(R5=0,N5=0),0,IF(OR(N5=0,N5="NM",R5="NM"),"NM",IF(N5<0,(R5/N5-1),-(R5/N5-1)))) -> 0.14015647
A6: Depreciation of tangible assets | B6: -42.745142 | C6: -47.380285 | D6: -48.614609 | E6: -50.741037 | F6: =E6+'Quarterly YTD'!O6-'Quarterly YTD'!K6 -> -56.226568 | G6: -10.386751 | H6: =C6-'Quarterly YTD'!D6 -> -11.997254 | I6: -12.244525 | J6: -13.211034 | K6: -10.236228 | L6: =D6-'Quarterly YTD'!H6 -> -12.922822 | M6: -12.306473 | N6: -11.951909 | O6: -13.19391 | P6: =E6-'Quarterly YTD'!L6 -> -13.288745 | Q6: -15.027019 | R6: -14.716894 | S6: =IF(AND(R6=0,Q6=0),0,IF(OR(Q6=0,Q6="NM",R6="NM"),"NM",IF(Q6<0,(R6/Q6-1),-(R6/Q6-1)))) -> -0.020637826 | T6: =IF(AND(R6=0,N6=0),0,IF(OR(N6=0,N6="NM",R6="NM"),"NM",IF(N6<0,(R6/N6-1),-(R6/N6-1)))) -> 0.23134254
A7: Amortization of intangible assets | B7: -11.955373 | C7: -15.925177 | D7: -20.609792 | E7: -19.385894 | F7: =E7+'Quarterly YTD'!O7-'Quarterly YTD'!K7 -> -18.961141 | G7: -4.173107 | H7: =C7-'Quarterly YTD'!D7 -> -4.928568 | I7: -5.009905 | J7: -5.304571 | K7: -5.122623 | L7: =D7-'Quarterly YTD'!H7 -> -5.172693 | M7: -4.898694 | N7: -5.10543 | O7: -5.151362 | P7: =E7-'Quarterly YTD'!L7 -> -4.230408 | Q7: -4.784049 | R7: -4.795322 | S7: =IF(AND(R7=0,Q7=0),0,IF(OR(Q7=0,Q7="NM",R7="NM"),"NM",IF(Q7<0,(R7/Q7-1),-(R7/Q7-1)))) -> 0.0023563722 | T7: =IF(AND(R7=0,N7=0),0,IF(OR(N7=0,N7="NM",R7="NM"),"NM",IF(N7<0,(R7/N7-1),-(R7/N7-1)))) -> -0.060740819
A8: (Provision)/write-back for expected credit losses on trade receivables | B8: 0 | C8: 0 | D8: 0 | E8: 0 | F8: =E8+'Quarterly YTD'!O8-'Quarterly YTD'!K8 -> 0 | G8: 0 | H8: =C8-'Quarterly YTD'!D8 -> 0 | I8: 0 | J8: 0 | K8: 0 | L8: =D8-'Quarterly YTD'!H8 -> 0 | M8: 0.039965 | N8: 0 | O8: 0 | P8: =E8-'Quarterly YTD'!L8 -> 0 | Q8: -0.115606 | R8: 0 | S8: =IF(AND(R8=0,Q8=0),0,IF(OR(Q8=0,Q8="NM",R8="NM"),"NM",IF(Q8<0,(R8/Q8-1),-(R8/Q8-1)))) -> -1 | T8: =IF(AND(R8=0,N8=0),0,IF(OR(N8=0,N8="NM",R8="NM"),"NM",IF(N8<0,(R8/N8-1),-(R8/N8-1)))) -> 0
A9: Write-back/(provision) for expected credit losses on trade receivables | B9: -1.660354 | C9: 1.024685 | D9: -0.904712 | E9: -0.605485 | F9: =E9+'Quarterly YTD'!O9-'Quarterly YTD'!K9 -> -0.218586 | G9: -0.008508 | H9: =C9-'Quarterly YTD'!D9 -> 1.056003 | I9: -0.008613 | J9: -0.07367 | K9: -0.455058 | L9: =D9-'Quarterly YTD'!H9 -> -0.367371 | M9: 0 | N9: -0.005824 | O9: -0.03522 | P9: =E9-'Quarterly YTD'!L9 -> -0.604406 | Q9: 0 | R9: 0.536646 | S9: =IF(AND(R9=0,Q9=0),0,IF(OR(Q9=0,Q9="NM",R9="NM"),"NM",IF(Q9<0,-(R9/Q9-1),R9/Q9-1))) -> NM | T9: =IF(AND(R9=0,N9=0),0,IF(OR(N9=0,N9="NM",R9="NM"),"NM",IF(N9<0,-(R9/N9-1),R9/N9-1))) -> 93.143887
A10: Provision for expected credit losses on balances due from related parties | B10: -0.390413 | C10: 0 | D10: -0.12936 | E10: -0.065328 | F10: =E10+'Quarterly YTD'!O10-'Quarterly YTD'!K10 -> -0.432576 | G10: 0 | H10: =C10-'Quarterly YTD'!D10 -> 0 | I10: 0 | J10: 0 | K10: -0.12936 | L10: =D10-'Quarterly YTD'!H10 -> 0 | M10: 0 | N10: -0.013296 | O10: -0.013345 | P10: =E10-'Quarterly YTD'!L10 -> -0.013296 | Q10: -0.338567 | R10: -0.067368 | S10: =IF(AND(R10=0,Q10=0),0,IF(OR(Q10=0,Q10="NM",R10="NM"),"NM",IF(Q10<0,-(R10/Q10-1),R10/Q10-1))) -> 0.80102018 | T10: =IF(AND(R10=0,N10=0),0,IF(OR(N10=0,N10="NM",R10="NM"),"NM",IF(N10<0,-(R10/N10-1),R10/N10-1))) -> -4.066787
A11: Receivables written off | B11: 0 | C11: 0 | D11: -0.072471 | E11: -0.06976 | F11: =E11+'Quarterly YTD'!O11-'Quarterly YTD'!K11 -> -0.084892 | G11: 0 | H11: =C11-'Quarterly YTD'!D11 -> 0 | I11: 0 | J11: 0 | K11: 0 | L11: =D11-'Quarterly YTD'!H11 -> -0.072471 | M11: 0 | N11: 0 | O11: 0 | P11: =E11-'Quarterly YTD'!L11 -> -0.06976 | Q11: 0 | R11: -0.015132 | S11: =IF(AND(R11=0,Q11=0),0,IF(OR(Q11=0,Q11="NM",R11="NM"),"NM",IF(Q11<0,(R11/Q11-1),-(R11/Q11-1)))) -> NM | T11: =IF(AND(R11=0,N11=0),0,IF(OR(N11=0,N11="NM",R11="NM"),"NM",IF(N11<0,(R11/N11-1),-(R11/N11-1)))) -> NM
A12: Other gain/(loss), net | B12: 8.760054 | C12: 12.047365 | D12: 1.444997 | E12: 4.922003 | F12: =E12+'Quarterly YTD'!O12-'Quarterly YTD'!K12 -> 5.827131 | G12: 0.649341 | H12: =C12-'Quarterly YTD'!D12 -> 11.983504 | I12: 0.289148 | J12: -0.703136 | K12: 1.788856 | L12: =D12-'Quarterly YTD'!H12 -> 0.070129 | M12: 0.095351 | N12: -0.20662 | O12: 1.138677 | P12: =E12-'Quarterly YTD'!L12 -> 3.869204 | Q12: -0.272845 | R12: 1.092095 | S12: =IF(AND(R12=0,Q12=0),0,IF(OR(Q12=0,Q12="NM",R12="NM"),"NM",IF(Q12<0,-(R12/Q12-1),R12/Q12-1))) -> 5.0026205 | T12: =IF(AND(R12=0,N12=0),0,IF(OR(N12=0,N12="NM",R12="NM"),"NM",IF(N12<0,-(R12/N12-1),R12/N12-1))) -> 6.2855242
A13: OPERATING PROFIT | B13: =SUM(B3:B7)+SUM(B9:B10)+B12 -> 15.907529 | C13: =SUM(C3:C7)+SUM(C9:C12) -> 51.030502 | D13: =SUM(D3:D7)+SUM(D9:D12) -> 10.285312 | E13: =SUM(E3:E7)+SUM(E9:E12) -> 68.503009 | F13: =E13+'Quarterly YTD'!O13-'Quarterly YTD'!K13 -> 83.856592 | G13: =SUM(G3:G7)+SUM(G9:G10)+G12 -> 7.637966 | H13: =SUM(H3:H12) -> 21.017925 | I13: =SUM(I3:I7)+I9+I12 -> 9.009009 | J13: =SUM(J3:J7)+J9+J12 -> 3.251025 | K13: =SUM(K3:K7)+SUM(K9:K10)+K12 -> 1.03463 | L13: =SUM(L3:L12) -> -3.009352 | M13: =SUM(M3:M8)+M10+M12 -> 11.805854 | N13: =SUM(N3:N7)+SUM(N9:N12) -> 12.353383 | O13: =SUM(O3:O7)+SUM(O9:O10)+O12 -> 27.54836 | P13: =SUM(P3:P12) -> 16.795412 | Q13: =SUM(Q3:Q8)+Q10+Q12 -> 18.505385 | R13: =SUM(R3:R7)+SUM(R9:R12) -> 21.007435 | S13: =IF(AND(R13=0,Q13=0),0,IF(OR(Q13=0,Q13="NM",R13="NM"),"NM",IF(Q13<0,-(R13/Q13-1),R13/Q13-1))) -> 0.13520659 | T13: =IF(AND(R13=0,N13=0),0,IF(OR(N13=0,N13="NM",R13="NM"),"NM",IF(N13<0,-(R13/N13-1),R13/N13-1))) -> 0.70054106
A14: Interest income on balances due from related parties | B14: 1.932958 | C14: 2.126254 | D14: 2.33888 | E14: 2.572767 | F14: =E14+'Quarterly YTD'!O14-'Quarterly YTD'!K14 -> 2.572767 | G14: 0 | H14: =C14-'Quarterly YTD'!D14 -> 2.126254 | I14: 0 | J14: 0 | K14: 0 | L14: =D14-'Quarterly YTD'!H14 -> 2.33888 | M14: 0 | N14: 0 | O14: 0 | P14: =E14-'Quarterly YTD'!L14 -> 2.572767 | Q14: 0 | R14: 0 | S14: =IF(AND(R14=0,Q14=0),0,IF(OR(Q14=0,Q14="NM",R14="NM"),"NM",IF(Q14<0,-(R14/Q14-1),R14/Q14-1))) -> 0 | T14: =IF(AND(R14=0,N14=0),0,IF(OR(N14=0,N14="NM",R14="NM"),"NM",IF(N14<0,-(R14/N14-1),R14/N14-1))) -> 0
A15: Interest income on balances due from a related party | B15: 0 | C15: 0 | D15: 0 | E15: 0 | F15: =E15+'Quarterly YTD'!O15-'Quarterly YTD'!K15 -> 0.128638 | G15: 0.531564 | H15: =C15-'Quarterly YTD'!D15 -> -1.594691 | I15: 0.58472 | J15: 0.58472 | K15: 0.58472 | L15: =D15-'Quarterly YTD'!H15 -> -1.75416 | M15: 0.643189 | N15: 0.643195 | O15: 0.643192 | P15: =E15-'Quarterly YTD'!L15 -> -1.929576 | Q15: 0.707511 | R15: 0.707511 | S15: =IF(AND(R15=0,Q15=0),0,IF(OR(Q15=0,Q15="NM",R15="NM"),"NM",IF(Q15<0,-(R15/Q15-1),R15/Q15-1))) -> 0 | T15: =IF(AND(R15=0,N15=0),0,IF(OR(N15=0,N15="NM",R15="NM"),"NM",IF(N15<0,-(R15/N15-1),R15/N15-1))) -> 0.099994558
A16: Other interest income | B16: 0.187722 | C16: 0.156096 | D16: 0.329062 | E16: 0.269998 | F16: =E16+'Quarterly YTD'!O16-'Quarterly YTD'!K16 -> 0.501385 | G16: 0.038724 | H16: =C16-'Quarterly YTD'!D16 -> 0.040954 | I16: 0.040809 | J16: 0.038332 | K16: 0.037117 | L16: =D16-'Quarterly YTD'!H16 -> 0.212804 | M16: 0.109547 | N16: 0.047734 | O16: 0.072899 | P16: =E16-'Quarterly YTD'!L16 -> 0.039818 | Q16: 0.236924 | R16: 0.151744 | S16: =IF(AND(R16=0,Q16=0),0,IF(OR(Q16=0,Q16="NM",R16="NM"),"NM",IF(Q16<0,-(R16/Q16-1),R16/Q16-1))) -> -0.35952457 | T16: =IF(AND(R16=0,N16=0),0,IF(OR(N16=0,N16="NM",R16="NM"),"NM",IF(N16<0,-(R16/N16-1),R16/N16-1))) -> 2.17895
A17: Finance costs, net | B17: -55.213244 | C17: -64.737849 | D17: -74.276529 | E17: -71.039195 | F17: =E17+'Quarterly YTD'!O17-'Quarterly YTD'!K17 -> -77.784129 | G17: -13.691071 | H17: =C17-'Quarterly YTD'!D17 -> -16.487628 | I17: -15.328047 | J17: -15.410468 | K17: -15.632486 | L17: =D17-'Quarterly YTD'!H17 -> -27.905528 | M17: -17.043553 | N17: -17.184806 | O17: -17.741476 | P17: =E17-'Quarterly YTD'!L17 -> -19.06936 | Q17: -20.252271 | R17: -20.721022 | S17: =IF(AND(R17=0,Q17=0),0,IF(OR(Q17=0,Q17="NM",R17="NM"),"NM",IF(Q17<0,(R17/Q17-1),-(R17/Q17-1)))) -> 0.023145602 | T17: =IF(AND(R17=0,N17=0),0,IF(OR(N17=0,N17="NM",R17="NM"),"NM",IF(N17<0,(R17/N17-1),-(R17/N17-1)))) -> 0.20577573
A18: Loss on exchange, net | B18: -24.108535 | C18: -114.15174 | D18: -39.271284 | E18: 37.680522 | F18: =E18+'Quarterly YTD'!O18-'Quarterly YTD'!K18 -> 33.66656 | G18: 2.115323 | H18: =C18-'Quarterly YTD'!D18 -> -30.669429 | I18: -12.388792 | J18: -10.767847 | K18: -10.3553 | L18: =D18-'Quarterly YTD'!H18 -> -5.759345 | M18: -5.577573 | N18: -7.600561 | O18: 15.383757 | P18: =E18-'Quarterly YTD'!L18 -> 35.474899 | Q18: -13.410153 | R18: -3.781943 | S18: =IF(AND(R18=0,Q18=0),0,IF(OR(Q18=0,Q18="NM",R18="NM"),"NM",IF(Q18<0,(R18/Q18-1),-(R18/Q18-1)))) -> -0.71797913 | T18: =IF(AND(R18=0,N18=0),0,IF(OR(N18=0,N18="NM",R18="NM"),"NM",IF(N18<0,(R18/N18-1),-(R18/N18-1)))) -> -0.50241265
A19: Net (loss)/gain on net monetary position | B19: 0 | C19: 21.543365 | D19: 3.558212 | E19: -1.599516 | F19: =E19+'Quarterly YTD'!O19-'Quarterly YTD'!K19 -> 1.419819 | G19: -3.066506 | H19: =C19-'Quarterly YTD'!D19 -> -7.755996 | I19: 3.717688 | J19: 0.254449 | K19: -1.266755 | L19: =D19-'Quarterly YTD'!H19 -> 0.85283 | M19: -0.211588 | N19: -0.017313 | O19: 0.6408 | P19: =E19-'Quarterly YTD'!L19 -> -2.011415 | Q19: 2.791561 | R19: -0.001127 | S19: =IF(AND(R19=0,Q19=0),0,IF(OR(Q19=0,Q19="NM",R19="NM"),"NM",IF(Q19<0,-(R19/Q19-1),R19/Q19-1))) -> -1.0004037 | T19: =IF(AND(R19=0,N19=0),0,IF(OR(N19=0,N19="NM",R19="NM"),"NM",IF(N19<0,-(R19/N19-1),R19/N19-1))) -> 0.93490441
A20: LOSS BEFORE INCOME TAX FROM CONTINUING OPERATIONS | B20: =SUM(B13:B14)+SUM(B16:B18) -> -61.29357 | C20: =SUM(C13:C14)+SUM(C16:C19) -> -104.03337 | D20: =SUM(D13:D14)+SUM(D16:D19) -> -97.036347 | E20: =SUM(E13:E14)+SUM(E16:E19) -> 36.387585 | F20: =E20+'Quarterly YTD'!O20-'Quarterly YTD'!K20 -> 44.361632 | G20: =G13+SUM(G15:G19) -> -6.434 | H20: =SUM(H13:H19) -> -33.322611 | I20: =I13+SUM(I15:I19) -> -14.364613 | J20: =J13+SUM(J15:J19) -> -22.049789 | K20: =K13+SUM(K15:K19) -> -25.598074 | L20: =SUM(L13:L19) -> -35.023871 | M20: =M13+SUM(M15:M19) -> -10.274124 | N20: =N13+SUM(N15:N19) -> -11.758368 | O20: =O13+SUM(O15:O19) -> 26.547532 | P20: =SUM(P13:P19) -> 31.872545 | Q20: =Q13+SUM(Q15:Q19) -> -11.421043 | R20: =R13+SUM(R15:R19) -> -2.637402 | S20: =IF(AND(R20=0,Q20=0),0,IF(OR(Q20=0,Q20="NM",R20="NM"),"NM",IF(Q20<0,-(R20/Q20-1),R20/Q20-1))) -> 0.76907521 | T20: =IF(AND(R20=0,N20=0),0,IF(OR(N20=0,N20="NM",R20="NM"),"NM",IF(N20<0,-(R20/N20-1),R20/N20-1))) -> 0.7757
A21: Income tax expense | B21: -0.891378 | C21: -11.454357 | D21: -6.737506 | E21: -6.007564 | F21: =E21+'Quarterly YTD'!O21-'Quarterly YTD'!K21 -> -9.937987 | G21: 3.536041 | H21: =C21-'Quarterly YTD'!D21 -> -5.868704 | I21: -1.168225 | J21: -1.159625 | K21: -1.888589 | L21: =D21-'Quarterly YTD'!H21 -> -2.521067 | M21: -0.619647 | N21: -0.722561 | O21: -2.98096 | P21: =E21-'Quarterly YTD'!L21 -> -1.684396 | Q21: -2.331424 | R21: -2.941207 | S21: =IF(AND(R21=0,Q21=0),0,IF(OR(Q21=0,Q21="NM",R21="NM"),"NM",IF(Q21<0,(R21/Q21-1),-(R21/Q21-1)))) -> 0.26154959 | T21: =IF(AND(R21=0,N21=0),0,IF(OR(N21=0,N21="NM",R21="NM"),"NM",IF(N21<0,(R21/N21-1),-(R21/N21-1)))) -> 3.0705311
A22: LOSS FOR THE PERIOD FROM CONTINUING OPERATIONS | B22: =SUM(B20:B21) -> -62.184948 | C22: =SUM(C20:C21) -> -115.48772 | D22: =SUM(D20:D21) -> -103.77385 | E22: =SUM(E20:E21) -> 30.380021 | F22: =SUM(F20:F21) -> 34.423645 | G22: =SUM(G20:G21) -> -2.897959 | H22: =SUM(H20:H21) -> -39.191315 | I22: =SUM(I20:I21) -> -15.532838 | ... R22: =SUM(R20:R21) -> -5.578609 | S22: =IF(AND(R22=0,Q22=0),0,IF(OR(Q22=0,Q22="NM",R22="NM"),"NM",IF(Q22<0,-(R22/Q22-1),R22/Q22-1))) -> 0.59435576 | T22: =IF(AND(R22=0,N22=0),0,IF(OR(N22=0,N22="NM",R22="NM"),"NM",IF(N22<0,-(R22/N22-1),R22/N22-1))) -> 0.55302935
A23: Profit/(loss) for the period from discontinued operations | B23: 0.397799 | C23: 0.001763 | D23: 0.042832 | E23: 0.042544 | F23: =E23+'Quarterly YTD'!O23-'Quarterly YTD'!K23 -> 0.003499 | G23: -0.0208 | H23: =C23-'Quarterly YTD'!D23 -> 0.01314 | I23: -0.026877 | J23: 0.029646 | K23: 0.003847 | L23: =D23-'Quarterly YTD'!H23 -> 0.036216 | M23: 0.00869 | N23: 0.026362 | O23: -0.039343 | P23: =E23-'Quarterly YTD'!L23 -> 0.046835 | Q23: -0.005043 | R23: 0.00105 | S23: =IF(AND(R23=0,Q23=0),0,IF(OR(Q23=0,Q23="NM",R23="NM"),"NM",IF(Q23<0,-(R23/Q23-1),R23/Q23-1))) -> 1.2082094 | T23: =IF(AND(R23=0,N23=0),0,IF(OR(N23=0,N23="NM",R23="NM"),"NM",IF(N23<0,-(R23/N23-1),R23/N23-1))) -> -0.96016994
A24: LOSS FOR THE PERIOD | B24: =SUM(B22:B23) -> -61.787149 | C24: =SUM(C22:C23) -> -115.48596 | D24: =SUM(D22:D23) -> -103.73102 | E24: =SUM(E22:E23) -> 30.422565 | F24: =SUM(F22:F23) -> 34.427144 | G24: =SUM(G22:G23) -> -2.918759 | H24: =SUM(H22:H23) -> -39.178175 | I24: =SUM(I22:I23) -> -15.559715 | ... R24: =SUM(R22:R23) -> -5.577559 | S24: =IF(AND(R24=0,Q24=0),0,IF(OR(Q24=0,Q24="NM",R24="NM"),"NM",IF(Q24<0,-(R24/Q24-1),R24/Q24-1))) -> 0.59458078 | T24: =IF(AND(R24=0,N24=0),0,IF(OR(N24=0,N24="NM",R24="NM"),"NM",IF(N24<0,-(R24/N24-1),R24/N24-1))) -> 0.55216757
A25: Equity holders of the Company | B25: -61.744696 | C25: -115.46815 | D25: -103.75874 | E25: 30.417809 | F25: =E25+'Quarterly YTD'!O25-'Quarterly YTD'!K25 -> 34.470036 | G25: -2.894362 | H25: =C25-'Quarterly YTD'!D25 -> -39.171689 | I25: -15.532933 | J25: -23.226568 | K25: -27.487553 | L25: =D25-'Quarterly YTD'!H25 -> -37.511688 | M25: -10.890588 | N25: -12.47359 | O25: 23.497866 | P25: =E25-'Quarterly YTD'!L25 -> 30.284121 | Q25: -13.714641 | R25: -5.59731 | S25: =IF(AND(R25=0,Q25=0),0,IF(OR(Q25=0,Q25="NM",R25="NM"),"NM",IF(Q25<0,-(R25/Q25-1),R25/Q25-1))) -> 0.59187339 | T25: =IF(AND(R25=0,N25=0),0,IF(OR(N25=0,N25="NM",R25="NM"),"NM",IF(N25<0,-(R25/N25-1),R25/N25-1))) -> 0.55126712
A26: Non-controlling interests | B26: -0.042453 | C26: -0.017809 | D26: 0.027721 | E26: 0.004756 | F26: =E26+'Quarterly YTD'!O26-'Quarterly YTD'!K26 -> -0.042892 | G26: -0.024397 | H26: =C26-'Quarterly YTD'!D26 -> -0.006486 | I26: -0.026782 | J26: 0.0468 | K26: 0.004737 | L26: =D26-'Quarterly YTD'!H26 -> 0.002966 | M26: 0.005507 | N26: 0.019023 | O26: 0.029363 | P26: =E26-'Quarterly YTD'!L26 -> -0.049137 | Q26: -0.042869 | R26: 0.019751 | S26: =IF(AND(R26=0,Q26=0),0,IF(OR(Q26=0,Q26="NM",R26="NM"),"NM",IF(Q26<0,-(R26/Q26-1),R26/Q26-1))) -> 1.4607292 | T26: =IF(AND(R26=0,N26=0),0,IF(OR(N26=0,N26="NM",R26="NM"),"NM",IF(N26<0,-(R26/N26-1),R26/N26-1))) -> 0.038269463
A27: Exchange differences on translation of foreign operations | B27: -1.064477 | C27: 52.549161 | D27: 10.984271 | E27: -21.059859 | F27: =E27+'Quarterly YTD'!O27-'Quarterly YTD'!K27 -> -13.242169 | G27: 41.250916 | H27: =C27-'Quarterly YTD'!D27 -> -0.805271 | I27: 8.750888 | J27: 2.694295 | K27: -1.462074 | L27: =D27-'Quarterly YTD'!H27 -> 1.001162 | M27: 0.736417 | N27: -0.079767 | O27: -8.302599 | P27: =E27-'Quarterly YTD'!L27 -> -13.4139 | Q27: 9.290292 | R27: -0.815962 | S27: =IF(AND(R27=0,Q27=0),0,IF(OR(Q27=0,Q27="NM",R27="NM"),"NM",IF(Q27<0,-(R27/Q27-1),R27/Q27-1))) -> -1.0878295 | T27: =IF(AND(R27=0,N27=0),0,IF(OR(N27=0,N27="NM",R27="NM"),"NM",IF(N27<0,-(R27/N27-1),R27/N27-1))) -> -9.2293179
A28: Defined benefit plan actuarial gain | B28: -0.048464 | C28: 0.016915 | D28: 0.078297 | E28: 0.73497 | F28: =E28+'Quarterly YTD'!O28-'Quarterly YTD'!K28 -> 0.73497 | G28: 0 | H28: =C28-'Quarterly YTD'!D28 -> 0.016915 | I28: 0 | J28: 0 | K28: 0 | L28: =D28-'Quarterly YTD'!H28 -> 0.078297 | M28: 0 | N28: 0 | O28: 0 | P28: =E28-'Quarterly YTD'!L28 -> 0.73497 | Q28: 0 | R28: 0 | S28: =IF(AND(R28=0,Q28=0),0,IF(OR(Q28=0,Q28="NM",R28="NM"),"NM",IF(Q28<0,-(R28/Q28-1),R28/Q28-1))) -> 0 | T28: =IF(AND(R28=0,N28=0),0,IF(OR(N28=0,N28="NM",R28="NM"),"NM",IF(N28<0,-(R28/N28-1),R28/N28-1))) -> 0
A29: Total other comprehensive (loss)/gain | B29: =SUM(B27:B28) -> -1.112941 | C29: =SUM(C27:C28) -> 52.566076 | D29: =SUM(D27:D28) -> 11.062568 | E29: =SUM(E27:E28) -> -20.324889 | F29: =SUM(F27:F28) -> -12.507199 | G29: =G27 -> 41.250916 | H29: =SUM(H27:H28) -> -0.788356 | I29: =I27 -> 8.750888 | J29: =J27 -> 2.694295 | K29: =K27 -> -1.462074 | L29: =SUM(L27:L28) -> 1.079459 | M29: =M27 -> 0.736417 | N29: =N27 -> -0.079767 | O29: =O27 -> -8.302599 | P29: =SUM(P27:P28) -> -12.67893 | Q29: =Q27 -> 9.290292 | R29: =R27 -> -0.815962 | S29: =IF(AND(R29=0,Q29=0),0,IF(OR(Q29=0,Q29="NM",R29="NM"),"NM",IF(Q29<0,-(R29/Q29-1),R29/Q29-1))) -> -1.0878295 | T29: =IF(AND(R29=0,N29=0),0,IF(OR(N29=0,N29="NM",R29="NM"),"NM",IF(N29<0,-(R29/N29-1),R29/N29-1))) -> -9.2293179
A30: TOTAL COMPREHENSIVE LOSS FOR THE PERIOD | B30: =B24+B29 -> -62.90009 | C30: =C24+C29 -> -62.919886 | D30: =D24+D29 -> -92.668453 | E30: =E24+E29 -> 10.097676 | F30: =F24+F29 -> 21.919945 | G30: =G24+G29 -> 38.332157 | H30: =H24+H29 -> -39.966531 | I30: =I24+I29 -> -6.808827 | ... R30: =R24+R29 -> -6.393521 | S30: =IF(AND(R30=0,Q30=0),0,IF(OR(Q30=0,Q30="NM",R30="NM"),"NM",IF(Q30<0,-(R30/Q30-1),R30/Q30-1))) -> -0.43120864 | T30: =IF(AND(R30=0,N30=0),0,IF(OR(N30=0,N30="NM",R30="NM"),"NM",IF(N30<0,-(R30/N30-1),R30/N30-1))) -> 0.48991937
A31: Equity holders of the Company | B31: -63.024558 | C31: -62.963777 | D31: -92.602016 | E31: 10.148129 | F31: =E31+'Quarterly YTD'!O31-'Quarterly YTD'!K31 -> 21.893804 | G31: 38.271897 | H31: =C31-'Quarterly YTD'!D31 -> -39.982908 | I31: -6.873388 | J31: -20.371297 | K31: -28.93372 | L31: =D31-'Quarterly YTD'!H31 -> -36.423611 | M31: -10.135332 | N31: -12.487411 | O31: 15.302297 | P31: =E31-'Quarterly YTD'!L31 -> 17.468586 | Q31: -4.556704 | R31: -6.320375 | S31: =IF(AND(R31=0,Q31=0),0,IF(OR(Q31=0,Q31="NM",R31="NM"),"NM",IF(Q31<0,-(R31/Q31-1),R31/Q31-1))) -> -0.38704972 | T31: =IF(AND(R31=0,N31=0),0,IF(OR(N31=0,N31="NM",R31="NM"),"NM",IF(N31<0,-(R31/N31-1),R31/N31-1))) -> 0.49386026
A32: Non-controlling interests | B32: 0.124468 | C32: 0.043891 | D32: -0.066437 | E32: -0.050453 | F32: =E32+'Quarterly YTD'!O32-'Quarterly YTD'!K32 -> 0.026141 | G32: 0.06026 | H32: =C32-'Quarterly YTD'!D32 -> 0.016377 | I32: 0.064561 | J32: -0.114176 | K32: -0.01117 | L32: =D32-'Quarterly YTD'!H32 -> -0.005652 | M32: -0.013332 | N32: -0.046923 | O32: -0.077667 | P32: =E32-'Quarterly YTD'!L32 -> 0.087468 | Q32: 0.089486 | R32: -0.073146 | S32: =IF(AND(R32=0,Q32=0),0,IF(OR(Q32=0,Q32="NM",R32="NM"),"NM",IF(Q32<0,-(R32/Q32-1),R32/Q32-1))) -> -1.8174016 | T32: =IF(AND(R32=0,N32=0),0,IF(OR(N32=0,N32="NM",R32="NM"),"NM",IF(N32<0,-(R32/N32-1),R32/N32-1))) -> -0.55885174
A34: Cash Flow Statement
A35: Loss before income tax from continuing operations | B35: -61.29357 | C35: -104.03337 | D35: -97.036347 | E35: 36.387585 | F35: =E35+'Quarterly YTD'!O35-'Quarterly YTD'!K35 -> 44.361632 | G35: ='Quarterly YTD'!D35-'Quarterly YTD'!C35 -> -6.434 | H35: =C35-'Quarterly YTD'!D35 -> -33.322611 | I35: -14.364613 | J35: ='Quarterly YTD'!G35-I35 -> -22.049789 | K35: ='Quarterly YTD'!H35-'Quarterly YTD'!G35 -> -25.598074 | L35: =D35-'Quarterly YTD'!H35 -> -35.023871 | M35: -10.274124 | N35: -11.758368 | O35: ='Quarterly YTD'!L35-'Quarterly YTD'!K35 -> 26.547532 | P35: =E35-'Quarterly YTD'!L35 -> 31.872545 | Q35: -11.421043 | R35: -2.637402
A36: Profit/(loss) from discontinued operations | B36: 0.397799 | C36: 0.001763 | D36: 0.042832 | E36: 0.042544 | F36: =E36+'Quarterly YTD'!O36-'Quarterly YTD'!K36 -> 0.003499 | G36: ='Quarterly YTD'!D36-'Quarterly YTD'!C36 -> -0.0208 | H36: =C36-'Quarterly YTD'!D36 -> 0.01314 | I36: -0.026877 | J36: ='Quarterly YTD'!G36-I36 -> 0.029646 | K36: ='Quarterly YTD'!H36-'Quarterly YTD'!G36 -> 0.003847 | L36: =D36-'Quarterly YTD'!H36 -> 0.036216 | M36: 0.00869 | N36: 0.026362 | O36: ='Quarterly YTD'!L36-'Quarterly YTD'!K36 -> -0.039343 | P36: =E36-'Quarterly YTD'!L36 -> 0.046835 | Q36: -0.005043 | R36: 0.00105
A37: Depreciation on tangible assets | B37: 42.745142 | C37: 47.380285 | D37: 48.614609 | E37: 50.741037 | F37: =E37+'Quarterly YTD'!O37-'Quarterly YTD'!K37 -> 56.226568 | G37: ='Quarterly YTD'!D37-'Quarterly YTD'!C37 -> 10.386751 | H37: =C37-'Quarterly YTD'!D37 -> 11.997254 | I37: 12.244525 | J37: ='Quarterly YTD'!G37-I37 -> 13.211034 | K37: ='Quarterly YTD'!H37-'Quarterly YTD'!G37 -> 10.236228 | L37: =D37-'Quarterly YTD'!H37 -> 12.922822 | M37: 12.306473 | N37: 11.951909 | O37: ='Quarterly YTD'!L37-'Quarterly YTD'!K37 -> 13.19391 | P37: =E37-'Quarterly YTD'!L37 -> 13.288745 | Q37: 15.027019 | R37: 14.716894
A38: Amortization of intangible assets | B38: 11.955373 | C38: 15.925177 | D38: 20.609792 | E38: 19.385894 | F38: =E38+'Quarterly YTD'!O38-'Quarterly YTD'!K38 -> 18.961141 | G38: ='Quarterly YTD'!D38-'Quarterly YTD'!C38 -> 4.173107 | H38: =C38-'Quarterly YTD'!D38 -> 4.928568 | I38: 5.009905 | J38: ='Quarterly YTD'!G38-I38 -> 5.304571 | K38: ='Quarterly YTD'!H38-'Quarterly YTD'!G38 -> 5.122623 | L38: =D38-'Quarterly YTD'!H38 -> 5.172693 | M38: 4.898694 | N38: 5.10543 | O38: ='Quarterly YTD'!L38-'Quarterly YTD'!K38 -> 5.151362 | P38: =E38-'Quarterly YTD'!L38 -> 4.230408 | Q38: 4.784049 | R38: 4.795322
A39: (Write-back) Provision for expected credit losses on trade receivables | B39: 0 | C39: 0 | D39: 0 | E39: 0 | F39: =E39+'Quarterly YTD'!O39-'Quarterly YTD'!K39 -> 0 | G39: ='Quarterly YTD'!D39-'Quarterly YTD'!C39 -> 0 | H39: =C39-'Quarterly YTD'!D39 -> 0 | I39: 0 | J39: ='Quarterly YTD'!G39-I39 -> 0.082283 | K39: ='Quarterly YTD'!H39-'Quarterly YTD'!G39 -> -0.082283 | L39: =D39-'Quarterly YTD'!H39 -> 0 | M39: 0 | N39: 0 | O39: ='Quarterly YTD'!L39-'Quarterly YTD'!K39+0.034141 -> 0.034141 | P39: =E39-'Quarterly YTD'!L39 -> 0 | Q39: 0 | R39: 0
A40: Provision for expected credit losses on trade receivables | B40: 1.070047 | C40: -1.024685 | D40: 0.849054 | E40: 0.615199 | F40: =E40+'Quarterly YTD'!O40-'Quarterly YTD'!K40 -> 0.615199 | G40: ='Quarterly YTD'!D40-'Quarterly YTD'!C40 -> 0.008508 | H40: =C40-'Quarterly YTD'!D40 -> -1.056003 | I40: 0.010468 | J40: ='Quarterly YTD'!G40-I40 -> -0.010468 | K40: ='Quarterly YTD'!H40-'Quarterly YTD'!G40 -> 0.537341 | L40: =D40-'Quarterly YTD'!H40 -> 0.311713 | M40: -0.039965 | N40: 0 | O40: ='Quarterly YTD'!L40-'Quarterly YTD'!K40 -> 0.001079 | P40: =E40-'Quarterly YTD'!L40 -> 0.61412 | Q40: 0.115606 | R40: 0
A41: Re-measurement gain on long-term liability | B41: 0 | C41: 0 | D41: -0.195467 | E41: 0 | F41: =E41+'Quarterly YTD'!O41-'Quarterly YTD'!K41 -> 0 | G41: ='Quarterly YTD'!D41-'Quarterly YTD'!C41 -> 0 | H41: =C41-'Quarterly YTD'!D41 -> 0 | I41: 0 | J41: ='Quarterly YTD'!G41-I41 -> 0 | K41: ='Quarterly YTD'!H41-'Quarterly YTD'!G41 -> 0 | L41: =D41-'Quarterly YTD'!H41 -> -0.195467 | M41: 0 | N41: 0 | O41: ='Quarterly YTD'!L41-'Quarterly YTD'!K41 -> 0 | P41: =E41-'Quarterly YTD'!L41 -> 0 | Q41: 0 | R41: 0
A42: Write-back for expected credit losses on trade receivables, net | B42: 0 | C42: 0 | D42: 0 | E42: 0 | F42: =E42+'Quarterly YTD'!O42-'Quarterly YTD'!K42 -> -0.386899 | G42: ='Quarterly YTD'!D42-'Quarterly YTD'!C42 -> 0 | H42: =C42-'Quarterly YTD'!D42 -> 0 | I42: 0 | J42: ='Quarterly YTD'!G42-I42 -> 0 | K42: ='Quarterly YTD'!H42-'Quarterly YTD'!G42 -> 0 | L42: =D42-'Quarterly YTD'!H42 -> 0 | M42: 0 | N42: 0.005824 | O42: ='Quarterly YTD'!L42-'Quarterly YTD'!K42 -> 0.034141 | P42: =E42-'Quarterly YTD'!L42 -> 0 | Q42: 0 | R42: -0.536646
A43: (Write-back) Provision for expected credit losses on bank balances | B43: 0 | C43: 0 | D43: 0 | E43: 0 | F43: =E43+'Quarterly YTD'!O43-'Quarterly YTD'!K43 -> 0.096145 | G43: ='Quarterly YTD'!D43-'Quarterly YTD'!C43 -> 0 | H43: =C43-'Quarterly YTD'!D43 -> 0 | I43: 0 | J43: ='Quarterly YTD'!G43-I43 -> 0 | K43: ='Quarterly YTD'!H43-'Quarterly YTD'!G43 -> 0 | L43: =D43-'Quarterly YTD'!H43 -> 0 | M43: 0 | N43: 0.033789 | O43: ='Quarterly YTD'!L43-'Quarterly YTD'!K43 -> -0.058709 | P43: =E43-'Quarterly YTD'!L43 -> 0 | Q43: 0 | R43: -0.09289
A44: Provision for expected credit losses on balance due from a related party | B44: 0.390413 | C44: 0 | D44: 0.12936 | E44: 0.065328 | F44: =E44+'Quarterly YTD'!O44-'Quarterly YTD'!K44 -> 0.432576 | G44: ='Quarterly YTD'!D44-'Quarterly YTD'!C44 -> 0 | H44: =C44-'Quarterly YTD'!D44 -> 0 | I44: 0 | J44: ='Quarterly YTD'!G44-I44 -> 0 | K44: ='Quarterly YTD'!H44-'Quarterly YTD'!G44 -> 0.12936 | L44: =D44-'Quarterly YTD'!H44 -> 0 | M44: 0.02539 | N44: 0.013296 | O44: ='Quarterly YTD'!L44-'Quarterly YTD'!K44+-0.000009 -> 0.013336 | P44: =E44-'Quarterly YTD'!L44 -> 0.013296 | Q44: 0.338567 | R44: 0.067368
A45: Provision (Write-back) for expected credit losses on bank balances | B45: 0 | C45: 0 | D45: 0 | E45: 0 | F45: =E45+'Quarterly YTD'!O45-'Quarterly YTD'!K45 -> 0 | G45: ='Quarterly YTD'!D45-'Quarterly YTD'!C45 -> 0 | H45: =C45-'Quarterly YTD'!D45 -> 0 | I45: 0 | J45: ='Quarterly YTD'!G45-I45 -> 0 | K45: ='Quarterly YTD'!H45-'Quarterly YTD'!G45 -> -0.033497 | L45: =D45-'Quarterly YTD'!H45 -> 0.033497 | M45: 0 | N45: 0 | O45: ='Quarterly YTD'!L45-'Quarterly YTD'!K45 -> 0.031576 | P45: =E45-'Quarterly YTD'!L45 -> -0.031576 | Q45: 0 | R45: 0
A46: Provision for/(write-back of) expected credit losses on bank balances | B46: 0 | C46: 0 | D46: -0.000452 | E46: 0.090045 | F46: =E46+'Quarterly YTD'!O46-'Quarterly YTD'!K46 -> 0.090045 | G46: ='Quarterly YTD'!D46-'Quarterly YTD'!C46 -> 0 | H46: =C46-'Quarterly YTD'!D46 -> 0 | I46: 0 | J46: ='Quarterly YTD'!G46-I46 -> 0 | K46: ='Quarterly YTD'!H46-'Quarterly YTD'!G46 -> 0 | L46: =D46-'Quarterly YTD'!H46 -> -0.000452 | M46: 0 | N46: 0 | O46: ='Quarterly YTD'!L46-'Quarterly YTD'!K46 -> 0 | P46: =E46-'Quarterly YTD'!L46 -> 0.090045 | Q46: 0 | R46: 0
A47: Provision for expected credit losses on bank balances | B47: 0.038122 | C47: 0.036329 | D47: 0 | E47: 0 | F47: =E47+'Quarterly YTD'!O47-'Quarterly YTD'!K47 -> 0 | G47: ='Quarterly YTD'!D47-'Quarterly YTD'!C47 -> -0.004655 | H47: =C47-'Quarterly YTD'!D47 -> 0.040984 | I47: 0 | J47: ='Quarterly YTD'!G47-I47 -> 0 | K47: ='Quarterly YTD'!H47-'Quarterly YTD'!G47 -> 0 | L47: =D47-'Quarterly YTD'!H47 -> 0 | M47: 0.02492 | N47: 0 | O47: ='Quarterly YTD'!L47-'Quarterly YTD'!K47+-0.058709 -> -0.058709 | P47: =E47-'Quarterly YTD'!L47 -> 0 | Q47: 0.247744 | R47: 0
A48: Net movement in other provisions during the period | B48: -0.133104 | C48: -1.237004 | D48: 2.400355 | E48: 1.255323 | F48: =E48+'Quarterly YTD'!O48-'Quarterly YTD'!K48 -> 1.263294 | G48: ='Quarterly YTD'!D48-'Quarterly YTD'!C48 -> -1.509798 | H48: =C48-'Quarterly YTD'!D48 -> -0.715181 | I48: 1.326513 | J48: ='Quarterly YTD'!G48-I48 -> -0.603222 | K48: ='Quarterly YTD'!H48-'Quarterly YTD'!G48 -> -0.00051 | L48: =D48-'Quarterly YTD'!H48 -> 1.677574 | M48: 0.147859 | N48: 0.513482 | O48: ='Quarterly YTD'!L48-'Quarterly YTD'!K48 -> 0.460688 | P48: =E48-'Quarterly YTD'!L48 -> 0.133294 | Q48: 0.571341 | R48: 0.097971
A49: (Reversal of)/provision for inventory obsolescence, net | B49: 0 | C49: 0 | D49: 0.028256 | E49: -0.390374 | F49: =E49+'Quarterly YTD'!O49-'Quarterly YTD'!K49 -> -0.390374 | G49: ='Quarterly YTD'!D49-'Quarterly YTD'!C49 -> 0 | H49: =C49-'Quarterly YTD'!D49 -> 0 | I49: 0 | J49: ='Quarterly YTD'!G49-I49 -> 0 | K49: ='Quarterly YTD'!H49-'Quarterly YTD'!G49 -> 0 | L49: =D49-'Quarterly YTD'!H49 -> 0.028256 | M49: 0 | N49: 0 | O49: ='Quarterly YTD'!L49-'Quarterly YTD'!K49 -> 0 | P49: =E49-'Quarterly YTD'!L49 -> -0.390374 | Q49: 0 | R49: 0
A50: (Write back)/provision for slow moving and obsolete inventory, net | B50: 0 | C50: 0 | D50: 0 | E50: 0 | F50: =E50+'Quarterly YTD'!O50-'Quarterly YTD'!K50 -> 0 | G50: ='Quarterly YTD'!D50-'Quarterly YTD'!C50 -> 0 | H50: =C50-'Quarterly YTD'!D50 -> 0 | I50: 0 | J50: ='Quarterly YTD'!G50-I50 -> 0 | K50: ='Quarterly YTD'!H50-'Quarterly YTD'!G50 -> 0.043954 | L50: =D50-'Quarterly YTD'!H50 -> -0.043954 | M50: 0.022856 | N50: 0 | O50: ='Quarterly YTD'!L50-'Quarterly YTD'!K50 -> -0.298746 | P50: =E50-'Quarterly YTD'!L50 -> 0.298746 | Q50: -0.169571 | R50: 0
A51: Write-back of provision for slow moving and obsolete inventory, net | B51: -0.070659 | C51: 0.556148 | D51: 0 | E51: 0 | F51: =E51+'Quarterly YTD'!O51-'Quarterly YTD'!K51 -> -0.21317 | G51: ='Quarterly YTD'!D51-'Quarterly YTD'!C51 -> 0.574714 | H51: =C51-'Quarterly YTD'!D51 -> 0.28726 | I51: -0.330228 | J51: ='Quarterly YTD'!G51-I51 -> 0.173323 | K51: ='Quarterly YTD'!H51-'Quarterly YTD'!G51 -> 0.156905 | L51: =D51-'Quarterly YTD'!H51 -> 0 | M51: 0 | N51: -0.20006 | O51: ='Quarterly YTD'!L51-'Quarterly YTD'!K51 -> 0.177204 | P51: =E51-'Quarterly YTD'!L51 -> 0 | Q51: 0 | R51: -0.220803
A52: Other interest income | B52: -0.187722 | C52: -0.156096 | D52: -0.329052 | E52: -0.269998 | F52: =E52+'Quarterly YTD'!O52-'Quarterly YTD'!K52 -> -0.501385 | G52: ='Quarterly YTD'!D52-'Quarterly YTD'!C52 -> -0.038724 | H52: =C52-'Quarterly YTD'!D52 -> -0.040954 | I52: -0.040809 | J52: ='Quarterly YTD'!G52-I52 -> -0.038332 | K52: ='Quarterly YTD'!H52-'Quarterly YTD'!G52 -> -0.037117 | L52: =D52-'Quarterly YTD'!H52 -> -0.212794 | M52: -0.109547 | N52: -0.047734 | O52: ='Quarterly YTD'!L52-'Quarterly YTD'!K52 -> -0.072899 | P52: =E52-'Quarterly YTD'!L52 -> -0.039818 | Q52: -0.236924 | R52: -0.151744
A53: Interest income on balances due from a related party | B53: -1.932958 | C53: -2.126254 | D53: -2.33888 | E53: -2.572767 | F53: =E53+'Quarterly YTD'!O53-'Quarterly YTD'!K53 -> -2.701405 | G53: ='Quarterly YTD'!D53-'Quarterly YTD'!C53 -> -0.531564 | H53: =C53-'Quarterly YTD'!D53 -> -0.531563 | I53: -0.58472 | J53: ='Quarterly YTD'!G53-I53 -> -0.58472 | K53: ='Quarterly YTD'!H53-'Quarterly YTD'!G53 -> -0.58472 | L53: =D53-'Quarterly YTD'!H53 -> -0.58472 | M53: -0.643189 | N53: -0.643195 | O53: ='Quarterly YTD'!L53-'Quarterly YTD'!K53 -> -0.643192 | P53: =E53-'Quarterly YTD'!L53 -> -0.643191 | Q53: -0.707511 | R53: -0.707511
A54: Finance costs | B54: 55.213244 | C54: 64.737849 | D54: 74.276529 | E54: 71.039195 | F54: =E54+'Quarterly YTD'!O54-'Quarterly YTD'!K54 -> 77.784129 | G54: ='Quarterly YTD'!D54-'Quarterly YTD'!C54 -> 13.393927 | H54: =C54-'Quarterly YTD'!D54 -> 19.476713 | I54: 15.328047 | J54: ='Quarterly YTD'!G54-I54 -> 15.410468 | K54: ='Quarterly YTD'!H54-'Quarterly YTD'!G54 -> 15.632486 | L54: =D54-'Quarterly YTD'!H54 -> 27.905528 | M54: 17.043553 | N54: 17.184806 | O54: ='Quarterly YTD'!L54-'Quarterly YTD'!K54 -> 17.741476 | P54: =E54-'Quarterly YTD'!L54 -> 19.06936 | Q54: 20.252271 | R54: 20.721022
A55: Gain on disposal of property and equipment | B55: -1.836886 | C55: 0.015574 | D55: -0.032154 | E55: -0.064657 | F55: =E55+'Quarterly YTD'!O55-'Quarterly YTD'!K55 -> -0.019359 | G55: ='Quarterly YTD'!D55-'Quarterly YTD'!C55 -> 0.000664 | H55: =C55-'Quarterly YTD'!D55 -> -0.011035 | I55: -0.017654 | J55: ='Quarterly YTD'!G55-I55 -> -0.000967 | K55: ='Quarterly YTD'!H55-'Quarterly YTD'!G55 -> -0.009836 | L55: =D55-'Quarterly YTD'!H55 -> -0.003697 | M55: -0.01457 | N55: -0.030728 | O55: ='Quarterly YTD'!L55-'Quarterly YTD'!K55 -> -0.006377 | P55: =E55-'Quarterly YTD'!L55 -> -0.012982 | Q55: 0 | R55: 0
A56: (Loss) gain on termination of lease contracts | B56: -0.009102 | C56: 0.023764 | D56: -0.054614 | E56: -0.047063 | F56: =E56+'Quarterly YTD'!O56-'Quarterly YTD'!K56 -> -0.092696 | G56: ='Quarterly YTD'!D56-'Quarterly YTD'!C56 -> -0.01335 | H56: =C56-'Quarterly YTD'!D56 -> 0.049436 | I56: -0.009214 | J56: ='Quarterly YTD'!G56-I56 -> -0.064849 | K56: ='Quarterly YTD'!H56-'Quarterly YTD'!G56 -> -0.038324 | L56: =D56-'Quarterly YTD'!H56 -> 0.057773 | M56: -0.004473 | N56: 0.004473 | O56: ='Quarterly YTD'!L56-'Quarterly YTD'!K56 -> 0 | P56: =E56-'Quarterly YTD'!L56 -> -0.047063 | Q56: -0.067118 | R56: 0.021485
A57: Loss on exchange, net | B57: 24.108535 | C57: 114.15174 | D57: 39.271284 | E57: -37.680522 | F57: =E57+'Quarterly YTD'!O57-'Quarterly YTD'!K57 -> -33.66656 | G57: ='Quarterly YTD'!D57-'Quarterly YTD'!C57 -> -2.115323 | H57: =C57-'Quarterly YTD'!D57 -> 30.669429 | I57: 12.388792 | J57: ='Quarterly YTD'!G57-I57 -> 10.767847 | K57: ='Quarterly YTD'!H57-'Quarterly YTD'!G57 -> 10.3553 | L57: =D57-'Quarterly YTD'!H57 -> 5.759345 | M57: 5.577573 | N57: 7.600561 | O57: ='Quarterly YTD'!L57-'Quarterly YTD'!K57 -> -15.383757 | P57: =E57-'Quarterly YTD'!L57 -> -35.474899 | Q57: 13.410153 | R57: 3.781943
A58: Net loss/(gain) on net monetary position | B58: 0 | C58: -21.543365 | D58: -3.558212 | E58: 1.599516 | F58: =E58+'Quarterly YTD'!O58-'Quarterly YTD'!K58 -> -1.419819 | G58: ='Quarterly YTD'!D58-'Quarterly YTD'!C58 -> 3.066506 | H58: =C58-'Quarterly YTD'!D58 -> 7.755996 | I58: -3.717688 | J58: ='Quarterly YTD'!G58-I58 -> -0.254449 | K58: ='Quarterly YTD'!H58-'Quarterly YTD'!G58 -> 1.266755 | L58: =D58-'Quarterly YTD'!H58 -> -0.85283 | M58: 0.211588 | N58: 0.017313 | O58: ='Quarterly YTD'!L58-'Quarterly YTD'!K58 -> -0.6408 | P58: =E58-'Quarterly YTD'!L58 -> 2.011415 | Q58: -2.791561 | R58: 0.001127
A59: Increase in trade receivables and contract costs | B59: -7.6196 | C59: -3.808835 | D59: -0.445687 | E59: -1.67919 | F59: =E59+'Quarterly YTD'!O59-'Quarterly YTD'!K59 -> -1.67919 | G59: ='Quarterly YTD'!D59-'Quarterly YTD'!C59 -> -2.869228 | H59: =C59-'Quarterly YTD'!D59 -> -1.952859 | I59: -1.099068 | J59: ='Quarterly YTD'!G59-I59 -> -1.348559 | K59: ='Quarterly YTD'!H59-'Quarterly YTD'!G59 -> 1.577894 | L59: =D59-'Quarterly YTD'!H59 -> 0.424046 | M59: -1.148641 | N59: 0 | O59: ='Quarterly YTD'!L59-'Quarterly YTD'!K59+1.250769 -> -2.20409 | P59: =E59-'Quarterly YTD'!L59 -> 1.775669 | Q59: -1.259565 | R59: 0
A60: Decrease/(increase) in trade receivables and contract assets | B60: 0 | C60: 0 | D60: 0 | E60: 0 | F60: =E60+'Quarterly YTD'!O60-'Quarterly YTD'!K60 -> 3.704261 | G60: ='Quarterly YTD'!D60-'Quarterly YTD'!C60 -> 0 | H60: =C60-'Quarterly YTD'!D60 -> 0 | I60: 0 | J60: ='Quarterly YTD'!G60-I60 -> 0 | K60: ='Quarterly YTD'!H60-'Quarterly YTD'!G60 -> 0 | L60: =D60-'Quarterly YTD'!H60 -> 0 | M60: 0 | N60: -0.440554 | O60: ='Quarterly YTD'!L60-'Quarterly YTD'!K60+-1.589195 -> 0 | P60: =E60-'Quarterly YTD'!L60 -> 0 | Q60: 0 | R60: 3.374631
A61: Decrease /(increase) in inventories | B61: -0.651903 | C61: -7.075708 | D61: 4.098743 | E61: 1.583755 | F61: =E61+'Quarterly YTD'!O61-'Quarterly YTD'!K61 -> 0.543746 | G61: ='Quarterly YTD'!D61-'Quarterly YTD'!C61 -> -1.193263 | H61: =C61-'Quarterly YTD'!D61 -> -5.428419 | I61: 0.773701 | J61: ='Quarterly YTD'!G61-I61 -> 2.748886 | K61: ='Quarterly YTD'!H61-'Quarterly YTD'!G61 -> 1.92062 | L61: =D61-'Quarterly YTD'!H61 -> -1.344464 | M61: 1.100836 | N61: -0.23542 | O61: ='Quarterly YTD'!L61-'Quarterly YTD'!K61 -> 0.081382 | P61: =E61-'Quarterly YTD'!L61 -> 0.636957 | Q61: -0.232414 | R61: 0.057821
A62: Prepayments and other debit balances | B62: 47.043432 | C62: -26.765219 | D62: 0 | E62: 0 | F62: =E62+'Quarterly YTD'!O62-'Quarterly YTD'!K62 -> 0 | G62: ='Quarterly YTD'!D62-'Quarterly YTD'!C62 -> 10.941115 | H62: =C62-'Quarterly YTD'!D62 -> -4.48836 | I62: -5.818776 | J62: ='Quarterly YTD'!G62-I62 -> -0.512009 | K62: ='Quarterly YTD'!H62-'Quarterly YTD'!G62 -> 6.889827 | L62: =D62-'Quarterly YTD'!H62 -> -0.559042 | M62: 0 | N62: 0 | O62: ='Quarterly YTD'!L62-'Quarterly YTD'!K62+8.678828 -> 3.939247 | P62: =E62-'Quarterly YTD'!L62 -> 4.739581 | Q62: 0 | R62: 0
A63: Increase in prepayments and other debit balances | B63: 0 | C63: 0 | D63: -12.040304 | E63: 5.289519 | F63: =E63+'Quarterly YTD'!O63-'Quarterly YTD'!K63 -> -4.354654 | G63: ='Quarterly YTD'!D63-'Quarterly YTD'!C63 -> 0 | H63: =C63-'Quarterly YTD'!D63 -> 0 | I63: 0 | J63: ='Quarterly YTD'!G63-I63 -> 0 | K63: ='Quarterly YTD'!H63-'Quarterly YTD'!G63 -> 0 | L63: =D63-'Quarterly YTD'!H63 -> -12.040304 | M63: -15.479729 | N63: 5.912828 | O63: ='Quarterly YTD'!L63-'Quarterly YTD'!K63+-7.155332 -> 0 | P63: =E63-'Quarterly YTD'!L63 -> 5.289519 | Q63: -18.964637 | R63: -6.31019
A64: Decrease in accounts payable, advances from distributors, and accrued expenses and | B64: 0 | C64: 0 | D64: 0 | E64: -35.839263 | F64: =E64+'Quarterly YTD'!O64-'Quarterly YTD'!K64 -> -35.839263 | G64: ='Quarterly YTD'!D64-'Quarterly YTD'!C64 -> 0 | H64: =C64-'Quarterly YTD'!D64 -> 0 | I64: 0 | J64: ='Quarterly YTD'!G64-I64 -> 0 | K64: ='Quarterly YTD'!H64-'Quarterly YTD'!G64 -> 0 | L64: =D64-'Quarterly YTD'!H64 -> 0 | M64: 0 | N64: 0 | O64: ='Quarterly YTD'!L64-'Quarterly YTD'!K64 -> 0 | P64: =E64-'Quarterly YTD'!L64 -> -35.839263 | Q64: 0 | R64: 0
A65: other credit expenses | B65: 0 | C65: 0 | D65: -31.924235 | E65: 0 | F65: =E65+'Quarterly YTD'!O65-'Quarterly YTD'!K65 -> 0 | G65: ='Quarterly YTD'!D65-'Quarterly YTD'!C65 -> 0 | H65: =C65-'Quarterly YTD'!D65 -> 0 | I65: 0 | J65: ='Quarterly YTD'!G65-I65 -> 0 | K65: ='Quarterly YTD'!H65-'Quarterly YTD'!G65 -> 0 | L65: =D65-'Quarterly YTD'!H65 -> -31.924235 | M65: 0 | N65: 0 | O65: ='Quarterly YTD'!L65-'Quarterly YTD'!K65 -> 0 | P65: =E65-'Quarterly YTD'!L65 -> 0 | Q65: 0 | R65: 0
A66: Increase/(decrease) in accounts payable, advances from distributors and accrued expenses and other credit balances | B66: 7.85232 | C66: 49.126942 | D66: 0 | E66: 0 | F66: =E66+'Quarterly YTD'!O66-'Quarterly YTD'!K66 -> -3.884561 | G66: ='Quarterly YTD'!D66-'Quarterly YTD'!C66 -> 21.417975 | H66: =C66-'Quarterly YTD'!D66 -> -2.278757 | I66: -2.820887 | J66: ='Quarterly YTD'!G66-I66 -> -2.08018 | K66: ='Quarterly YTD'!H66-'Quarterly YTD'!G66 -> 22.38257 | L66: =D66-'Quarterly YTD'!H66 -> -17.481503 | M66: -3.063081 | N66: -8.185032 | O66: ='Quarterly YTD'!L66-'Quarterly YTD'!K66+-0.302812 -> -15.105121 | P66: =E66-'Quarterly YTD'!L66 -> 20.772359 | Q66: -6.98016 | R66: 1.968951
A67: Balance with related parties | B67: 0 | C67: 0 | D67: 0 | E67: 0 | F67: =E67+'Quarterly YTD'!O67-'Quarterly YTD'!K67 -> 0 | G67: ='Quarterly YTD'!D67-'Quarterly YTD'!C67 -> 0 | H67: =C67-'Quarterly YTD'!D67 -> 0 | I67: 0 | J67: ='Quarterly YTD'!G67-I67 -> 0 | K67: ='Quarterly YTD'!H67-'Quarterly YTD'!G67 -> 0.443359 | L67: =D67-'Quarterly YTD'!H67 -> -0.443359 | M67: 0 | N67: 0 | O67: ='Quarterly YTD'!L67-'Quarterly YTD'!K67 -> -1.597284 | P67: =E67-'Quarterly YTD'!L67 -> 1.597284 | Q67: 0 | R67: 0
A68: Contract liabilities | B68: 3.843218 | C68: 1.255676 | D68: 0 | E68: 0 | F68: =E68+'Quarterly YTD'!O68-'Quarterly YTD'!K68 -> 0 | G68: ='Quarterly YTD'!D68-'Quarterly YTD'!C68 -> -1.030982 | H68: =C68-'Quarterly YTD'!D68 -> -0.645817 | I68: 2.022442 | J68: ='Quarterly YTD'!G68-I68 -> -0.773256 | K68: ='Quarterly YTD'!H68-'Quarterly YTD'!G68 -> -2.201364 | L68: =D68-'Quarterly YTD'!H68 -> 0.952178 | M68: 0 | N68: 0 | O68: ='Quarterly YTD'!L68-'Quarterly YTD'!K68+0.196409 -> -0.018117 | P68: =E68-'Quarterly YTD'!L68 -> 0.214526 | Q68: 0 | R68: 0
A69: Balances with a related party and shareholders | B69: -0.388153 | C69: 21.720609 | D69: 0.075676 | E69: -12.012494 | F69: =E69+'Quarterly YTD'!O69-'Quarterly YTD'!K69 -> -17.808495 | G69: ='Quarterly YTD'!D69-'Quarterly YTD'!C69 -> 17.82741 | H69: =C69-'Quarterly YTD'!D69 -> 3.893199 | I69: 0.138788 | J69: ='Quarterly YTD'!G69-I69 -> -0.262643 | K69: ='Quarterly YTD'!H69-'Quarterly YTD'!G69 -> 0.123855 | L69: =D69-'Quarterly YTD'!H69 -> 0.075676 | M69: -0.60457 | N69: -0.569236 | O69: ='Quarterly YTD'!L69-'Quarterly YTD'!K69 -> 1.173806 | P69: =E69-'Quarterly YTD'!L69 -> -12.012494 | Q69: -3.699358 | R69: -3.270449
A70: Decrease in long term debt to supplier | B70: 0 | C70: 0 | D70: 10.080507 | E70: 0.39442 | F70: =E70+'Quarterly YTD'!O70-'Quarterly YTD'!K70 -> 0.764209 | G70: ='Quarterly YTD'!D70-'Quarterly YTD'!C70 -> 0 | H70: =C70-'Quarterly YTD'!D70 -> 0 | I70: 0 | J70: ='Quarterly YTD'!G70-I70 -> 0 | K70: ='Quarterly YTD'!H70-'Quarterly YTD'!G70 -> 0 | L70: =D70-'Quarterly YTD'!H70 -> 10.080507 | M70: -0.872592 | N70: -1.61126 | O70: ='Quarterly YTD'!L70-'Quarterly YTD'!K70 -> 2.483852 | P70: =E70-'Quarterly YTD'!L70 -> 0.39442 | Q70: -0.349321 | R70: -1.764742
A71: Increase/(decrease) in restricted bank balances | B71: 0 | C71: 0 | D71: 10.786602 | E71: -0.088701 | F71: =E71+'Quarterly YTD'!O71-'Quarterly YTD'!K71 -> -3.873222 | G71: ='Quarterly YTD'!D71-'Quarterly YTD'!C71 -> 0 | H71: =C71-'Quarterly YTD'!D71 -> 0 | I71: 0 | J71: ='Quarterly YTD'!G71-I71 -> 0 | K71: ='Quarterly YTD'!H71-'Quarterly YTD'!G71 -> 0 | L71: =D71-'Quarterly YTD'!H71 -> 10.786602 | M71: -16.646159 | N71: 17.673997 | O71: ='Quarterly YTD'!L71-'Quarterly YTD'!K71+1.027838 -> 0 | P71: =E71-'Quarterly YTD'!L71 -> -0.088701 | Q71: -19.009125 | R71: 16.252442
A72: (Decrease)/increase in contract liabilities | B72: 0 | C72: 0 | D72: 0.011885 | E72: 3.23386 | F72: =E72+'Quarterly YTD'!O72-'Quarterly YTD'!K72 -> 2.291673 | G72: ='Quarterly YTD'!D72-'Quarterly YTD'!C72 -> 0 | H72: =C72-'Quarterly YTD'!D72 -> 0 | I72: 0 | J72: ='Quarterly YTD'!G72-I72 -> 0 | K72: ='Quarterly YTD'!H72-'Quarterly YTD'!G72 -> 0 | L72: =D72-'Quarterly YTD'!H72 -> 0.011885 | M72: 0.09547 | N72: 0.046547 | O72: ='Quarterly YTD'!L72-'Quarterly YTD'!K72 -> -0.142017 | P72: =E72-'Quarterly YTD'!L72 -> 3.23386 | Q72: 1.704665 | R72: -2.504835
A73: Interest received | B73: 0.187722 | C73: 0.156096 | D73: 0.329052 | E73: 0.269998 | F73: =E73+'Quarterly YTD'!O73-'Quarterly YTD'!K73 -> 0.501385 | G73: ='Quarterly YTD'!D73-'Quarterly YTD'!C73 -> 0.038724 | H73: =C73-'Quarterly YTD'!D73 -> 0.040954 | I73: 0.040809 | J73: ='Quarterly YTD'!G73-I73 -> 0.038332 | K73: ='Quarterly YTD'!H73-'Quarterly YTD'!G73 -> 0.037117 | L73: =D73-'Quarterly YTD'!H73 -> 0.212794 | M73: 0.109547 | N73: 0.047734 | O73: ='Quarterly YTD'!L73-'Quarterly YTD'!K73 -> 0.072899 | P73: =E73-'Quarterly YTD'!L73 -> 0.039818 | Q73: 0.236924 | R73: 0.151744
A74: Finance costs paid | B74: -4.512994 | C74: -7.191377 | D74: -16.33502 | E74: -45.285543 | F74: =E74+'Quarterly YTD'!O74-'Quarterly YTD'!K74 -> -49.73991 | G74: ='Quarterly YTD'!D74-'Quarterly YTD'!C74 -> 0 | H74: =C74-'Quarterly YTD'!D74 -> -7.191377 | I74: -2.559133 | J74: ='Quarterly YTD'!G74-I74 -> -16.88587 | K74: ='Quarterly YTD'!H74-'Quarterly YTD'!G74 -> -10.201007 | L74: =D74-'Quarterly YTD'!H74 -> 13.31099 | M74: -2.407847 | N74: -18.889983 | O74: ='Quarterly YTD'!L74-'Quarterly YTD'!K74 -> -3.511305 | P74: =E74-'Quarterly YTD'!L74 -> -20.476408 | Q74: -4.30736 | R74: -21.444837
A75: Cash from operations | B75: 116.20872 | C75: 140.12604 | D75: 47.314112 | E75: 56.062646 | F75: =E75+'Quarterly YTD'!O75-'Quarterly YTD'!K75 -> 51.06854 | G75: ='Quarterly YTD'!D75-'Quarterly YTD'!C75 -> 66.02899 | H75: =C75-'Quarterly YTD'!D75 -> 21.605139 | I75: 20.412647 | J75: ='Quarterly YTD'!G75-I75 -> 19.144615 | K75: ='Quarterly YTD'!H75-'Quarterly YTD'!G75 -> 48.237199 | L75: =D75-'Quarterly YTD'!H75 -> -40.480349 | M75: -7.436738 | N75: 23.526781 | O75: ='Quarterly YTD'!L75-'Quarterly YTD'!K75+-18.892036 -> 34.962156 | P75: =E75-'Quarterly YTD'!L75 -> -19.272922 | Q75: -9.441936 | R75: 26.367722
A76: Income tax paid | B76: -3.350279 | C76: -5.782459 | D76: -7.184522 | E76: -6.091108 | F76: =E76+'Quarterly YTD'!O76-'Quarterly YTD'!K76 -> -6.512825 | G76: ='Quarterly YTD'!D76-'Quarterly YTD'!C76 -> -1.547474 | H76: =C76-'Quarterly YTD'!D76 -> -1.827052 | I76: -1.75688 | J76: ='Quarterly YTD'!G76-I76 -> -0.977884 | K76: ='Quarterly YTD'!H76-'Quarterly YTD'!G76 -> -1.421533 | L76: =D76-'Quarterly YTD'!H76 -> -3.028225 | M76: -0.9154 | N76: -0.92147 | O76: ='Quarterly YTD'!L76-'Quarterly YTD'!K76 -> -1.638141 | P76: =E76-'Quarterly YTD'!L76 -> -2.616097 | Q76: -1.015886 | R76: -1.242701
A77: Provisions paid | B77: -0.332177 | C77: -2.195829 | D77: -0.403325 | E77: -1.099098 | F77: =E77+'Quarterly YTD'!O77-'Quarterly YTD'!K77 -> -0.413471 | G77: ='Quarterly YTD'!D77-'Quarterly YTD'!C77 -> -0.010913 | H77: =C77-'Quarterly YTD'!D77 -> -2.055755 | I77: -0.182869 | J77: ='Quarterly YTD'!G77-I77 -> -0.080178 | K77: ='Quarterly YTD'!H77-'Quarterly YTD'!G77 -> -0.040452 | L77: =D77-'Quarterly YTD'!H77 -> -0.099826 | M77: -0.074396 | N77: -0.854521 | O77: ='Quarterly YTD'!L77-'Quarterly YTD'!K77 -> -0.055703 | P77: =E77-'Quarterly YTD'!L77 -> -0.114478 | Q77: -0.217241 | R77: -0.026049
A78: Net cash from operating activities | B78: =SUM(B35:B38)+B40+B44+SUM(B47:B48)+SUM(B51:B59)+SUM(B61:B62)+B66+SUM(B68:B69)+SUM(B73:B74)+SUM(B76:B77) -> 112.52626 | C78: =SUM(C35:C38)+SUM(C40:C41)+C44+SUM(C47:C48)+SUM(C51:C59)+SUM(C61:C62)+C66+SUM(C68:C70)+SUM(C73:C74)+SUM(C76:C77) -> 132.14775 | D78: =SUM(D35:D38)+SUM(D40:D41)+D44+D46+SUM(D48:D49)+SUM(D52:D59)+D61+D63+D65+SUM(D69:D74)+SUM(D76:D77) -> 39.726265 | E78: =SUM(E35:E38)+SUM(E40:E41)+E44+E46+SUM(E48:E49)+SUM(E52:E59)+E61+SUM(E63:E64)+SUM(E69:E74)+SUM(E76:E77) -> 48.87244 | F78: =E78+'Quarterly YTD'!O78-'Quarterly YTD'!K78 -> 44.142244 | G78: =SUM(G35:G74)+SUM(G76:G77) -> 64.509327 | H78: =SUM(H35:H74)+SUM(H76:H77) -> 17.60719 | I78: =SUM(I35:I38)+I40+I44+SUM(I47:I48)+SUM(I51:I59)+SUM(I61:I62)+I66+SUM(I68:I69)+SUM(I73:I74)+SUM(I76:I77) -> 15.954574 | J78: =SUM(J35:J74)+SUM(J76:J77) -> 1.239015 | K78: =SUM(K35:K74)+SUM(K76:K77) -> 36.611324 | L78: =SUM(L35:L74)+SUM(L76:L77) -> -14.078648 | M78: =SUM(M35:M38)+M40+M44+SUM(M47:M48)+M50+SUM(M52:M59)+M61+M63+M66+SUM(M69:M74)+SUM(M76:M77) -> -10.724834 | N78: =SUM(N35:N38)+SUM(N42:N44)+N48+SUM(N51:N58)+SUM(N60:N61)+N63+N66+SUM(N69:N74)+SUM(N76:N77) -> 21.75079 | O78: =SUM(O35:O74)+SUM(O76:O77) -> 29.663321 | P78: =SUM(P35:P74)+SUM(P76:P77) -> 2.575458 | Q78: =SUM(Q35:Q38)+Q40+Q44+SUM(Q47:Q48)+Q50+SUM(Q52:Q59)+Q61+Q63+Q66+SUM(Q69:Q74)+SUM(Q76:Q77) -> -14.745499 | R78: =SUM(R35:R38)+SUM(R42:R44)+R48+SUM(R51:R58)+SUM(R60:R61)+R63+R66+SUM(R69:R74)+SUM(R76:R77) -> 25.098972 | S78: =IF(AND(R78=0,Q78=0),0,IF(OR(Q78=0,Q78="NM",R78="NM"),"NM",IF(Q78<0,-(R78/Q78-1),R78/Q78-1))) -> 2.7021446 | T78: =IF(AND(R78=0,N78=0),0,IF(OR(N78=0,N78="NM",R78="NM"),"NM",IF(N78<0,-(R78/N78-1),R78/N78-1))) -> 0.15393381
A79: Acquisition of property, equipment and intangible assets | B79: -84.254415 | C79: -74.376186 | D79: -29.126253 | E79: -47.541704 | F79: =E79+'Quarterly YTD'!O79-'Quarterly YTD'!K79 -> -59.743655 | G79: ='Quarterly YTD'!D79-'Quarterly YTD'!C79 -> -29.470083 | H79: =C79-'Quarterly YTD'!D79 -> -26.193054 | I79: -7.297599 | J79: ='Quarterly YTD'!G79-I79 -> -7.972824 | K79: ='Quarterly YTD'!H79-'Quarterly YTD'!G79 -> -9.170407 | L79: =D79-'Quarterly YTD'!H79 -> -4.685423 | M79: -3.520287 | N79: -11.240657 | O79: ='Quarterly YTD'!L79-'Quarterly YTD'!K79+-3.505909 -> -12.649652 | P79: =E79-'Quarterly YTD'!L79 -> -17.435065 | Q79: -11.909148 | R79: -22.684751
A80: Acquisition of intangible assets | B80: -15.165416 | C80: -24.361971 | D80: -20.599286 | E80: -8.286235 | F80: =E80+'Quarterly YTD'!O80-'Quarterly YTD'!K80 -> -8.286235 | G80: ='Quarterly YTD'!D80-'Quarterly YTD'!C80 -> -2.944637 | H80: =C80-'Quarterly YTD'!D80 -> -15.438866 | I80: -4.986627 | J80: ='Quarterly YTD'!G80-I80 -> 1.293468 | K80: ='Quarterly YTD'!H80-'Quarterly YTD'!G80 -> -3.89397 | L80: =D80-'Quarterly YTD'!H80 -> -13.012157 | M80: -0.923889 | N80: 0 | O80: ='Quarterly YTD'!L80-'Quarterly YTD'!K80+2.393394 -> -2.081539 | P80: =E80-'Quarterly YTD'!L80 -> -3.811302 | Q80: -3.41435 | R80: 0
A81: Due from related parties | B81: -0.406392 | C81: -0.009795 | D81: 0 | E81: 0 | F81: =E81+'Quarterly YTD'!O81-'Quarterly YTD'!K81 -> 0 | G81: ='Quarterly YTD'!D81-'Quarterly YTD'!C81 -> 0 | H81: =C81-'Quarterly YTD'!D81 -> -0.009795 | I81: 0 | J81: ='Quarterly YTD'!G81-I81 -> 0 | K81: ='Quarterly YTD'!H81-'Quarterly YTD'!G81 -> 0 | L81: =D81-'Quarterly YTD'!H81 -> 0 | M81: 0 | N81: 0 | O81: ='Quarterly YTD'!L81-'Quarterly YTD'!K81 -> 0 | P81: =E81-'Quarterly YTD'!L81 -> 0 | Q81: 0 | R81: 0
A82: Payment for telecom license | B82: 0 | C82: 0 | D82: 0 | E82: -5.02211 | F82: =E82+'Quarterly YTD'!O82-'Quarterly YTD'!K82 -> -5.02211 | G82: ='Quarterly YTD'!D82-'Quarterly YTD'!C82 -> 0 | H82: =C82-'Quarterly YTD'!D82 -> 0 | I82: 0 | J82: ='Quarterly YTD'!G82-I82 -> 0 | K82: ='Quarterly YTD'!H82-'Quarterly YTD'!G82 -> 0 | L82: =D82-'Quarterly YTD'!H82 -> 0 | M82: 0 | N82: 0 | O82: ='Quarterly YTD'!L82-'Quarterly YTD'!K82 -> 0 | P82: =E82-'Quarterly YTD'!L82 -> -5.02211 | Q82: 0 | R82: 0
A83: Advances to suppliers | B83: 0 | C83: 0 | D83: 0 | E83: 0 | F83: =E83+'Quarterly YTD'!O83-'Quarterly YTD'!K83 -> -12.520713 | G83: ='Quarterly YTD'!D83-'Quarterly YTD'!C83 -> 0 | H83: =C83-'Quarterly YTD'!D83 -> 0 | I83: 0 | J83: ='Quarterly YTD'!G83-I83 -> 0 | K83: ='Quarterly YTD'!H83-'Quarterly YTD'!G83 -> 0 | L83: =D83-'Quarterly YTD'!H83 -> 0 | M83: 0 | N83: 2.3034 | O83: ='Quarterly YTD'!L83-'Quarterly YTD'!K83 -> 0.108169 | P83: =E83-'Quarterly YTD'!L83 -> 0 | Q83: 0 | R83: -4.15356
A84: Proceeds from disposal of property and equipment | B84: 10.346399 | C84: 0.037732 | D84: 0.06133 | E84: 0.253132 | F84: =E84+'Quarterly YTD'!O84-'Quarterly YTD'!K84 -> 0.099428 | G84: ='Quarterly YTD'!D84-'Quarterly YTD'!C84 -> -0.014394 | H84: =C84-'Quarterly YTD'!D84 -> 0.012994 | I84: 0.074162 | J84: ='Quarterly YTD'!G84-I84 -> -0.02599 | K84: ='Quarterly YTD'!H84-'Quarterly YTD'!G84 -> 0.026253 | L84: =D84-'Quarterly YTD'!H84 -> -0.013095 | M84: 0.016625 | N84: 0.137079 | O84: ='Quarterly YTD'!L84-'Quarterly YTD'!K84 -> 0.042928 | P84: =E84-'Quarterly YTD'!L84 -> 0.0565 | Q84: 0 | R84: 0
A85: Due from a related party | B85: 0 | C85: 0 | D85: 0 | E85: 0 | F85: =E85+'Quarterly YTD'!O85-'Quarterly YTD'!K85 -> 0 | G85: ='Quarterly YTD'!D85-'Quarterly YTD'!C85 -> 0.128807 | H85: =C85-'Quarterly YTD'!D85 -> 0.100571 | I85: 0 | J85: ='Quarterly YTD'!G85-I85 -> 0 | K85: ='Quarterly YTD'!H85-'Quarterly YTD'!G85 -> 0 | L85: =D85-'Quarterly YTD'!H85 -> 0 | M85: 0 | N85: 0 | O85: ='Quarterly YTD'!L85-'Quarterly YTD'!K85 -> 0 | P85: =E85-'Quarterly YTD'!L85 -> 0 | Q85: 0 | R85: 0
A86: Movement in term deposits | B86: 0.132403 | C86: -0.025433 | D86: 0.747273 | E86: -0.110069 | F86: =E86+'Quarterly YTD'!O86-'Quarterly YTD'!K86 -> -0.106187 | G86: ='Quarterly YTD'!D86-'Quarterly YTD'!C86 -> 0.066109 | H86: =C86-'Quarterly YTD'!D86 -> -0.033428 | I86: 0.019769 | J86: ='Quarterly YTD'!G86-I86 -> -0.03499 | K86: ='Quarterly YTD'!H86-'Quarterly YTD'!G86 -> -0.003446 | L86: =D86-'Quarterly YTD'!H86 -> 0.76594 | M86: 0 | N86: 0 | O86: ='Quarterly YTD'!L86-'Quarterly YTD'!K86 -> 0 | P86: =E86-'Quarterly YTD'!L86 -> -0.110069 | Q86: 0.110067 | R86: -0.106185
A87: Net cash used in investing activities | B87: =SUM(B79:B81)+B84+B86 -> -89.347421 | C87: =SUM(C79:C81)+C84+C86 -> -98.735653 | D87: =SUM(D79:D80)+D82+D84+D86 -> -48.916936 | E87: =SUM(E79:E80)+E82+E84+E86 -> -60.706986 | F87: =E87+'Quarterly YTD'!O87-'Quarterly YTD'!K87 -> -85.579472 | G87: =SUM(G79:G86) -> -32.234198 | H87: =SUM(H79:H86) -> -41.561578 | I87: =SUM(I79:I80)+SUM(I84:I86) -> -12.190295 | J87: =SUM(J79:J86) -> -6.740336 | K87: =SUM(K79:K86) -> -13.04157 | L87: =SUM(L79:L86) -> -16.944735 | M87: =SUM(M79:M80)+M84+M86 -> -4.427551 | N87: =N79+SUM(N83:N84)+N86 -> -8.800178 | O87: =SUM(O79:O86) -> -14.580094 | P87: =SUM(P79:P86) -> -26.322046 | Q87: =SUM(Q79:Q80)+Q84+Q86 -> -15.213431 | R87: =R79+SUM(R83:R84)+R86 -> -26.944496 | S87: =IF(AND(R87=0,Q87=0),0,IF(OR(Q87=0,Q87="NM",R87="NM"),"NM",IF(Q87<0,(R87/Q87-1),-(R87/Q87-1)))) -> 0.77109923 | T87: =IF(AND(R87=0,N87=0),0,IF(OR(N87=0,N87="NM",R87="NM"),"NM",IF(N87<0,(R87/N87-1),-(R87/N87-1)))) -> 2.0618126
A88: Term loans proceeds | B88: 10.230431 | C88: 43.919974 | D88: 0.674215 | E88: 17.005817 | F88: =E88+'Quarterly YTD'!O88-'Quarterly YTD'!K88 -> 22.461817 | G88: ='Quarterly YTD'!D88-'Quarterly YTD'!C88 -> -9.834668 | H88: =C88-'Quarterly YTD'!D88 -> 43.754642 | I88: 0 | J88: ='Quarterly YTD'!G88-I88 -> 0.663423 | K88: ='Quarterly YTD'!H88-'Quarterly YTD'!G88 -> 0.000961 | L88: =D88-'Quarterly YTD'!H88 -> 0.009831 | M88: 0 | N88: 0 | O88: ='Quarterly YTD'!L88-'Quarterly YTD'!K88 -> 3.734815 | P88: =E88-'Quarterly YTD'!L88 -> 13.271002 | Q88: 3.375991 | R88: 2.080009
A89: Terms loans payments | B89: -37.974252 | C89: -47.519074 | D89: -253.91816 | E89: -6.611861 | F89: =E89+'Quarterly YTD'!O89-'Quarterly YTD'!K89 -> -9.555588 | G89: ='Quarterly YTD'!D89-'Quarterly YTD'!C89 -> 1.574842 | H89: =C89-'Quarterly YTD'!D89 -> -40.557865 | I89: -9.946342 | J89: ='Quarterly YTD'!G89-I89 -> -0.59036 | K89: ='Quarterly YTD'!H89-'Quarterly YTD'!G89 -> -18.020226 | L89: =D89-'Quarterly YTD'!H89 -> -225.36123 | M89: -1.213323 | N89: -0.318403 | O89: ='Quarterly YTD'!L89-'Quarterly YTD'!K89 -> -1.234702 | P89: =E89-'Quarterly YTD'!L89 -> -3.845433 | Q89: -2.060207 | R89: -2.415246
A90: Lease liabilities paid | B90: -25.358133 | C90: -22.91447 | D90: -23.943408 | E90: -31.839486 | F90: =E90+'Quarterly YTD'!O90-'Quarterly YTD'!K90 -> -38.581958 | G90: ='Quarterly YTD'!D90-'Quarterly YTD'!C90 -> -0.213037 | H90: =C90-'Quarterly YTD'!D90 -> -22.701433 | I90: -7.524722 | J90: ='Quarterly YTD'!G90-I90 -> -2.916943 | K90: ='Quarterly YTD'!H90-'Quarterly YTD'!G90 -> -6.037692 | L90: =D90-'Quarterly YTD'!H90 -> -7.464051 | M90: -7.053757 | N90: -6.81598 | O90: ='Quarterly YTD'!L90-'Quarterly YTD'!K90 -> 5e-05 | P90: =E90-'Quarterly YTD'!L90 -> -17.969799 | Q90: -13.470987 | R90: -7.141222
A91: Interest paid | B91: 0 | C91: 0 | D91: 0 | E91: 0 | F91: =E91+'Quarterly YTD'!O91-'Quarterly YTD'!K91 -> 0 | G91: ='Quarterly YTD'!D91-'Quarterly YTD'!C91 -> -13.013968 | H91: =C91-'Quarterly YTD'!D91 -> 42.589607 | I91: 0 | J91: ='Quarterly YTD'!G91-I91 -> 0 | K91: ='Quarterly YTD'!H91-'Quarterly YTD'!G91 -> 0 | L91: =D91-'Quarterly YTD'!H91 -> 0 | M91: 0 | N91: 0 | O91: ='Quarterly YTD'!L91-'Quarterly YTD'!K91 -> 0 | P91: =E91-'Quarterly YTD'!L91 -> 0 | Q91: 0 | R91: 0
A92: Restricted bank balances | B92: -6.559526 | C92: -0.143868 | D92: 0 | E92: 0 | F92: =E92+'Quarterly YTD'!O92-'Quarterly YTD'!K92 -> 0 | G92: ='Quarterly YTD'!D92-'Quarterly YTD'!C92 -> -0.036024 | H92: =C92-'Quarterly YTD'!D92 -> -0.036139 | I92: 2.490096 | J92: ='Quarterly YTD'!G92-I92 -> 7.476554 | K92: ='Quarterly YTD'!H92-'Quarterly YTD'!G92 -> -10.073296 | L92: =D92-'Quarterly YTD'!H92 -> 0.106646 | M92: 0 | N92: 0 | O92: ='Quarterly YTD'!L92-'Quarterly YTD'!K92+-1.027838 -> -17.03403 | P92: =E92-'Quarterly YTD'!L92 -> 16.006192 | Q92: 0 | R92: 0
A93: Proceeds from bond issued | B93: 0 | C93: 0 | D93: 300 | E93: 0 | F93: =E93+'Quarterly YTD'!O93-'Quarterly YTD'!K93 -> 56.796935 | G93: ='Quarterly YTD'!D93-'Quarterly YTD'!C93 -> 0 | H93: =C93-'Quarterly YTD'!D93 -> 0 | I93: 0 | J93: ='Quarterly YTD'!G93-I93 -> 0 | K93: ='Quarterly YTD'!H93-'Quarterly YTD'!G93 -> 0 | L93: =D93-'Quarterly YTD'!H93 -> 300 | M93: 0 | N93: 0 | O93: ='Quarterly YTD'!L93-'Quarterly YTD'!K93 -> 0 | P93: =E93-'Quarterly YTD'!L93 -> 0 | Q93: 56.796935 | R93: 0
A94: Net cash (used in)/from financing activities | B94: =SUM(B88:B90)+B92 -> -59.66148 | C94: =SUM(C88:C90)+SUM(C92:C93) -> -26.657438 | D94: =SUM(D88:D90)+D93 -> 22.812648 | E94: =SUM(E88:E90)+E93 -> -21.44553 | F94: =E94+'Quarterly YTD'!O94-'Quarterly YTD'!K94 -> 31.121206 | G94: =SUM(G88:G93) -> -21.522855 | H94: =SUM(H88:H93) -> 23.048812 | I94: =SUM(I88:I92) -> -14.980968 | J94: =SUM(J88:J93) -> 4.632674 | K94: =SUM(K88:K93) -> -34.130253 | L94: =SUM(L88:L93) -> 67.291195 | M94: =SUM(M88:M90)+M93 -> -8.26708 | N94: =SUM(N88:N90)+N93 -> -7.134383 | O94: =SUM(O88:O93) -> -14.533867 | P94: =SUM(P88:P93) -> 7.461962 | Q94: =SUM(Q88:Q90)+Q93 -> 44.641732 | R94: =SUM(R88:R90)+R93 -> -7.476459 | S94: =IF(AND(R94=0,Q94=0),0,IF(OR(Q94=0,Q94="NM",R94="NM"),"NM",IF(Q94<0,-(R94/Q94-1),R94/Q94-1))) -> -1.1674769 | T94: =IF(AND(R94=0,N94=0),0,IF(OR(N94=0,N94="NM",R94="NM"),"NM",IF(N94<0,-(R94/N94-1),R94/N94-1))) -> -0.047947524
A95: (DECREASE) / INCREASE IN CASH AND CASH EQUIVALENTS | B95: =B78+B87+B94 -> -36.482641 | C95: =C78+C87+C94 -> 6.754658 | D95: =D78+D87+D94 -> 13.621977 | E95: =E78+E87+E94 -> -33.280076 | F95: =F78+F87+F94 -> -10.316022 | G95: =G78+G87+G94 -> 10.752274 | H95: =H78+H87+H94 -> -0.905576 | I95: =I78+I87+I94 -> -11.216689 | ... R95: =R78+R87+R94 -> -9.321983 | S95: =IF(AND(R95=0,Q95=0),0,IF(OR(Q95=0,Q95="NM",R95="NM"),"NM",IF(Q95<0,-(R95/Q95-1),R95/Q95-1))) -> -1.6348913 | T95: =IF(AND(R95=0,N95=0),0,IF(OR(N95=0,N95="NM",R95="NM"),"NM",IF(N95<0,-(R95/N95-1),R95/N95-1))) -> -2.6027538
A96: Effects of exchange rate changes | B96: -0.432477 | C96: -0.533686 | D96: 7.427334 | E96: 9.581113 | F96: =E96+'Quarterly YTD'!O96-'Quarterly YTD'!K96 -> 9.360146 | G96: ='Quarterly YTD'!D96-'Quarterly YTD'!C96 -> -2.251309 | H96: =C96-'Quarterly YTD'!D96 -> 8.034176 | I96: 0.19168 | J96: ='Quarterly YTD'!G96-I96 -> 1.444214 | K96: ='Quarterly YTD'!H96-'Quarterly YTD'!G96 -> -4.355493 | L96: =D96-'Quarterly YTD'!H96 -> 10.146933 | M96: -1.470098 | N96: -0.75526 | O96: ='Quarterly YTD'!L96-'Quarterly YTD'!K96+0.000009 -> -2.966845 | P96: =E96-'Quarterly YTD'!L96 -> 14.773326 | Q96: 5.460782 | R96: -7.907108
A97: Cash and cash equivalents at beginning of the period | B97: 23.60309 | C97: -13.312028 | D97: -7.091056 | E97: ='Quarterly YTD'!K97 -> 13.958255 | F97: ='Quarterly YTD'!K98 -> -5.870339 | G97: ='Quarterly YTD'!C98 -> -22.720621 | H97: ='Quarterly YTD'!D98 -> -14.219656 | I97: =D97 -> -7.091056 | J97: =I98 -> -18.116065 | K97: ='Quarterly YTD'!G98 -> -17.540498 | L97: ='Quarterly YTD'!H98 -> -29.034284 | M97: ='Quarterly YTD'!K97 -> 13.958255 | N97: -10.931308 | O97: ='Quarterly YTD'!K98 -> -5.870339 | P97: ='Quarterly YTD'!L98 -> -8.229408 | Q97: ='Quarterly YTD'!O97 -> -9.740708 | R97: 10.402876 | S97: =IF(AND(R97=0,Q97=0),0,IF(OR(Q97=0,Q97="NM",R97="NM"),"NM",IF(Q97<0,-(R97/Q97-1),R97/Q97-1))) -> 2.0679795 | T97: =IF(AND(R97=0,N97=0),0,IF(OR(N97=0,N97="NM",R97="NM"),"NM",IF(N97<0,-(R97/N97-1),R97/N97-1))) -> 1.9516588
A98: CASH AND CASH EQUIVALENTS AT 30 JUNE | B98: =SUM(B95:B97) -> -13.312028 | C98: =SUM(C95:C97) -> -7.091056 | D98: =SUM(D95:D97) -> 13.958255 | E98: =SUM(E95:E97) -> -9.740708 | F98: =((E95+E96)+('Quarterly YTD'!O95+'Quarterly YTD'!O96)-('Quarterly YTD'!K95+'Quarterly YTD'!K96))+F97 -> -6.826215 | G98: =SUM(G95:G97) -> -14.219656 | H98: =SUM(H95:H97) -> -7.091056 | I98: =SUM(I95:I97) -> -18.116065 | J98: =SUM(J95:J97) -> -17.540498 | K98: ='Quarterly YTD'!H98 -> -29.034284 | L98: =D98 -> 13.958255 | M98: =SUM(M95:M97) -> -10.931308 | N98: =SUM(N95:N97) -> -5.870339 | O98: =SUM(O95:O97) -> -8.287824 | P98: =SUM(P95:P97) -> -9.740708 | Q98: =SUM(Q95:Q97) -> 10.402876 | R98: =SUM(R95:R97) -> -6.826215 | S98: =IF(AND(R98=0,Q98=0),0,IF(OR(Q98=0,Q98="NM",R98="NM"),"NM",IF(Q98<0,-(R98/Q98-1),R98/Q98-1))) -> -1.6561854 | T98: =IF(AND(R98=0,N98=0),0,IF(OR(N98=0,N98="NM",R98="NM"),"NM",IF(N98<0,-(R98/N98-1),R98/N98-1))) -> -0.16283148
A100: Balance Sheet
A101: Goodwill | B101: 12.743364 | C101: 58.270178 | D101: 65.66836 | E101: 68.02026 | F101: =R101 -> 72.283156 | H101: 58.270178 | J101: 63.306458 | K101: 64.783184 | L101: 65.66836 | M101: 66.264948 | N101: 66.830334 | O101: 67.986917 | P101: 68.02026 | Q101: 72.295538 | R101: 72.283156 | S101: =IF(AND(R101=0,Q101=0),0,IF(OR(Q101=0,Q101="NM",R101="NM"),"NM",IF(Q101<0,-(R101/Q101-1),R101/Q101-1))) -> -0.00017126921 | T101: =IF(AND(R101=0,N101=0),0,IF(OR(N101=0,N101="NM",R101="NM"),"NM",IF(N101<0,-(R101/N101-1),R101/N101-1))) -> 0.081592021
A102: Intangible assets | B102: 72.676461 | C102: 77.898462 | D102: 79.281757 | E102: 75.923436 | F102: =R102 -> 78.219311 | H102: 77.898462 | J102: 71.26127 | K102: 69.320984 | L102: 79.281757 | M102: 75.418243 | N102: 68.46526 | O102: 71.981934 | P102: 75.923436 | Q102: 75.683398 | R102: 78.219311 | S102: =IF(AND(R102=0,Q102=0),0,IF(OR(Q102=0,Q102="NM",R102="NM"),"NM",IF(Q102<0,-(R102/Q102-1),R102/Q102-1))) -> 0.03350686 | T102: =IF(AND(R102=0,N102=0),0,IF(OR(N102=0,N102="NM",R102="NM"),"NM",IF(N102<0,-(R102/N102-1),R102/N102-1))) -> 0.14246716
...

Sheet Quarterly YTD
A1: $mm, Dec year-end | B1: FY22 | C1: 1H23 | D1: 3Q23 | E1: FY23 | F1: 1Q24 | G1: 1H24 | H1: 3Q24 | I1: FY24 | J1: 1Q25 | K1: 1H25 | L1: 3Q25 | M1: FY25 | N1: 1Q26 | O1: 1H26
A2: Income Statement
A3: Revenues | B3: 308.10876 | C3: 192.91752 | D3: 264.09102 | E3: 356.19708 | F3: 85.804548 | G3: 174.60041 | H3: 262.65717 | I3: 355.99368 | J3: 93.498313 | K3: 193.80809 | L3: 300.56417 | M3: 408.64877 | N3: 114.34153 | O3: 230.83109
A4: Operating costs and commissions | B4: -136.08515 | C4: -78.961943 | D4: -108.12842 | E4: -139.63505 | F4: -31.334551 | G4: -69.10429 | H4: -110.56408 | I4: -145.86452 | J4: -34.165761 | K4: -70.122326 | L4: -105.63809 | M4: -144.11926 | N4: -37.420421 | O4: -75.354043
A5: Administrative, marketing and selling expenses | B5: -108.12485 | C5: -59.152889 | D5: -79.602924 | E5: -115.29811 | F5: -28.487093 | G5: -56.969784 | H5: -88.377712 | I5: -130.95791 | J5: -30.456847 | K5: -65.173595 | L5: -91.610392 | M5: -130.081 | N5: -37.877638 | O5: -77.460163
A6: Depreciation of tangible assets | B6: -42.745142 | C6: -24.99628 | D6: -35.383031 | E6: -47.380285 | F6: -12.244525 | G6: -25.455559 | H6: -35.691787 | I6: -48.614609 | J6: -12.306473 | K6: -24.258382 | L6: -37.452292 | M6: -50.741037 | N6: -15.027019 | O6: -29.743913
A7: Amortization of intangible assets | B7: -11.955373 | C7: -6.823502 | D7: -10.996609 | E7: -15.925177 | F7: -5.009905 | G7: -10.314476 | H7: -15.437099 | I7: -20.609792 | J7: -4.898694 | K7: -10.004124 | L7: -15.155486 | M7: -19.385894 | N7: -4.784049 | O7: -9.579371
A8: (Provision)/write-back for expected credit losses on trade receivables | B8: 0 | C8: 0 | D8: 0 | E8: 0 | F8: 0 | G8: 0 | H8: 0 | I8: 0 | J8: 0.039965 | K8: 0 | L8: 0 | M8: 0 | N8: -0.115606 | O8: 0
A9: Write-back/(provision) for expected credit losses on trade receivables | B9: -1.660354 | C9: -0.02281 | D9: -0.031318 | E9: 1.024685 | F9: -0.008613 | G9: -0.082283 | H9: -0.537341 | I9: -0.904712 | J9: 0 | K9: 0.034141 | L9: -0.001079 | M9: -0.605485 | N9: 0 | O9: 0.42104
A10: Provision for expected credit losses on balances due from related parties | B10: -0.390413 | C10: 0 | D10: 0 | E10: 0 | F10: 0 | G10: 0 | H10: -0.12936 | I10: -0.12936 | J10: 0 | K10: -0.038687 | L10: -0.052032 | M10: -0.065328 | N10: -0.338567 | O10: -0.405935
A11: Receivables written off | B11: 0 | C11: 0 | D11: 0 | E11: 0 | F11: 0 | G11: 0 | H11: 0 | I11: -0.072471 | J11: 0 | K11: 0 | L11: 0 | M11: -0.06976 | N11: 0 | O11: -0.015132
A12: Other gain/(loss), net | B12: 8.760054 | C12: -0.58548 | D12: 0.063861 | E12: 12.047365 | F12: 0.289148 | G12: -0.413988 | H12: 1.374868 | I12: 1.444997 | J12: 0.095351 | K12: -0.085878 | L12: 1.052799 | M12: 4.922003 | N12: -0.272845 | O12: 0.81925
A13: OPERATING PROFIT | B13: =SUM(B3:B7)+SUM(B9:B10)+B12 -> 15.907529 | C13: =SUM(C3:C7)+C9+C12 -> 22.374611 | D13: =SUM(D3:D7)+SUM(D9:D10)+D12 -> 30.012577 | E13: =SUM(E3:E7)+SUM(E9:E12) -> 51.030502 | F13: =SUM(F3:F7)+F9+F12 -> 9.009009 | G13: =SUM(G3:G7)+G9+G12 -> 12.260034 | H13: =SUM(H3:H7)+SUM(H9:H10)+H12 -> 13.294664 | I13: =SUM(I3:I7)+SUM(I9:I12) -> 10.285312 | J13: =SUM(J3:J8)+J10+J12 -> 11.805854 | K13: =SUM(K3:K7)+SUM(K9:K12) -> 24.159237 | L13: =SUM(L3:L7)+SUM(L9:L10)+L12 -> 51.707597 | M13: =SUM(M3:M7)+SUM(M9:M12) -> 68.503009 | N13: =SUM(N3:N8)+N10+N12 -> 18.505385 | O13: =SUM(O3:O7)+SUM(O9:O12) -> 39.51282
A14: Interest income on balances due from related parties | B14: 1.932958 | C14: 0 | D14: 0 | E14: 2.126254 | F14: 0 | G14: 0 | H14: 0 | I14: 2.33888 | J14: 0 | K14: 0 | L14: 0 | M14: 2.572767 | N14: 0 | O14: 0
A15: Interest income on balances due from a related party | B15: 0 | C15: 1.063127 | D15: 1.594691 | E15: 0 | F15: 0.58472 | G15: 1.16944 | H15: 1.75416 | I15: 0 | J15: 0.643189 | K15: 1.286384 | L15: 1.929576 | M15: 0 | N15: 0.707511 | O15: 1.415022
A16: Other interest income | B16: 0.187722 | C16: 0.076418 | D16: 0.115142 | E16: 0.156096 | F16: 0.040809 | G16: 0.079141 | H16: 0.116258 | I16: 0.329062 | J16: 0.109547 | K16: 0.157281 | L16: 0.23018 | M16: 0.269998 | N16: 0.236924 | O16: 0.388668
A17: Finance costs, net | B17: -55.213244 | C17: -34.55915 | D17: -48.250221 | E17: -64.737849 | F17: -15.328047 | G17: -30.738515 | H17: -46.371001 | I17: -74.276529 | J17: -17.043553 | K17: -34.228359 | L17: -51.969835 | M17: -71.039195 | N17: -20.252271 | O17: -40.973293
A18: Loss on exchange, net | B18: -24.108535 | C18: -85.59763 | D18: -83.482307 | E18: -114.15174 | F18: -12.388792 | G18: -23.156639 | H18: -33.511939 | I18: -39.271284 | J18: -5.577573 | K18: -13.178134 | L18: 2.205623 | M18: 37.680522 | N18: -13.410153 | O18: -17.192096
A19: Net (loss)/gain on net monetary position | B19: 0 | C19: 32.365867 | D19: 29.299361 | E19: 21.543365 | F19: 3.717688 | G19: 3.972137 | H19: 2.705382 | I19: 3.558212 | J19: -0.211588 | K19: -0.228901 | L19: 0.411899 | M19: -1.599516 | N19: 2.791561 | O19: 2.790434
A20: LOSS BEFORE INCOME TAX FROM CONTINUING OPERATIONS | B20: =SUM(B13:B14)+SUM(B16:B18) -> -61.29357 | C20: =C13+SUM(C15:C19) -> -64.276757 | D20: =D13+SUM(D15:D19) -> -70.710757 | E20: =SUM(E13:E14)+SUM(E16:E19) -> -104.03337 | F20: =F13+SUM(F15:F19) -> -14.364613 | G20: =G13+SUM(G15:G19) -> -36.414402 | H20: =H13+SUM(H15:H19) -> -62.012476 | I20: =SUM(I13:I14)+SUM(I16:I19) -> -97.036347 | J20: =J13+SUM(J15:J19) -> -10.274124 | K20: =K13+SUM(K15:K19) -> -22.032492 | L20: =L13+SUM(L15:L19) -> 4.51504 | M20: =SUM(M13:M14)+SUM(M16:M19) -> 36.387585 | N20: =N13+SUM(N15:N19) -> -11.421043 | O20: =O13+SUM(O15:O19) -> -14.058445
A21: Income tax expense | B21: -0.891378 | C21: -9.121694 | D21: -5.585653 | E21: -11.454357 | F21: -1.168225 | G21: -2.32785 | H21: -4.216439 | I21: -6.737506 | J21: -0.619647 | K21: -1.342208 | L21: -4.323168 | M21: -6.007564 | N21: -2.331424 | O21: -5.272631
A22: LOSS FOR THE PERIOD FROM CONTINUING OPERATIONS | B22: =SUM(B20:B21) -> -62.184948 | C22: =SUM(C20:C21) -> -73.398451 | D22: =SUM(D20:D21) -> -76.29641 | E22: =SUM(E20:E21) -> -115.48772 | F22: =SUM(F20:F21) -> -15.532838 | G22: =SUM(G20:G21) -> -38.742252 | H22: =SUM(H20:H21) -> -66.228915 | I22: =SUM(I20:I21) -> -103.77385 | ... O22: =SUM(O20:O21) -> -19.331076
A23: Profit/(loss) for the period from discontinued operations | B23: 0.397799 | C23: 0.009423 | D23: -0.011377 | E23: 0.001763 | F23: -0.026877 | G23: 0.002769 | H23: 0.006616 | I23: 0.042832 | J23: 0.00869 | K23: 0.035052 | L23: -0.004291 | M23: 0.042544 | N23: -0.005043 | O23: -0.003993
A24: LOSS FOR THE PERIOD | B24: =SUM(B22:B23) -> -61.787149 | C24: =SUM(C22:C23) -> -73.389028 | D24: =SUM(D22:D23) -> -76.307787 | E24: =SUM(E22:E23) -> -115.48596 | F24: =SUM(F22:F23) -> -15.559715 | G24: =SUM(G22:G23) -> -38.739483 | H24: =SUM(H22:H23) -> -66.222299 | I24: =SUM(I22:I23) -> -103.73102 | ... O24: =SUM(O22:O23) -> -19.335069
A25: Equity holders of the Company | B25: -61.744696 | C25: -73.402102 | D25: -76.296464 | E25: -115.46815 | F25: -15.532933 | G25: -38.759501 | H25: -66.247054 | I25: -103.75874 | J25: -10.890588 | K25: -23.364178 | L25: 0.133688 | M25: 30.417809 | N25: -13.714641 | O25: -19.311951
A26: Non-controlling interests | B26: -0.042453 | C26: 0.013074 | D26: -0.011323 | E26: -0.017809 | F26: -0.026782 | G26: 0.020018 | H26: 0.024755 | I26: 0.027721 | J26: 0.005507 | K26: 0.02453 | L26: 0.053893 | M26: 0.004756 | N26: -0.042869 | O26: -0.023118
A27: Exchange differences on translation of foreign operations | B27: -1.064477 | C27: 12.103516 | D27: 53.354432 | E27: 52.549161 | F27: 8.750888 | G27: 11.445183 | H27: 9.983109 | I27: 10.984271 | J27: 0.736417 | K27: 0.65664 | L27: -7.645959 | M27: -21.059859 | N27: 9.290292 | O27: 8.47433
A28: Defined benefit plan actuarial gain | B28: -0.048464 | C28: 0 | D28: 0 | E28: 0.016915 | F28: 0 | G28: 0 | H28: 0 | I28: 0.078297 | J28: 0 | K28: 0 | L28: 0 | M28: 0.73497 | N28: 0 | O28: 0
A29: Total other comprehensive (loss)/gain | B29: =SUM(B27:B28) -> -1.112941 | C29: =C27 -> 12.103516 | D29: =D27 -> 53.354432 | E29: =SUM(E27:E28) -> 52.566076 | F29: =F27 -> 8.750888 | G29: =G27 -> 11.445183 | H29: =H27 -> 9.983109 | I29: =SUM(I27:I28) -> 11.062568 | J29: =J27 -> 0.736417 | K29: =K27 -> 0.65664 | L29: =L27 -> -7.645959 | M29: =SUM(M27:M28) -> -20.324889 | N29: =N27 -> 9.290292 | O29: =O27 -> 8.47433
A30: TOTAL COMPREHENSIVE LOSS FOR THE PERIOD | B30: =B24+B29 -> -62.90009 | C30: =C24+C29 -> -61.285512 | D30: =D24+D29 -> -22.953355 | E30: =E24+E29 -> -62.919886 | F30: =F24+F29 -> -6.808827 | G30: =G24+G29 -> -27.2943 | H30: =H24+H29 -> -56.23919 | I30: =I24+I29 -> -92.668453 | ... O30: =O24+O29 -> -10.860739
A31: Equity holders of the Company | B31: -63.024558 | C31: -61.252766 | D31: -22.980869 | E31: -62.963777 | F31: -6.873388 | G31: -27.244685 | H31: -56.178405 | I31: -92.602016 | J31: -10.135332 | K31: -22.622754 | L31: -7.320457 | M31: 10.148129 | N31: -4.556704 | O31: -10.877079
A32: Non-controlling interests | B32: 0.124468 | C32: -0.032746 | D32: 0.027514 | E32: 0.043891 | F32: 0.064561 | G32: -0.049615 | H32: -0.060785 | I32: -0.066437 | J32: -0.013332 | K32: -0.060254 | L32: -0.137921 | M32: -0.050453 | N32: 0.089486 | O32: 0.01634
A34: Cash Flow Statement
A35: Loss before income tax from continuing operations | B35: -61.29357 | C35: -64.276757 | D35: -70.710757 | E35: -104.03337 | F35: -14.364613 | G35: -36.414402 | H35: -62.012476 | I35: -97.036347 | J35: -10.274124 | K35: -22.032492 | L35: 4.51504 | M35: 36.387585 | N35: -11.421043 | O35: -14.058445
A36: Profit/(loss) from discontinued operations | B36: 0.397799 | C36: 0.009423 | D36: -0.011377 | E36: 0.001763 | F36: -0.026877 | G36: 0.002769 | H36: 0.006616 | I36: 0.042832 | J36: 0.00869 | K36: 0.035052 | L36: -0.004291 | M36: 0.042544 | N36: -0.005043 | O36: -0.003993
A37: Depreciation on tangible assets | B37: 42.745142 | C37: 24.99628 | D37: 35.383031 | E37: 47.380285 | F37: 12.244525 | G37: 25.455559 | H37: 35.691787 | I37: 48.614609 | J37: 12.306473 | K37: 24.258382 | L37: 37.452292 | M37: 50.741037 | N37: 15.027019 | O37: 29.743913
A38: Amortization of intangible assets | B38: 11.955373 | C38: 6.823502 | D38: 10.996609 | E38: 15.925177 | F38: 5.009905 | G38: 10.314476 | H38: 15.437099 | I38: 20.609792 | J38: 4.898694 | K38: 10.004124 | L38: 15.155486 | M38: 19.385894 | N38: 4.784049 | O38: 9.579371
A39: (Write-back) Provision for expected credit losses on trade receivables | B39: 0 | C39: 0 | D39: 0 | E39: 0 | F39: 0 | G39: 0.082283 | H39: 0 | I39: 0 | J39: 0 | K39: 0 | L39: 0 | M39: 0 | N39: 0 | O39: 0
A40: Provision for expected credit losses on trade receivables | B40: 1.070047 | C40: 0.02281 | D40: 0.031318 | E40: -1.024685 | F40: 0.010468 | G40: 0 | H40: 0.537341 | I40: 0.849054 | J40: -0.039965 | K40: 0 | L40: 0.001079 | M40: 0.615199 | N40: 0.115606 | O40: 0
A41: Re-measurement gain on long-term liability | B41: 0 | C41: 0 | D41: 0 | E41: 0 | F41: 0 | G41: 0 | H41: 0 | I41: -0.195467 | J41: 0 | K41: 0 | L41: 0 | M41: 0 | N41: 0 | O41: 0
A42: Write-back for expected credit losses on trade receivables, net | B42: 0 | C42: 0 | D42: 0 | E42: 0 | F42: 0 | G42: 0 | H42: 0 | I42: 0 | J42: 0 | K42: -0.034141 | L42: 0 | M42: 0 | N42: 0 | O42: -0.42104
A43: (Write-back) Provision for expected credit losses on bank balances | B43: 0 | C43: 0 | D43: 0 | E43: 0 | F43: 0 | G43: 0 | H43: 0 | I43: 0 | J43: 0 | K43: 0.058709 | L43: 0 | M43: 0 | N43: 0 | O43: 0.154854
A44: Provision for expected credit losses on balance due from a related party | B44: 0.390413 | C44: 0 | D44: 0 | E44: 0 | F44: 0 | G44: 0 | H44: 0.12936 | I44: 0.12936 | J44: 0.02539 | K44: 0.038687 | L44: 0.052032 | M44: 0.065328 | N44: 0.338567 | O44: 0.405935
A45: Provision (Write-back) for expected credit losses on bank balances | B45: 0 | C45: 0 | D45: 0 | E45: 0 | F45: 0 | G45: 0 | H45: -0.033497 | I45: 0 | J45: 0 | K45: 0 | L45: 0.031576 | M45: 0 | N45: 0 | O45: 0
A46: Provision for/(write-back of) expected credit losses on bank balances | B46: 0 | C46: 0 | D46: 0 | E46: 0 | F46: 0 | G46: 0 | H46: 0 | I46: -0.000452 | J46: 0 | K46: 0 | L46: 0 | M46: 0.090045 | N46: 0 | O46: 0
... A77: Provisions paid | B77: -0.332177 | C77: -0.129161 | D77: -0.140074 | E77: -2.195829 | F77: -0.182869 | G77: -0.263047 | H77: -0.303499 | I77: -0.403325 | J77: -0.074396 | K77: -0.928917 | L77: -0.98462 | M77: -1.099098 | N77: -0.217241 | O77: -0.24329
A78: Net cash from operating activities | B78: =SUM(B35:B38)+B40+B44+SUM(B47:B48)+SUM(B51:B59)+SUM(B61:B62)+B66+SUM(B68:B69)+SUM(B73:B74)+SUM(B76:B77) -> 112.52626 | C78: =SUM(C35:C38)+C40+C48+SUM(C51:C59)+SUM(C61:C62)+C66+SUM(C68:C69)+C73+SUM(C76:C77) -> 50.031232 | D78: =SUM(D35:D38)+D40+D44+SUM(D47:D48)+SUM(D51:D59)+SUM(D61:D62)+D66+SUM(D68:D69)+D73+SUM(D76:D77) -> 114.54056 | E78: =SUM(E35:E38)+SUM(E40:E41)+E44+SUM(E47:E48)+SUM(E51:E59)+SUM(E61:E62)+E66+SUM(E68:E70)+SUM(E73:E74)+SUM(E76:E77) -> 132.14775 | F78: =SUM(F35:F38)+F40+F44+SUM(F47:F48)+SUM(F51:F59)+SUM(F61:F62)+F66+SUM(F68:F69)+SUM(F73:F74)+SUM(F76:F77) -> 15.954574 | G78: =SUM(G35:G39)+G44+SUM(G47:G48)+SUM(G51:G59)+SUM(G61:G62)+G66+SUM(G68:G70)+SUM(G73:G74)+SUM(G76:G77) -> 17.193589 | H78: =SUM(H35:H38)+H40+SUM(H44:H45)+H48+H50+SUM(H52:H59)+SUM(H61:H62)+SUM(H66:H68)+SUM(H73:H74)+SUM(H76:H77) -> 53.804913 | I78: =SUM(I35:I38)+SUM(I40:I41)+I44+I46+SUM(I48:I49)+SUM(I52:I59)+I61+I63+I65+SUM(I69:I74)+SUM(I76:I77) -> 39.726265 | J78: =SUM(J35:J38)+J40+J44+SUM(J47:J48)+J50+SUM(J52:J59)+J61+J63+J66+SUM(J69:J74)+SUM(J76:J77) -> -10.724834 | K78: =SUM(K35:K38)+SUM(K42:K44)+K48+SUM(K51:K58)+SUM(K60:K61)+K63+K66+SUM(K69:K74)+SUM(K76:K77) -> 18.715589 | L78: =SUM(L35:L38)+L40+SUM(L44:L45)+L48+L50+SUM(L52:L59)+SUM(L61:L62)+SUM(L66:L68)+SUM(L73:L74)+SUM(L76:L77) -> 46.296982 | M78: =SUM(M35:M38)+SUM(M40:M41)+M44+M46+SUM(M48:M49)+SUM(M52:M59)+M61+SUM(M63:M64)+SUM(M69:M74)+SUM(M76:M77) -> 48.87244 | N78: =SUM(N35:N38)+N40+N44+SUM(N47:N48)+N50+SUM(N52:N59)+N61+N63+N66+SUM(N69:N74)+SUM(N76:N77) -> -14.745499 | O78: =SUM(O35:O38)+SUM(O42:O44)+O48+SUM(O51:O58)+SUM(O60:O61)+O63+O66+SUM(O69:O74)+SUM(O76:O77) -> 13.985393
A79: Acquisition of property, equipment and intangible assets | B79: -84.254415 | C79: -18.713049 | D79: -48.183132 | E79: -74.376186 | F79: -7.297599 | G79: -15.270423 | H79: -24.44083 | I79: -29.126253 | J79: -3.520287 | K79: -20.962896 | L79: -30.106639 | M79: -47.541704 | N79: -11.909148 | O79: -33.164847
A80: Acquisition of intangible assets | B80: -15.165416 | C80: -5.978468 | D80: -8.923105 | E80: -24.361971 | F80: -4.986627 | G80: -3.693159 | H80: -7.587129 | I80: -20.599286 | J80: -0.923889 | K80: 0 | L80: -4.474933 | M80: -8.286235 | N80: -3.41435 | O80: 0
A81: Due from related parties | B81: -0.406392 | C81: 0 | D81: 0 | E81: -0.009795 | F81: 0 | G81: 0 | H81: 0 | I81: 0 | J81: 0 | K81: 0 | L81: 0 | M81: 0 | N81: 0 | O81: 0
A82: Payment for telecom license | B82: 0 | C82: 0 | D82: 0 | E82: 0 | F82: 0 | G82: 0 | H82: 0 | I82: 0 | J82: 0 | K82: 0 | L82: 0 | M82: -5.02211 | N82: 0 | O82: 0
A83: Advances to suppliers | B83: 0 | C83: 0 | D83: 0 | E83: 0 | F83: 0 | G83: 0 | H83: 0 | I83: 0 | J83: 0 | K83: -0.108169 | L83: 0 | M83: 0 | N83: 0 | O83: -12.628882
A84: Proceeds from disposal of property and equipment | B84: 10.346399 | C84: 0.039132 | D84: 0.024738 | E84: 0.037732 | F84: 0.074162 | G84: 0.048172 | H84: 0.074425 | I84: 0.06133 | J84: 0.016625 | K84: 0.153704 | L84: 0.196632 | M84: 0.253132 | N84: 0 | O84: 0
A85: Due from a related party | B85: 0 | C85: -0.229378 | D85: -0.100571 | E85: 0 | F85: 0 | G85: 0 | H85: 0 | I85: 0 | J85: 0 | K85: 0 | L85: 0 | M85: 0 | N85: 0 | O85: 0
A86: Movement in term deposits | B86: 0.132403 | C86: -0.058114 | D86: 0.007995 | E86: -0.025433 | F86: 0.019769 | G86: -0.015221 | H86: -0.018667 | I86: 0.747273 | J86: 0 | K86: 0 | L86: 0 | M86: -0.110069 | N86: 0.110067 | O86: 0.003882
A87: Net cash used in investing activities | B87: =SUM(B79:B81)+B84+B86 -> -89.347421 | C87: =SUM(C79:C80)+SUM(C84:C86) -> -24.939877 | D87: =SUM(D79:D80)+SUM(D84:D86) -> -57.174075 | E87: =SUM(E79:E81)+E84+E86 -> -98.735653 | F87: =SUM(F79:F80)+SUM(F84:F86) -> -12.190295 | G87: =SUM(G79:G80)+G84+G86 -> -18.930631 | H87: =SUM(H79:H80)+H84+H86 -> -31.972201 | I87: =SUM(I79:I80)+I82+I84+I86 -> -48.916936 | J87: =SUM(J79:J80)+J84+J86 -> -4.427551 | K87: =K79+SUM(K83:K84)+K86 -> -20.917361 | L87: =SUM(L79:L80)+L84+L86 -> -34.38494 | M87: =SUM(M79:M80)+M82+M84+M86 -> -60.706986 | N87: =SUM(N79:N80)+N84+N86 -> -15.213431 | O87: =O79+SUM(O83:O84)+O86 -> -45.789847
A88: Term loans proceeds | B88: 10.230431 | C88: 10 | D88: 0.165332 | E88: 43.919974 | F88: 0 | G88: 0.663423 | H88: 0.664384 | I88: 0.674215 | J88: 0 | K88: 0 | L88: 3.734815 | M88: 17.005817 | N88: 3.375991 | O88: 5.456
A89: Terms loans payments | B89: -37.974252 | C89: -8.536051 | D89: -6.961209 | E89: -47.519074 | F89: -9.946342 | G89: -10.536702 | H89: -28.556928 | I89: -253.91816 | J89: -1.213323 | K89: -1.531726 | L89: -2.766428 | M89: -6.611861 | N89: -2.060207 | O89: -4.475453
A90: Lease liabilities paid | B90: -25.358133 | C90: 0 | D90: -0.213037 | E90: -22.91447 | F90: -7.524722 | G90: -10.441665 | H90: -16.479357 | I90: -23.943408 | J90: -7.053757 | K90: -13.869737 | L90: -13.869687 | M90: -31.839486 | N90: -13.470987 | O90: -20.612209
A91: Interest paid | B91: 0 | C91: -29.575639 | D91: -42.589607 | E91: 0 | F91: 0 | G91: 0 | H91: 0 | I91: 0 | J91: 0 | K91: 0 | L91: 0 | M91: 0 | N91: 0 | O91: 0
A92: Restricted bank balances | B92: -6.559526 | C92: -0.071705 | D92: -0.107729 | E92: -0.143868 | F92: 2.490096 | G92: 9.96665 | H92: -0.106646 | I92: 0 | J92: 0 | K92: 0 | L92: -16.006192 | M92: 0 | N92: 0 | O92: 0
A93: Proceeds from bond issued | B93: 0 | C93: 0 | D93: 0 | E93: 0 | F93: 0 | G93: 0 | H93: 0 | I93: 300 | J93: 0 | K93: 0 | L93: 0 | M93: 0 | N93: 56.796935 | O93: 56.796935
A94: Net cash (used in)/from financing activities | B94: =SUM(B88:B90)+B92 -> -59.66148 | C94: =SUM(C88:C92) -> -28.183395 | D94: =SUM(D88:D92) -> -49.70625 | E94: =SUM(E88:E90)+SUM(E92:E93) -> -26.657438 | F94: =SUM(F88:F92) -> -14.980968 | G94: =SUM(G88:G90)+G92 -> -10.348294 | H94: =SUM(H88:H90)+H92 -> -44.478547 | I94: =SUM(I88:I90)+I93 -> 22.812648 | J94: =SUM(J88:J90)+J93 -> -8.26708 | K94: =SUM(K88:K90)+K93 -> -15.401463 | L94: =SUM(L88:L90)+L92 -> -28.907492 | M94: =SUM(M88:M90)+M93 -> -21.44553 | N94: =SUM(N88:N90)+N93 -> 44.641732 | O94: =SUM(O88:O90)+O93 -> 37.165273
A95: (DECREASE) / INCREASE IN CASH AND CASH EQUIVALENTS | B95: =B78+B87+B94 -> -36.482641 | C95: =C78+C87+C94 -> -3.09204 | D95: =D78+D87+D94 -> 7.660234 | E95: =E78+E87+E94 -> 6.754658 | F95: =F78+F87+F94 -> -11.216689 | G95: =G78+G87+G94 -> -12.085336 | H95: =H78+H87+H94 -> -22.645835 | I95: =I78+I87+I94 -> 13.621977 | ... O95: =O78+O87+O94 -> 5.360819
A96: Effects of exchange rate changes | B96: -0.432477 | C96: -6.316553 | D96: -8.567862 | E96: -0.533686 | F96: 0.19168 | G96: 1.635894 | H96: -2.719599 | I96: 7.427334 | J96: -1.470098 | K96: -2.225359 | L96: -5.192213 | M96: 9.581113 | N96: 5.460782 | O96: -2.446326
A97: Cash and cash equivalents at beginning of the period | B97: 23.60309 | C97: =E97 -> -13.312028 | D97: =E97 -> -13.312028 | E97: -13.312028 | F97: =I97 -> -7.091056 | G97: =I97 -> -7.091056 | H97: =I97 -> -7.091056 | I97: -7.091056 | J97: =K97 -> 13.958255 | K97: 13.958255 | L97: =K97 -> 13.958255 | M97: =K97 -> 13.958255 | N97: =O97 -> -9.740708 | O97: -9.740708
A98: CASH AND CASH EQUIVALENTS AT 30 JUNE | B98: =SUM(B95:B97) -> -13.312028 | C98: =SUM(C95:C97) -> -22.720621 | D98: =SUM(D95:D97) -> -14.219656 | E98: =SUM(E95:E97) -> -7.091056 | F98: =SUM(F95:F97) -> -18.116065 | G98: =SUM(G95:G97) -> -17.540498 | H98: -29.034284 | I98: =SUM(I95:I97) -> 13.958255 | J98: =SUM(J95:J97) -> -10.931308 | K98: =SUM(K95:K97) -> -5.870339 | L98: =SUM(L95:L97) -> -8.229408 | M98: =SUM(M95:M97) -> -9.740708 | N98: =SUM(N95:N97) -> 10.402876 | O98: =SUM(O95:O97) -> -6.826215
A100: Balance Sheet
A101: Goodwill | B101: 12.743364 | E101: 58.270178 | G101: ='Annual and Quarterly'!J101 -> 63.306458 | H101: ='Annual and Quarterly'!K101 -> 64.783184 | I101: 65.66836 | J101: 66.264948 | K101: ='Annual and Quarterly'!N101 -> 66.830334 | L101: ='Annual and Quarterly'!O101 -> 67.986917 | M101: 68.02026 | N101: 72.295538 | O101: ='Annual and Quarterly'!R101 -> 72.283156
A102: Intangible assets | B102: 72.676461 | E102: 77.898462 | G102: ='Annual and Quarterly'!J102 -> 71.26127 | H102: ='Annual and Quarterly'!K102 -> 69.320984 | I102: 79.281757 | J102: 75.418243 | K102: ='Annual and Quarterly'!N102 -> 68.46526 | L102: ='Annual and Quarterly'!O102 -> 71.981934 | M102: 75.923436 | N102: 75.683398 | O102: ='Annual and Quarterly'!R102 -> 78.219311
A103: Property and equipment | B103: 199.42993 | E103: 198.45436 | G103: ='Annual and Quarterly'!J103 -> 198.15654 | H103: ='Annual and Quarterly'!K103 -> 186.79259 | I103: 188.23099 | J103: 180.14423 | K103: ='Annual and Quarterly'!N103 -> 184.9803 | L103: ='Annual and Quarterly'!O103 -> 192.22994 | M103: 204.12869 | N103: 207.12029 | O103: ='Annual and Quarterly'!R103 -> 213.70598
A104: Right-of-use assets | B104: 173.52727 | E104: 121.17346 | G104: ='Annual and Quarterly'!J104 -> 109.79669 | H104: ='Annual and Quarterly'!K104 -> 104.47486 | I104: 96.64911 | J104: 94.715846 | K104: ='Annual and Quarterly'!N104 -> 91.785329 | L104: ='Annual and Quarterly'!O104 -> 95.712509 | M104: 106.55989 | N104: 99.809927 | O104: ='Annual and Quarterly'!R104 -> 97.262678
A105: Deferred tax assets | B105: 9.248969 | E105: 4.153279 | G105: ='Annual and Quarterly'!J105 -> 4.507584 | H105: ='Annual and Quarterly'!K105 -> 4.280837 | I105: 10.29944 | J105: 10.324458 | K105: ='Annual and Quarterly'!N105 -> 10.344395 | L105: ='Annual and Quarterly'!O105 -> 9.240384 | M105: 10.043497 | N105: 10.295438 | O105: ='Annual and Quarterly'!R105 -> 10.267833
A106: Due from related parties | B106: 20.862334 | E106: 22.998383 | G106: ='Annual and Quarterly'!J106 -> 24.167823 | H106: ='Annual and Quarterly'!K106 -> 24.623183 | I106: 25.578011 | J106: 26.626797 | K106: ='Annual and Quarterly'!N106 -> 27.695011 | L106: ='Annual and Quarterly'!O106 -> 29.792436 | M106: 39.916191 | N106: 43.885995 | O106: ='Annual and Quarterly'!R106 -> 47.819387
A107: Advances to suppliers | B107: 0 | E107: 4.674381 | G107: ='Annual and Quarterly'!J107 -> 0 | H107: ='Annual and Quarterly'!K107 -> 0 | I107: 1.466235 | J107: 3.745293 | K107: ='Annual and Quarterly'!N107 -> 1.574404 | L107: ='Annual and Quarterly'!O107 -> 0.525107 | M107: 0.394769 | N107: 8.870091 | O107: ='Annual and Quarterly'!R107 -> 13.023651
A108: Non-current assets | B108: =SUM(B101:B106) -> 488.48832 | E108: =SUM(E101:E107) -> 487.6225 | G108: ='Annual and Quarterly'!J108 -> 471.19636 | H108: ='Annual and Quarterly'!K108 -> 454.27563 | I108: =SUM(I101:I107) -> 467.1739 | J108: =SUM(J101:J107) -> 457.23981 | K108: ='Annual and Quarterly'!N108 -> 451.67504 | L108: ='Annual and Quarterly'!O108 -> 467.46923 | M108: =SUM(M101:M107) -> 504.98673 | N108: =SUM(N101:N107) -> 517.96068 | O108: ='Annual and Quarterly'!R108 -> 532.582
A109: Due from related parties | B109: 21.730404 | E109: 0 | G109: ='Annual and Quarterly'!J109 -> 0 | H109: ='Annual and Quarterly'!K109 -> 0 | I109: 0 | J109: 0 | K109: ='Annual and Quarterly'!N109 -> 0 | L109: ='Annual and Quarterly'!O109 -> 0 | M109: 0 | N109: 0 | O109: ='Annual and Quarterly'!R109 -> 0
A110: Due from a related party | B110: 0 | E110: 0 | G110: ='Annual and Quarterly'!J110 -> 0.356293 | H110: ='Annual and Quarterly'!K110 -> 0.356297 | I110: 0 | J110: 0 | K110: ='Annual and Quarterly'!N110 -> 0 | L110: ='Annual and Quarterly'!O110 -> 0 | M110: 0 | N110: 0 | O110: ='Annual and Quarterly'!R110 -> 0
A111: Inventories | B111: 5.008999 | E111: 8.711839 | G111: ='Annual and Quarterly'!J111 -> 5.092315 | H111: ='Annual and Quarterly'!K111 -> 3.945797 | I111: 3.994316 | J111: 3.007941 | K111: ='Annual and Quarterly'!N111 -> 3.296766 | L111: ='Annual and Quarterly'!O111 -> 3.378874 | M111: 2.721913 | N111: 3.109391 | O111: ='Annual and Quarterly'!R111 -> 3.273109
A112: Prepayments and other debit balances | B112: 26.504855 | E112: 31.520558 | G112: ='Annual and Quarterly'!J112 -> 41.001499 | H112: ='Annual and Quarterly'!K112 -> 34.710443 | I112: 44.909836 | J112: 57.255092 | K112: ='Annual and Quarterly'!N112 -> 52.064241 | L112: ='Annual and Quarterly'!O112 -> 48.600933 | M112: 36.072733 | N112: 35.985972 | O112: ='Annual and Quarterly'!R112 -> 42.110862
A113: Contract assets | B113: 1.849877 | E113: 1.732034 | G113: ='Annual and Quarterly'!J113 -> 2.565419 | H113: ='Annual and Quarterly'!K113 -> 2.361934 | I113: 1.372195 | J113: 1.275084 | K113: ='Annual and Quarterly'!N113 -> 1.220784 | L113: ='Annual and Quarterly'!O113 -> 2.2552 | M113: 1.551668 | N113: 1.749126 | O113: ='Annual and Quarterly'!R113 -> 1.515745
A114: Trade receivables | B114: 9.130196 | E114: 11.172111 | G114: ='Annual and Quarterly'!J114 -> 12.31978 | H114: ='Annual and Quarterly'!K114 -> 11.007746 | I114: 12.244475 | J114: 11.851068 | K114: ='Annual and Quarterly'!N114 -> 13.665945 | L114: ='Annual and Quarterly'!O114 -> 14.832315 | M114: 13.280304 | N114: 14.24382 | O114: ='Annual and Quarterly'!R114 -> 11.655281
A115: Bank balances and cash | B115: 24.929057 | E115: 33.308627 | G115: ='Annual and Quarterly'!J115 -> 23.241426 | H115: ='Annual and Quarterly'!K115 -> 16.538026 | I115: 44.057919 | J115: 38.454304 | K115: ='Annual and Quarterly'!N115 -> 26.67968 | L115: ='Annual and Quarterly'!O115 -> 38.970909 | M115: 24.969687 | N115: 66.672997 | O115: ='Annual and Quarterly'!R115 -> 35.369198
A116: Current assets | B116: =B109+SUM(B111:B115) -> 89.153388 | E116: =SUM(E111:E115) -> 86.445169 | G116: ='Annual and Quarterly'!J116 -> 84.576732 | H116: ='Annual and Quarterly'!K116 -> 68.920243 | I116: =SUM(I111:I115) -> 106.57874 | J116: =SUM(J111:J115) -> 111.84349 | K116: ='Annual and Quarterly'!N116 -> 96.927416 | L116: ='Annual and Quarterly'!O116 -> 108.03823 | M116: =SUM(M111:M115) -> 78.596305 | N116: =SUM(N111:N115) -> 121.76131 | O116: ='Annual and Quarterly'!R116 -> 93.924195
A117: TOTAL ASSETS | B117: =B108+B116 -> 577.64171 | E117: =E108+E116 -> 574.06767 | G117: ='Annual and Quarterly'!J117 -> 555.77309 | H117: ='Annual and Quarterly'!K117 -> 523.19587 | I117: =I108+I116 -> 573.75265 | J117: =J108+J116 -> 569.0833 | K117: ='Annual and Quarterly'!N117 -> 548.60245 | L117: ='Annual and Quarterly'!O117 -> 575.50746 | M117: =M108+M116 -> 583.58304 | N117: =N108+N116 -> 639.72199 | O117: ='Annual and Quarterly'!R117 -> 626.5062
A118: Share capital | B118: 10 | E118: 10 | G118: ='Annual and Quarterly'!J118 -> 10 | H118: ='Annual and Quarterly'!K118 -> 10 | I118: 10 | J118: 10 | K118: ='Annual and Quarterly'!N118 -> 10 | L118: ='Annual and Quarterly'!O118 -> 10 | M118: 10 | N118: 10 | O118: ='Annual and Quarterly'!R118 -> 10
A119: Other reserve | B119: 1.08499 | E119: 1.101905 | G119: ='Annual and Quarterly'!J119 -> 1.101905 | H119: ='Annual and Quarterly'!K119 -> 1.101905 | I119: 1.180202 | J119: 1.180202 | K119: ='Annual and Quarterly'!N119 -> 1.180202 | L119: ='Annual and Quarterly'!O119 -> 1.180202 | M119: 1.915172 | N119: 1.915172 | O119: ='Annual and Quarterly'!R119 -> 1.915172
A120: Legal reserve | B120: 0.006667 | E120: 0.006667 | G120: ='Annual and Quarterly'!J120 -> 0.006667 | H120: ='Annual and Quarterly'!K120 -> 0.006667 | I120: 0.006667 | J120: 0.006667 | K120: ='Annual and Quarterly'!N120 -> 0.006667 | L120: ='Annual and Quarterly'!O120 -> 0.006667 | M120: 0.006667 | N120: 0.006667 | O120: ='Annual and Quarterly'!R120 -> 0.006667
A121: Foreign currency translation reserve | B121: -104.06557 | E121: -51.578114 | G121: ='Annual and Quarterly'!J121 -> -40.063298 | H121: ='Annual and Quarterly'!K121 -> -41.509465 | I121: -40.499685 | J121: -39.744429 | K121: ='Annual and Quarterly'!N121 -> -39.758261 | L121: ='Annual and Quarterly'!O121 -> -47.95383 | M121: -61.504335 | N121: -52.346398 | O121: ='Annual and Quarterly'!R121 -> -53.069463
A122: Accumulated losses | B122: 47.544593 | E122: -67.92356 | G122: ='Annual and Quarterly'!J122 -> -106.50116 | H122: ='Annual and Quarterly'!K122 -> -134.17061 | I122: -171.6823 | J122: -182.5475 | K122: ='Annual and Quarterly'!N122 -> -195.04648 | L122: ='Annual and Quarterly'!O122 -> -171.54861 | M122: -141.26449 | N122: -154.97913 | O122: ='Annual and Quarterly'!R122 -> -160.57644
A123: Equity attributable to equity holders of the Company | B123: =SUM(B118:B122) -> -45.429325 | E123: =SUM(E118:E122) -> -108.3931 | G123: ='Annual and Quarterly'!J123 -> -135.45588 | H123: ='Annual and Quarterly'!K123 -> -164.57151 | I123: =SUM(I118:I122) -> -200.99512 | J123: =SUM(J118:J122) -> -211.10506 | K123: ='Annual and Quarterly'!N123 -> -223.61787 | L123: ='Annual and Quarterly'!O123 -> -208.31557 | M123: =SUM(M118:M122) -> -190.84699 | N123: =SUM(N118:N122) -> -195.40369 | O123: ='Annual and Quarterly'!R123 -> -201.72407
A124: Non-controlling interests | B124: -3.510631 | E124: -3.46674 | G124: ='Annual and Quarterly'!J124 -> -3.516355 | H124: ='Annual and Quarterly'!K124 -> -3.527525 | I124: -3.533177 | J124: -3.546509 | K124: ='Annual and Quarterly'!N124 -> -3.593431 | L124: ='Annual and Quarterly'!O124 -> -3.671098 | M124: -3.578152 | N124: -3.488666 | O124: ='Annual and Quarterly'!R124 -> -3.561812
A125: Total equity | B125: =SUM(B123:B124) -> -48.939956 | E125: =SUM(E123:E124) -> -111.85984 | G125: ='Annual and Quarterly'!J125 -> -138.97224 | H125: ='Annual and Quarterly'!K125 -> -168.09903 | I125: =SUM(I123:I124) -> -204.5283 | J125: =SUM(J123:J124) -> -214.65157 | K125: ='Annual and Quarterly'!N125 -> -227.2113 | L125: ='Annual and Quarterly'!O125 -> -211.98667 | M125: =SUM(M123:M124) -> -194.42514 | N125: =SUM(N123:N124) -> -198.89236 | O125: ='Annual and Quarterly'!R125 -> -205.28588
A126: Deferred tax liabilities | B126: 2.09078 | E126: 7.207006 | G126: ='Annual and Quarterly'!J126 -> 7.755778 | H126: ='Annual and Quarterly'!K126 -> 7.273408 | I126: 13.00988 | J126: 13.189459 | K126: ='Annual and Quarterly'!N126 -> 12.9446 | L126: ='Annual and Quarterly'!O126 -> 11.421267 | M126: 11.038669 | N126: 11.752926 | O126: ='Annual and Quarterly'!R126 -> 11.712991
A127: Provisions for risks and charges | B127: 12.445668 | E127: 8.455179 | G127: ='Annual and Quarterly'!J127 -> 8.759279 | H127: ='Annual and Quarterly'!K127 -> 8.568663 | I127: 10.869566 | J127: 11.054325 | K127: ='Annual and Quarterly'!N127 -> 10.576061 | L127: ='Annual and Quarterly'!O127 -> 11.455138 | M127: 11.073739 | N127: 11.226006 | O127: ='Annual and Quarterly'!R127 -> 11.629339
A128: Other long-term payables | B128: 14.47218 | E128: 11.435248 | G128: ='Annual and Quarterly'!J128 -> 12.65524 | H128: ='Annual and Quarterly'!K128 -> 8.094857 | I128: 8.936963 | J128: 9.547316 | K128: ='Annual and Quarterly'!N128 -> 10.10654 | L128: ='Annual and Quarterly'!O128 -> 10.784527 | M128: 11.531037 | N128: 12.316782 | O128: ='Annual and Quarterly'!R128 -> 13.156133
A129: Term loans | B129: 0 | E129: 180.97229 | G129: ='Annual and Quarterly'!J129 -> 153.35056 | H129: ='Annual and Quarterly'!K129 -> 138.66943 | I129: 0.86771 | J129: 0.257279 | K129: ='Annual and Quarterly'!N129 -> 0.20275 | L129: ='Annual and Quarterly'!O129 -> 1.027616 | M129: 6.455915 | N129: 7.209799 | O129: ='Annual and Quarterly'!R129 -> 7.46783
A130: Lease liabilities | B130: 181.99711 | E130: 173.51927 | G130: ='Annual and Quarterly'!J130 -> 164.41744 | H130: ='Annual and Quarterly'!K130 -> 158.87668 | I130: 154.20466 | J130: 152.36673 | K130: ='Annual and Quarterly'!N130 -> 152.59541 | L130: ='Annual and Quarterly'!O130 -> 149.1027 | M130: 145.03402 | N130: 141.60042 | O130: ='Annual and Quarterly'!R130 -> 138.5254
A131: Senior Secured Notes | B131: 0 | E131: 0 | G131: ='Annual and Quarterly'!J131 -> 0 | H131: ='Annual and Quarterly'!K131 -> 0 | I131: 300 | J131: 300 | K131: ='Annual and Quarterly'!N131 -> 300 | L131: ='Annual and Quarterly'!O131 -> 300 | M131: 300 | N131: 346.78549 | O131: ='Annual and Quarterly'!R131 -> 347.49142
A132: Long-term debt to a supplier | B132: 0 | E132: 0 | G132: ='Annual and Quarterly'!J132 -> 0 | H132: ='Annual and Quarterly'!K132 -> 0 | I132: 10.080508 | J132: 9.216275 | K132: ='Annual and Quarterly'!N132 -> 8.352044 | L132: ='Annual and Quarterly'!O132 -> 11.050898 | M132: 10.474928 | N132: 10.125607 | O132: ='Annual and Quarterly'!R132 -> 8.360865
...

Sheet Rolling LTM
A1: $mm, Dec year-end | B1: FY22 | C1: 2Q23 | D1: 3Q23 | E1: FY23 | F1: 1Q24 | G1: 2Q24 | H1: 3Q24 | I1: FY24 | J1: 1Q25 | K1: 2Q25 | L1: 3Q25 | M1: FY25 | N1: 1Q26 | O1: 2Q26
A2: Income Statement
A3: Revenues | B3: 308.10876 | E3: 356.19708 | G3: =E3+'Quarterly YTD'!G3-'Quarterly YTD'!C3 -> 337.87998 | H3: =E3+'Quarterly YTD'!H3-'Quarterly YTD'!D3 -> 354.76324 | I3: 355.99368 | J3: =I3+'Quarterly YTD'!J3-'Quarterly YTD'!F3 -> 363.68745 | K3: =I3+'Quarterly YTD'!K3-'Quarterly YTD'!G3 -> 375.20136 | L3: =I3+'Quarterly YTD'!L3-'Quarterly YTD'!H3 -> 393.90068 | M3: 408.64877 | N3: =M3+'Quarterly YTD'!N3-'Quarterly YTD'!J3 -> 429.49199 | O3: =M3+'Quarterly YTD'!O3-'Quarterly YTD'!K3 -> 445.67177
A4: Operating costs and commissions | B4: -136.08515 | E4: -139.63505 | G4: =E4+'Quarterly YTD'!G4-'Quarterly YTD'!C4 -> -129.7774 | H4: =E4+'Quarterly YTD'!H4-'Quarterly YTD'!D4 -> -142.07071 | I4: -145.86452 | J4: =I4+'Quarterly YTD'!J4-'Quarterly YTD'!F4 -> -148.69573 | K4: =I4+'Quarterly YTD'!K4-'Quarterly YTD'!G4 -> -146.88255 | L4: =I4+'Quarterly YTD'!L4-'Quarterly YTD'!H4 -> -140.93853 | M4: -144.11926 | N4: =M4+'Quarterly YTD'!N4-'Quarterly YTD'!J4 -> -147.37392 | O4: =M4+'Quarterly YTD'!O4-'Quarterly YTD'!K4 -> -149.35098
A5: Administrative, marketing and selling expenses | B5: -108.12485 | E5: -115.29811 | G5: =E5+'Quarterly YTD'!G5-'Quarterly YTD'!C5 -> -113.11501 | H5: =E5+'Quarterly YTD'!H5-'Quarterly YTD'!D5 -> -124.0729 | I5: -130.95791 | J5: =I5+'Quarterly YTD'!J5-'Quarterly YTD'!F5 -> -132.92766 | K5: =I5+'Quarterly YTD'!K5-'Quarterly YTD'!G5 -> -139.16172 | L5: =I5+'Quarterly YTD'!L5-'Quarterly YTD'!H5 -> -134.19059 | M5: -130.081 | N5: =M5+'Quarterly YTD'!N5-'Quarterly YTD'!J5 -> -137.50179 | O5: =M5+'Quarterly YTD'!O5-'Quarterly YTD'!K5 -> -142.36757
A6: Depreciation of tangible assets | B6: -42.745142 | E6: -47.380285 | G6: =E6+'Quarterly YTD'!G6-'Quarterly YTD'!C6 -> -47.839564 | H6: =E6+'Quarterly YTD'!H6-'Quarterly YTD'!D6 -> -47.689041 | I6: -48.614609 | J6: =I6+'Quarterly YTD'!J6-'Quarterly YTD'!F6 -> -48.676557 | K6: =I6+'Quarterly YTD'!K6-'Quarterly YTD'!G6 -> -47.417432 | L6: =I6+'Quarterly YTD'!L6-'Quarterly YTD'!H6 -> -50.375114 | M6: -50.741037 | N6: =M6+'Quarterly YTD'!N6-'Quarterly YTD'!J6 -> -53.461583 | O6: =M6+'Quarterly YTD'!O6-'Quarterly YTD'!K6 -> -56.226568
A7: Amortization of intangible assets | B7: -11.955373 | E7: -15.925177 | G7: =E7+'Quarterly YTD'!G7-'Quarterly YTD'!C7 -> -19.416151 | H7: =E7+'Quarterly YTD'!H7-'Quarterly YTD'!D7 -> -20.365667 | I7: -20.609792 | J7: =I7+'Quarterly YTD'!J7-'Quarterly YTD'!F7 -> -20.498581 | K7: =I7+'Quarterly YTD'!K7-'Quarterly YTD'!G7 -> -20.29944 | L7: =I7+'Quarterly YTD'!L7-'Quarterly YTD'!H7 -> -20.328179 | M7: -19.385894 | N7: =M7+'Quarterly YTD'!N7-'Quarterly YTD'!J7 -> -19.271249 | O7: =M7+'Quarterly YTD'!O7-'Quarterly YTD'!K7 -> -18.961141
A8: (Provision)/write-back for expected credit losses on trade receivables | B8: 0 | E8: 0 | G8: =E8+'Quarterly YTD'!G8-'Quarterly YTD'!C8 -> 0 | H8: =E8+'Quarterly YTD'!H8-'Quarterly YTD'!D8 -> 0 | I8: 0 | J8: =I8+'Quarterly YTD'!J8-'Quarterly YTD'!F8 -> 0.039965 | K8: =I8+'Quarterly YTD'!K8-'Quarterly YTD'!G8 -> 0 | L8: =I8+'Quarterly YTD'!L8-'Quarterly YTD'!H8 -> 0 | M8: 0 | N8: =M8+'Quarterly YTD'!N8-'Quarterly YTD'!J8 -> -0.155571 | O8: =M8+'Quarterly YTD'!O8-'Quarterly YTD'!K8 -> 0
A9: Write-back/(provision) for expected credit losses on trade receivables | B9: -1.660354 | E9: 1.024685 | G9: =E9+'Quarterly YTD'!G9-'Quarterly YTD'!C9 -> 0.965212 | H9: =E9+'Quarterly YTD'!H9-'Quarterly YTD'!D9 -> 0.518662 | I9: -0.904712 | J9: =I9+'Quarterly YTD'!J9-'Quarterly YTD'!F9 -> -0.896099 | K9: =I9+'Quarterly YTD'!K9-'Quarterly YTD'!G9 -> -0.788288 | L9: =I9+'Quarterly YTD'!L9-'Quarterly YTD'!H9 -> -0.36845 | M9: -0.605485 | N9: =M9+'Quarterly YTD'!N9-'Quarterly YTD'!J9 -> -0.605485 | O9: =M9+'Quarterly YTD'!O9-'Quarterly YTD'!K9 -> -0.218586
A10: Provision for expected credit losses on balances due from related parties | B10: -0.390413 | E10: 0 | G10: =E10+'Quarterly YTD'!G10-'Quarterly YTD'!C10 -> 0 | H10: =E10+'Quarterly YTD'!H10-'Quarterly YTD'!D10 -> -0.12936 | I10: -0.12936 | J10: =I10+'Quarterly YTD'!J10-'Quarterly YTD'!F10 -> -0.12936 | K10: =I10+'Quarterly YTD'!K10-'Quarterly YTD'!G10 -> -0.168047 | L10: =I10+'Quarterly YTD'!L10-'Quarterly YTD'!H10 -> -0.052032 | M10: -0.065328 | N10: =M10+'Quarterly YTD'!N10-'Quarterly YTD'!J10 -> -0.403895 | O10: =M10+'Quarterly YTD'!O10-'Quarterly YTD'!K10 -> -0.432576
A11: Receivables written off | B11: 0 | E11: 0 | G11: =E11+'Quarterly YTD'!G11-'Quarterly YTD'!C11 -> 0 | H11: =E11+'Quarterly YTD'!H11-'Quarterly YTD'!D11 -> 0 | I11: -0.072471 | J11: =I11+'Quarterly YTD'!J11-'Quarterly YTD'!F11 -> -0.072471 | K11: =I11+'Quarterly YTD'!K11-'Quarterly YTD'!G11 -> -0.072471 | L11: =I11+'Quarterly YTD'!L11-'Quarterly YTD'!H11 -> -0.072471 | M11: -0.06976 | N11: =M11+'Quarterly YTD'!N11-'Quarterly YTD'!J11 -> -0.06976 | O11: =M11+'Quarterly YTD'!O11-'Quarterly YTD'!K11 -> -0.084892
A12: Other gain/(loss), net | B12: 8.760054 | E12: 12.047365 | G12: =E12+'Quarterly YTD'!G12-'Quarterly YTD'!C12 -> 12.218857 | H12: =E12+'Quarterly YTD'!H12-'Quarterly YTD'!D12 -> 13.358372 | I12: 1.444997 | J12: =I12+'Quarterly YTD'!J12-'Quarterly YTD'!F12 -> 1.2512 | K12: =I12+'Quarterly YTD'!K12-'Quarterly YTD'!G12 -> 1.773107 | L12: =I12+'Quarterly YTD'!L12-'Quarterly YTD'!H12 -> 1.122928 | M12: 4.922003 | N12: =M12+'Quarterly YTD'!N12-'Quarterly YTD'!J12 -> 4.553807 | O12: =M12+'Quarterly YTD'!O12-'Quarterly YTD'!K12 -> 5.827131
A13: OPERATING PROFIT | B13: =SUM(B3:B7)+SUM(B9:B10)+B12 -> 15.907529 | E13: =SUM(E3:E7)+SUM(E9:E12) -> 51.030502 | G13: =E13+'Quarterly YTD'!G13-'Quarterly YTD'!C13 -> 40.915925 | H13: =E13+'Quarterly YTD'!H13-'Quarterly YTD'!D13 -> 34.312589 | I13: =SUM(I3:I7)+SUM(I9:I12) -> 10.285312 | J13: =I13+'Quarterly YTD'!J13-'Quarterly YTD'!F13 -> 13.082157 | K13: =I13+'Quarterly YTD'!K13-'Quarterly YTD'!G13 -> 22.184515 | L13: =I13+'Quarterly YTD'!L13-'Quarterly YTD'!H13 -> 48.698245 | M13: =SUM(M3:M7)+SUM(M9:M12) -> 68.503009 | N13: =M13+'Quarterly YTD'!N13-'Quarterly YTD'!J13 -> 75.20254 | O13: =M13+'Quarterly YTD'!O13-'Quarterly YTD'!K13 -> 83.856592
A14: Interest income on balances due from related parties | B14: 1.932958 | E14: 2.126254 | G14: =E14+'Quarterly YTD'!G14-'Quarterly YTD'!C14 -> 2.126254 | H14: =E14+'Quarterly YTD'!H14-'Quarterly YTD'!D14 -> 2.126254 | I14: 2.33888 | J14: =I14+'Quarterly YTD'!J14-'Quarterly YTD'!F14 -> 2.33888 | K14: =I14+'Quarterly YTD'!K14-'Quarterly YTD'!G14 -> 2.33888 | L14: =I14+'Quarterly YTD'!L14-'Quarterly YTD'!H14 -> 2.33888 | M14: 2.572767 | N14: =M14+'Quarterly YTD'!N14-'Quarterly YTD'!J14 -> 2.572767 | O14: =M14+'Quarterly YTD'!O14-'Quarterly YTD'!K14 -> 2.572767
A15: Interest income on balances due from a related party | B15: 0 | E15: 0 | G15: =E15+'Quarterly YTD'!G15-'Quarterly YTD'!C15 -> 0.106313 | H15: =E15+'Quarterly YTD'!H15-'Quarterly YTD'!D15 -> 0.159469 | I15: 0 | J15: =I15+'Quarterly YTD'!J15-'Quarterly YTD'!F15 -> 0.058469 | K15: =I15+'Quarterly YTD'!K15-'Quarterly YTD'!G15 -> 0.116944 | L15: =I15+'Quarterly YTD'!L15-'Quarterly YTD'!H15 -> 0.175416 | M15: 0 | N15: =M15+'Quarterly YTD'!N15-'Quarterly YTD'!J15 -> 0.064322 | O15: =M15+'Quarterly YTD'!O15-'Quarterly YTD'!K15 -> 0.128638
A16: Other interest income | B16: 0.187722 | E16: 0.156096 | G16: =E16+'Quarterly YTD'!G16-'Quarterly YTD'!C16 -> 0.158819 | H16: =E16+'Quarterly YTD'!H16-'Quarterly YTD'!D16 -> 0.157212 | I16: 0.329062 | J16: =I16+'Quarterly YTD'!J16-'Quarterly YTD'!F16 -> 0.3978 | K16: =I16+'Quarterly YTD'!K16-'Quarterly YTD'!G16 -> 0.407202 | L16: =I16+'Quarterly YTD'!L16-'Quarterly YTD'!H16 -> 0.442984 | M16: 0.269998 | N16: =M16+'Quarterly YTD'!N16-'Quarterly YTD'!J16 -> 0.397375 | O16: =M16+'Quarterly YTD'!O16-'Quarterly YTD'!K16 -> 0.501385
A17: Finance costs, net | B17: -55.213244 | E17: -64.737849 | G17: =E17+'Quarterly YTD'!G17-'Quarterly YTD'!C17 -> -60.917214 | H17: =E17+'Quarterly YTD'!H17-'Quarterly YTD'!D17 -> -62.858629 | I17: -74.276529 | J17: =I17+'Quarterly YTD'!J17-'Quarterly YTD'!F17 -> -75.992035 | K17: =I17+'Quarterly YTD'!K17-'Quarterly YTD'!G17 -> -77.766373 | L17: =I17+'Quarterly YTD'!L17-'Quarterly YTD'!H17 -> -79.875363 | M17: -71.039195 | N17: =M17+'Quarterly YTD'!N17-'Quarterly YTD'!J17 -> -74.247913 | O17: =M17+'Quarterly YTD'!O17-'Quarterly YTD'!K17 -> -77.784129
A18: Loss on exchange, net | B18: -24.108535 | E18: -114.15174 | G18: =E18+'Quarterly YTD'!G18-'Quarterly YTD'!C18 -> -51.710745 | H18: =E18+'Quarterly YTD'!H18-'Quarterly YTD'!D18 -> -64.181368 | I18: -39.271284 | J18: =I18+'Quarterly YTD'!J18-'Quarterly YTD'!F18 -> -32.460065 | K18: =I18+'Quarterly YTD'!K18-'Quarterly YTD'!G18 -> -29.292779 | L18: =I18+'Quarterly YTD'!L18-'Quarterly YTD'!H18 -> -3.553722 | M18: 37.680522 | N18: =M18+'Quarterly YTD'!N18-'Quarterly YTD'!J18 -> 29.847942 | O18: =M18+'Quarterly YTD'!O18-'Quarterly YTD'!K18 -> 33.66656
A19: Net (loss)/gain on net monetary position | B19: 0 | E19: 21.543365 | G19: =E19+'Quarterly YTD'!G19-'Quarterly YTD'!C19 -> -6.850365 | H19: =E19+'Quarterly YTD'!H19-'Quarterly YTD'!D19 -> -5.050614 | I19: 3.558212 | J19: =I19+'Quarterly YTD'!J19-'Quarterly YTD'!F19 -> -0.371064 | K19: =I19+'Quarterly YTD'!K19-'Quarterly YTD'!G19 -> -0.642826 | L19: =I19+'Quarterly YTD'!L19-'Quarterly YTD'!H19 -> 1.264729 | M19: -1.599516 | N19: =M19+'Quarterly YTD'!N19-'Quarterly YTD'!J19 -> 1.403633 | O19: =M19+'Quarterly YTD'!O19-'Quarterly YTD'!K19 -> 1.419819
A20: LOSS BEFORE INCOME TAX FROM CONTINUING OPERATIONS | B20: =SUM(B13:B14)+SUM(B16:B18) -> -61.29357 | E20: =SUM(E13:E14)+SUM(E16:E19) -> -104.03337 | G20: =E20+'Quarterly YTD'!G20-'Quarterly YTD'!C20 -> -76.171013 | H20: =E20+'Quarterly YTD'!H20-'Quarterly YTD'!D20 -> -95.335087 | I20: =SUM(I13:I14)+SUM(I16:I19) -> -97.036347 | J20: =I20+'Quarterly YTD'!J20-'Quarterly YTD'!F20 -> -92.945858 | K20: =I20+'Quarterly YTD'!K20-'Quarterly YTD'!G20 -> -82.654437 | L20: =I20+'Quarterly YTD'!L20-'Quarterly YTD'!H20 -> -30.508831 | M20: =SUM(M13:M14)+SUM(M16:M19) -> 36.387585 | N20: =M20+'Quarterly YTD'!N20-'Quarterly YTD'!J20 -> 35.240666 | O20: =M20+'Quarterly YTD'!O20-'Quarterly YTD'!K20 -> 44.361632
A21: Income tax expense | B21: -0.891378 | E21: -11.454357 | G21: =E21+'Quarterly YTD'!G21-'Quarterly YTD'!C21 -> -4.660513 | H21: =E21+'Quarterly YTD'!H21-'Quarterly YTD'!D21 -> -10.085143 | I21: -6.737506 | J21: =I21+'Quarterly YTD'!J21-'Quarterly YTD'!F21 -> -6.188928 | K21: =I21+'Quarterly YTD'!K21-'Quarterly YTD'!G21 -> -5.751864 | L21: =I21+'Quarterly YTD'!L21-'Quarterly YTD'!H21 -> -6.844235 | M21: -6.007564 | N21: =M21+'Quarterly YTD'!N21-'Quarterly YTD'!J21 -> -7.719341 | O21: =M21+'Quarterly YTD'!O21-'Quarterly YTD'!K21 -> -9.937987
A22: LOSS FOR THE PERIOD FROM CONTINUING OPERATIONS | B22: =SUM(B20:B21) -> -62.184948 | E22: =SUM(E20:E21) -> -115.48772 | G22: =SUM(G20:G21) -> -80.831526 | H22: =SUM(H20:H21) -> -105.42023 | I22: =SUM(I20:I21) -> -103.77385 | J22: =SUM(J20:J21) -> -99.134786 | K22: =SUM(K20:K21) -> -88.406301 | L22: =SUM(L20:L21) -> -37.353066 | M22: =SUM(M20:M21) -> 30.380021 | N22: =SUM(N20:N21) -> 27.521325 | O22: =SUM(O20:O21) -> 34.423645
A23: Profit/(loss) for the period from discontinued operations | B23: 0.397799 | E23: 0.001763 | G23: =E23+'Quarterly YTD'!G23-'Quarterly YTD'!C23 -> -0.004891 | H23: =E23+'Quarterly YTD'!H23-'Quarterly YTD'!D23 -> 0.019756 | I23: 0.042832 | J23: =I23+'Quarterly YTD'!J23-'Quarterly YTD'!F23 -> 0.078399 | K23: =I23+'Quarterly YTD'!K23-'Quarterly YTD'!G23 -> 0.075115 | L23: =I23+'Quarterly YTD'!L23-'Quarterly YTD'!H23 -> 0.031925 | M23: 0.042544 | N23: =M23+'Quarterly YTD'!N23-'Quarterly YTD'!J23 -> 0.028811 | O23: =M23+'Quarterly YTD'!O23-'Quarterly YTD'!K23 -> 0.003499
A24: LOSS FOR THE PERIOD | B24: =SUM(B22:B23) -> -61.787149 | E24: =SUM(E22:E23) -> -115.48596 | G24: =SUM(G22:G23) -> -80.836417 | H24: =SUM(H22:H23) -> -105.40047 | I24: =SUM(I22:I23) -> -103.73102 | J24: =SUM(J22:J23) -> -99.056387 | K24: =SUM(K22:K23) -> -88.331186 | L24: =SUM(L22:L23) -> -37.321141 | M24: =SUM(M22:M23) -> 30.422565 | N24: =SUM(N22:N23) -> 27.550136 | O24: =SUM(O22:O23) -> 34.427144
A25: Equity holders of the Company | B25: -61.744696 | E25: -115.46815 | G25: =E25+'Quarterly YTD'!G25-'Quarterly YTD'!C25 -> -80.825552 | H25: =E25+'Quarterly YTD'!H25-'Quarterly YTD'!D25 -> -105.41874 | I25: -103.75874 | J25: =I25+'Quarterly YTD'!J25-'Quarterly YTD'!F25 -> -99.116397 | K25: =I25+'Quarterly YTD'!K25-'Quarterly YTD'!G25 -> -88.363419 | L25: =I25+'Quarterly YTD'!L25-'Quarterly YTD'!H25 -> -37.378 | M25: 30.417809 | N25: =M25+'Quarterly YTD'!N25-'Quarterly YTD'!J25 -> 27.593756 | O25: =M25+'Quarterly YTD'!O25-'Quarterly YTD'!K25 -> 34.470036
A26: Non-controlling interests | B26: -0.042453 | E26: -0.017809 | G26: =E26+'Quarterly YTD'!G26-'Quarterly YTD'!C26 -> -0.010865 | H26: =E26+'Quarterly YTD'!H26-'Quarterly YTD'!D26 -> 0.018269 | I26: 0.027721 | J26: =I26+'Quarterly YTD'!J26-'Quarterly YTD'!F26 -> 0.06001 | K26: =I26+'Quarterly YTD'!K26-'Quarterly YTD'!G26 -> 0.032233 | L26: =I26+'Quarterly YTD'!L26-'Quarterly YTD'!H26 -> 0.056859 | M26: 0.004756 | N26: =M26+'Quarterly YTD'!N26-'Quarterly YTD'!J26 -> -0.04362 | O26: =M26+'Quarterly YTD'!O26-'Quarterly YTD'!K26 -> -0.042892
A27: Exchange differences on translation of foreign operations | B27: -1.064477 | E27: 52.549161 | G27: =E27+'Quarterly YTD'!G27-'Quarterly YTD'!C27 -> 51.890828 | H27: =E27+'Quarterly YTD'!H27-'Quarterly YTD'!D27 -> 9.177838 | I27: 10.984271 | J27: =I27+'Quarterly YTD'!J27-'Quarterly YTD'!F27 -> 2.9698 | K27: =I27+'Quarterly YTD'!K27-'Quarterly YTD'!G27 -> 0.195728 | L27: =I27+'Quarterly YTD'!L27-'Quarterly YTD'!H27 -> -6.644797 | M27: -21.059859 | N27: =M27+'Quarterly YTD'!N27-'Quarterly YTD'!J27 -> -12.505984 | O27: =M27+'Quarterly YTD'!O27-'Quarterly YTD'!K27 -> -13.242169
A28: Defined benefit plan actuarial gain | B28: -0.048464 | E28: 0.016915 | G28: =E28+'Quarterly YTD'!G28-'Quarterly YTD'!C28 -> 0.016915 | H28: =E28+'Quarterly YTD'!H28-'Quarterly YTD'!D28 -> 0.016915 | I28: 0.078297 | J28: =I28+'Quarterly YTD'!J28-'Quarterly YTD'!F28 -> 0.078297 | K28: =I28+'Quarterly YTD'!K28-'Quarterly YTD'!G28 -> 0.078297 | L28: =I28+'Quarterly YTD'!L28-'Quarterly YTD'!H28 -> 0.078297 | M28: 0.73497 | N28: =M28+'Quarterly YTD'!N28-'Quarterly YTD'!J28 -> 0.73497 | O28: =M28+'Quarterly YTD'!O28-'Quarterly YTD'!K28 -> 0.73497
A29: Total other comprehensive (loss)/gain | B29: =SUM(B27:B28) -> -1.112941 | E29: =SUM(E27:E28) -> 52.566076 | G29: =SUM(G27:G28) -> 51.907743 | H29: =SUM(H27:H28) -> 9.194753 | I29: =SUM(I27:I28) -> 11.062568 | J29: =SUM(J27:J28) -> 3.048097 | K29: =SUM(K27:K28) -> 0.274025 | L29: =SUM(L27:L28) -> -6.5665 | M29: =SUM(M27:M28) -> -20.324889 | N29: =SUM(N27:N28) -> -11.771014 | O29: =SUM(O27:O28) -> -12.507199
A30: TOTAL COMPREHENSIVE LOSS FOR THE PERIOD | B30: =B24+B29 -> -62.90009 | E30: =E24+E29 -> -62.919886 | G30: =G24+G29 -> -28.928674 | H30: =H24+H29 -> -96.205721 | I30: =I24+I29 -> -92.668453 | J30: =J24+J29 -> -96.00829 | K30: =K24+K29 -> -88.057161 | L30: =L24+L29 -> -43.887641 | M30: =M24+M29 -> 10.097676 | N30: =N24+N29 -> 15.779122 | O30: =O24+O29 -> 21.919945
A31: Equity holders of the Company | B31: -63.024558 | E31: -62.963777 | G31: =E31+'Quarterly YTD'!G31-'Quarterly YTD'!C31 -> -28.955696 | H31: =E31+'Quarterly YTD'!H31-'Quarterly YTD'!D31 -> -96.161313 | I31: -92.602016 | J31: =I31+'Quarterly YTD'!J31-'Quarterly YTD'!F31 -> -95.86396 | K31: =I31+'Quarterly YTD'!K31-'Quarterly YTD'!G31 -> -87.980085 | L31: =I31+'Quarterly YTD'!L31-'Quarterly YTD'!H31 -> -43.744068 | M31: 10.148129 | N31: =M31+'Quarterly YTD'!N31-'Quarterly YTD'!J31 -> 15.726757 | O31: =M31+'Quarterly YTD'!O31-'Quarterly YTD'!K31 -> 21.893804
A32: Non-controlling interests | B32: 0.124468 | E32: 0.043891 | G32: =E32+'Quarterly YTD'!G32-'Quarterly YTD'!C32 -> 0.027022 | H32: =E32+'Quarterly YTD'!H32-'Quarterly YTD'!D32 -> -0.044408 | I32: -0.066437 | J32: =I32+'Quarterly YTD'!J32-'Quarterly YTD'!F32 -> -0.14433 | K32: =I32+'Quarterly YTD'!K32-'Quarterly YTD'!G32 -> -0.077076 | L32: =I32+'Quarterly YTD'!L32-'Quarterly YTD'!H32 -> -0.143573 | M32: -0.050453 | N32: =M32+'Quarterly YTD'!N32-'Quarterly YTD'!J32 -> 0.052365 | O32: =M32+'Quarterly YTD'!O32-'Quarterly YTD'!K32 -> 0.026141
A34: Cash Flow Statement
A35: Loss before income tax from continuing operations | B35: -61.29357 | E35: -104.03337 | G35: =E35+'Quarterly YTD'!G35-'Quarterly YTD'!C35 -> -76.171013 | H35: =E35+'Quarterly YTD'!H35-'Quarterly YTD'!D35 -> -95.335087 | I35: -97.036347 | J35: =I35+'Quarterly YTD'!J35-'Quarterly YTD'!F35 -> -92.945858 | K35: =I35+'Quarterly YTD'!K35-'Quarterly YTD'!G35 -> -82.654437 | L35: =I35+'Quarterly YTD'!L35-'Quarterly YTD'!H35 -> -30.508831 | M35: 36.387585 | N35: =M35+'Quarterly YTD'!N35-'Quarterly YTD'!J35 -> 35.240666 | O35: =M35+'Quarterly YTD'!O35-'Quarterly YTD'!K35 -> 44.361632
A36: Profit/(loss) from discontinued operations | B36: 0.397799 | E36: 0.001763 | G36: =E36+'Quarterly YTD'!G36-'Quarterly YTD'!C36 -> -0.004891 | H36: =E36+'Quarterly YTD'!H36-'Quarterly YTD'!D36 -> 0.019756 | I36: 0.042832 | J36: =I36+'Quarterly YTD'!J36-'Quarterly YTD'!F36 -> 0.078399 | K36: =I36+'Quarterly YTD'!K36-'Quarterly YTD'!G36 -> 0.075115 | L36: =I36+'Quarterly YTD'!L36-'Quarterly YTD'!H36 -> 0.031925 | M36: 0.042544 | N36: =M36+'Quarterly YTD'!N36-'Quarterly YTD'!J36 -> 0.028811 | O36: =M36+'Quarterly YTD'!O36-'Quarterly YTD'!K36 -> 0.003499
A37: Depreciation on tangible assets | B37: 42.745142 | E37: 47.380285 | G37: =E37+'Quarterly YTD'!G37-'Quarterly YTD'!C37 -> 47.839564 | H37: =E37+'Quarterly YTD'!H37-'Quarterly YTD'!D37 -> 47.689041 | I37: 48.614609 | J37: =I37+'Quarterly YTD'!J37-'Quarterly YTD'!F37 -> 48.676557 | K37: =I37+'Quarterly YTD'!K37-'Quarterly YTD'!G37 -> 47.417432 | L37: =I37+'Quarterly YTD'!L37-'Quarterly YTD'!H37 -> 50.375114 | M37: 50.741037 | N37: =M37+'Quarterly YTD'!N37-'Quarterly YTD'!J37 -> 53.461583 | O37: =M37+'Quarterly YTD'!O37-'Quarterly YTD'!K37 -> 56.226568
A38: Amortization of intangible assets | B38: 11.955373 | E38: 15.925177 | G38: =E38+'Quarterly YTD'!G38-'Quarterly YTD'!C38 -> 19.416151 | H38: =E38+'Quarterly YTD'!H38-'Quarterly YTD'!D38 -> 20.365667 | I38: 20.609792 | J38: =I38+'Quarterly YTD'!J38-'Quarterly YTD'!F38 -> 20.498581 | K38: =I38+'Quarterly YTD'!K38-'Quarterly YTD'!G38 -> 20.29944 | L38: =I38+'Quarterly YTD'!L38-'Quarterly YTD'!H38 -> 20.328179 | M38: 19.385894 | N38: =M38+'Quarterly YTD'!N38-'Quarterly YTD'!J38 -> 19.271249 | O38: =M38+'Quarterly YTD'!O38-'Quarterly YTD'!K38 -> 18.961141
A39: (Write-back) Provision for expected credit losses on trade receivables | B39: 0 | E39: 0 | G39: =E39+'Quarterly YTD'!G39-'Quarterly YTD'!C39 -> 0.082283 | H39: =E39+'Quarterly YTD'!H39-'Quarterly YTD'!D39 -> 0 | I39: 0 | J39: =I39+'Quarterly YTD'!J39-'Quarterly YTD'!F39 -> 0 | K39: =I39+'Quarterly YTD'!K39-'Quarterly YTD'!G39 -> -0.082283 | L39: =I39+'Quarterly YTD'!L39-'Quarterly YTD'!H39 -> 0 | M39: 0 | N39: =M39+'Quarterly YTD'!N39-'Quarterly YTD'!J39 -> 0 | O39: =M39+'Quarterly YTD'!O39-'Quarterly YTD'!K39 -> 0
A40: Provision for expected credit losses on trade receivables | B40: 1.070047 | E40: -1.024685 | G40: =E40+'Quarterly YTD'!G40-'Quarterly YTD'!C40 -> -1.047495 | H40: =E40+'Quarterly YTD'!H40-'Quarterly YTD'!D40 -> -0.518662 | I40: 0.849054 | J40: =I40+'Quarterly YTD'!J40-'Quarterly YTD'!F40 -> 0.798621 | K40: =I40+'Quarterly YTD'!K40-'Quarterly YTD'!G40 -> 0.849054 | L40: =I40+'Quarterly YTD'!L40-'Quarterly YTD'!H40 -> 0.312792 | M40: 0.615199 | N40: =M40+'Quarterly YTD'!N40-'Quarterly YTD'!J40 -> 0.77077 | O40: =M40+'Quarterly YTD'!O40-'Quarterly YTD'!K40 -> 0.615199
A41: Re-measurement gain on long-term liability | B41: 0 | E41: 0 | G41: =E41+'Quarterly YTD'!G41-'Quarterly YTD'!C41 -> 0 | H41: =E41+'Quarterly YTD'!H41-'Quarterly YTD'!D41 -> 0 | I41: -0.195467 | J41: =I41+'Quarterly YTD'!J41-'Quarterly YTD'!F41 -> -0.195467 | K41: =I41+'Quarterly YTD'!K41-'Quarterly YTD'!G41 -> -0.195467 | L41: =I41+'Quarterly YTD'!L41-'Quarterly YTD'!H41 -> -0.195467 | M41: 0 | N41: =M41+'Quarterly YTD'!N41-'Quarterly YTD'!J41 -> 0 | O41: =M41+'Quarterly YTD'!O41-'Quarterly YTD'!K41 -> 0
A42: Write-back for expected credit losses on trade receivables, net | B42: 0 | E42: 0 | G42: =E42+'Quarterly YTD'!G42-'Quarterly YTD'!C42 -> 0 | H42: =E42+'Quarterly YTD'!H42-'Quarterly YTD'!D42 -> 0 | I42: 0 | J42: =I42+'Quarterly YTD'!J42-'Quarterly YTD'!F42 -> 0 | K42: =I42+'Quarterly YTD'!K42-'Quarterly YTD'!G42 -> -0.034141 | L42: =I42+'Quarterly YTD'!L42-'Quarterly YTD'!H42 -> 0 | M42: 0 | N42: =M42+'Quarterly YTD'!N42-'Quarterly YTD'!J42 -> 0 | O42: =M42+'Quarterly YTD'!O42-'Quarterly YTD'!K42 -> -0.386899
A43: (Write-back) Provision for expected credit losses on bank balances | B43: 0 | E43: 0 | G43: =E43+'Quarterly YTD'!G43-'Quarterly YTD'!C43 -> 0 | H43: =E43+'Quarterly YTD'!H43-'Quarterly YTD'!D43 -> 0 | I43: 0 | J43: =I43+'Quarterly YTD'!J43-'Quarterly YTD'!F43 -> 0 | K43: =I43+'Quarterly YTD'!K43-'Quarterly YTD'!G43 -> 0.058709 | L43: =I43+'Quarterly YTD'!L43-'Quarterly YTD'!H43 -> 0 | M43: 0 | N43: =M43+'Quarterly YTD'!N43-'Quarterly YTD'!J43 -> 0 | O43: =M43+'Quarterly YTD'!O43-'Quarterly YTD'!K43 -> 0.096145
A44: Provision for expected credit losses on balance due from a related party | B44: 0.390413 | E44: 0 | G44: =E44+'Quarterly YTD'!G44-'Quarterly YTD'!C44 -> 0 | H44: =E44+'Quarterly YTD'!H44-'Quarterly YTD'!D44 -> 0.12936 | I44: 0.12936 | J44: =I44+'Quarterly YTD'!J44-'Quarterly YTD'!F44 -> 0.15475 | K44: =I44+'Quarterly YTD'!K44-'Quarterly YTD'!G44 -> 0.168047 | L44: =I44+'Quarterly YTD'!L44-'Quarterly YTD'!H44 -> 0.052032 | M44: 0.065328 | N44: =M44+'Quarterly YTD'!N44-'Quarterly YTD'!J44 -> 0.378505 | O44: =M44+'Quarterly YTD'!O44-'Quarterly YTD'!K44 -> 0.432576
A45: Provision (Write-back) for expected credit losses on bank balances | B45: 0 | E45: 0 | G45: =E45+'Quarterly YTD'!G45-'Quarterly YTD'!C45 -> 0 | H45: =E45+'Quarterly YTD'!H45-'Quarterly YTD'!D45 -> -0.033497 | I45: 0 | J45: =I45+'Quarterly YTD'!J45-'Quarterly YTD'!F45 -> 0 | K45: =I45+'Quarterly YTD'!K45-'Quarterly YTD'!G45 -> 0 | L45: =I45+'Quarterly YTD'!L45-'Quarterly YTD'!H45 -> 0.065073 | M45: 0 | N45: =M45+'Quarterly YTD'!N45-'Quarterly YTD'!J45 -> 0 | O45: =M45+'Quarterly YTD'!O45-'Quarterly YTD'!K45 -> 0
A46: Provision for/(write-back of) expected credit losses on bank balances | B46: 0 | E46: 0 | G46: =E46+'Quarterly YTD'!G46-'Quarterly YTD'!C46 -> 0 | H46: =E46+'Quarterly YTD'!H46-'Quarterly YTD'!D46 -> 0 | I46: -0.000452 | J46: =I46+'Quarterly YTD'!J46-'Quarterly YTD'!F46 -> -0.000452 | K46: =I46+'Quarterly YTD'!K46-'Quarterly YTD'!G46 -> -0.000452 | L46: =I46+'Quarterly YTD'!L46-'Quarterly YTD'!H46 -> -0.000452 | M46: 0.090045 | N46: =M46+'Quarterly YTD'!N46-'Quarterly YTD'!J46 -> 0.090045 | O46: =M46+'Quarterly YTD'!O46-'Quarterly YTD'!K46 -> 0.090045
... A77: Provisions paid | B77: -0.332177 | E77: -2.195829 | G77: =E77+'Quarterly YTD'!G77-'Quarterly YTD'!C77 -> -2.329715 | H77: =E77+'Quarterly YTD'!H77-'Quarterly YTD'!D77 -> -2.359254 | I77: -0.403325 | J77: =I77+'Quarterly YTD'!J77-'Quarterly YTD'!F77 -> -0.294852 | K77: =I77+'Quarterly YTD'!K77-'Quarterly YTD'!G77 -> -1.069195 | L77: =I77+'Quarterly YTD'!L77-'Quarterly YTD'!H77 -> -1.084446 | M77: -1.099098 | N77: =M77+'Quarterly YTD'!N77-'Quarterly YTD'!J77 -> -1.241943 | O77: =M77+'Quarterly YTD'!O77-'Quarterly YTD'!K77 -> -0.413471
A78: Net cash from operating activities | B78: =SUM(B35:B38)+B40+B44+SUM(B47:B48)+SUM(B51:B59)+SUM(B61:B62)+B66+SUM(B68:B69)+SUM(B73:B74)+SUM(B76:B77) -> 112.52626 | E78: =SUM(E35:E38)+SUM(E40:E41)+E44+SUM(E47:E48)+SUM(E51:E59)+SUM(E61:E62)+E66+SUM(E68:E70)+SUM(E73:E74)+SUM(E76:E77) -> 132.14775 | G78: =E78+'Quarterly YTD'!G78-'Quarterly YTD'!C78 -> 99.310106 | H78: =E78+'Quarterly YTD'!H78-'Quarterly YTD'!D78 -> 71.412103 | I78: =SUM(I35:I38)+SUM(I40:I41)+I44+I46+SUM(I48:I49)+SUM(I52:I59)+I61+I63+I65+SUM(I69:I74)+SUM(I76:I77) -> 39.726265 | J78: =I78+'Quarterly YTD'!J78-'Quarterly YTD'!F78 -> 13.046857 | K78: =I78+'Quarterly YTD'!K78-'Quarterly YTD'!G78 -> 41.248265 | L78: =I78+'Quarterly YTD'!L78-'Quarterly YTD'!H78 -> 32.218334 | M78: =SUM(M35:M38)+SUM(M40:M41)+M44+M46+SUM(M48:M49)+SUM(M52:M59)+M61+SUM(M63:M64)+SUM(M69:M74)+SUM(M76:M77) -> 48.87244 | N78: =M78+'Quarterly YTD'!N78-'Quarterly YTD'!J78 -> 44.851775 | O78: =M78+'Quarterly YTD'!O78-'Quarterly YTD'!K78 -> 44.142244
A79: Acquisition of property, equipment and intangible assets | B79: -84.254415 | E79: -74.376186 | G79: =E79+'Quarterly YTD'!G79-'Quarterly YTD'!C79 -> -70.93356 | H79: =E79+'Quarterly YTD'!H79-'Quarterly YTD'!D79 -> -50.633884 | I79: -29.126253 | J79: =I79+'Quarterly YTD'!J79-'Quarterly YTD'!F79 -> -25.348941 | K79: =I79+'Quarterly YTD'!K79-'Quarterly YTD'!G79 -> -34.818726 | L79: =I79+'Quarterly YTD'!L79-'Quarterly YTD'!H79 -> -34.792062 | M79: -47.541704 | N79: =M79+'Quarterly YTD'!N79-'Quarterly YTD'!J79 -> -55.930565 | O79: =M79+'Quarterly YTD'!O79-'Quarterly YTD'!K79 -> -59.743655
A80: Acquisition of intangible assets | B80: -15.165416 | E80: -24.361971 | G80: =E80+'Quarterly YTD'!G80-'Quarterly YTD'!C80 -> -22.076662 | H80: =E80+'Quarterly YTD'!H80-'Quarterly YTD'!D80 -> -23.025995 | I80: -20.599286 | J80: =I80+'Quarterly YTD'!J80-'Quarterly YTD'!F80 -> -16.536548 | K80: =I80+'Quarterly YTD'!K80-'Quarterly YTD'!G80 -> -16.906127 | L80: =I80+'Quarterly YTD'!L80-'Quarterly YTD'!H80 -> -17.48709 | M80: -8.286235 | N80: =M80+'Quarterly YTD'!N80-'Quarterly YTD'!J80 -> -10.776696 | O80: =M80+'Quarterly YTD'!O80-'Quarterly YTD'!K80 -> -8.286235
A81: Due from related parties | B81: -0.406392 | E81: -0.009795 | G81: =E81+'Quarterly YTD'!G81-'Quarterly YTD'!C81 -> -0.009795 | H81: =E81+'Quarterly YTD'!H81-'Quarterly YTD'!D81 -> -0.009795 | I81: 0 | J81: =I81+'Quarterly YTD'!J81-'Quarterly YTD'!F81 -> 0 | K81: =I81+'Quarterly YTD'!K81-'Quarterly YTD'!G81 -> 0 | L81: =I81+'Quarterly YTD'!L81-'Quarterly YTD'!H81 -> 0 | M81: 0 | N81: =M81+'Quarterly YTD'!N81-'Quarterly YTD'!J81 -> 0 | O81: =M81+'Quarterly YTD'!O81-'Quarterly YTD'!K81 -> 0
A82: Payment for telecom license | B82: 0 | E82: 0 | G82: =E82+'Quarterly YTD'!G82-'Quarterly YTD'!C82 -> 0 | H82: =E82+'Quarterly YTD'!H82-'Quarterly YTD'!D82 -> 0 | I82: 0 | J82: =I82+'Quarterly YTD'!J82-'Quarterly YTD'!F82 -> 0 | K82: =I82+'Quarterly YTD'!K82-'Quarterly YTD'!G82 -> 0 | L82: =I82+'Quarterly YTD'!L82-'Quarterly YTD'!H82 -> 0 | M82: -5.02211 | N82: =M82+'Quarterly YTD'!N82-'Quarterly YTD'!J82 -> -5.02211 | O82: =M82+'Quarterly YTD'!O82-'Quarterly YTD'!K82 -> -5.02211
A83: Advances to suppliers | B83: 0 | E83: 0 | G83: =E83+'Quarterly YTD'!G83-'Quarterly YTD'!C83 -> 0 | H83: =E83+'Quarterly YTD'!H83-'Quarterly YTD'!D83 -> 0 | I83: 0 | J83: =I83+'Quarterly YTD'!J83-'Quarterly YTD'!F83 -> 0 | K83: =I83+'Quarterly YTD'!K83-'Quarterly YTD'!G83 -> -0.108169 | L83: =I83+'Quarterly YTD'!L83-'Quarterly YTD'!H83 -> 0 | M83: 0 | N83: =M83+'Quarterly YTD'!N83-'Quarterly YTD'!J83 -> 0 | O83: =M83+'Quarterly YTD'!O83-'Quarterly YTD'!K83 -> -12.520713
A84: Proceeds from disposal of property and equipment | B84: 10.346399 | E84: 0.037732 | G84: =E84+'Quarterly YTD'!G84-'Quarterly YTD'!C84 -> 0.046772 | H84: =E84+'Quarterly YTD'!H84-'Quarterly YTD'!D84 -> 0.087419 | I84: 0.06133 | J84: =I84+'Quarterly YTD'!J84-'Quarterly YTD'!F84 -> 0.003793 | K84: =I84+'Quarterly YTD'!K84-'Quarterly YTD'!G84 -> 0.166862 | L84: =I84+'Quarterly YTD'!L84-'Quarterly YTD'!H84 -> 0.183537 | M84: 0.253132 | N84: =M84+'Quarterly YTD'!N84-'Quarterly YTD'!J84 -> 0.236507 | O84: =M84+'Quarterly YTD'!O84-'Quarterly YTD'!K84 -> 0.099428
A85: Due from a related party | B85: 0 | E85: 0 | G85: =E85+'Quarterly YTD'!G85-'Quarterly YTD'!C85 -> 0.229378 | H85: =E85+'Quarterly YTD'!H85-'Quarterly YTD'!D85 -> 0.100571 | I85: 0 | J85: =I85+'Quarterly YTD'!J85-'Quarterly YTD'!F85 -> 0 | K85: =I85+'Quarterly YTD'!K85-'Quarterly YTD'!G85 -> 0 | L85: =I85+'Quarterly YTD'!L85-'Quarterly YTD'!H85 -> 0 | M85: 0 | N85: =M85+'Quarterly YTD'!N85-'Quarterly YTD'!J85 -> 0 | O85: =M85+'Quarterly YTD'!O85-'Quarterly YTD'!K85 -> 0
A86: Movement in term deposits | B86: 0.132403 | E86: -0.025433 | G86: =E86+'Quarterly YTD'!G86-'Quarterly YTD'!C86 -> 0.01746 | H86: =E86+'Quarterly YTD'!H86-'Quarterly YTD'!D86 -> -0.052095 | I86: 0.747273 | J86: =I86+'Quarterly YTD'!J86-'Quarterly YTD'!F86 -> 0.727504 | K86: =I86+'Quarterly YTD'!K86-'Quarterly YTD'!G86 -> 0.762494 | L86: =I86+'Quarterly YTD'!L86-'Quarterly YTD'!H86 -> 0.76594 | M86: -0.110069 | N86: =M86+'Quarterly YTD'!N86-'Quarterly YTD'!J86 -> -2e-06 | O86: =M86+'Quarterly YTD'!O86-'Quarterly YTD'!K86 -> -0.106187
A87: Net cash used in investing activities | B87: =SUM(B79:B81)+B84+B86 -> -89.347421 | E87: =SUM(E79:E81)+E84+E86 -> -98.735653 | G87: =E87+'Quarterly YTD'!G87-'Quarterly YTD'!C87 -> -92.726407 | H87: =E87+'Quarterly YTD'!H87-'Quarterly YTD'!D87 -> -73.533779 | I87: =SUM(I79:I80)+I82+I84+I86 -> -48.916936 | J87: =I87+'Quarterly YTD'!J87-'Quarterly YTD'!F87 -> -41.154192 | K87: =I87+'Quarterly YTD'!K87-'Quarterly YTD'!G87 -> -50.903666 | L87: =I87+'Quarterly YTD'!L87-'Quarterly YTD'!H87 -> -51.329675 | M87: =SUM(M79:M80)+M82+M84+M86 -> -60.706986 | N87: =M87+'Quarterly YTD'!N87-'Quarterly YTD'!J87 -> -71.492866 | O87: =M87+'Quarterly YTD'!O87-'Quarterly YTD'!K87 -> -85.579472
A88: Term loans proceeds | B88: 10.230431 | E88: 43.919974 | G88: =E88+'Quarterly YTD'!G88-'Quarterly YTD'!C88 -> 34.583397 | H88: =E88+'Quarterly YTD'!H88-'Quarterly YTD'!D88 -> 44.419026 | I88: 0.674215 | J88: =I88+'Quarterly YTD'!J88-'Quarterly YTD'!F88 -> 0.674215 | K88: =I88+'Quarterly YTD'!K88-'Quarterly YTD'!G88 -> 0.010792 | L88: =I88+'Quarterly YTD'!L88-'Quarterly YTD'!H88 -> 3.744646 | M88: 17.005817 | N88: =M88+'Quarterly YTD'!N88-'Quarterly YTD'!J88 -> 20.381808 | O88: =M88+'Quarterly YTD'!O88-'Quarterly YTD'!K88 -> 22.461817
A89: Terms loans payments | B89: -37.974252 | E89: -47.519074 | G89: =E89+'Quarterly YTD'!G89-'Quarterly YTD'!C89 -> -49.519725 | H89: =E89+'Quarterly YTD'!H89-'Quarterly YTD'!D89 -> -69.114793 | I89: -253.91816 | J89: =I89+'Quarterly YTD'!J89-'Quarterly YTD'!F89 -> -245.18514 | K89: =I89+'Quarterly YTD'!K89-'Quarterly YTD'!G89 -> -244.91318 | L89: =I89+'Quarterly YTD'!L89-'Quarterly YTD'!H89 -> -228.12766 | M89: -6.611861 | N89: =M89+'Quarterly YTD'!N89-'Quarterly YTD'!J89 -> -7.458745 | O89: =M89+'Quarterly YTD'!O89-'Quarterly YTD'!K89 -> -9.555588
A90: Lease liabilities paid | B90: -25.358133 | E90: -22.91447 | G90: =E90+'Quarterly YTD'!G90-'Quarterly YTD'!C90 -> -33.356135 | H90: =E90+'Quarterly YTD'!H90-'Quarterly YTD'!D90 -> -39.18079 | I90: -23.943408 | J90: =I90+'Quarterly YTD'!J90-'Quarterly YTD'!F90 -> -23.472443 | K90: =I90+'Quarterly YTD'!K90-'Quarterly YTD'!G90 -> -27.37148 | L90: =I90+'Quarterly YTD'!L90-'Quarterly YTD'!H90 -> -21.333738 | M90: -31.839486 | N90: =M90+'Quarterly YTD'!N90-'Quarterly YTD'!J90 -> -38.256716 | O90: =M90+'Quarterly YTD'!O90-'Quarterly YTD'!K90 -> -38.581958
A91: Interest paid | B91: 0 | E91: 0 | G91: =E91+'Quarterly YTD'!G91-'Quarterly YTD'!C91 -> 29.575639 | H91: =E91+'Quarterly YTD'!H91-'Quarterly YTD'!D91 -> 42.589607 | I91: 0 | J91: =I91+'Quarterly YTD'!J91-'Quarterly YTD'!F91 -> 0 | K91: =I91+'Quarterly YTD'!K91-'Quarterly YTD'!G91 -> 0 | L91: =I91+'Quarterly YTD'!L91-'Quarterly YTD'!H91 -> 0 | M91: 0 | N91: =M91+'Quarterly YTD'!N91-'Quarterly YTD'!J91 -> 0 | O91: =M91+'Quarterly YTD'!O91-'Quarterly YTD'!K91 -> 0
A92: Restricted bank balances | B92: -6.559526 | E92: -0.143868 | G92: =E92+'Quarterly YTD'!G92-'Quarterly YTD'!C92 -> 9.894487 | H92: =E92+'Quarterly YTD'!H92-'Quarterly YTD'!D92 -> -0.142785 | I92: 0 | J92: =I92+'Quarterly YTD'!J92-'Quarterly YTD'!F92 -> -2.490096 | K92: =I92+'Quarterly YTD'!K92-'Quarterly YTD'!G92 -> -9.96665 | L92: =I92+'Quarterly YTD'!L92-'Quarterly YTD'!H92 -> -15.899546 | M92: 0 | N92: =M92+'Quarterly YTD'!N92-'Quarterly YTD'!J92 -> 0 | O92: =M92+'Quarterly YTD'!O92-'Quarterly YTD'!K92 -> 0
A93: Proceeds from bond issued | B93: 0 | E93: 0 | G93: =E93+'Quarterly YTD'!G93-'Quarterly YTD'!C93 -> 0 | H93: =E93+'Quarterly YTD'!H93-'Quarterly YTD'!D93 -> 0 | I93: 300 | J93: =I93+'Quarterly YTD'!J93-'Quarterly YTD'!F93 -> 300 | K93: =I93+'Quarterly YTD'!K93-'Quarterly YTD'!G93 -> 300 | L93: =I93+'Quarterly YTD'!L93-'Quarterly YTD'!H93 -> 300 | M93: 0 | N93: =M93+'Quarterly YTD'!N93-'Quarterly YTD'!J93 -> 56.796935 | O93: =M93+'Quarterly YTD'!O93-'Quarterly YTD'!K93 -> 56.796935
A94: Net cash (used in)/from financing activities | B94: =SUM(B88:B90)+B92 -> -59.66148 | E94: =SUM(E88:E90)+SUM(E92:E93) -> -26.657438 | G94: =E94+'Quarterly YTD'!G94-'Quarterly YTD'!C94 -> -8.822337 | H94: =E94+'Quarterly YTD'!H94-'Quarterly YTD'!D94 -> -21.429735 | I94: =SUM(I88:I90)+I93 -> 22.812648 | J94: =I94+'Quarterly YTD'!J94-'Quarterly YTD'!F94 -> 29.526536 | K94: =I94+'Quarterly YTD'!K94-'Quarterly YTD'!G94 -> 17.759479 | L94: =I94+'Quarterly YTD'!L94-'Quarterly YTD'!H94 -> 38.383703 | M94: =SUM(M88:M90)+M93 -> -21.44553 | N94: =M94+'Quarterly YTD'!N94-'Quarterly YTD'!J94 -> 31.463282 | O94: =M94+'Quarterly YTD'!O94-'Quarterly YTD'!K94 -> 31.121206
A95: (DECREASE) / INCREASE IN CASH AND CASH EQUIVALENTS | B95: =B78+B87+B94 -> -36.482641 | E95: =E78+E87+E94 -> 6.754658 | G95: =G78+G87+G94 -> -2.238638 | H95: =H78+H87+H94 -> -23.551411 | I95: =I78+I87+I94 -> 13.621977 | J95: =J78+J87+J94 -> 1.419201 | K95: =K78+K87+K94 -> 8.104078 | L95: =L78+L87+L94 -> 19.272362 | M95: =M78+M87+M94 -> -33.280076 | N95: =N78+N87+N94 -> 4.822191 | O95: =O78+O87+O94 -> -10.316022
A96: Effects of exchange rate changes | B96: -0.432477 | E96: -0.533686 | G96: =E96+'Quarterly YTD'!G96-'Quarterly YTD'!C96 -> 7.418761 | H96: =E96+'Quarterly YTD'!H96-'Quarterly YTD'!D96 -> 5.314577 | I96: 7.427334 | J96: =I96+'Quarterly YTD'!J96-'Quarterly YTD'!F96 -> 5.765556 | K96: =I96+'Quarterly YTD'!K96-'Quarterly YTD'!G96 -> 3.566081 | L96: =I96+'Quarterly YTD'!L96-'Quarterly YTD'!H96 -> 4.95472 | M96: 9.581113 | N96: =M96+'Quarterly YTD'!N96-'Quarterly YTD'!J96 -> 16.511993 | O96: =M96+'Quarterly YTD'!O96-'Quarterly YTD'!K96 -> 9.360146
A97: Cash and cash equivalents at beginning of the period | B97: 23.60309 | E97: -13.312028 | G97: ='Quarterly YTD'!C98 -> -22.720621 | H97: ='Quarterly YTD'!D98 -> -14.219656 | I97: -7.091056 | J97: ='Quarterly YTD'!F98 -> -18.116065 | K97: ='Quarterly YTD'!G98 -> -17.540498 | L97: ='Quarterly YTD'!H98 -> -29.034284 | M97: ='Quarterly YTD'!K97 -> 13.958255 | N97: ='Quarterly YTD'!J98 -> -10.931308 | O97: ='Quarterly YTD'!K98 -> -5.870339
A98: CASH AND CASH EQUIVALENTS AT 30 JUNE | B98: =SUM(B95:B97) -> -13.312028 | E98: =SUM(E95:E97) -> -7.091056 | G98: =((E95+E96)+('Quarterly YTD'!G95+'Quarterly YTD'!G96)-('Quarterly YTD'!C95+'Quarterly YTD'!C96))+G97 -> -17.540498 | H98: ='Quarterly YTD'!H98 -> -29.034284 | I98: =SUM(I95:I97) -> 13.958255 | J98: =((I95+I96)+('Quarterly YTD'!J95+'Quarterly YTD'!J96)-('Quarterly YTD'!F95+'Quarterly YTD'!F96))+J97 -> -10.931308 | K98: =((I95+I96)+('Quarterly YTD'!K95+'Quarterly YTD'!K96)-('Quarterly YTD'!G95+'Quarterly YTD'!G96))+K97 -> -5.870339 | L98: ='Quarterly YTD'!L98 -> -8.229408 | M98: =SUM(M95:M97) -> -9.740708 | N98: =((M95+M96)+('Quarterly YTD'!N95+'Quarterly YTD'!N96)-('Quarterly YTD'!J95+'Quarterly YTD'!J96))+N97 -> 10.402876 | O98: =((M95+M96)+('Quarterly YTD'!O95+'Quarterly YTD'!O96)-('Quarterly YTD'!K95+'Quarterly YTD'!K96))+O97 -> -6.826215
A100: Balance Sheet
A101: Goodwill | B101: 12.743364 | E101: 58.270178 | G101: ='Annual and Quarterly'!J101 -> 63.306458 | H101: ='Annual and Quarterly'!K101 -> 64.783184 | I101: 65.66836 | J101: ='Quarterly YTD'!J101 -> 66.264948 | K101: ='Annual and Quarterly'!N101 -> 66.830334 | L101: ='Annual and Quarterly'!O101 -> 67.986917 | M101: 68.02026 | N101: ='Quarterly YTD'!N101 -> 72.295538 | O101: ='Annual and Quarterly'!R101 -> 72.283156
A102: Intangible assets | B102: 72.676461 | E102: 77.898462 | G102: ='Annual and Quarterly'!J102 -> 71.26127 | H102: ='Annual and Quarterly'!K102 -> 69.320984 | I102: 79.281757 | J102: ='Quarterly YTD'!J102 -> 75.418243 | K102: ='Annual and Quarterly'!N102 -> 68.46526 | L102: ='Annual and Quarterly'!O102 -> 71.981934 | M102: 75.923436 | N102: ='Quarterly YTD'!N102 -> 75.683398 | O102: ='Annual and Quarterly'!R102 -> 78.219311
A103: Property and equipment | B103: 199.42993 | E103: 198.45436 | G103: ='Annual and Quarterly'!J103 -> 198.15654 | H103: ='Annual and Quarterly'!K103 -> 186.79259 | I103: 188.23099 | J103: ='Quarterly YTD'!J103 -> 180.14423 | K103: ='Annual and Quarterly'!N103 -> 184.9803 | L103: ='Annual and Quarterly'!O103 -> 192.22994 | M103: 204.12869 | N103: ='Quarterly YTD'!N103 -> 207.12029 | O103: ='Annual and Quarterly'!R103 -> 213.70598
A104: Right-of-use assets | B104: 173.52727 | E104: 121.17346 | G104: ='Annual and Quarterly'!J104 -> 109.79669 | H104: ='Annual and Quarterly'!K104 -> 104.47486 | I104: 96.64911 | J104: ='Quarterly YTD'!J104 -> 94.715846 | K104: ='Annual and Quarterly'!N104 -> 91.785329 | L104: ='Annual and Quarterly'!O104 -> 95.712509 | M104: 106.55989 | N104: ='Quarterly YTD'!N104 -> 99.809927 | O104: ='Annual and Quarterly'!R104 -> 97.262678
A105: Deferred tax assets | B105: 9.248969 | E105: 4.153279 | G105: ='Annual and Quarterly'!J105 -> 4.507584 | H105: ='Annual and Quarterly'!K105 -> 4.280837 | I105: 10.29944 | J105: ='Quarterly YTD'!J105 -> 10.324458 | K105: ='Annual and Quarterly'!N105 -> 10.344395 | L105: ='Annual and Quarterly'!O105 -> 9.240384 | M105: 10.043497 | N105: ='Quarterly YTD'!N105 -> 10.295438 | O105: ='Annual and Quarterly'!R105 -> 10.267833
A106: Due from related parties | B106: 20.862334 | E106: 22.998383 | G106: ='Annual and Quarterly'!J106 -> 24.167823 | H106: ='Annual and Quarterly'!K106 -> 24.623183 | I106: 25.578011 | J106: ='Quarterly YTD'!J106 -> 26.626797 | K106: ='Annual and Quarterly'!N106 -> 27.695011 | L106: ='Annual and Quarterly'!O106 -> 29.792436 | M106: 39.916191 | N106: ='Quarterly YTD'!N106 -> 43.885995 | O106: ='Annual and Quarterly'!R106 -> 47.819387
A107: Advances to suppliers | B107: 0 | E107: 4.674381 | G107: ='Annual and Quarterly'!J107 -> 0 | H107: ='Annual and Quarterly'!K107 -> 0 | I107: 1.466235 | J107: ='Quarterly YTD'!J107 -> 3.745293 | K107: ='Annual and Quarterly'!N107 -> 1.574404 | L107: ='Annual and Quarterly'!O107 -> 0.525107 | M107: 0.394769 | N107: ='Quarterly YTD'!N107 -> 8.870091 | O107: ='Annual and Quarterly'!R107 -> 13.023651
A108: Non-current assets | B108: =SUM(B101:B106) -> 488.48832 | E108: =SUM(E101:E107) -> 487.6225 | G108: ='Annual and Quarterly'!J108 -> 471.19636 | H108: ='Annual and Quarterly'!K108 -> 454.27563 | I108: =SUM(I101:I107) -> 467.1739 | J108: ='Quarterly YTD'!J108 -> 457.23981 | K108: ='Annual and Quarterly'!N108 -> 451.67504 | L108: ='Annual and Quarterly'!O108 -> 467.46923 | M108: =SUM(M101:M107) -> 504.98673 | N108: ='Quarterly YTD'!N108 -> 517.96068 | O108: ='Annual and Quarterly'!R108 -> 532.582
A109: Due from related parties | B109: 21.730404 | E109: 0 | G109: ='Annual and Quarterly'!J109 -> 0 | H109: ='Annual and Quarterly'!K109 -> 0 | I109: 0 | J109: ='Quarterly YTD'!J109 -> 0 | K109: ='Annual and Quarterly'!N109 -> 0 | L109: ='Annual and Quarterly'!O109 -> 0 | M109: 0 | N109: ='Quarterly YTD'!N109 -> 0 | O109: ='Annual and Quarterly'!R109 -> 0
A110: Due from a related party | B110: 0 | E110: 0 | G110: ='Annual and Quarterly'!J110 -> 0.356293 | H110: ='Annual and Quarterly'!K110 -> 0.356297 | I110: 0 | J110: ='Quarterly YTD'!J110 -> 0 | K110: ='Annual and Quarterly'!N110 -> 0 | L110: ='Annual and Quarterly'!O110 -> 0 | M110: 0 | N110: ='Quarterly YTD'!N110 -> 0 | O110: ='Annual and Quarterly'!R110 -> 0
A111: Inventories | B111: 5.008999 | E111: 8.711839 | G111: ='Annual and Quarterly'!J111 -> 5.092315 | H111: ='Annual and Quarterly'!K111 -> 3.945797 | I111: 3.994316 | J111: ='Quarterly YTD'!J111 -> 3.007941 | K111: ='Annual and Quarterly'!N111 -> 3.296766 | L111: ='Annual and Quarterly'!O111 -> 3.378874 | M111: 2.721913 | N111: ='Quarterly YTD'!N111 -> 3.109391 | O111: ='Annual and Quarterly'!R111 -> 3.273109
A112: Prepayments and other debit balances | B112: 26.504855 | E112: 31.520558 | G112: ='Annual and Quarterly'!J112 -> 41.001499 | H112: ='Annual and Quarterly'!K112 -> 34.710443 | I112: 44.909836 | J112: ='Quarterly YTD'!J112 -> 57.255092 | K112: ='Annual and Quarterly'!N112 -> 52.064241 | L112: ='Annual and Quarterly'!O112 -> 48.600933 | M112: 36.072733 | N112: ='Quarterly YTD'!N112 -> 35.985972 | O112: ='Annual and Quarterly'!R112 -> 42.110862
A113: Contract assets | B113: 1.849877 | E113: 1.732034 | G113: ='Annual and Quarterly'!J113 -> 2.565419 | H113: ='Annual and Quarterly'!K113 -> 2.361934 | I113: 1.372195 | J113: ='Quarterly YTD'!J113 -> 1.275084 | K113: ='Annual and Quarterly'!N113 -> 1.220784 | L113: ='Annual and Quarterly'!O113 -> 2.2552 | M113: 1.551668 | N113: ='Quarterly YTD'!N113 -> 1.749126 | O113: ='Annual and Quarterly'!R113 -> 1.515745
A114: Trade receivables | B114: 9.130196 | E114: 11.172111 | G114: ='Annual and Quarterly'!J114 -> 12.31978 | H114: ='Annual and Quarterly'!K114 -> 11.007746 | I114: 12.244475 | J114: ='Quarterly YTD'!J114 -> 11.851068 | K114: ='Annual and Quarterly'!N114 -> 13.665945 | L114: ='Annual and Quarterly'!O114 -> 14.832315 | M114: 13.280304 | N114: ='Quarterly YTD'!N114 -> 14.24382 | O114: ='Annual and Quarterly'!R114 -> 11.655281
A115: Bank balances and cash | B115: 24.929057 | E115: 33.308627 | G115: ='Annual and Quarterly'!J115 -> 23.241426 | H115: ='Annual and Quarterly'!K115 -> 16.538026 | I115: 44.057919 | J115: ='Quarterly YTD'!J115 -> 38.454304 | K115: ='Annual and Quarterly'!N115 -> 26.67968 | L115: ='Annual and Quarterly'!O115 -> 38.970909 | M115: 24.969687 | N115: ='Quarterly YTD'!N115 -> 66.672997 | O115: ='Annual and Quarterly'!R115 -> 35.369198
A116: Current assets | B116: =B109+SUM(B111:B115) -> 89.153388 | E116: =SUM(E111:E115) -> 86.445169 | G116: ='Annual and Quarterly'!J116 -> 84.576732 | H116: ='Annual and Quarterly'!K116 -> 68.920243 | I116: =SUM(I111:I115) -> 106.57874 | J116: ='Quarterly YTD'!J116 -> 111.84349 | K116: ='Annual and Quarterly'!N116 -> 96.927416 | L116: ='Annual and Quarterly'!O116 -> 108.03823 | M116: =SUM(M111:M115) -> 78.596305 | N116: ='Quarterly YTD'!N116 -> 121.76131 | O116: ='Annual and Quarterly'!R116 -> 93.924195
A117: TOTAL ASSETS | B117: =B108+B116 -> 577.64171 | E117: =E108+E116 -> 574.06767 | G117: ='Annual and Quarterly'!J117 -> 555.77309 | H117: ='Annual and Quarterly'!K117 -> 523.19587 | I117: =I108+I116 -> 573.75265 | J117: ='Quarterly YTD'!J117 -> 569.0833 | K117: ='Annual and Quarterly'!N117 -> 548.60245 | L117: ='Annual and Quarterly'!O117 -> 575.50746 | M117: =M108+M116 -> 583.58304 | N117: ='Quarterly YTD'!N117 -> 639.72199 | O117: ='Annual and Quarterly'!R117 -> 626.5062
A118: Share capital | B118: 10 | E118: 10 | G118: ='Annual and Quarterly'!J118 -> 10 | H118: ='Annual and Quarterly'!K118 -> 10 | I118: 10 | J118: ='Quarterly YTD'!J118 -> 10 | K118: ='Annual and Quarterly'!N118 -> 10 | L118: ='Annual and Quarterly'!O118 -> 10 | M118: 10 | N118: ='Quarterly YTD'!N118 -> 10 | O118: ='Annual and Quarterly'!R118 -> 10
A119: Other reserve | B119: 1.08499 | E119: 1.101905 | G119: ='Annual and Quarterly'!J119 -> 1.101905 | H119: ='Annual and Quarterly'!K119 -> 1.101905 | I119: 1.180202 | J119: ='Quarterly YTD'!J119 -> 1.180202 | K119: ='Annual and Quarterly'!N119 -> 1.180202 | L119: ='Annual and Quarterly'!O119 -> 1.180202 | M119: 1.915172 | N119: ='Quarterly YTD'!N119 -> 1.915172 | O119: ='Annual and Quarterly'!R119 -> 1.915172
A120: Legal reserve | B120: 0.006667 | E120: 0.006667 | G120: ='Annual and Quarterly'!J120 -> 0.006667 | H120: ='Annual and Quarterly'!K120 -> 0.006667 | I120: 0.006667 | J120: ='Quarterly YTD'!J120 -> 0.006667 | K120: ='Annual and Quarterly'!N120 -> 0.006667 | L120: ='Annual and Quarterly'!O120 -> 0.006667 | M120: 0.006667 | N120: ='Quarterly YTD'!N120 -> 0.006667 | O120: ='Annual and Quarterly'!R120 -> 0.006667
A121: Foreign currency translation reserve | B121: -104.06557 | E121: -51.578114 | G121: ='Annual and Quarterly'!J121 -> -40.063298 | H121: ='Annual and Quarterly'!K121 -> -41.509465 | I121: -40.499685 | J121: ='Quarterly YTD'!J121 -> -39.744429 | K121: ='Annual and Quarterly'!N121 -> -39.758261 | L121: ='Annual and Quarterly'!O121 -> -47.95383 | M121: -61.504335 | N121: ='Quarterly YTD'!N121 -> -52.346398 | O121: ='Annual and Quarterly'!R121 -> -53.069463
A122: Accumulated losses | B122: 47.544593 | E122: -67.92356 | G122: ='Annual and Quarterly'!J122 -> -106.50116 | H122: ='Annual and Quarterly'!K122 -> -134.17061 | I122: -171.6823 | J122: ='Quarterly YTD'!J122 -> -182.5475 | K122: ='Annual and Quarterly'!N122 -> -195.04648 | L122: ='Annual and Quarterly'!O122 -> -171.54861 | M122: -141.26449 | N122: ='Quarterly YTD'!N122 -> -154.97913 | O122: ='Annual and Quarterly'!R122 -> -160.57644
A123: Equity attributable to equity holders of the Company | B123: =SUM(B118:B122) -> -45.429325 | E123: =SUM(E118:E122) -> -108.3931 | G123: ='Annual and Quarterly'!J123 -> -135.45588 | H123: ='Annual and Quarterly'!K123 -> -164.57151 | I123: =SUM(I118:I122) -> -200.99512 | J123: ='Quarterly YTD'!J123 -> -211.10506 | K123: ='Annual and Quarterly'!N123 -> -223.61787 | L123: ='Annual and Quarterly'!O123 -> -208.31557 | M123: =SUM(M118:M122) -> -190.84699 | N123: ='Quarterly YTD'!N123 -> -195.40369 | O123: ='Annual and Quarterly'!R123 -> -201.72407
A124: Non-controlling interests | B124: -3.510631 | E124: -3.46674 | G124: ='Annual and Quarterly'!J124 -> -3.516355 | H124: ='Annual and Quarterly'!K124 -> -3.527525 | I124: -3.533177 | J124: ='Quarterly YTD'!J124 -> -3.546509 | K124: ='Annual and Quarterly'!N124 -> -3.593431 | L124: ='Annual and Quarterly'!O124 -> -3.671098 | M124: -3.578152 | N124: ='Quarterly YTD'!N124 -> -3.488666 | O124: ='Annual and Quarterly'!R124 -> -3.561812
A125: Total equity | B125: =SUM(B123:B124) -> -48.939956 | E125: =SUM(E123:E124) -> -111.85984 | G125: ='Annual and Quarterly'!J125 -> -138.97224 | H125: ='Annual and Quarterly'!K125 -> -168.09903 | I125: =SUM(I123:I124) -> -204.5283 | J125: ='Quarterly YTD'!J125 -> -214.65157 | K125: ='Annual and Quarterly'!N125 -> -227.2113 | L125: ='Annual and Quarterly'!O125 -> -211.98667 | M125: =SUM(M123:M124) -> -194.42514 | N125: ='Quarterly YTD'!N125 -> -198.89236 | O125: ='Annual and Quarterly'!R125 -> -205.28588
A126: Deferred tax liabilities | B126: 2.09078 | E126: 7.207006 | G126: ='Annual and Quarterly'!J126 -> 7.755778 | H126: ='Annual and Quarterly'!K126 -> 7.273408 | I126: 13.00988 | J126: ='Quarterly YTD'!J126 -> 13.189459 | K126: ='Annual and Quarterly'!N126 -> 12.9446 | L126: ='Annual and Quarterly'!O126 -> 11.421267 | M126: 11.038669 | N126: ='Quarterly YTD'!N126 -> 11.752926 | O126: ='Annual and Quarterly'!R126 -> 11.712991
A127: Provisions for risks and charges | B127: 12.445668 | E127: 8.455179 | G127: ='Annual and Quarterly'!J127 -> 8.759279 | H127: ='Annual and Quarterly'!K127 -> 8.568663 | I127: 10.869566 | J127: ='Quarterly YTD'!J127 -> 11.054325 | K127: ='Annual and Quarterly'!N127 -> 10.576061 | L127: ='Annual and Quarterly'!O127 -> 11.455138 | M127: 11.073739 | N127: ='Quarterly YTD'!N127 -> 11.226006 | O127: ='Annual and Quarterly'!R127 -> 11.629339
A128: Other long-term payables | B128: 14.47218 | E128: 11.435248 | G128: ='Annual and Quarterly'!J128 -> 12.65524 | H128: ='Annual and Quarterly'!K128 -> 8.094857 | I128: 8.936963 | J128: ='Quarterly YTD'!J128 -> 9.547316 | K128: ='Annual and Quarterly'!N128 -> 10.10654 | L128: ='Annual and Quarterly'!O128 -> 10.784527 | M128: 11.531037 | N128: ='Quarterly YTD'!N128 -> 12.316782 | O128: ='Annual and Quarterly'!R128 -> 13.156133
A129: Term loans | B129: 0 | E129: 180.97229 | G129: ='Annual and Quarterly'!J129 -> 153.35056 | H129: ='Annual and Quarterly'!K129 -> 138.66943 | I129: 0.86771 | J129: ='Quarterly YTD'!J129 -> 0.257279 | K129: ='Annual and Quarterly'!N129 -> 0.20275 | L129: ='Annual and Quarterly'!O129 -> 1.027616 | M129: 6.455915 | N129: ='Quarterly YTD'!N129 -> 7.209799 | O129: ='Annual and Quarterly'!R129 -> 7.46783
A130: Lease liabilities | B130: 181.99711 | E130: 173.51927 | G130: ='Annual and Quarterly'!J130 -> 164.41744 | H130: ='Annual and Quarterly'!K130 -> 158.87668 | I130: 154.20466 | J130: ='Quarterly YTD'!J130 -> 152.36673 | K130: ='Annual and Quarterly'!N130 -> 152.59541 | L130: ='Annual and Quarterly'!O130 -> 149.1027 | M130: 145.03402 | N130: ='Quarterly YTD'!N130 -> 141.60042 | O130: ='Annual and Quarterly'!R130 -> 138.5254
A131: Senior Secured Notes | B131: 0 | E131: 0 | G131: ='Annual and Quarterly'!J131 -> 0 | H131: ='Annual and Quarterly'!K131 -> 0 | I131: 300 | J131: ='Quarterly YTD'!J131 -> 300 | K131: ='Annual and Quarterly'!N131 -> 300 | L131: ='Annual and Quarterly'!O131 -> 300 | M131: 300 | N131: ='Quarterly YTD'!N131 -> 346.78549 | O131: ='Annual and Quarterly'!R131 -> 347.49142
A132: Long-term debt to a supplier | B132: 0 | E132: 0 | G132: ='Annual and Quarterly'!J132 -> 0 | H132: ='Annual and Quarterly'!K132 -> 0 | I132: 10.080508 | J132: ='Quarterly YTD'!J132 -> 9.216275 | K132: ='Annual and Quarterly'!N132 -> 8.352044 | L132: ='Annual and Quarterly'!O132 -> 11.050898 | M132: 10.474928 | N132: ='Quarterly YTD'!N132 -> 10.125607 | O132: ='Annual and Quarterly'!R132 -> 8.360865
...
